{
  "type": "Feature",
  "properties": {
    "gn:admin1_code":"C",
    "gn:admin2_code":"20.0",
    "gn:asciiname":"Doodaun",
    "gn:country_code":"IE",
    "gn:dem":67,
    "gn:feature_class":"P",
    "gn:feature_code":"PPLL",
    "gn:name":"Doodaun",
    "gn:population":0,
    "gn:timezone":"Europe/Dublin",
    "iso:country":"IE",
    "wof:name":"Doodaun",
    "wof:placetype":"locality"
},
  "geometry": {"coordinates":[-9.515,54.05028000000001],"type":"Point"}
}