{
  "type": "Feature",
  "properties": {
    "gn:admin1_code":"M",
    "gn:admin2_code":"42",
    "gn:asciiname":"Tour Bridge",
    "gn:country_code":"IE",
    "gn:dem":151,
    "gn:feature_class":"P",
    "gn:feature_code":"PPLL",
    "gn:name":"Tour Bridge",
    "gn:population":0,
    "gn:timezone":"Europe/Dublin",
    "iso:country":"IE",
    "wof:name":"Tour Bridge",
    "wof:placetype":"locality"
},
  "geometry": {"coordinates":[-9.14417,52.36833],"type":"Point"}
}