{
  "type": "Feature",
  "properties": {
    "gn:admin1_code":"L",
    "gn:admin2_code":"31.0",
    "gn:asciiname":"Toberbeg",
    "gn:country_code":"IE",
    "gn:dem":211,
    "gn:feature_class":"P",
    "gn:feature_code":"PPL",
    "gn:name":"Toberbeg",
    "gn:population":0,
    "gn:timezone":"Europe/Dublin",
    "iso:country":"IE",
    "wof:name":"Toberbeg",
    "wof:placetype":"locality"
},
  "geometry": {"coordinates":[-6.67361,53.03694],"type":"Point"}
}