{
  "type": "Feature",
  "properties": {
    "gn:admin1_code":"L",
    "gn:admin2_code":"13",
    "gn:asciiname":"Clonamery",
    "gn:country_code":"IE",
    "gn:dem":127,
    "gn:feature_class":"P",
    "gn:feature_code":"PPL",
    "gn:name":"Clonamery",
    "gn:population":0,
    "gn:timezone":"Europe/Dublin",
    "iso:country":"IE",
    "wof:name":"Clonamery",
    "wof:placetype":"locality"
},
  "geometry": {"coordinates":[-7.02194,52.4725],"type":"Point"}
}