{
  "type": "Feature",
  "properties": {
    "gn:admin1_code":"C",
    "gn:admin2_code":"20",
    "gn:asciiname":"Tooreen",
    "gn:country_code":"IE",
    "gn:dem":20,
    "gn:feature_class":"P",
    "gn:feature_code":"PPL",
    "gn:name":"Tooreen",
    "gn:population":0,
    "gn:timezone":"Europe/Dublin",
    "iso:country":"IE",
    "wof:name":"Tooreen",
    "wof:placetype":"locality"
},
  "geometry": {"coordinates":[-9.28333,53.66667],"type":"Point"}
}