{
  "type": "Feature",
  "properties": {
    "gn:admin1_code":"M",
    "gn:admin2_code":"26.0",
    "gn:asciiname":"Aglish",
    "gn:country_code":"IE",
    "gn:dem":62,
    "gn:feature_class":"P",
    "gn:feature_code":"PPL",
    "gn:name":"Aglish",
    "gn:population":0,
    "gn:timezone":"Europe/Dublin",
    "iso:country":"IE",
    "wof:name":"Aglish",
    "wof:placetype":"locality"
},
  "geometry": {"coordinates":[-8.09031,53.04231],"type":"Point"}
}