{
  "type": "Feature",
  "properties": {
    "gn:admin1_code":"M",
    "gn:admin2_code":"26.0",
    "gn:asciiname":"Aglish",
    "gn:country_code":"IE",
    "gn:dem":62,
    "gn:feature_class":"P",
    "gn:feature_code":"PPL",
    "gn:name":"Aglish",
    "gn:population":0,
    "gn:timezone":"Europe/Dublin",
    "iso:country":"IE",
    "name:ceb_x_preferred":[
        "Aglish"
    ],
    "name:eus_x_preferred":[
        "Aglish"
    ],
    "name:fas_x_preferred":[
        "\u0627\u06af\u0644\u06cc\u0634"
    ],
    "name:gle_x_preferred":[
        "An Eaglais"
    ],
    "name:rus_x_preferred":[
        "\u0410\u0433\u043b\u0438\u0448"
    ],
    "name:spa_x_preferred":[
        "Aglish"
    ],
    "name:swe_x_preferred":[
        "Aglish"
    ],
    "name:urd_x_preferred":[
        "\u0627\u06af\u0644\u06cc\u0634"
    ],
    "wof:name":"Aglish",
    "wof:placetype":"locality"
},
  "geometry": {"coordinates":[-8.09031,53.04231],"type":"Point"}
}