{
  "type": "Feature",
  "properties": {
    "gn:admin1_code":"L",
    "gn:admin2_code":"30",
    "gn:asciiname":"Courthoyle",
    "gn:country_code":"IE",
    "gn:dem":85,
    "gn:feature_class":"P",
    "gn:feature_code":"PPL",
    "gn:name":"Courthoyle",
    "gn:population":0,
    "gn:timezone":"Europe/Dublin",
    "iso:country":"IE",
    "wof:name":"Courthoyle",
    "wof:placetype":"locality"
},
  "geometry": {"coordinates":[-6.80056,52.38389],"type":"Point"}
}