{
  "type": "Feature",
  "properties": {
    "gn:admin1_code":"L",
    "gn:admin2_code":"31.0",
    "gn:asciiname":"Glencree",
    "gn:cc2":"IE",
    "gn:country_code":"IE",
    "gn:dem":517,
    "gn:feature_class":"P",
    "gn:feature_code":"PPL",
    "gn:name":"Glencree",
    "gn:population":0,
    "gn:timezone":"Europe/Dublin",
    "iso:country":"IE",
    "name:fra_x_preferred":[
        "Glencree"
    ],
    "name:gle_x_preferred":[
        "Gleann Cr\u00ed"
    ],
    "name:spa_x_preferred":[
        "Glencree"
    ],
    "name:und_x_variant":[
        "Gleann Cr\u00edthigh",
        "Glencree"
    ],
    "wof:name":"Glencree",
    "wof:placetype":"locality"
},
  "geometry": {"coordinates":[-6.30611,53.19472],"type":"Point"}
}