{
  "type": "Feature",
  "properties": {
    "gn:admin1_code":"L",
    "gn:admin2_code":"30",
    "gn:asciiname":"Redgate",
    "gn:country_code":"IE",
    "gn:dem":67,
    "gn:feature_class":"P",
    "gn:feature_code":"PPL",
    "gn:name":"Redgate",
    "gn:population":0,
    "gn:timezone":"Europe/Dublin",
    "iso:country":"IE",
    "name:heb_x_preferred":[
        "\u05e8\u05d3\u05d2\u05d9\u05d9\u05d8"
    ],
    "wof:name":"Redgate",
    "wof:placetype":"locality"
},
  "geometry": {"coordinates":[-6.50278,52.41833],"type":"Point"}
}