{
  "type": "Feature",
  "properties": {
    "gn:admin1_code":"C",
    "gn:admin2_code":"10.0",
    "gn:asciiname":"The Fishpond Cross Roads",
    "gn:country_code":"IE",
    "gn:dem":72,
    "gn:feature_class":"P",
    "gn:feature_code":"PPL",
    "gn:name":"The Fishpond Cross Roads",
    "gn:population":0,
    "gn:timezone":"Europe/Dublin",
    "iso:country":"IE",
    "wof:name":"The Fishpond Cross Roads",
    "wof:placetype":"locality"
},
  "geometry": {"coordinates":[-8.67333,53.16444],"type":"Point"}
}