{
  "type": "Feature",
  "properties": {
    "gn:admin1_code":"M",
    "gn:admin2_code":"04",
    "gn:asciiname":"Meelin",
    "gn:country_code":"IE",
    "gn:dem":263,
    "gn:feature_class":"P",
    "gn:feature_code":"PPL",
    "gn:name":"Meelin",
    "gn:population":0,
    "gn:timezone":"Europe/Dublin",
    "iso:country":"IE",
    "name:eus_x_preferred":[
        "Meelin"
    ],
    "wof:name":"Meelin",
    "wof:placetype":"locality"
},
  "geometry": {"coordinates":[-9.03333,52.26667],"type":"Point"}
}