{
  "type": "Feature",
  "properties": {
    "gn:admin1_code":"L",
    "gn:admin2_code":"21",
    "gn:asciiname":"Bobsville",
    "gn:country_code":"IE",
    "gn:dem":125,
    "gn:feature_class":"P",
    "gn:feature_code":"PPL",
    "gn:name":"Bobsville",
    "gn:population":0,
    "gn:timezone":"Europe/Dublin",
    "iso:country":"IE",
    "wof:name":"Bobsville",
    "wof:placetype":"locality"
},
  "geometry": {"coordinates":[-7.06988,53.71747],"type":"Point"}
}