{
  "type": "Feature",
  "properties": {
    "gn:admin1_code":"U",
    "gn:admin2_code":"06",
    "gn:asciiname":"Cloghan",
    "gn:country_code":"IE",
    "gn:dem":134,
    "gn:feature_class":"P",
    "gn:feature_code":"PPL",
    "gn:name":"Cloghan",
    "gn:population":0,
    "gn:timezone":"Europe/Dublin",
    "iso:country":"IE",
    "name:eng_x_preferred":[
        "Cloghan"
    ],
    "name:gle_x_preferred":[
        "An Cloch\u00e1n"
    ],
    "name:rus_x_preferred":[
        "\u041a\u043b\u043e\u0445\u0430\u043d"
    ],
    "wof:name":"Cloghan",
    "wof:placetype":"locality"
},
  "geometry": {"coordinates":[-7.93361,54.8425],"type":"Point"}
}