{
  "type": "Feature",
  "properties": {
    "gn:country":"IE",
    "gn:fcode":"PPL",
    "gn:population":0,
    "iso:country":"IE",
    "name:eng_x_preferred":[
        "Aughris"
    ],
    "name:eus_x_preferred":[
        "Aughris"
    ],
    "name:gle_x_preferred":[
        "Eachrois"
    ],
    "name:nld_x_preferred":[
        "Aughris"
    ],
    "qs_pg:aaroncc":"IE",
    "qs_pg:gn_country":"IE",
    "qs_pg:gn_fcode":"PPL",
    "qs_pg:gn_pop":0,
    "qs_pg:name":"Aughris",
    "qs_pg:name_adm0":"Ireland",
    "qs_pg:name_adm1":"Sligo",
    "qs_pg:photos":193,
    "qs_pg:photos_1k":39,
    "qs_pg:photos_9k":1,
    "qs_pg:photos_9r":4,
    "qs_pg:photos_all":193,
    "qs_pg:photos_sr":4,
    "qs_pg:pop_sr":0,
    "qs_pg:qs_pg_placetype":"locality",
    "qs_pg:qs_pg_placetype_gp":"Town",
    "qs_pg:woe_adm0":23424803,
    "woe:adm0_id":23424803,
    "woe:name_adm0":"Ireland",
    "woe:name_adm1":"Sligo",
    "woe:placetype":"Town",
    "wof:name":"Aughris",
    "wof:placetype":"locality"
},
  "geometry": {"coordinates":[-8.76944,54.27306],"type":"Point"}
}