{
  "type": "Feature",
  "properties": {
    "gn:gn_country":"IE",
    "gn:gn_fcode":"PPL",
    "gn:gn_pop":0,
    "iso:country":"IE",
    "name:eng_x_preferred":[
        "Glandore"
    ],
    "name:eus_x_preferred":[
        "Glandore"
    ],
    "name:gle_x_preferred":[
        "C\u00faan Dor"
    ],
    "name:gle_x_variant":[
        "Cuan Dor"
    ],
    "name:jpn_x_preferred":[
        "\u30b0\u30e9\u30f3\u30c9\u30fc\u30eb"
    ],
    "name:nld_x_preferred":[
        "Glandore"
    ],
    "name:rus_x_preferred":[
        "\u0413\u043b\u0430\u043d\u0434\u043e\u0440"
    ],
    "name:swe_x_preferred":[
        "Glandore"
    ],
    "qs_pg:aaroncc":"IE",
    "qs_pg:gn_country":"IE",
    "qs_pg:gn_fcode":"PPL",
    "qs_pg:gn_pop":0,
    "qs_pg:name":"Glandore",
    "qs_pg:name_adm0":"Ireland",
    "qs_pg:name_adm1":"Cork",
    "qs_pg:photos":346,
    "qs_pg:photos_1k":70,
    "qs_pg:photos_9k":2,
    "qs_pg:photos_9r":5,
    "qs_pg:photos_all":346,
    "qs_pg:photos_sr":5,
    "qs_pg:pop_sr":0,
    "qs_pg:qs_pg_placetype":"locality",
    "qs_pg:qs_pg_placetype_gp":"Town",
    "qs_pg:woe_adm0":23424803,
    "woe:adm0_id":23424803,
    "woe:name_adm0":"Ireland",
    "woe:name_adm1":"Cork",
    "woe:placetype":"Town",
    "wof:name":"Glandore",
    "wof:placetype":"locality"
},
  "geometry": {"coordinates":[-9.11889,51.57306],"type":"Point"}
}