{
  "type": "Feature",
  "properties": {
    "gn:admin1_code":"M",
    "gn:admin2_code":"42.0",
    "gn:asciiname":"Glenogra Bridge",
    "gn:country_code":"IE",
    "gn:dem":59,
    "gn:feature_class":"P",
    "gn:feature_code":"PPL",
    "gn:name":"Glenogra Bridge",
    "gn:population":0,
    "gn:timezone":"Europe/Dublin",
    "iso:country":"IE",
    "wof:name":"Glenogra Bridge",
    "wof:placetype":"locality"
},
  "geometry": {"coordinates":[-8.60333,52.53],"type":"Point"}
}