{
  "type": "Feature",
  "properties": {
    "gn:admin1_code":"M",
    "gn:admin2_code":"11",
    "gn:asciiname":"Gowlin",
    "gn:country_code":"IE",
    "gn:dem":70,
    "gn:feature_class":"P",
    "gn:feature_code":"PPL",
    "gn:name":"Gowlin",
    "gn:population":0,
    "gn:timezone":"Europe/Dublin",
    "iso:country":"IE",
    "name:eng_x_preferred":[
        "Gowlin"
    ],
    "name:gle_x_preferred":[
        "Gualainn"
    ],
    "wof:name":"Gowlin",
    "wof:placetype":"locality"
},
  "geometry": {"coordinates":[-10.17722,52.15056],"type":"Point"}
}