{
  "type": "Feature",
  "properties": {
    "iso:country":"IE",
    "qs_pg:aaroncc":"IE",
    "qs_pg:name":"Inis Corthaidh",
    "qs_pg:name_adm0":"Ireland",
    "qs_pg:name_adm1":"Wexford",
    "qs_pg:photos":169,
    "qs_pg:photos_1k":34,
    "qs_pg:photos_9k":1,
    "qs_pg:photos_9r":4,
    "qs_pg:photos_all":169,
    "qs_pg:photos_sr":4,
    "qs_pg:pop_sr":0,
    "qs_pg:qs_pg_placetype":"locality",
    "qs_pg:qs_pg_placetype_gp":"Town",
    "qs_pg:woe_adm0":23424803,
    "woe:adm0_id":23424803,
    "woe:name_adm0":"Ireland",
    "woe:name_adm1":"Wexford",
    "woe:placetype":"Town",
    "wof:name":"Inis Corthaidh",
    "wof:placetype":"locality"
},
  "geometry": {"coordinates":[-6.576948,52.502824],"type":"Point"}
}