{
  "type": "Feature",
  "properties": {
    "gn:admin1_code":"U",
    "gn:admin2_code":"22.0",
    "gn:asciiname":"Tydavnet",
    "gn:country_code":"IE",
    "gn:dem":95,
    "gn:feature_class":"P",
    "gn:feature_code":"PPL",
    "gn:name":"Tydavnet",
    "gn:population":0,
    "gn:timezone":"Europe/Dublin",
    "iso:country":"IE",
    "name:eus_x_preferred":[
        "Tydavnet"
    ],
    "name:fra_x_preferred":[
        "Tydavnet"
    ],
    "name:gle_x_preferred":[
        "Tigh Damhnata"
    ],
    "name:nld_x_preferred":[
        "Tydavnet"
    ],
    "name:rus_x_preferred":[
        "\u0422\u0435\u0434\u0430\u0432\u043d\u0435\u0442"
    ],
    "wof:name":"Tydavnet",
    "wof:placetype":"locality"
},
  "geometry": {"coordinates":[-7.01576,54.29587],"type":"Point"}
}