{
  "type": "Feature",
  "properties": {
    "gn:admin1_code":"M",
    "gn:admin2_code":"44",
    "gn:asciiname":"Knocknahoola",
    "gn:country_code":"IE",
    "gn:dem":201,
    "gn:feature_class":"P",
    "gn:feature_code":"PPL",
    "gn:name":"Knocknahoola",
    "gn:population":0,
    "gn:timezone":"Europe/Dublin",
    "iso:country":"IE",
    "wof:name":"Knocknahoola",
    "wof:placetype":"locality"
},
  "geometry": {"coordinates":[-7.70278,52.04861],"type":"Point"}
}