{
  "type": "Feature",
  "properties": {
    "gn:admin1_code":"L",
    "gn:admin2_code":"12.0",
    "gn:asciiname":"The Curragh",
    "gn:country_code":"IE",
    "gn:dem":122,
    "gn:feature_class":"P",
    "gn:feature_code":"PPL",
    "gn:name":"The Curragh",
    "gn:population":0,
    "gn:timezone":"Europe/Dublin",
    "iso:country":"IE",
    "wof:name":"The Curragh",
    "wof:placetype":"locality"
},
  "geometry": {"coordinates":[-6.83041,53.14686999999999],"type":"Point"}
}