{
  "type": "Feature",
  "properties": {
    "gn:admin1_code":"C",
    "gn:admin2_code":"20.0",
    "gn:asciiname":"Cummer",
    "gn:country_code":"IE",
    "gn:dem":71,
    "gn:feature_class":"P",
    "gn:feature_code":"PPL",
    "gn:name":"Cummer",
    "gn:population":0,
    "gn:timezone":"Europe/Dublin",
    "iso:country":"IE",
    "wof:name":"Cummer",
    "wof:placetype":"locality"
},
  "geometry": {"coordinates":[-9.3981,53.8668],"type":"Point"}
}