{
  "type": "Feature",
  "properties": {
    "gn:admin1_code":"C",
    "gn:admin2_code":"10",
    "gn:asciiname":"Powers Cross",
    "gn:country_code":"IE",
    "gn:dem":39,
    "gn:feature_class":"P",
    "gn:feature_code":"PPL",
    "gn:name":"Powers Cross",
    "gn:population":0,
    "gn:timezone":"Europe/Dublin",
    "iso:country":"IE",
    "wof:name":"Powers Cross",
    "wof:placetype":"locality"
},
  "geometry": {"coordinates":[-8.33083,53.07111],"type":"Point"}
}