{
  "type": "Feature",
  "properties": {
    "gn:admin1_code":"M",
    "gn:admin2_code":"42",
    "gn:asciiname":"Oldmill Bridge",
    "gn:country_code":"IE",
    "gn:dem":105,
    "gn:feature_class":"P",
    "gn:feature_code":"PPL",
    "gn:name":"Oldmill Bridge",
    "gn:population":0,
    "gn:timezone":"Europe/Dublin",
    "iso:country":"IE",
    "wof:name":"Oldmill Bridge",
    "wof:placetype":"locality"
},
  "geometry": {"coordinates":[-9.10222,52.47833000000001],"type":"Point"}
}