{
  "type": "Feature",
  "properties": {
    "gn:admin1_code":"U",
    "gn:admin2_code":"06",
    "gn:asciiname":"Glenmore Bridge",
    "gn:country_code":"IE",
    "gn:dem":126,
    "gn:feature_class":"P",
    "gn:feature_code":"PPLL",
    "gn:name":"Glenmore Bridge",
    "gn:population":0,
    "gn:timezone":"Europe/Dublin",
    "iso:country":"IE",
    "wof:name":"Glenmore Bridge",
    "wof:placetype":"locality"
},
  "geometry": {"coordinates":[-7.89667,54.55722],"type":"Point"}
}