{
  "type": "Feature",
  "properties": {
    "gn:admin1_code":"L",
    "gn:admin2_code":"15.0",
    "gn:asciiname":"Pallas",
    "gn:country_code":"IE",
    "gn:dem":100,
    "gn:feature_class":"P",
    "gn:feature_code":"PPL",
    "gn:name":"Pallas",
    "gn:population":0,
    "gn:timezone":"Europe/Dublin",
    "iso:country":"IE",
    "name:als_x_preferred":[
        "Pallas"
    ],
    "name:bre_x_preferred":[
        "Pallas"
    ],
    "name:cat_x_preferred":[
        "Pallas"
    ],
    "name:ceb_x_preferred":[
        "Pallas"
    ],
    "name:ces_x_preferred":[
        "Pallas"
    ],
    "name:dan_x_preferred":[
        "Pallas"
    ],
    "name:deu_x_preferred":[
        "Pallas"
    ],
    "name:ell_x_preferred":[
        "\u03a0\u03ac\u03bb\u03bb\u03b1\u03bd\u03c4\u03b1\u03c2"
    ],
    "name:epo_x_preferred":[
        "Pallas"
    ],
    "name:est_x_preferred":[
        "Pallas"
    ],
    "name:fas_x_preferred":[
        "\u067e\u0627\u0644\u0627\u0633"
    ],
    "name:fin_x_preferred":[
        "Pallas"
    ],
    "name:fra_x_preferred":[
        "Pallas"
    ],
    "name:frr_x_preferred":[
        "Pallas"
    ],
    "name:heb_x_preferred":[
        "\u05e4\u05d0\u05dc\u05d0\u05e1"
    ],
    "name:hrv_x_preferred":[
        "Pallas"
    ],
    "name:hun_x_preferred":[
        "Pallas"
    ],
    "name:ita_x_preferred":[
        "Pallas"
    ],
    "name:jpn_x_preferred":[
        "\u30d1\u30e9\u30b9"
    ],
    "name:kor_x_preferred":[
        "\ud314\ub77c\uc2a4"
    ],
    "name:lat_x_preferred":[
        "Pallas"
    ],
    "name:nld_x_preferred":[
        "Pallas"
    ],
    "name:nno_x_preferred":[
        "Pallas"
    ],
    "name:nor_x_preferred":[
        "Pallas"
    ],
    "name:pol_x_preferred":[
        "Pallas"
    ],
    "name:por_x_preferred":[
        "Pallas"
    ],
    "name:ron_x_preferred":[
        "Pallas"
    ],
    "name:rus_x_preferred":[
        "\u041f\u0430\u043b\u043b\u0430\u0441"
    ],
    "name:slk_x_preferred":[
        "Pallas"
    ],
    "name:spa_x_preferred":[
        "Pallas"
    ],
    "name:swe_x_preferred":[
        "Pallas"
    ],
    "name:tha_x_preferred":[
        "\u0e1e\u0e32\u0e25\u0e25\u0e31\u0e2a"
    ],
    "name:tur_x_preferred":[
        "Pallas"
    ],
    "name:ukr_x_preferred":[
        "\u041f\u0430\u043b\u043b\u0430\u0441"
    ],
    "name:zho_x_preferred":[
        "\u5e15\u62c9\u65af"
    ],
    "wof:name":"Pallas",
    "wof:placetype":"locality"
},
  "geometry": {"coordinates":[-7.34028,53.04306],"type":"Point"}
}