{
  "type": "Feature",
  "properties": {
    "gn:admin1_code":"L",
    "gn:admin2_code":"23.0",
    "gn:asciiname":"Myrtlegrove",
    "gn:country_code":"IE",
    "gn:dem":102,
    "gn:feature_class":"P",
    "gn:feature_code":"PPL",
    "gn:name":"Myrtlegrove",
    "gn:population":0,
    "gn:timezone":"Europe/Dublin",
    "iso:country":"IE",
    "wof:name":"Myrtlegrove",
    "wof:placetype":"locality"
},
  "geometry": {"coordinates":[-7.95472,52.91917],"type":"Point"}
}