{
  "type": "Feature",
  "properties": {
    "gn:admin1_code":"M",
    "gn:admin2_code":"11",
    "gn:asciiname":"Lissatinnig Bridge",
    "gn:country_code":"IE",
    "gn:dem":81,
    "gn:feature_class":"P",
    "gn:feature_code":"PPL",
    "gn:name":"Lissatinnig Bridge",
    "gn:population":0,
    "gn:timezone":"Europe/Dublin",
    "iso:country":"IE",
    "name:eng_x_preferred":[
        "Lissatinnig Bridge"
    ],
    "name:gle_x_preferred":[
        "Lios an tSonnaigh"
    ],
    "wof:name":"Lissatinnig Bridge",
    "wof:placetype":"locality"
},
  "geometry": {"coordinates":[-9.99528,51.92944],"type":"Point"}
}