{
  "type": "Feature",
  "properties": {
    "gn:admin1_code":"U",
    "gn:admin2_code":"22",
    "gn:asciiname":"Tattyboy",
    "gn:country_code":"IE",
    "gn:dem":86,
    "gn:feature_class":"P",
    "gn:feature_code":"PPLL",
    "gn:name":"Tattyboy",
    "gn:population":0,
    "gn:timezone":"Europe/Dublin",
    "iso:country":"IE",
    "wof:name":"Tattyboy",
    "wof:placetype":"locality"
},
  "geometry": {"coordinates":[-6.62111,54.02306],"type":"Point"}
}