{
  "type": "Feature",
  "properties": {
    "gn:admin1_code":"M",
    "gn:admin2_code":"03",
    "gn:asciiname":"Bealaclugga",
    "gn:cc2":"IE",
    "gn:country_code":"IE",
    "gn:dem":12,
    "gn:feature_class":"P",
    "gn:feature_code":"PPL",
    "gn:name":"Bealaclugga",
    "gn:population":0,
    "gn:timezone":"Europe/Dublin",
    "iso:country":"IE",
    "name:und_x_variant":[
        "Bell Harbour",
        "Bealaclugga"
    ],
    "wof:name":"Bealaclugga",
    "wof:placetype":"locality"
},
  "geometry": {"coordinates":[-9.06833,53.12167],"type":"Point"}
}