{
  "type": "Feature",
  "properties": {
    "gn:admin1_code":"L",
    "gn:admin2_code":"12.0",
    "gn:asciiname":"Thornton",
    "gn:country_code":"IE",
    "gn:dem":167,
    "gn:feature_class":"P",
    "gn:feature_code":"PPL",
    "gn:name":"Thornton",
    "gn:population":0,
    "gn:timezone":"Europe/Dublin",
    "iso:country":"IE",
    "name:ara_x_preferred":[
        "\u062b\u0648\u0631\u0646\u062a\u0648\u0646"
    ],
    "name:cat_x_preferred":[
        "Thornton"
    ],
    "name:ceb_x_preferred":[
        "Thornton"
    ],
    "name:ces_x_preferred":[
        "Thornton"
    ],
    "name:cym_x_preferred":[
        "Thornton"
    ],
    "name:deu_x_preferred":[
        "Thornton"
    ],
    "name:fin_x_preferred":[
        "Thornton"
    ],
    "name:fra_x_preferred":[
        "Thornton"
    ],
    "name:heb_x_preferred":[
        "\u05ea'\u05d5\u05e8\u05e0\u05d8\u05d5\u05df"
    ],
    "name:ita_x_preferred":[
        "Thornton"
    ],
    "name:jpn_x_preferred":[
        "\u30bd\u30fc\u30f3\u30c8\u30f3"
    ],
    "name:lim_x_preferred":[
        "Thornton"
    ],
    "name:nld_x_preferred":[
        "Thornton"
    ],
    "name:pol_x_preferred":[
        "Thornton"
    ],
    "name:por_x_preferred":[
        "Thornton"
    ],
    "name:rus_x_preferred":[
        "\u0422\u043e\u0440\u043d\u0442\u043e\u043d"
    ],
    "name:slv_x_preferred":[
        "Thornton"
    ],
    "name:spa_x_preferred":[
        "Thornton"
    ],
    "name:srp_x_preferred":[
        "\u0422\u043e\u0440\u043d\u0442\u043e\u043d"
    ],
    "name:swe_x_preferred":[
        "Thornton"
    ],
    "name:ukr_x_preferred":[
        "\u0422\u043e\u0440\u043d\u0442\u043e\u043d"
    ],
    "name:vol_x_preferred":[
        "Thornton"
    ],
    "wof:name":"Thornton",
    "wof:placetype":"locality"
},
  "geometry": {"coordinates":[-6.735,53.07556],"type":"Point"}
}