{
  "type": "Feature",
  "properties": {
    "gn:admin1_code":"M",
    "gn:admin2_code":"04",
    "gn:asciiname":"Derrynacaheragh",
    "gn:country_code":"IE",
    "gn:dem":103,
    "gn:feature_class":"P",
    "gn:feature_code":"PPL",
    "gn:name":"Derrynacaheragh",
    "gn:population":0,
    "gn:timezone":"Europe/Dublin",
    "iso:country":"IE",
    "wof:name":"Derrynacaheragh",
    "wof:placetype":"locality"
},
  "geometry": {"coordinates":[-9.19,51.7625],"type":"Point"}
}