{
  "type": "Feature",
  "properties": {
    "gn:admin1_code":"M",
    "gn:admin2_code":"04",
    "gn:asciiname":"Mossgrove Cross Roads",
    "gn:country_code":"IE",
    "gn:dem":131,
    "gn:feature_class":"P",
    "gn:feature_code":"PPLL",
    "gn:name":"Mossgrove Cross Roads",
    "gn:population":0,
    "gn:timezone":"Europe/Dublin",
    "iso:country":"IE",
    "wof:name":"Mossgrove Cross Roads",
    "wof:placetype":"locality"
},
  "geometry": {"coordinates":[-8.85167,51.79861],"type":"Point"}
}