{
  "type": "Feature",
  "properties": {
    "gn:admin1_code":"C",
    "gn:admin2_code":"25.0",
    "gn:asciiname":"Annaghmore",
    "gn:country_code":"IE",
    "gn:dem":112,
    "gn:feature_class":"P",
    "gn:feature_code":"PPL",
    "gn:name":"Annaghmore",
    "gn:population":0,
    "gn:timezone":"Europe/Dublin",
    "iso:country":"IE",
    "name:gla_x_preferred":[
        "Eanach M\u00f3r"
    ],
    "name:gle_x_preferred":[
        "Eanach M\u00f3r"
    ],
    "name:msa_x_preferred":[
        "Annaghmore"
    ],
    "name:pli_x_preferred":[
        "\u0905\u0928\u094d\u0928\u093e\u0918\u094d\u092e\u094b\u0930\u0947"
    ],
    "wof:name":"Annaghmore",
    "wof:placetype":"locality"
},
  "geometry": {"coordinates":[-8.56028,53.97583],"type":"Point"}
}