{
  "type": "Feature",
  "properties": {
    "gn:admin1_code":"M",
    "gn:admin2_code":"11",
    "gn:asciiname":"Ahavoher Bridge",
    "gn:country_code":"IE",
    "gn:dem":35,
    "gn:feature_class":"P",
    "gn:feature_code":"PPL",
    "gn:name":"Ahavoher Bridge",
    "gn:population":0,
    "gn:timezone":"Europe/Dublin",
    "iso:country":"IE",
    "wof:name":"Ahavoher Bridge",
    "wof:placetype":"locality"
},
  "geometry": {"coordinates":[-9.37111,52.47722],"type":"Point"}
}