{
  "type": "Feature",
  "properties": {
    "gn:admin1_code":"M",
    "gn:admin2_code":"04",
    "gn:asciiname":"Moanflugh",
    "gn:country_code":"IE",
    "gn:dem":195,
    "gn:feature_class":"P",
    "gn:feature_code":"PPLL",
    "gn:name":"Moanflugh",
    "gn:population":0,
    "gn:timezone":"Europe/Dublin",
    "iso:country":"IE",
    "wof:name":"Moanflugh",
    "wof:placetype":"locality"
},
  "geometry": {"coordinates":[-8.9825,51.96778],"type":"Point"}
}