{
  "type": "Feature",
  "properties": {
    "iso:country":"IE",
    "name:rus_x_preferred":[
        "\u041a\u043b\u043e\u0445\u0430\u043d"
    ],
    "qs_pg:aaroncc":"IE",
    "qs_pg:name":"Cloghan",
    "qs_pg:name_adm0":"Ireland",
    "qs_pg:name_adm1":"Offaly",
    "qs_pg:photos":8,
    "qs_pg:photos_1k":2,
    "qs_pg:photos_9k":1,
    "qs_pg:photos_9r":1,
    "qs_pg:photos_all":8,
    "qs_pg:photos_sr":1,
    "qs_pg:pop_sr":0,
    "qs_pg:qs_pg_placetype":"localadmin",
    "qs_pg:qs_pg_placetype_gp":"LocalAdmin",
    "qs_pg:woe_adm0":23424803,
    "woe:adm0_id":23424803,
    "woe:name_adm0":"Ireland",
    "woe:name_adm1":"Offaly",
    "woe:placetype":"LocalAdmin",
    "wof:name":"Cloghan",
    "wof:placetype":"localadmin"
},
  "geometry": {"coordinates":[-7.88417,53.22167],"type":"Point"}
}