{
  "type": "Feature",
  "properties": {
    "gn:admin1_code":"M",
    "gn:admin2_code":"44",
    "gn:asciiname":"Raheens",
    "gn:country_code":"IE",
    "gn:dem":80,
    "gn:feature_class":"P",
    "gn:feature_code":"PPL",
    "gn:name":"Raheens",
    "gn:population":0,
    "gn:timezone":"Europe/Dublin",
    "iso:country":"IE",
    "wof:name":"Raheens",
    "wof:placetype":"locality"
},
  "geometry": {"coordinates":[-7.2575,52.2075],"type":"Point"}
}