{
  "type": "Feature",
  "properties": {
    "gn:admin1_code":"U",
    "gn:admin2_code":"2.0",
    "gn:asciiname":"Mully",
    "gn:country_code":"IE",
    "gn:dem":119,
    "gn:feature_class":"P",
    "gn:feature_code":"PPLL",
    "gn:name":"Mully",
    "gn:population":0,
    "gn:timezone":"Europe/Dublin",
    "iso:country":"IE",
    "wof:name":"Mully",
    "wof:placetype":"locality"
},
  "geometry": {"coordinates":[-7.90222,54.20306],"type":"Point"}
}