{
  "type": "Feature",
  "properties": {
    "iso:country":"IE",
    "name:eng_x_preferred":[
        "Merrion"
    ],
    "wof:name":"Merrion",
    "wof:placetype":"neighbourhood"
},
  "geometry": {"coordinates":[-6.212476,53.318677],"type":"Point"}
}