{
  "type": "Feature",
  "properties": {
    "gn:admin1_code":"C",
    "gn:admin2_code":"20",
    "gn:asciiname":"Termoncarragh",
    "gn:country_code":"IE",
    "gn:dem":6,
    "gn:feature_class":"P",
    "gn:feature_code":"PPL",
    "gn:name":"Termoncarragh",
    "gn:population":0,
    "gn:timezone":"Europe/Dublin",
    "iso:country":"IE",
    "name:eng_x_preferred":[
        "Termoncarragh"
    ],
    "name:gle_x_preferred":[
        "Tearmann Caithreach"
    ],
    "wof:name":"Termoncarragh",
    "wof:placetype":"locality"
},
  "geometry": {"coordinates":[-10.07118,54.25268000000001],"type":"Point"}
}