{
  "type": "Feature",
  "properties": {
    "gn:admin1_code":"U",
    "gn:admin2_code":"22",
    "gn:asciiname":"Corvally",
    "gn:country_code":"IE",
    "gn:dem":131,
    "gn:feature_class":"P",
    "gn:feature_code":"PPLL",
    "gn:name":"Corvally",
    "gn:population":0,
    "gn:timezone":"Europe/Dublin",
    "iso:country":"IE",
    "wof:name":"Corvally",
    "wof:placetype":"locality"
},
  "geometry": {"coordinates":[-6.85222,53.99472],"type":"Point"}
}