{
  "type": "Feature",
  "properties": {
    "gn:gn_country":"IE",
    "gn:gn_fcode":"PPL",
    "gn:gn_pop":0,
    "gn:population":375,
    "iso:country":"IE",
    "name:eng_x_preferred":[
        "Geashill"
    ],
    "name:gle_x_preferred":[
        "G\u00e9isill"
    ],
    "qs_pg:aaroncc":"IE",
    "qs_pg:gn_country":"IE",
    "qs_pg:gn_fcode":"PPL",
    "qs_pg:gn_pop":0,
    "qs_pg:name":"Geashill",
    "qs_pg:name_adm0":"Ireland",
    "qs_pg:name_adm1":"Offaly",
    "qs_pg:photos":3,
    "qs_pg:photos_1k":1,
    "qs_pg:photos_9k":1,
    "qs_pg:photos_9r":5,
    "qs_pg:photos_all":304,
    "qs_pg:photos_sr":1,
    "qs_pg:pop_sr":0,
    "qs_pg:qs_pg_placetype":"localadmin",
    "qs_pg:qs_pg_placetype_gp":"LocalAdmin",
    "qs_pg:woe_adm0":23424803,
    "woe:adm0_id":23424803,
    "woe:name_adm0":"Ireland",
    "woe:name_adm1":"Offaly",
    "woe:placetype":"LocalAdmin",
    "wof:name":"Geashill",
    "wof:placetype":"localadmin",
    "wof:population":375
},
  "geometry": {"coordinates":[-7.32,53.23528],"type":"Point"}
}