{
  "type": "Feature",
  "properties": {
    "gn:admin1_code":"M",
    "gn:admin2_code":"04",
    "gn:asciiname":"Ballinhassig",
    "gn:country_code":"IE",
    "gn:dem":83,
    "gn:feature_class":"P",
    "gn:feature_code":"PPL",
    "gn:name":"Ballinhassig",
    "gn:population":0,
    "gn:timezone":"Europe/Dublin",
    "iso:country":"IE",
    "wof:name":"Ballinhassig",
    "wof:placetype":"locality"
},
  "geometry": {"coordinates":[-8.53694,51.81417],"type":"Point"}
}