{
  "type": "Feature",
  "properties": {
    "gn:admin1_code":"C",
    "gn:admin2_code":"20.0",
    "gn:asciiname":"An Bheairic",
    "gn:country_code":"IE",
    "gn:dem":9,
    "gn:feature_class":"P",
    "gn:feature_code":"PPL",
    "gn:name":"An Bheairic",
    "gn:population":0,
    "gn:timezone":"Europe/Dublin",
    "iso:country":"IE",
    "name:eng_x_preferred":[
        "Barrack"
    ],
    "name:gle_x_preferred":[
        "An Bheairic"
    ],
    "wof:name":"An Bheairic",
    "wof:placetype":"locality"
},
  "geometry": {"coordinates":[-10.09104,54.16338],"type":"Point"}
}