{
  "type": "Feature",
  "properties": {
    "gn:admin1_code":"L",
    "gn:admin2_code":"31",
    "gn:asciiname":"Lugglass Lower",
    "gn:country_code":"IE",
    "gn:dem":257,
    "gn:feature_class":"P",
    "gn:feature_code":"PPL",
    "gn:name":"Lugglass Lower",
    "gn:population":0,
    "gn:timezone":"Europe/Dublin",
    "iso:country":"IE",
    "wof:name":"Lugglass Lower",
    "wof:placetype":"locality"
},
  "geometry": {"coordinates":[-6.55528,53.06583000000001],"type":"Point"}
}