{
  "type": "Feature",
  "properties": {
    "gn:admin1_code":"C",
    "gn:admin2_code":"24",
    "gn:asciiname":"Lisacul",
    "gn:country_code":"IE",
    "gn:dem":76,
    "gn:feature_class":"P",
    "gn:feature_code":"PPL",
    "gn:name":"Lisacul",
    "gn:population":0,
    "gn:timezone":"Europe/Dublin",
    "iso:country":"IE",
    "wof:name":"Lisacul",
    "wof:placetype":"locality"
},
  "geometry": {"coordinates":[-8.63333,53.85],"type":"Point"}
}