{
  "type": "Feature",
  "properties": {
    "gn:gn_country":"IE",
    "gn:gn_fcode":"PPLL",
    "gn:gn_pop":0,
    "iso:country":"IE",
    "name:gle_x_preferred":[
        "Machaire Bui"
    ],
    "qs_pg:aaroncc":"IE",
    "qs_pg:gn_country":"IE",
    "qs_pg:gn_fcode":"PPLL",
    "qs_pg:gn_pop":0,
    "qs_pg:name":"Magheraboy",
    "qs_pg:name_adm0":"Ireland",
    "qs_pg:name_adm1":"Donegal",
    "qs_pg:photos":1,
    "qs_pg:photos_1k":1,
    "qs_pg:photos_9k":1,
    "qs_pg:photos_9r":1,
    "qs_pg:photos_all":1,
    "qs_pg:photos_sr":1,
    "qs_pg:pop_sr":0,
    "qs_pg:qs_pg_placetype":"localadmin",
    "qs_pg:qs_pg_placetype_gp":"LocalAdmin",
    "qs_pg:woe_adm0":23424803,
    "woe:adm0_id":23424803,
    "woe:name_adm0":"Ireland",
    "woe:name_adm1":"Donegal",
    "woe:placetype":"LocalAdmin",
    "wof:name":"Magheraboy",
    "wof:placetype":"localadmin"
},
  "geometry": {"coordinates":[-7.65389,54.77444],"type":"Point"}
}