{
  "type": "Feature",
  "properties": {
    "gn:admin1_code":"C",
    "gn:admin2_code":"20.0",
    "gn:asciiname":"Sheeans",
    "gn:country_code":"IE",
    "gn:dem":185,
    "gn:feature_class":"P",
    "gn:feature_code":"PPL",
    "gn:name":"Sheeans",
    "gn:population":0,
    "gn:timezone":"Europe/Dublin",
    "iso:country":"IE",
    "wof:name":"Sheeans",
    "wof:placetype":"locality"
},
  "geometry": {"coordinates":[-9.30456,53.94165],"type":"Point"}
}