{
  "type": "Feature",
  "properties": {
    "gn:admin1_code":"M",
    "gn:admin2_code":"42",
    "gn:asciiname":"Broken Bridge",
    "gn:country_code":"IE",
    "gn:dem":70,
    "gn:feature_class":"P",
    "gn:feature_code":"PPLL",
    "gn:name":"Broken Bridge",
    "gn:population":0,
    "gn:timezone":"Europe/Dublin",
    "iso:country":"IE",
    "wof:name":"Broken Bridge",
    "wof:placetype":"locality"
},
  "geometry": {"coordinates":[-8.94306,52.39056],"type":"Point"}
}