{
  "type": "Feature",
  "properties": {
    "gn:admin1_code":"L",
    "gn:admin2_code":"15.0",
    "gn:asciiname":"Carn Bridge",
    "gn:country_code":"IE",
    "gn:dem":88,
    "gn:feature_class":"P",
    "gn:feature_code":"PPLL",
    "gn:name":"Carn Bridge",
    "gn:population":0,
    "gn:timezone":"Europe/Dublin",
    "iso:country":"IE",
    "wof:name":"Carn Bridge",
    "wof:placetype":"locality"
},
  "geometry": {"coordinates":[-7.24,53.10694],"type":"Point"}
}