{
  "type": "Feature",
  "properties": {
    "gn:admin1_code":"C",
    "gn:admin2_code":"20.0",
    "gn:asciiname":"Cuillonaghtan",
    "gn:country_code":"IE",
    "gn:dem":108,
    "gn:feature_class":"P",
    "gn:feature_code":"PPL",
    "gn:name":"Cuillonaghtan",
    "gn:population":0,
    "gn:timezone":"Europe/Dublin",
    "iso:country":"IE",
    "wof:name":"Cuillonaghtan",
    "wof:placetype":"locality"
},
  "geometry": {"coordinates":[-9.04998,53.97187],"type":"Point"}
}