{
  "type": "Feature",
  "properties": {
    "gn:admin1_code":"M",
    "gn:admin2_code":"03",
    "gn:asciiname":"Pulleen",
    "gn:country_code":"IE",
    "gn:dem":30,
    "gn:feature_class":"P",
    "gn:feature_code":"PPL",
    "gn:name":"Pulleen",
    "gn:population":0,
    "gn:timezone":"Europe/Dublin",
    "iso:country":"IE",
    "wof:name":"Pulleen",
    "wof:placetype":"locality"
},
  "geometry": {"coordinates":[-9.58333,52.73333],"type":"Point"}
}