{
  "type": "Feature",
  "properties": {
    "gn:admin1_code":"L",
    "gn:admin2_code":"21.0",
    "gn:asciiname":"Adamstown",
    "gn:country_code":"IE",
    "gn:dem":61,
    "gn:feature_class":"P",
    "gn:feature_code":"PPL",
    "gn:name":"Adamstown",
    "gn:population":0,
    "gn:timezone":"Europe/Dublin",
    "iso:country":"IE",
    "name:bel_x_preferred":[
        "\u0410\u0434\u0430\u043c\u0441\u0442\u0430\u045e\u043d"
    ],
    "name:bre_x_preferred":[
        "Adamstown"
    ],
    "name:bul_x_preferred":[
        "\u0410\u0434\u0430\u043c\u0441\u0442\u0430\u0443\u043d"
    ],
    "name:ceb_x_preferred":[
        "Adamstown"
    ],
    "name:cym_x_preferred":[
        "Adamstown"
    ],
    "name:deu_x_preferred":[
        "Adamstown"
    ],
    "name:fry_x_preferred":[
        "Adamstown"
    ],
    "name:hun_x_preferred":[
        "Adamstown"
    ],
    "name:kor_x_preferred":[
        "\uc560\ub364\uc2a4\ud0c0\uc6b4"
    ],
    "name:nld_x_preferred":[
        "Adamstown"
    ],
    "name:pol_x_preferred":[
        "Adamstown"
    ],
    "name:rus_x_preferred":[
        "\u0410\u0434\u0430\u043c\u0441\u0442\u0430\u0443\u043d"
    ],
    "name:spa_x_preferred":[
        "Adamstown"
    ],
    "name:srp_x_preferred":[
        "\u0410\u0434\u0430\u043c\u0441\u0442\u0430\u0443\u043d"
    ],
    "name:swe_x_preferred":[
        "Adamstown"
    ],
    "name:zho_x_preferred":[
        "\u4e9a\u5f53\u65af\u6566"
    ],
    "wof:name":"Adamstown",
    "wof:placetype":"locality"
},
  "geometry": {"coordinates":[-6.74256,53.53842],"type":"Point"}
}