{
  "type": "Feature",
  "properties": {
    "gn:admin1_code":"L",
    "gn:admin2_code":"31",
    "gn:asciiname":"Knockananna",
    "gn:country_code":"IE",
    "gn:dem":213,
    "gn:feature_class":"P",
    "gn:feature_code":"PPL",
    "gn:name":"Knockananna",
    "gn:population":141,
    "gn:timezone":"Europe/Dublin",
    "iso:country":"IE",
    "wof:name":"Knockananna",
    "wof:placetype":"locality",
    "wof:population":141
},
  "geometry": {"coordinates":[-6.49672,52.87311999999999],"type":"Point"}
}