{
  "type": "Feature",
  "properties": {
    "gn:admin1_code":"L",
    "gn:admin2_code":"13.0",
    "gn:asciiname":"Lawcus",
    "gn:country_code":"IE",
    "gn:dem":45,
    "gn:feature_class":"P",
    "gn:feature_code":"PPL",
    "gn:name":"Lawcus",
    "gn:population":355,
    "gn:timezone":"Europe/Dublin",
    "iso:country":"IE",
    "name:und_x_variant":[
        "Lawcus-Stoneyford"
    ],
    "wof:name":"Lawcus",
    "wof:placetype":"locality",
    "wof:population":355
},
  "geometry": {"coordinates":[-7.22941,52.53596],"type":"Point"}
}