{
  "type": "Feature",
  "properties": {
    "gn:admin1_code":"U",
    "gn:admin2_code":"02",
    "gn:asciiname":"Tirlahode Lower",
    "gn:country_code":"IE",
    "gn:dem":170,
    "gn:feature_class":"P",
    "gn:feature_code":"PPL",
    "gn:name":"Tirlahode Lower",
    "gn:population":0,
    "gn:timezone":"Europe/Dublin",
    "iso:country":"IE",
    "wof:name":"Tirlahode Lower",
    "wof:placetype":"locality"
},
  "geometry": {"coordinates":[-7.18639,53.94611],"type":"Point"}
}