{
  "type": "Feature",
  "properties": {
    "gn:admin1_code":"C",
    "gn:admin2_code":"10",
    "gn:asciiname":"Peterswell",
    "gn:cc2":"IE",
    "gn:country_code":"IE",
    "gn:dem":41,
    "gn:feature_class":"P",
    "gn:feature_code":"PPL",
    "gn:name":"Peterswell",
    "gn:population":0,
    "gn:timezone":"Europe/Dublin",
    "iso:country":"IE",
    "name:eng_x_preferred":[
        "Peterswell"
    ],
    "name:gle_x_preferred":[
        "Tobar Pheadair"
    ],
    "wof:name":"Peterswell",
    "wof:placetype":"locality"
},
  "geometry": {"coordinates":[-8.74139,53.115],"type":"Point"}
}