{
  "type": "Feature",
  "properties": {
    "gn:admin1_code":"M",
    "gn:admin2_code":"04",
    "gn:asciiname":"Barrykilla",
    "gn:country_code":"IE",
    "gn:dem":15,
    "gn:feature_class":"P",
    "gn:feature_code":"PPL",
    "gn:name":"Barrykilla",
    "gn:population":0,
    "gn:timezone":"Europe/Dublin",
    "iso:country":"IE",
    "wof:name":"Barrykilla",
    "wof:placetype":"locality"
},
  "geometry": {"coordinates":[-8.16833,51.84417],"type":"Point"}
}