{
  "type": "Feature",
  "properties": {
    "iso:country":"IE",
    "name:eng_x_preferred":[
        "Clonea"
    ],
    "qs:a0":"Ireland",
    "qs:a1":"*Waterford",
    "qs:a1r":"0",
    "qs:adm0":"Ireland",
    "qs:la_lc":"*",
    "qs:level":"locality",
    "qs:loc":"Clonea",
    "qs:loc_alt":"Clonea",
    "qs:pop":0,
    "qs:type":"buffered point",
    "wof:lang":[
        "eng"
    ],
    "wof:name":"Clonea",
    "wof:placetype":"locality"
},
  "geometry": {"coordinates":[-7.436942,52.278881],"type":"Point"}
}