{
  "type": "Feature",
  "properties": {
    "gn:admin1_code":"C",
    "gn:admin2_code":"20.0",
    "gn:asciiname":"Cloontia",
    "gn:country_code":"IE",
    "gn:dem":100,
    "gn:feature_class":"P",
    "gn:feature_code":"PPL",
    "gn:name":"Cloontia",
    "gn:population":0,
    "gn:timezone":"Europe/Dublin",
    "iso:country":"IE",
    "wof:name":"Cloontia",
    "wof:placetype":"locality"
},
  "geometry": {"coordinates":[-8.6175,53.97806],"type":"Point"}
}