{
  "type": "Feature",
  "properties": {
    "gn:admin1_code":"M",
    "gn:admin2_code":"04",
    "gn:asciiname":"Whitewell",
    "gn:country_code":"IE",
    "gn:dem":21,
    "gn:feature_class":"P",
    "gn:feature_code":"PPL",
    "gn:name":"Whitewell",
    "gn:population":0,
    "gn:timezone":"Europe/Dublin",
    "iso:country":"IE",
    "wof:name":"Whitewell",
    "wof:placetype":"locality"
},
  "geometry": {"coordinates":[-8.16722,51.85194],"type":"Point"}
}