{
  "type": "Feature",
  "properties": {
    "gn:admin1_code":"C",
    "gn:admin2_code":"20.0",
    "gn:asciiname":"Letterlough",
    "gn:country_code":"IE",
    "gn:dem":48,
    "gn:feature_class":"P",
    "gn:feature_code":"PPL",
    "gn:name":"Letterlough",
    "gn:population":0,
    "gn:timezone":"Europe/Dublin",
    "iso:country":"IE",
    "wof:name":"Letterlough",
    "wof:placetype":"locality"
},
  "geometry": {"coordinates":[-9.49833,53.90995],"type":"Point"}
}