{
  "type": "Feature",
  "properties": {
    "gn:admin1_code":"M",
    "gn:admin2_code":"11",
    "gn:asciiname":"Paddock",
    "gn:country_code":"IE",
    "gn:dem":31,
    "gn:feature_class":"P",
    "gn:feature_code":"PPL",
    "gn:name":"Paddock",
    "gn:population":0,
    "gn:timezone":"Europe/Dublin",
    "iso:country":"IE",
    "name:eng_x_preferred":[
        "Paddock"
    ],
    "name:gle_x_preferred":[
        "An Paideac"
    ],
    "wof:name":"Paddock",
    "wof:placetype":"locality"
},
  "geometry": {"coordinates":[-9.76667,52.44583000000001],"type":"Point"}
}