{
  "type": "Feature",
  "properties": {
    "gn:gn_country":"IE",
    "gn:gn_fcode":"PPL",
    "gn:gn_pop":0,
    "iso:country":"IE",
    "name:eng_x_preferred":[
        "Blackwater"
    ],
    "name:eus_x_preferred":[
        "Blackwater"
    ],
    "name:gle_x_preferred":[
        "An Abhainn Dubh"
    ],
    "name:nld_x_preferred":[
        "Blackwater"
    ],
    "name:rus_x_preferred":[
        "\u0411\u043b\u044d\u043a\u0443\u043e\u0442\u0435\u0440"
    ],
    "name:urd_x_preferred":[
        "\u0628\u0644\u06cc\u06a9 \u0648\u0627\u0679\u0631\u060c \u06a9\u0627\u0624\u0646\u0679\u06cc \u0648\u06cc\u06a9\u0633\u0641\u0648\u0631\u0688"
    ],
    "name:urd_x_variant":[
        "\u0628\u0644\u06cc\u06a9 \u0648\u0627\u0679\u0631"
    ],
    "qs_pg:aaroncc":"IE",
    "qs_pg:gn_country":"IE",
    "qs_pg:gn_fcode":"PPL",
    "qs_pg:gn_pop":0,
    "qs_pg:name":"Blackwater",
    "qs_pg:name_adm0":"Ireland",
    "qs_pg:name_adm1":"Wexford",
    "qs_pg:photos":408,
    "qs_pg:photos_1k":83,
    "qs_pg:photos_9k":2,
    "qs_pg:photos_9r":5,
    "qs_pg:photos_all":408,
    "qs_pg:photos_sr":6,
    "qs_pg:pop_sr":0,
    "qs_pg:qs_pg_placetype":"locality",
    "qs_pg:qs_pg_placetype_gp":"Town",
    "qs_pg:woe_adm0":23424803,
    "woe:adm0_id":23424803,
    "woe:name_adm0":"Ireland",
    "woe:name_adm1":"Wexford",
    "woe:placetype":"Town",
    "wof:name":"Blackwater",
    "wof:placetype":"locality"
},
  "geometry": {"coordinates":[-6.34528,52.44667],"type":"Point"}
}