{
  "type": "Feature",
  "properties": {
    "gn:admin1_code":"M",
    "gn:admin2_code":"11",
    "gn:asciiname":"Kilclogherane",
    "gn:country_code":"IE",
    "gn:dem":51,
    "gn:feature_class":"P",
    "gn:feature_code":"PPLL",
    "gn:name":"Kilclogherane",
    "gn:population":0,
    "gn:timezone":"Europe/Dublin",
    "iso:country":"IE",
    "wof:name":"Kilclogherane",
    "wof:placetype":"locality"
},
  "geometry": {"coordinates":[-9.63583,52.08861],"type":"Point"}
}