{
  "type": "Feature",
  "properties": {
    "gn:admin1_code":"L",
    "gn:admin2_code":"21.0",
    "gn:asciiname":"Mullaghboy",
    "gn:country_code":"IE",
    "gn:dem":57,
    "gn:feature_class":"P",
    "gn:feature_code":"PPL",
    "gn:name":"Mullaghboy",
    "gn:population":0,
    "gn:timezone":"Europe/Dublin",
    "iso:country":"IE",
    "wof:name":"Mullaghboy",
    "wof:placetype":"locality"
},
  "geometry": {"coordinates":[-6.70765,53.64501],"type":"Point"}
}