{
  "type": "Feature",
  "properties": {
    "gn:admin1_code":"L",
    "gn:admin2_code":"21.0",
    "gn:asciiname":"Mullaghboy",
    "gn:country_code":"IE",
    "gn:dem":57,
    "gn:feature_class":"P",
    "gn:feature_code":"PPL",
    "gn:name":"Mullaghboy",
    "gn:population":0,
    "gn:timezone":"Europe/Dublin",
    "iso:country":"IE",
    "name:eus_x_preferred":[
        "Mullaghboy"
    ],
    "name:fas_x_preferred":[
        "\u0645\u0648\u0644\u0627\u06af\u0628\u0648\u06cc"
    ],
    "name:gla_x_preferred":[
        "Mullach Bu\u00ed"
    ],
    "name:gle_x_preferred":[
        "Mullach Bu\u00ed"
    ],
    "name:msa_x_preferred":[
        "Mullaghboy"
    ],
    "name:pli_x_preferred":[
        "\u092e\u0941\u0932\u094d\u0932\u093e\u0918\u094d\u092c\u094b\u092f"
    ],
    "name:spa_x_preferred":[
        "Mullaghboy"
    ],
    "wof:name":"Mullaghboy",
    "wof:placetype":"locality"
},
  "geometry": {"coordinates":[-6.70765,53.64501],"type":"Point"}
}