{
  "type": "Feature",
  "properties": {
    "gn:admin1_code":"M",
    "gn:admin2_code":"04",
    "gn:asciiname":"Knockyhena",
    "gn:country_code":"IE",
    "gn:dem":184,
    "gn:feature_class":"P",
    "gn:feature_code":"PPL",
    "gn:name":"Knockyhena",
    "gn:population":0,
    "gn:timezone":"Europe/Dublin",
    "iso:country":"IE",
    "wof:name":"Knockyhena",
    "wof:placetype":"locality"
},
  "geometry": {"coordinates":[-9.21667,52.13333],"type":"Point"}
}