{
  "type": "Feature",
  "properties": {
    "gn:admin1_code":"U",
    "gn:admin2_code":"06",
    "gn:asciiname":"Stranagoppoge",
    "gn:country_code":"IE",
    "gn:dem":149,
    "gn:feature_class":"P",
    "gn:feature_code":"PPLL",
    "gn:name":"Stranagoppoge",
    "gn:population":0,
    "gn:timezone":"Europe/Dublin",
    "iso:country":"IE",
    "name:eng_x_preferred":[
        "Stranagoppoge"
    ],
    "name:gle_x_preferred":[
        "Srath na gCop\u00f3g"
    ],
    "name:und_x_variant":[
        "Stranagappoge"
    ],
    "wof:name":"Stranagoppoge",
    "wof:placetype":"locality"
},
  "geometry": {"coordinates":[-7.23722,55.17471999999999],"type":"Point"}
}