{
  "type": "Feature",
  "properties": {
    "gn:admin1_code":"U",
    "gn:admin2_code":"06",
    "gn:asciiname":"Meenasrona",
    "gn:country_code":"IE",
    "gn:dem":251,
    "gn:feature_class":"P",
    "gn:feature_code":"PPLL",
    "gn:name":"Meenasrona",
    "gn:population":0,
    "gn:timezone":"Europe/Dublin",
    "iso:country":"IE",
    "name:eng_x_preferred":[
        "Meenasrona"
    ],
    "name:gle_x_preferred":[
        "M\u00edn na Sr\u00f3na"
    ],
    "wof:name":"Meenasrona",
    "wof:placetype":"locality"
},
  "geometry": {"coordinates":[-7.9475,54.87083000000001],"type":"Point"}
}