{
  "type": "Feature",
  "properties": {
    "gn:admin1_code":"M",
    "gn:admin2_code":"04",
    "gn:asciiname":"Greenhall",
    "gn:country_code":"IE",
    "gn:dem":106,
    "gn:feature_class":"P",
    "gn:feature_code":"PPL",
    "gn:name":"Greenhall",
    "gn:population":0,
    "gn:timezone":"Europe/Dublin",
    "iso:country":"IE",
    "wof:name":"Greenhall",
    "wof:placetype":"locality"
},
  "geometry": {"coordinates":[-8.80333,52.21333],"type":"Point"}
}