{
  "type": "Feature",
  "properties": {
    "gn:admin1_code":"C",
    "gn:admin2_code":"14.0",
    "gn:asciiname":"Corryolus",
    "gn:country_code":"IE",
    "gn:dem":43,
    "gn:feature_class":"P",
    "gn:feature_code":"PPLL",
    "gn:name":"Corryolus",
    "gn:population":0,
    "gn:timezone":"Europe/Dublin",
    "iso:country":"IE",
    "wof:name":"Corryolus",
    "wof:placetype":"locality"
},
  "geometry": {"coordinates":[-8.09167,53.95472],"type":"Point"}
}