{
  "type": "Feature",
  "properties": {
    "gn:admin1_code":"U",
    "gn:admin2_code":"02",
    "gn:asciiname":"Eylagh",
    "gn:country_code":"IE",
    "gn:dem":83,
    "gn:feature_class":"P",
    "gn:feature_code":"PPLL",
    "gn:name":"Eylagh",
    "gn:population":0,
    "gn:timezone":"Europe/Dublin",
    "iso:country":"IE",
    "wof:name":"Eylagh",
    "wof:placetype":"locality"
},
  "geometry": {"coordinates":[-7.6025,54.04472],"type":"Point"}
}