{
  "type": "Feature",
  "properties": {
    "gn:admin1_code":"L",
    "gn:admin2_code":"31.0",
    "gn:asciiname":"Kelsha Bridge",
    "gn:country_code":"IE",
    "gn:dem":160,
    "gn:feature_class":"P",
    "gn:feature_code":"PPL",
    "gn:name":"Kelsha Bridge",
    "gn:population":0,
    "gn:timezone":"Europe/Dublin",
    "iso:country":"IE",
    "wof:name":"Kelsha Bridge",
    "wof:placetype":"locality"
},
  "geometry": {"coordinates":[-6.605,52.98861],"type":"Point"}
}