{
  "type": "Feature",
  "properties": {
    "gn:admin1_code":"L",
    "gn:admin2_code":"29",
    "gn:asciiname":"Tang",
    "gn:country_code":"IE",
    "gn:dem":43,
    "gn:feature_class":"P",
    "gn:feature_code":"PPL",
    "gn:name":"Tang",
    "gn:population":0,
    "gn:timezone":"Europe/Dublin",
    "iso:country":"IE",
    "name:eus_x_preferred":[
        "Tang"
    ],
    "name:gle_x_preferred":[
        "An Teanga"
    ],
    "name:rus_x_preferred":[
        "\u0422\u0430\u043d\u0433"
    ],
    "wof:name":"Tang",
    "wof:placetype":"locality"
},
  "geometry": {"coordinates":[-7.78333,53.53333000000001],"type":"Point"}
}