{
  "type": "Feature",
  "properties": {
    "gn:admin1_code":"M",
    "gn:admin2_code":"04",
    "gn:asciiname":"Ballinvuskig",
    "gn:country_code":"IE",
    "gn:dem":205,
    "gn:feature_class":"P",
    "gn:feature_code":"PPL",
    "gn:name":"Ballinvuskig",
    "gn:population":0,
    "gn:timezone":"Europe/Dublin",
    "iso:country":"IE",
    "wof:name":"Ballinvuskig",
    "wof:placetype":"locality"
},
  "geometry": {"coordinates":[-8.60194,52.10194],"type":"Point"}
}