{
  "type": "Feature",
  "properties": {
    "gn:admin1_code":"M",
    "gn:admin2_code":"04",
    "gn:asciiname":"Carrigbaun Cross Roads",
    "gn:country_code":"IE",
    "gn:dem":76,
    "gn:feature_class":"P",
    "gn:feature_code":"PPLL",
    "gn:name":"Carrigbaun Cross Roads",
    "gn:population":0,
    "gn:timezone":"Europe/Dublin",
    "iso:country":"IE",
    "wof:name":"Carrigbaun Cross Roads",
    "wof:placetype":"locality"
},
  "geometry": {"coordinates":[-9.17806,51.63583],"type":"Point"}
}