{
  "type": "Feature",
  "properties": {
    "gn:admin1_code":"C",
    "gn:admin2_code":"14.0",
    "gn:asciiname":"Annagh Upper",
    "gn:country_code":"IE",
    "gn:dem":47,
    "gn:feature_class":"P",
    "gn:feature_code":"PPL",
    "gn:name":"Annagh Upper",
    "gn:population":0,
    "gn:timezone":"Europe/Dublin",
    "iso:country":"IE",
    "wof:name":"Annagh Upper",
    "wof:placetype":"locality"
},
  "geometry": {"coordinates":[-8.04556,54.18333000000001],"type":"Point"}
}