{
  "type": "Feature",
  "properties": {
    "gn:admin1_code":"L",
    "gn:admin2_code":"15.0",
    "gn:asciiname":"Killenard",
    "gn:country_code":"IE",
    "gn:dem":107,
    "gn:feature_class":"P",
    "gn:feature_code":"PPL",
    "gn:name":"Killenard",
    "gn:population":622,
    "gn:timezone":"Europe/Dublin",
    "iso:country":"IE",
    "name:ceb_x_preferred":[
        "Killenard"
    ],
    "name:spa_x_preferred":[
        "Killenard"
    ],
    "name:swe_x_preferred":[
        "Killenard"
    ],
    "wof:name":"Killenard",
    "wof:placetype":"locality",
    "wof:population":622
},
  "geometry": {"coordinates":[-7.14861,53.13306],"type":"Point"}
}