{
  "type": "Feature",
  "properties": {
    "gn:admin1_code":"M",
    "gn:admin2_code":"11",
    "gn:asciiname":"Kilcow",
    "gn:country_code":"IE",
    "gn:dem":34,
    "gn:feature_class":"P",
    "gn:feature_code":"PPL",
    "gn:name":"Kilcow",
    "gn:population":0,
    "gn:timezone":"Europe/Dublin",
    "iso:country":"IE",
    "wof:name":"Kilcow",
    "wof:placetype":"locality"
},
  "geometry": {"coordinates":[-9.49139,52.21806],"type":"Point"}
}