{
  "type": "Feature",
  "properties": {
    "gn:admin1_code":"L",
    "gn:admin2_code":"35.0",
    "gn:asciiname":"Cappoge",
    "gn:country_code":"IE",
    "gn:dem":78,
    "gn:feature_class":"P",
    "gn:feature_code":"PPL",
    "gn:name":"Cappoge",
    "gn:population":0,
    "gn:timezone":"Europe/Dublin",
    "iso:country":"IE",
    "wof:name":"Cappoge",
    "wof:placetype":"locality"
},
  "geometry": {"coordinates":[-6.32917,53.40083000000001],"type":"Point"}
}