{
  "type": "Feature",
  "properties": {
    "gn:admin1_code":"M",
    "gn:admin2_code":"26",
    "gn:asciiname":"Barrettstown",
    "gn:country_code":"IE",
    "gn:dem":84,
    "gn:feature_class":"P",
    "gn:feature_code":"PPL",
    "gn:name":"Barrettstown",
    "gn:population":0,
    "gn:timezone":"Europe/Dublin",
    "iso:country":"IE",
    "wof:name":"Barrettstown",
    "wof:placetype":"locality"
},
  "geometry": {"coordinates":[-7.73139,52.46056],"type":"Point"}
}