{
  "type": "Feature",
  "properties": {
    "iso:country":"IE",
    "qs_pg:aaroncc":"IE",
    "qs_pg:name":"Maynooth",
    "qs_pg:name_adm0":"Ireland",
    "qs_pg:name_adm1":"Kildare",
    "qs_pg:photos":6,
    "qs_pg:photos_1k":1,
    "qs_pg:photos_9k":22,
    "qs_pg:photos_9r":14,
    "qs_pg:photos_all":5006,
    "qs_pg:photos_sr":1,
    "qs_pg:pop_sr":0,
    "qs_pg:qs_pg_placetype":"localadmin",
    "qs_pg:qs_pg_placetype_gp":"LocalAdmin",
    "qs_pg:woe_adm0":23424803,
    "woe:adm0_id":23424803,
    "woe:name_adm0":"Ireland",
    "woe:name_adm1":"Kildare",
    "woe:placetype":"LocalAdmin",
    "wof:name":"Maynooth",
    "wof:placetype":"localadmin"
},
  "geometry": {"coordinates":[-6.5942,53.380704],"type":"Point"}
}