{
  "type": "Feature",
  "properties": {
    "iso:country":"IE",
    "name:bre_x_preferred":[
        "Maigh Nuad"
    ],
    "name:bul_x_preferred":[
        "\u041c\u0435\u0439\u043d\u0443\u0442"
    ],
    "name:cat_x_preferred":[
        "Maynooth"
    ],
    "name:ceb_x_preferred":[
        "Maynooth"
    ],
    "name:dan_x_preferred":[
        "Maynooth"
    ],
    "name:deu_x_preferred":[
        "Maynooth"
    ],
    "name:eus_x_preferred":[
        "Maynooth"
    ],
    "name:fas_x_preferred":[
        "\u0645\u0646\u0648\u062b"
    ],
    "name:fra_x_preferred":[
        "Maynooth"
    ],
    "name:gle_x_preferred":[
        "Maigh Nuad"
    ],
    "name:heb_x_preferred":[
        "\u05de\u05d9\u05d9\u05e0\u05d5\u05ea'"
    ],
    "name:hun_x_preferred":[
        "Maynooth"
    ],
    "name:ind_x_preferred":[
        "Maynooth"
    ],
    "name:ita_x_preferred":[
        "Maynooth"
    ],
    "name:jpn_x_preferred":[
        "\u30e1\u30a4\u30cc\u30fc\u30b9"
    ],
    "name:lat_x_preferred":[
        "Manutia"
    ],
    "name:lit_x_preferred":[
        "Meinutas"
    ],
    "name:nld_x_preferred":[
        "Maynooth"
    ],
    "name:pol_x_preferred":[
        "Maynooth"
    ],
    "name:por_x_preferred":[
        "Maynooth"
    ],
    "name:rus_x_preferred":[
        "\u041c\u0435\u0439\u043d\u0443\u0442"
    ],
    "name:sco_x_preferred":[
        "Maynooth"
    ],
    "name:slk_x_preferred":[
        "Maynooth"
    ],
    "name:spa_x_preferred":[
        "Maynooth"
    ],
    "name:swe_x_preferred":[
        "Maynooth"
    ],
    "name:urd_x_preferred":[
        "\u0645\u06cc\u0646\u0648\u062a\u06be"
    ],
    "name:zho_x_preferred":[
        "\u6885\u52aa\u65af"
    ],
    "qs_pg:aaroncc":"IE",
    "qs_pg:name":"Maynooth",
    "qs_pg:name_adm0":"Ireland",
    "qs_pg:name_adm1":"Kildare",
    "qs_pg:photos":6,
    "qs_pg:photos_1k":1,
    "qs_pg:photos_9k":22,
    "qs_pg:photos_9r":14,
    "qs_pg:photos_all":5006,
    "qs_pg:photos_sr":1,
    "qs_pg:pop_sr":0,
    "qs_pg:qs_pg_placetype":"localadmin",
    "qs_pg:qs_pg_placetype_gp":"LocalAdmin",
    "qs_pg:woe_adm0":23424803,
    "woe:adm0_id":23424803,
    "woe:name_adm0":"Ireland",
    "woe:name_adm1":"Kildare",
    "woe:placetype":"LocalAdmin",
    "wof:name":"Maynooth",
    "wof:placetype":"localadmin"
},
  "geometry": {"coordinates":[-6.5942,53.380704],"type":"Point"}
}