{
  "type": "Feature",
  "properties": {
    "gn:admin1_code":"L",
    "gn:admin2_code":"30.0",
    "gn:asciiname":"Barntown",
    "gn:country_code":"IE",
    "gn:dem":62,
    "gn:feature_class":"P",
    "gn:feature_code":"PPL",
    "gn:name":"Barntown",
    "gn:population":461,
    "gn:timezone":"Europe/Dublin",
    "iso:country":"IE",
    "name:ceb_x_preferred":[
        "Barntown"
    ],
    "name:rus_x_preferred":[
        "\u0411\u0430\u0440\u043d\u0442\u0430\u0443\u043d"
    ],
    "name:swe_x_preferred":[
        "Barntown"
    ],
    "wof:name":"Barntown",
    "wof:placetype":"locality",
    "wof:population":461
},
  "geometry": {"coordinates":[-6.53086,52.341],"type":"Point"}
}