{
  "type": "Feature",
  "properties": {
    "gn:admin1_code":"U",
    "gn:admin2_code":"06",
    "gn:asciiname":"Aghalenty",
    "gn:country_code":"IE",
    "gn:dem":127,
    "gn:feature_class":"P",
    "gn:feature_code":"PPLL",
    "gn:name":"Aghalenty",
    "gn:population":0,
    "gn:timezone":"Europe/Dublin",
    "iso:country":"IE",
    "wof:name":"Aghalenty",
    "wof:placetype":"locality"
},
  "geometry": {"coordinates":[-7.68389,54.99],"type":"Point"}
}