{
  "type": "Feature",
  "properties": {
    "gn:admin1_code":"U",
    "gn:admin2_code":"06",
    "gn:asciiname":"Losset",
    "gn:country_code":"IE",
    "gn:dem":102,
    "gn:feature_class":"P",
    "gn:feature_code":"PPLL",
    "gn:name":"Losset",
    "gn:population":0,
    "gn:timezone":"Europe/Dublin",
    "iso:country":"IE",
    "wof:name":"Losset",
    "wof:placetype":"locality"
},
  "geometry": {"coordinates":[-7.88278,55.03167],"type":"Point"}
}