{
  "type": "Feature",
  "properties": {
    "iso:country":"IE",
    "qs_pg:aaroncc":"IE",
    "qs_pg:name":"Garadice",
    "qs_pg:name_adm0":"Ireland",
    "qs_pg:name_adm1":"Leitrim",
    "qs_pg:photos":1,
    "qs_pg:photos_1k":1,
    "qs_pg:photos_9k":1,
    "qs_pg:photos_9r":1,
    "qs_pg:photos_all":1,
    "qs_pg:photos_sr":1,
    "qs_pg:pop_sr":0,
    "qs_pg:qs_pg_placetype":"locality",
    "qs_pg:qs_pg_placetype_gp":"Town",
    "qs_pg:woe_adm0":23424803,
    "woe:adm0_id":23424803,
    "woe:name_adm0":"Ireland",
    "woe:name_adm1":"Leitrim",
    "woe:placetype":"Town",
    "wof:name":"Garadice",
    "wof:placetype":"locality"
},
  "geometry": {"coordinates":[-7.747266,54.060966],"type":"Point"}
}