{
  "type": "Feature",
  "properties": {
    "gn:admin1_code":"L",
    "gn:admin2_code":"13",
    "gn:asciiname":"Ballymartin",
    "gn:country_code":"IE",
    "gn:dem":218,
    "gn:feature_class":"P",
    "gn:feature_code":"PPL",
    "gn:name":"Ballymartin",
    "gn:population":0,
    "gn:timezone":"Europe/Dublin",
    "iso:country":"IE",
    "name:deu_x_preferred":[
        "Ballymartin"
    ],
    "name:spa_x_preferred":[
        "Ballymartin"
    ],
    "wof:name":"Ballymartin",
    "wof:placetype":"locality"
},
  "geometry": {"coordinates":[-7.10667,52.3925],"type":"Point"}
}