{
  "type": "Feature",
  "properties": {
    "gn:admin1_code":"C",
    "gn:admin2_code":"20.0",
    "gn:asciiname":"Surgeview",
    "gn:country_code":"IE",
    "gn:dem":36,
    "gn:feature_class":"P",
    "gn:feature_code":"PPL",
    "gn:name":"Surgeview",
    "gn:population":0,
    "gn:timezone":"Europe/Dublin",
    "iso:country":"IE",
    "name:eng_x_preferred":[
        "Surgeview"
    ],
    "name:gle_x_preferred":[
        "Toin na hOlla\u00ed"
    ],
    "wof:name":"Surgeview",
    "wof:placetype":"locality"
},
  "geometry": {"coordinates":[-10.11973,54.10452],"type":"Point"}
}