{
  "type": "Feature",
  "properties": {
    "gn:admin1_code":"U",
    "gn:admin2_code":"06",
    "gn:asciiname":"Inch",
    "gn:country_code":"IE",
    "gn:dem":8,
    "gn:feature_class":"P",
    "gn:feature_code":"PPL",
    "gn:name":"Inch",
    "gn:population":0,
    "gn:timezone":"Europe/Dublin",
    "iso:country":"IE",
    "name:eng_x_preferred":[
        "Inch"
    ],
    "name:gle_x_preferred":[
        "An Inis"
    ],
    "wof:name":"Inch",
    "wof:placetype":"locality"
},
  "geometry": {"coordinates":[-7.48056,55.07028],"type":"Point"}
}