{
  "type": "Feature",
  "properties": {
    "gn:admin1_code":"L",
    "gn:admin2_code":"15.0",
    "gn:asciiname":"Garrymaddock",
    "gn:country_code":"IE",
    "gn:dem":72,
    "gn:feature_class":"P",
    "gn:feature_code":"PPL",
    "gn:name":"Garrymaddock",
    "gn:population":0,
    "gn:timezone":"Europe/Dublin",
    "iso:country":"IE",
    "wof:name":"Garrymaddock",
    "wof:placetype":"locality"
},
  "geometry": {"coordinates":[-7.16528,53.06889],"type":"Point"}
}