{
  "type": "Feature",
  "properties": {
    "gn:admin1_code":"L",
    "gn:admin2_code":"29.0",
    "gn:asciiname":"Glonickilvant",
    "gn:country_code":"IE",
    "gn:dem":103,
    "gn:feature_class":"P",
    "gn:feature_code":"PPL",
    "gn:name":"Glonickilvant",
    "gn:population":0,
    "gn:timezone":"Europe/Dublin",
    "iso:country":"IE",
    "wof:name":"Glonickilvant",
    "wof:placetype":"locality"
},
  "geometry": {"coordinates":[-7.20169,53.5348],"type":"Point"}
}