{
  "type": "Feature",
  "properties": {
    "gn:gn_country":"IE",
    "gn:gn_fcode":"PPL",
    "gn:gn_pop":0,
    "gn:population":2061,
    "iso:country":"IE",
    "name:bul_x_preferred":[
        "\u0411\u0430\u043b\u0442\u0438\u043d\u0433\u043b\u0430\u0441"
    ],
    "name:cat_x_preferred":[
        "Baltinglass"
    ],
    "name:dut_x_preferred":[
        "Baltinglass"
    ],
    "name:eng_x_preferred":[
        "Baltinglass"
    ],
    "name:fre_x_preferred":[
        "Baltinglass"
    ],
    "name:ger_x_preferred":[
        "Baltinglass"
    ],
    "name:gle_x_preferred":[
        "Bealach Conglais"
    ],
    "name:ita_x_preferred":[
        "Baltinglass"
    ],
    "name:lit_x_preferred":[
        "Baltinglasas"
    ],
    "name:pol_x_preferred":[
        "Baltinglass"
    ],
    "name:rus_x_preferred":[
        "\u0411\u0430\u043b\u0442\u0438\u043d\u0433\u043b\u0430\u0441\u0441"
    ],
    "name:slo_x_preferred":[
        "Baltinglass"
    ],
    "name:swe_x_preferred":[
        "Baltinglass"
    ],
    "qs_pg:aaroncc":"IE",
    "qs_pg:gn_country":"IE",
    "qs_pg:gn_fcode":"PPL",
    "qs_pg:gn_pop":0,
    "qs_pg:name":"Baltinglass",
    "qs_pg:name_adm0":"Ireland",
    "qs_pg:name_adm1":"Wicklow",
    "qs_pg:photos":279,
    "qs_pg:photos_1k":57,
    "qs_pg:photos_9k":1,
    "qs_pg:photos_9r":4,
    "qs_pg:photos_all":279,
    "qs_pg:photos_sr":5,
    "qs_pg:pop_sr":0,
    "qs_pg:qs_pg_placetype":"locality",
    "qs_pg:qs_pg_placetype_gp":"Town",
    "qs_pg:woe_adm0":23424803,
    "woe:adm0_id":23424803,
    "woe:name_adm0":"Ireland",
    "woe:name_adm1":"Wicklow",
    "woe:placetype":"Town",
    "wof:name":"Baltinglass",
    "wof:placetype":"locality",
    "wof:population":2061
},
  "geometry": {"coordinates":[-6.70917,52.93722],"type":"Point"}
}