{
  "type": "Feature",
  "properties": {
    "gn:admin1_code":"C",
    "gn:admin2_code":"20.0",
    "gn:asciiname":"Conaghra",
    "gn:country_code":"IE",
    "gn:dem":138,
    "gn:feature_class":"P",
    "gn:feature_code":"PPLL",
    "gn:name":"Conaghra",
    "gn:population":0,
    "gn:timezone":"Europe/Dublin",
    "iso:country":"IE",
    "name:eng_x_preferred":[
        "Conaghra"
    ],
    "name:gle_x_preferred":[
        "Conach R\u00e9idh"
    ],
    "wof:name":"Conaghra",
    "wof:placetype":"locality"
},
  "geometry": {"coordinates":[-9.30917,54.27721999999999],"type":"Point"}
}