{
  "type": "Feature",
  "properties": {
    "gn:admin1_code":"M",
    "gn:admin2_code":"11",
    "gn:asciiname":"Creeveen",
    "gn:country_code":"IE",
    "gn:dem":217,
    "gn:feature_class":"P",
    "gn:feature_code":"PPL",
    "gn:name":"Creeveen",
    "gn:population":0,
    "gn:timezone":"Europe/Dublin",
    "iso:country":"IE",
    "wof:name":"Creeveen",
    "wof:placetype":"locality"
},
  "geometry": {"coordinates":[-9.93639,52.00194000000001],"type":"Point"}
}