{
  "type": "Feature",
  "properties": {
    "gn:admin1_code":"C",
    "gn:admin2_code":"20.0",
    "gn:asciiname":"Tullaghaunnashammer",
    "gn:country_code":"IE",
    "gn:dem":3,
    "gn:feature_class":"P",
    "gn:feature_code":"PPL",
    "gn:name":"Tullaghaunnashammer",
    "gn:population":0,
    "gn:timezone":"Europe/Dublin",
    "iso:country":"IE",
    "wof:name":"Tullaghaunnashammer",
    "wof:placetype":"locality"
},
  "geometry": {"coordinates":[-9.83402,54.11743000000001],"type":"Point"}
}