{
  "type": "Feature",
  "properties": {
    "gn:gn_country":"IE",
    "gn:gn_fcode":"PPL",
    "gn:gn_pop":0,
    "iso:country":"IE",
    "qs_pg:aaroncc":"IE",
    "qs_pg:gn_country":"IE",
    "qs_pg:gn_fcode":"PPL",
    "qs_pg:gn_pop":0,
    "qs_pg:name":"Derryvillane",
    "qs_pg:name_adm0":"Ireland",
    "qs_pg:name_adm1":"Cork",
    "qs_pg:photos":1,
    "qs_pg:photos_1k":1,
    "qs_pg:photos_9k":1,
    "qs_pg:photos_9r":1,
    "qs_pg:photos_all":1,
    "qs_pg:photos_sr":1,
    "qs_pg:pop_sr":0,
    "qs_pg:qs_pg_placetype":"localadmin",
    "qs_pg:qs_pg_placetype_gp":"LocalAdmin",
    "qs_pg:woe_adm0":23424803,
    "woe:adm0_id":23424803,
    "woe:name_adm0":"Ireland",
    "woe:name_adm1":"Cork",
    "woe:placetype":"LocalAdmin",
    "wof:name":"Derryvillane",
    "wof:placetype":"localadmin"
},
  "geometry": {"coordinates":[-8.38556,52.21972],"type":"Point"}
}