{
  "type": "Feature",
  "properties": {
    "gn:admin1_code":"L",
    "gn:admin2_code":"12.0",
    "gn:asciiname":"Bigstone",
    "gn:country_code":"IE",
    "gn:dem":112,
    "gn:feature_class":"P",
    "gn:feature_code":"PPL",
    "gn:name":"Bigstone",
    "gn:population":0,
    "gn:timezone":"Europe/Dublin",
    "iso:country":"IE",
    "wof:name":"Bigstone",
    "wof:placetype":"locality"
},
  "geometry": {"coordinates":[-6.75583,52.90389],"type":"Point"}
}