{
  "type": "Feature",
  "properties": {
    "gn:admin1_code":"M",
    "gn:admin2_code":"04",
    "gn:asciiname":"Ballymadog",
    "gn:country_code":"IE",
    "gn:dem":5,
    "gn:feature_class":"P",
    "gn:feature_code":"PPL",
    "gn:name":"Ballymadog",
    "gn:population":0,
    "gn:timezone":"Europe/Dublin",
    "iso:country":"IE",
    "wof:name":"Ballymadog",
    "wof:placetype":"locality"
},
  "geometry": {"coordinates":[-7.91333,51.92111],"type":"Point"}
}