{
  "type": "Feature",
  "properties": {
    "gn:admin1_code":"M",
    "gn:admin2_code":"11",
    "gn:asciiname":"Tullig",
    "gn:country_code":"IE",
    "gn:dem":85,
    "gn:feature_class":"P",
    "gn:feature_code":"PPL",
    "gn:name":"Tullig",
    "gn:population":0,
    "gn:timezone":"Europe/Dublin",
    "iso:country":"IE",
    "name:eng_x_preferred":[
        "Tullig"
    ],
    "name:gle_x_preferred":[
        "An Tulaigh"
    ],
    "wof:name":"Tullig",
    "wof:placetype":"locality"
},
  "geometry": {"coordinates":[-9.5975,52.36694],"type":"Point"}
}