{
  "type": "Feature",
  "properties": {
    "gn:admin1_code":"C",
    "gn:admin2_code":"10.0",
    "gn:asciiname":"Tullanwicky",
    "gn:country_code":"IE",
    "gn:dem":88,
    "gn:feature_class":"P",
    "gn:feature_code":"PPL",
    "gn:name":"Tullanwicky",
    "gn:population":0,
    "gn:timezone":"Europe/Dublin",
    "iso:country":"IE",
    "wof:name":"Tullanwicky",
    "wof:placetype":"locality"
},
  "geometry": {"coordinates":[-8.48083,53.36139],"type":"Point"}
}