{
  "type": "Feature",
  "properties": {
    "gn:admin1_code":"C",
    "gn:admin2_code":"10.0",
    "gn:asciiname":"Clogharevaun Bridge",
    "gn:country_code":"IE",
    "gn:dem":37,
    "gn:feature_class":"P",
    "gn:feature_code":"PPL",
    "gn:name":"Clogharevaun Bridge",
    "gn:population":0,
    "gn:timezone":"Europe/Dublin",
    "iso:country":"IE",
    "wof:name":"Clogharevaun Bridge",
    "wof:placetype":"locality"
},
  "geometry": {"coordinates":[-8.62583,53.26416999999999],"type":"Point"}
}