{
  "type": "Feature",
  "properties": {
    "gn:admin1_code":"M",
    "gn:admin2_code":"04",
    "gn:asciiname":"Deshure",
    "gn:country_code":"IE",
    "gn:dem":131,
    "gn:feature_class":"P",
    "gn:feature_code":"PPL",
    "gn:name":"Deshure",
    "gn:population":0,
    "gn:timezone":"Europe/Dublin",
    "iso:country":"IE",
    "wof:name":"Deshure",
    "wof:placetype":"locality"
},
  "geometry": {"coordinates":[-8.99694,51.84611],"type":"Point"}
}