{
  "type": "Feature",
  "properties": {
    "gn:admin1_code":"C",
    "gn:admin2_code":"20.0",
    "gn:asciiname":"Knockboy",
    "gn:country_code":"IE",
    "gn:dem":7,
    "gn:feature_class":"P",
    "gn:feature_code":"PPL",
    "gn:name":"Knockboy",
    "gn:population":0,
    "gn:timezone":"Europe/Dublin",
    "iso:country":"IE",
    "wof:name":"Knockboy",
    "wof:placetype":"locality"
},
  "geometry": {"coordinates":[-9.60797,53.89093],"type":"Point"}
}