{
  "type": "Feature",
  "properties": {
    "gn:admin1_code":"M",
    "gn:admin2_code":"04",
    "gn:asciiname":"Lissagraffin",
    "gn:country_code":"IE",
    "gn:dem":49,
    "gn:feature_class":"P",
    "gn:feature_code":"PPLL",
    "gn:name":"Lissagraffin",
    "gn:population":0,
    "gn:timezone":"Europe/Dublin",
    "iso:country":"IE",
    "wof:name":"Lissagraffin",
    "wof:placetype":"locality"
},
  "geometry": {"coordinates":[-9.78306,51.48361],"type":"Point"}
}