{
  "type": "Feature",
  "properties": {
    "gn:country":"IE",
    "gn:fcode":"PPL",
    "gn:population":0,
    "iso:country":"IE",
    "name:eng_x_preferred":[
        "Rosenallis"
    ],
    "name:eus_x_preferred":[
        "Rosenallis"
    ],
    "name:gle_x_preferred":[
        "Ros Fhionnghlaise"
    ],
    "name:nld_x_preferred":[
        "Rosenallis"
    ],
    "name:rus_x_preferred":[
        "\u0420\u043e\u0437\u0435\u043d\u0430\u043b\u043b\u0438\u0441"
    ],
    "name:swe_x_preferred":[
        "Rosenallis"
    ],
    "qs_pg:aaroncc":"IE",
    "qs_pg:gn_country":"IE",
    "qs_pg:gn_fcode":"PPL",
    "qs_pg:gn_pop":0,
    "qs_pg:name":"Rosenallis",
    "qs_pg:name_adm0":"Ireland",
    "qs_pg:name_adm1":"Laois",
    "qs_pg:photos":78,
    "qs_pg:photos_1k":16,
    "qs_pg:photos_9k":1,
    "qs_pg:photos_9r":3,
    "qs_pg:photos_all":78,
    "qs_pg:photos_sr":3,
    "qs_pg:pop_sr":0,
    "qs_pg:qs_pg_placetype":"locality",
    "qs_pg:qs_pg_placetype_gp":"Town",
    "qs_pg:woe_adm0":23424803,
    "woe:adm0_id":23424803,
    "woe:name_adm0":"Ireland",
    "woe:name_adm1":"Laois",
    "woe:placetype":"Town",
    "wof:name":"Rosenallis",
    "wof:placetype":"locality"
},
  "geometry": {"coordinates":[-7.40444,53.13444],"type":"Point"}
}