{
  "type": "Feature",
  "properties": {
    "gn:admin1_code":"U",
    "gn:admin2_code":"06",
    "gn:asciiname":"Moneyhaughly",
    "gn:country_code":"IE",
    "gn:dem":65,
    "gn:feature_class":"P",
    "gn:feature_code":"PPL",
    "gn:name":"Moneyhaughly",
    "gn:population":0,
    "gn:timezone":"Europe/Dublin",
    "iso:country":"IE",
    "wof:name":"Moneyhaughly",
    "wof:placetype":"locality"
},
  "geometry": {"coordinates":[-7.58972,54.97417],"type":"Point"}
}