{
  "type": "Feature",
  "properties": {
    "gn:admin1_code":"C",
    "gn:admin2_code":"10.0",
    "gn:asciiname":"Gortskeagh",
    "gn:country_code":"IE",
    "gn:dem":15,
    "gn:feature_class":"P",
    "gn:feature_code":"PPLL",
    "gn:name":"Gortskeagh",
    "gn:population":0,
    "gn:timezone":"Europe/Dublin",
    "iso:country":"IE",
    "wof:name":"Gortskeagh",
    "wof:placetype":"locality"
},
  "geometry": {"coordinates":[-8.95944,53.11722],"type":"Point"}
}