{
  "type": "Feature",
  "properties": {
    "gn:admin1_code":"M",
    "gn:admin2_code":"04",
    "gn:asciiname":"Strawhall Cross Roads",
    "gn:country_code":"IE",
    "gn:dem":145,
    "gn:feature_class":"P",
    "gn:feature_code":"PPLL",
    "gn:name":"Strawhall Cross Roads",
    "gn:population":0,
    "gn:timezone":"Europe/Dublin",
    "iso:country":"IE",
    "wof:name":"Strawhall Cross Roads",
    "wof:placetype":"locality"
},
  "geometry": {"coordinates":[-8.80778,51.82472],"type":"Point"}
}