{
  "type": "Feature",
  "properties": {
    "gn:admin1_code":"M",
    "gn:admin2_code":"04",
    "gn:asciiname":"Curragh",
    "gn:country_code":"IE",
    "gn:dem":54,
    "gn:feature_class":"P",
    "gn:feature_code":"PPL",
    "gn:name":"Curragh",
    "gn:population":0,
    "gn:timezone":"Europe/Dublin",
    "iso:country":"IE",
    "name:cat_x_preferred":[
        "Curragh"
    ],
    "name:deu_x_preferred":[
        "Curragh"
    ],
    "name:eus_x_preferred":[
        "Curragh"
    ],
    "name:gle_x_preferred":[
        "An Currach"
    ],
    "name:swe_x_preferred":[
        "Curragh"
    ],
    "wof:name":"Curragh",
    "wof:placetype":"locality"
},
  "geometry": {"coordinates":[-8.20361,52.13972],"type":"Point"}
}