{
  "type": "Feature",
  "properties": {
    "gn:admin1_code":"L",
    "gn:admin2_code":"33.0",
    "gn:asciiname":"Clanbrassil Street",
    "gn:country_code":"IE",
    "gn:dem":19,
    "gn:feature_class":"P",
    "gn:feature_code":"PPL",
    "gn:name":"Clanbrassil Street",
    "gn:population":0,
    "gn:timezone":"Europe/Dublin",
    "iso:country":"IE",
    "wof:name":"Clanbrassil Street",
    "wof:placetype":"locality"
},
  "geometry": {"coordinates":[-6.27528,53.33222],"type":"Point"}
}