{
  "type": "Feature",
  "properties": {
    "gn:admin1_code":"L",
    "gn:admin2_code":"23.0",
    "gn:asciiname":"Five Roads Cross",
    "gn:country_code":"IE",
    "gn:dem":51,
    "gn:feature_class":"P",
    "gn:feature_code":"PPL",
    "gn:name":"Five Roads Cross",
    "gn:population":0,
    "gn:timezone":"Europe/Dublin",
    "iso:country":"IE",
    "wof:name":"Five Roads Cross",
    "wof:placetype":"locality"
},
  "geometry": {"coordinates":[-7.94444,53.17139],"type":"Point"}
}