{
  "type": "Feature",
  "properties": {
    "iso:country":"IE",
    "qs_pg:aaroncc":"IE",
    "qs_pg:name":"Monaghan Urban",
    "qs_pg:name_adm0":"Ireland",
    "qs_pg:name_adm1":"Monaghan",
    "qs_pg:photos":70,
    "qs_pg:photos_1k":14,
    "qs_pg:photos_9k":3,
    "qs_pg:photos_9r":5,
    "qs_pg:photos_all":607,
    "qs_pg:photos_sr":2,
    "qs_pg:pop_sr":0,
    "qs_pg:qs_pg_placetype":"localadmin",
    "qs_pg:qs_pg_placetype_gp":"LocalAdmin",
    "qs_pg:woe_adm0":23424803,
    "woe:adm0_id":23424803,
    "woe:name_adm0":"Ireland",
    "woe:name_adm1":"Monaghan",
    "woe:placetype":"LocalAdmin",
    "wof:name":"Monaghan Urban",
    "wof:placetype":"localadmin"
},
  "geometry": {"coordinates":[-6.97031,54.247988],"type":"Point"}
}