{
  "type": "Feature",
  "properties": {
    "gn:gn_country":"IE",
    "gn:gn_fcode":"PPL",
    "gn:gn_pop":0,
    "iso:country":"IE",
    "qs_pg:aaroncc":"IE",
    "qs_pg:gn_country":"IE",
    "qs_pg:gn_fcode":"PPL",
    "qs_pg:gn_pop":0,
    "qs_pg:name":"Clontarf",
    "qs_pg:name_adm0":"Ireland",
    "qs_pg:name_adm1":"Dublin",
    "qs_pg:photos":7158,
    "qs_pg:photos_1k":1000,
    "qs_pg:photos_9k":32,
    "qs_pg:photos_9r":15,
    "qs_pg:photos_all":7158,
    "qs_pg:photos_sr":25,
    "qs_pg:pop_sr":0,
    "qs_pg:qs_pg_placetype":"neighbourhood",
    "qs_pg:qs_pg_placetype_gp":"Suburb",
    "qs_pg:woe_adm0":23424803,
    "woe:adm0_id":23424803,
    "woe:name_adm0":"Ireland",
    "woe:name_adm1":"Dublin",
    "woe:placetype":"Suburb",
    "wof:name":"Clontarf",
    "wof:placetype":"neighbourhood"
},
  "geometry": {"coordinates":[-6.20822,53.36244],"type":"Point"}
}