{
  "type": "Feature",
  "properties": {
    "gn:population":329,
    "iso:country":"IE",
    "name:ceb_x_preferred":[
        "Clonroche"
    ],
    "name:eng_x_preferred":[
        "Clonroche"
    ],
    "name:eus_x_preferred":[
        "Clonroche"
    ],
    "name:gle_x_preferred":[
        "Cluain an R\u00f3istigh"
    ],
    "name:nld_x_preferred":[
        "Clonroche"
    ],
    "name:rus_x_preferred":[
        "\u041a\u043b\u043e\u043d\u0440\u043e\u0447"
    ],
    "name:spa_x_preferred":[
        "Clonroche"
    ],
    "name:swe_x_preferred":[
        "Clonroche"
    ],
    "qs:a0":"Ireland",
    "qs:a1":"*Wexford",
    "qs:a1r":"0",
    "qs:adm0":"Ireland",
    "qs:la_lc":"*",
    "qs:level":"locality",
    "qs:loc":"Clonroche",
    "qs:loc_alt":"Clonroche",
    "qs:pop":0,
    "qs:type":"buffered point",
    "wd:wordcount":571,
    "wof:lang":[
        "eng"
    ],
    "wof:name":"Clonroche",
    "wof:placetype":"locality",
    "wof:population":329
},
  "geometry": {"coordinates":[-6.716051,52.44939],"type":"Point"}
}