{
  "type": "Feature",
  "properties": {
    "gn:admin1_code":"U",
    "gn:admin2_code":"22.0",
    "gn:asciiname":"Aghlaverty",
    "gn:country_code":"IE",
    "gn:dem":68,
    "gn:feature_class":"P",
    "gn:feature_code":"PPLL",
    "gn:name":"Aghlaverty",
    "gn:population":0,
    "gn:timezone":"Europe/Dublin",
    "iso:country":"IE",
    "wof:name":"Aghlaverty",
    "wof:placetype":"locality"
},
  "geometry": {"coordinates":[-6.89917,54.24556],"type":"Point"}
}