{
  "type": "Feature",
  "properties": {
    "gn:admin1_code":"L",
    "gn:admin2_code":"18",
    "gn:asciiname":"Drumnee Upper",
    "gn:country_code":"IE",
    "gn:dem":40,
    "gn:feature_class":"P",
    "gn:feature_code":"PPL",
    "gn:name":"Drumnee Upper",
    "gn:population":0,
    "gn:timezone":"Europe/Dublin",
    "iso:country":"IE",
    "name:und_x_variant":[
        "Drumnee",
        "Drumnee Upper"
    ],
    "wof:name":"Drumnee Upper",
    "wof:placetype":"locality"
},
  "geometry": {"coordinates":[-7.88333,53.56667],"type":"Point"}
}