{
  "type": "Feature",
  "properties": {
    "gn:admin1_code":"M",
    "gn:admin2_code":"3.0",
    "gn:asciiname":"Aughaglanna Bridge",
    "gn:country_code":"IE",
    "gn:dem":84,
    "gn:feature_class":"P",
    "gn:feature_code":"PPL",
    "gn:name":"Aughaglanna Bridge",
    "gn:population":0,
    "gn:timezone":"Europe/Dublin",
    "iso:country":"IE",
    "wof:name":"Aughaglanna Bridge",
    "wof:placetype":"locality"
},
  "geometry": {"coordinates":[-9.16778,52.82778],"type":"Point"}
}