{
  "type": "Feature",
  "properties": {
    "gn:admin1_code":"U",
    "gn:admin2_code":"2.0",
    "gn:asciiname":"Legnagrow",
    "gn:country_code":"IE",
    "gn:dem":137,
    "gn:feature_class":"P",
    "gn:feature_code":"PPLL",
    "gn:name":"Legnagrow",
    "gn:population":0,
    "gn:timezone":"Europe/Dublin",
    "iso:country":"IE",
    "wof:name":"Legnagrow",
    "wof:placetype":"locality"
},
  "geometry": {"coordinates":[-7.90528,54.2125],"type":"Point"}
}