{
  "type": "Feature",
  "properties": {
    "gn:admin1_code":"U",
    "gn:admin2_code":"06",
    "gn:asciiname":"Brinlack",
    "gn:cc2":"IE",
    "gn:country_code":"IE",
    "gn:dem":44,
    "gn:feature_class":"P",
    "gn:feature_code":"PPL",
    "gn:name":"Brinlack",
    "gn:population":441,
    "gn:timezone":"Europe/Dublin",
    "iso:country":"IE",
    "name:eng_x_preferred":[
        "Brinlack"
    ],
    "name:gle_x_preferred":[
        "Bun na Leaca"
    ],
    "wof:name":"Brinlack",
    "wof:placetype":"locality",
    "wof:population":441
},
  "geometry": {"coordinates":[-8.28333,55.11666999999999],"type":"Point"}
}