{
  "type": "Feature",
  "properties": {
    "gn:admin1_code":"L",
    "gn:admin2_code":"30",
    "gn:asciiname":"Boley's Cross Roads",
    "gn:country_code":"IE",
    "gn:dem":12,
    "gn:feature_class":"P",
    "gn:feature_code":"PPL",
    "gn:name":"Boley\u2019s Cross Roads",
    "gn:population":0,
    "gn:timezone":"Europe/Dublin",
    "iso:country":"IE",
    "wof:name":"Boley's Cross Roads",
    "wof:placetype":"locality"
},
  "geometry": {"coordinates":[-6.51417,52.20528],"type":"Point"}
}