{
  "type": "Feature",
  "properties": {
    "iso:country":"IE",
    "qs_pg:aaroncc":"IE",
    "qs_pg:name":"Whitecastle",
    "qs_pg:name_adm0":"Ireland",
    "qs_pg:name_adm1":"Donegal",
    "qs_pg:photos":13,
    "qs_pg:photos_1k":3,
    "qs_pg:photos_9k":1,
    "qs_pg:photos_9r":4,
    "qs_pg:photos_all":156,
    "qs_pg:photos_sr":1,
    "qs_pg:pop_sr":0,
    "qs_pg:qs_pg_placetype":"localadmin",
    "qs_pg:qs_pg_placetype_gp":"LocalAdmin",
    "qs_pg:woe_adm0":23424803,
    "woe:adm0_id":23424803,
    "woe:name_adm0":"Ireland",
    "woe:name_adm1":"Donegal",
    "woe:placetype":"LocalAdmin",
    "wof:name":"Whitecastle",
    "wof:placetype":"localadmin"
},
  "geometry": {"coordinates":[-7.127165,55.157738],"type":"Point"}
}