{
  "type": "Feature",
  "properties": {
    "gn:admin1_code":"C",
    "gn:admin2_code":"20",
    "gn:asciiname":"Corclogh",
    "gn:country_code":"IE",
    "gn:dem":28,
    "gn:feature_class":"P",
    "gn:feature_code":"PPL",
    "gn:name":"Corclogh",
    "gn:population":0,
    "gn:timezone":"Europe/Dublin",
    "iso:country":"IE",
    "name:eng_x_preferred":[
        "Corclogh"
    ],
    "name:gle_x_preferred":[
        "An Chorrchloch"
    ],
    "wof:name":"Corclogh",
    "wof:placetype":"locality"
},
  "geometry": {"coordinates":[-10.04209,54.25457],"type":"Point"}
}