{
  "type": "Feature",
  "properties": {
    "gn:admin1_code":"L",
    "gn:admin2_code":"12.0",
    "gn:asciiname":"Mylerstown Cross Roads",
    "gn:country_code":"IE",
    "gn:dem":130,
    "gn:feature_class":"P",
    "gn:feature_code":"PPL",
    "gn:name":"Mylerstown Cross Roads",
    "gn:population":0,
    "gn:timezone":"Europe/Dublin",
    "iso:country":"IE",
    "wof:name":"Mylerstown Cross Roads",
    "wof:placetype":"locality"
},
  "geometry": {"coordinates":[-6.68944,53.17333000000001],"type":"Point"}
}