{
  "type": "Feature",
  "properties": {
    "gn:admin1_code":"M",
    "gn:admin2_code":"44",
    "gn:asciiname":"Knockane",
    "gn:country_code":"IE",
    "gn:dem":6,
    "gn:feature_class":"P",
    "gn:feature_code":"PPL",
    "gn:name":"Knockane",
    "gn:population":0,
    "gn:timezone":"Europe/Dublin",
    "iso:country":"IE",
    "wof:name":"Knockane",
    "wof:placetype":"locality"
},
  "geometry": {"coordinates":[-7.29778,52.29167],"type":"Point"}
}