{
  "type": "Feature",
  "properties": {
    "gn:admin1_code":"M",
    "gn:admin2_code":"42.0",
    "gn:asciiname":"Ballycullane",
    "gn:country_code":"IE",
    "gn:dem":94,
    "gn:feature_class":"P",
    "gn:feature_code":"PPL",
    "gn:name":"Ballycullane",
    "gn:population":0,
    "gn:timezone":"Europe/Dublin",
    "iso:country":"IE",
    "wof:name":"Ballycullane",
    "wof:placetype":"locality"
},
  "geometry": {"coordinates":[-8.58056,52.415],"type":"Point"}
}