{
  "type": "Feature",
  "properties": {
    "gn:admin1_code":"M",
    "gn:admin2_code":"42.0",
    "gn:asciiname":"Ballycullane",
    "gn:country_code":"IE",
    "gn:dem":94,
    "gn:feature_class":"P",
    "gn:feature_code":"PPL",
    "gn:name":"Ballycullane",
    "gn:population":0,
    "gn:timezone":"Europe/Dublin",
    "iso:country":"IE",
    "name:ceb_x_preferred":[
        "Ballycullane"
    ],
    "name:eus_x_preferred":[
        "Ballycullane"
    ],
    "name:rus_x_preferred":[
        "\u0411\u0430\u043b\u043b\u0438\u043a\u0430\u043b\u043b\u0435\u0439\u043d"
    ],
    "name:spa_x_preferred":[
        "Ballycullane"
    ],
    "name:swe_x_preferred":[
        "Ballycullane"
    ],
    "wof:name":"Ballycullane",
    "wof:placetype":"locality"
},
  "geometry": {"coordinates":[-8.58056,52.415],"type":"Point"}
}