{
  "type": "Feature",
  "properties": {
    "gn:gn_country":"IE",
    "gn:gn_fcode":"PPL",
    "gn:gn_pop":0,
    "gn:population":1028,
    "iso:country":"IE",
    "name:unk_x_variant":[
        "Kilmacanogue"
    ],
    "qs_pg:aaroncc":"IE",
    "qs_pg:gn_country":"IE",
    "qs_pg:gn_fcode":"PPL",
    "qs_pg:gn_pop":0,
    "qs_pg:name":"Kilmacanoge",
    "qs_pg:name_adm0":"Ireland",
    "qs_pg:name_adm1":"Wicklow",
    "qs_pg:photos":3,
    "qs_pg:photos_1k":1,
    "qs_pg:photos_9k":1,
    "qs_pg:photos_9r":5,
    "qs_pg:photos_all":308,
    "qs_pg:photos_sr":1,
    "qs_pg:pop_sr":0,
    "qs_pg:qs_pg_placetype":"localadmin",
    "qs_pg:qs_pg_placetype_gp":"LocalAdmin",
    "qs_pg:woe_adm0":23424803,
    "woe:adm0_id":23424803,
    "woe:name_adm0":"Ireland",
    "woe:name_adm1":"Wicklow",
    "woe:placetype":"LocalAdmin",
    "wof:name":"Kilmacanoge",
    "wof:placetype":"localadmin",
    "wof:population":1028
},
  "geometry": {"coordinates":[-6.13361,53.16722],"type":"Point"}
}