{
  "type": "Feature",
  "properties": {
    "gn:admin1_code":"L",
    "gn:admin2_code":"13",
    "gn:asciiname":"Damma Lower Cross Roads",
    "gn:country_code":"IE",
    "gn:dem":80,
    "gn:feature_class":"P",
    "gn:feature_code":"PPL",
    "gn:name":"Damma Lower Cross Roads",
    "gn:population":0,
    "gn:timezone":"Europe/Dublin",
    "iso:country":"IE",
    "wof:name":"Damma Lower Cross Roads",
    "wof:placetype":"locality"
},
  "geometry": {"coordinates":[-7.32361,52.63472],"type":"Point"}
}