{
  "type": "Feature",
  "properties": {
    "gn:admin1_code":"M",
    "gn:admin2_code":"04",
    "gn:asciiname":"Slievemore",
    "gn:country_code":"IE",
    "gn:dem":20,
    "gn:feature_class":"P",
    "gn:feature_code":"PPLL",
    "gn:name":"Slievemore",
    "gn:population":0,
    "gn:timezone":"Europe/Dublin",
    "iso:country":"IE",
    "name:ceb_x_preferred":[
        "Slievemore"
    ],
    "name:ita_x_preferred":[
        "Slievemore"
    ],
    "name:lmo_x_preferred":[
        "Sliabh M\u00f3r"
    ],
    "name:nno_x_preferred":[
        "Slievemore"
    ],
    "wof:name":"Slievemore",
    "wof:placetype":"locality"
},
  "geometry": {"coordinates":[-9.43361,51.45941],"type":"Point"}
}