{
  "type": "Feature",
  "properties": {
    "gn:gn_country":"IE",
    "gn:gn_fcode":"PPL",
    "gn:gn_pop":0,
    "gn:population":334,
    "iso:country":"IE",
    "name:bul_x_preferred":[
        "\u0414\u0443\u0440\u0443\u0441"
    ],
    "name:ceb_x_preferred":[
        "Durrus"
    ],
    "name:eng_x_preferred":[
        "Durrus"
    ],
    "name:eus_x_preferred":[
        "Durrus"
    ],
    "name:fra_x_preferred":[
        "Durrus"
    ],
    "name:gle_x_preferred":[
        "D\u00faras"
    ],
    "name:gle_x_variant":[
        "Dur\u00e1s"
    ],
    "name:nld_x_preferred":[
        "Durrus"
    ],
    "name:rus_x_preferred":[
        "\u0414\u0430\u0440\u0440\u0443\u0441"
    ],
    "name:spa_x_preferred":[
        "Durrus"
    ],
    "name:swe_x_preferred":[
        "Durrus"
    ],
    "qs_pg:aaroncc":"IE",
    "qs_pg:gn_country":"IE",
    "qs_pg:gn_fcode":"PPL",
    "qs_pg:gn_pop":0,
    "qs_pg:name":"Durrus",
    "qs_pg:name_adm0":"Ireland",
    "qs_pg:name_adm1":"Cork",
    "qs_pg:photos":202,
    "qs_pg:photos_1k":41,
    "qs_pg:photos_9k":1,
    "qs_pg:photos_9r":4,
    "qs_pg:photos_all":202,
    "qs_pg:photos_sr":4,
    "qs_pg:pop_sr":0,
    "qs_pg:qs_pg_placetype":"locality",
    "qs_pg:qs_pg_placetype_gp":"Town",
    "qs_pg:woe_adm0":23424803,
    "woe:adm0_id":23424803,
    "woe:name_adm0":"Ireland",
    "woe:name_adm1":"Cork",
    "woe:placetype":"Town",
    "wof:name":"Durrus",
    "wof:placetype":"locality",
    "wof:population":334
},
  "geometry": {"coordinates":[-9.53333,51.61667],"type":"Point"}
}