{
  "type": "Feature",
  "properties": {
    "gn:admin1_code":"L",
    "gn:admin2_code":"13",
    "gn:asciiname":"Castlemarket Bridge",
    "gn:country_code":"IE",
    "gn:dem":98,
    "gn:feature_class":"P",
    "gn:feature_code":"PPL",
    "gn:name":"Castlemarket Bridge",
    "gn:population":0,
    "gn:timezone":"Europe/Dublin",
    "iso:country":"IE",
    "wof:name":"Castlemarket Bridge",
    "wof:placetype":"locality"
},
  "geometry": {"coordinates":[-7.32028,52.85167],"type":"Point"}
}