{
  "type": "Feature",
  "properties": {
    "gn:admin1_code":"L",
    "gn:admin2_code":"30",
    "gn:asciiname":"Ballyfad",
    "gn:cc2":"IE",
    "gn:country_code":"IE",
    "gn:dem":120,
    "gn:feature_class":"P",
    "gn:feature_code":"PPL",
    "gn:name":"Ballyfad",
    "gn:population":0,
    "gn:timezone":"Europe/Dublin",
    "iso:country":"IE",
    "name:und_x_variant":[
        "Ballyfadd",
        "Ballyfad"
    ],
    "wof:name":"Ballyfad",
    "wof:placetype":"locality"
},
  "geometry": {"coordinates":[-6.26722,52.76556],"type":"Point"}
}