{
  "type": "Feature",
  "properties": {
    "gn:gn_country":"IE",
    "gn:gn_fcode":"PPL",
    "gn:gn_pop":0,
    "gn:population":359,
    "iso:country":"IE",
    "name:eng_x_preferred":[
        "Kinnitty"
    ],
    "name:gle_x_preferred":[
        "Cionn Eitigh"
    ],
    "name:unk_x_variant":[
        "Kinitty"
    ],
    "qs_pg:aaroncc":"IE",
    "qs_pg:gn_country":"IE",
    "qs_pg:gn_fcode":"PPL",
    "qs_pg:gn_pop":0,
    "qs_pg:name":"Kinnitty",
    "qs_pg:name_adm0":"Ireland",
    "qs_pg:name_adm1":"Offaly",
    "qs_pg:photos":53,
    "qs_pg:photos_1k":11,
    "qs_pg:photos_9k":1,
    "qs_pg:photos_9r":4,
    "qs_pg:photos_all":229,
    "qs_pg:photos_sr":2,
    "qs_pg:pop_sr":0,
    "qs_pg:qs_pg_placetype":"localadmin",
    "qs_pg:qs_pg_placetype_gp":"LocalAdmin",
    "qs_pg:woe_adm0":23424803,
    "woe:adm0_id":23424803,
    "woe:name_adm0":"Ireland",
    "woe:name_adm1":"Offaly",
    "woe:placetype":"LocalAdmin",
    "wof:name":"Kinnitty",
    "wof:placetype":"localadmin",
    "wof:population":359
},
  "geometry": {"coordinates":[-7.72139,53.09556],"type":"Point"}
}