{
  "type": "Feature",
  "properties": {
    "gn:admin1_code":"L",
    "gn:admin2_code":"21.0",
    "gn:asciiname":"Woodpole",
    "gn:country_code":"IE",
    "gn:dem":80,
    "gn:feature_class":"P",
    "gn:feature_code":"PPL",
    "gn:name":"Woodpole",
    "gn:population":0,
    "gn:timezone":"Europe/Dublin",
    "iso:country":"IE",
    "wof:name":"Woodpole",
    "wof:placetype":"locality"
},
  "geometry": {"coordinates":[-6.97129,53.74915],"type":"Point"}
}