{
  "type": "Feature",
  "properties": {
    "gn:admin1_code":"U",
    "gn:admin2_code":"02",
    "gn:asciiname":"Grousehall",
    "gn:country_code":"IE",
    "gn:dem":183,
    "gn:feature_class":"P",
    "gn:feature_code":"PPL",
    "gn:name":"Grousehall",
    "gn:population":0,
    "gn:timezone":"Europe/Dublin",
    "iso:country":"IE",
    "wof:name":"Grousehall",
    "wof:placetype":"locality"
},
  "geometry": {"coordinates":[-7.11667,53.95],"type":"Point"}
}