{
  "type": "Feature",
  "properties": {
    "gn:admin1_code":"L",
    "gn:admin2_code":"31.0",
    "gn:asciiname":"Drummin",
    "gn:country_code":"IE",
    "gn:dem":330,
    "gn:feature_class":"P",
    "gn:feature_code":"PPLL",
    "gn:name":"Drummin",
    "gn:population":0,
    "gn:timezone":"Europe/Dublin",
    "iso:country":"IE",
    "wof:name":"Drummin",
    "wof:placetype":"locality"
},
  "geometry": {"coordinates":[-6.28778,53.03944],"type":"Point"}
}