{
  "type": "Feature",
  "properties": {
    "iso:country":"IE",
    "qs_pg:aaroncc":"IE",
    "qs_pg:name":"Newport West",
    "qs_pg:name_adm0":"Ireland",
    "qs_pg:name_adm1":"Mayo",
    "qs_pg:photos":616,
    "qs_pg:photos_1k":125,
    "qs_pg:photos_9k":5,
    "qs_pg:photos_9r":7,
    "qs_pg:photos_all":1032,
    "qs_pg:photos_sr":8,
    "qs_pg:pop_sr":0,
    "qs_pg:qs_pg_placetype":"localadmin",
    "qs_pg:qs_pg_placetype_gp":"LocalAdmin",
    "qs_pg:woe_adm0":23424803,
    "woe:adm0_id":23424803,
    "woe:name_adm0":"Ireland",
    "woe:name_adm1":"Mayo",
    "woe:placetype":"LocalAdmin",
    "wof:name":"Newport West",
    "wof:placetype":"localadmin"
},
  "geometry": {"coordinates":[-9.785127,53.905804],"type":"Point"}
}