{
  "type": "Feature",
  "properties": {
    "iso:country":"IE",
    "qs_pg:aaroncc":"IE",
    "qs_pg:name":"Droichead Nua Town",
    "qs_pg:name_adm0":"Ireland",
    "qs_pg:name_adm1":"Kildare",
    "qs_pg:photos":295,
    "qs_pg:photos_1k":60,
    "qs_pg:photos_9k":4,
    "qs_pg:photos_9r":6,
    "qs_pg:photos_all":823,
    "qs_pg:photos_sr":5,
    "qs_pg:pop_sr":0,
    "qs_pg:qs_pg_placetype":"localadmin",
    "qs_pg:qs_pg_placetype_gp":"LocalAdmin",
    "qs_pg:woe_adm0":23424803,
    "woe:adm0_id":23424803,
    "woe:name_adm0":"Ireland",
    "woe:name_adm1":"Kildare",
    "woe:placetype":"LocalAdmin",
    "wof:name":"Droichead Nua Town",
    "wof:placetype":"localadmin"
},
  "geometry": {"coordinates":[-6.79896,53.178572],"type":"Point"}
}