{
  "type": "Feature",
  "properties": {
    "gn:gn_country":"IE",
    "gn:gn_fcode":"PPLA2",
    "gn:gn_pop":17708,
    "gn:population":19913,
    "iso:country":"IE",
    "name:bel_x_preferred":[
        "\u0423\u044d\u043a\u0441\u0444\u0430\u0440\u0434"
    ],
    "name:bre_x_preferred":[
        "Loch Garman"
    ],
    "name:bul_x_preferred":[
        "\u0423\u0435\u043a\u0441\u0444\u043e\u0440\u0434"
    ],
    "name:cat_x_preferred":[
        "Wexford"
    ],
    "name:ceb_x_preferred":[
        "Loch Garman"
    ],
    "name:ces_x_preferred":[
        "Wexford"
    ],
    "name:cym_x_preferred":[
        "Loch Garman"
    ],
    "name:dan_x_preferred":[
        "Wexford"
    ],
    "name:deu_x_preferred":[
        "Wexford"
    ],
    "name:eng_x_preferred":[
        "Wexford"
    ],
    "name:epo_x_preferred":[
        "Wexford"
    ],
    "name:eus_x_preferred":[
        "Wexford"
    ],
    "name:fas_x_preferred":[
        "\u0648\u06a9\u0633 \u0641\u0648\u0631\u062f"
    ],
    "name:fin_x_preferred":[
        "Wexford"
    ],
    "name:fra_x_preferred":[
        "Wexford"
    ],
    "name:gle_x_preferred":[
        "Loch Garman"
    ],
    "name:glg_x_preferred":[
        "Wexford - Loch Garman"
    ],
    "name:glv_x_preferred":[
        "Logh Garman"
    ],
    "name:heb_x_preferred":[
        "\u05d5\u05e7\u05e1\u05e4\u05d5\u05e8\u05d3"
    ],
    "name:ind_x_preferred":[
        "Wexford"
    ],
    "name:ita_x_preferred":[
        "Wexford"
    ],
    "name:jpn_x_preferred":[
        "\u30a6\u30a7\u30c3\u30af\u30b9\u30d5\u30a9\u30fc\u30c9"
    ],
    "name:kat_x_preferred":[
        "\u10e3\u10d4\u10e5\u10e1\u10e4\u10dd\u10e0\u10d3\u10d8"
    ],
    "name:kor_x_preferred":[
        "\uc6e9\uc2a4\ud37c\ub4dc"
    ],
    "name:lat_x_preferred":[
        "Vexfordia"
    ],
    "name:lit_x_preferred":[
        "Veksfordas"
    ],
    "name:nld_x_preferred":[
        "Wexford"
    ],
    "name:nno_x_preferred":[
        "Wexford"
    ],
    "name:nob_x_preferred":[
        "Wexford"
    ],
    "name:nor_x_preferred":[
        "Wexford"
    ],
    "name:pol_x_preferred":[
        "Wexford"
    ],
    "name:por_x_preferred":[
        "Wexford"
    ],
    "name:rus_x_preferred":[
        "\u0423\u044d\u043a\u0441\u0444\u043e\u0440\u0434"
    ],
    "name:slk_x_preferred":[
        "Wexford"
    ],
    "name:slv_x_preferred":[
        "Wexford"
    ],
    "name:spa_x_preferred":[
        "Wexford"
    ],
    "name:srp_x_preferred":[
        "\u0412\u0435\u043a\u0441\u0444\u043e\u0440\u0434"
    ],
    "name:swa_x_preferred":[
        "Wexford"
    ],
    "name:swe_x_preferred":[
        "Wexford"
    ],
    "name:ukr_x_preferred":[
        "\u0412\u0435\u043a\u0441\u0444\u043e\u0440\u0434"
    ],
    "name:urd_x_preferred":[
        "\u0648\u06cc\u06a9\u0633\u0641\u0631\u0688"
    ],
    "name:zho_x_preferred":[
        "\u97e6\u514b\u65af\u798f\u5fb7"
    ],
    "qs_pg:aaroncc":"IE",
    "qs_pg:gn_country":"IE",
    "qs_pg:gn_fcode":"PPLA2",
    "qs_pg:gn_pop":17708,
    "qs_pg:name":"Loch Garman",
    "qs_pg:photos_9r":0,
    "qs_pg:photos_sr":0,
    "qs_pg:pop_sr":6,
    "qs_pg:qs_pg_placetype":"locality",
    "wof:name":"Loch Garman",
    "wof:placetype":"locality",
    "wof:population":19913
},
  "geometry": {"coordinates":[-6.4575,52.33417],"type":"Point"}
}