{
  "type": "Feature",
  "properties": {
    "gn:admin1_code":"C",
    "gn:admin2_code":"10.0",
    "gn:asciiname":"Coogla",
    "gn:country_code":"IE",
    "gn:dem":26,
    "gn:feature_class":"P",
    "gn:feature_code":"PPL",
    "gn:name":"Coogla",
    "gn:population":0,
    "gn:timezone":"Europe/Dublin",
    "iso:country":"IE",
    "wof:name":"Coogla",
    "wof:placetype":"locality"
},
  "geometry": {"coordinates":[-9.93971,53.39014],"type":"Point"}
}