{
  "type": "Feature",
  "properties": {
    "gn:gn_country":"IE",
    "gn:gn_fcode":"PPL",
    "gn:gn_pop":0,
    "gn:population":385,
    "iso:country":"IE",
    "name:baq_x_preferred":[
        "Athea"
    ],
    "name:bul_x_preferred":[
        "\u0410\u0442\u0445\u0435\u0430"
    ],
    "name:dut_x_preferred":[
        "Athea"
    ],
    "name:eng_x_preferred":[
        "Athea"
    ],
    "name:fre_x_preferred":[
        "Athea"
    ],
    "name:ger_x_preferred":[
        "Athea"
    ],
    "name:gle_x_preferred":[
        "\u00c1th an tSl\u00e9ibhe"
    ],
    "name:ita_x_preferred":[
        "Athea"
    ],
    "name:pol_x_preferred":[
        "Athea"
    ],
    "name:rus_x_preferred":[
        "\u0410\u0442\u0438\u0430"
    ],
    "name:spa_x_preferred":[
        "Athea"
    ],
    "name:swe_x_preferred":[
        "Athea"
    ],
    "qs_pg:aaroncc":"IE",
    "qs_pg:gn_country":"IE",
    "qs_pg:gn_fcode":"PPL",
    "qs_pg:gn_pop":0,
    "qs_pg:name":"Athea",
    "qs_pg:name_adm0":"Ireland",
    "qs_pg:name_adm1":"Limerick",
    "qs_pg:photos":12,
    "qs_pg:photos_1k":2,
    "qs_pg:photos_9k":1,
    "qs_pg:photos_9r":1,
    "qs_pg:photos_all":12,
    "qs_pg:photos_sr":1,
    "qs_pg:pop_sr":0,
    "qs_pg:qs_pg_placetype":"locality",
    "qs_pg:qs_pg_placetype_gp":"Town",
    "qs_pg:woe_adm0":23424803,
    "woe:adm0_id":23424803,
    "woe:name_adm0":"Ireland",
    "woe:name_adm1":"Limerick",
    "woe:placetype":"Town",
    "wof:name":"Athea",
    "wof:placetype":"locality",
    "wof:population":385
},
  "geometry": {"coordinates":[-9.28944,52.45972],"type":"Point"}
}