{
  "type": "Feature",
  "properties": {
    "gn:admin1_code":"L",
    "gn:admin2_code":"35.0",
    "gn:asciiname":"Beldaragh",
    "gn:country_code":"IE",
    "gn:dem":134,
    "gn:feature_class":"P",
    "gn:feature_code":"PPL",
    "gn:name":"Beldaragh",
    "gn:population":0,
    "gn:timezone":"Europe/Dublin",
    "iso:country":"IE",
    "wof:name":"Beldaragh",
    "wof:placetype":"locality"
},
  "geometry": {"coordinates":[-6.25083,53.56972],"type":"Point"}
}