{
  "type": "Feature",
  "properties": {
    "gn:admin1_code":"C",
    "gn:admin2_code":"20",
    "gn:asciiname":"Cloghmore",
    "gn:country_code":"IE",
    "gn:dem":69,
    "gn:feature_class":"P",
    "gn:feature_code":"PPL",
    "gn:name":"Cloghmore",
    "gn:population":0,
    "gn:timezone":"Europe/Dublin",
    "iso:country":"IE",
    "name:eng_x_preferred":[
        "Cloghmore"
    ],
    "name:gle_x_preferred":[
        "An Clocich Mh\u00f3ir"
    ],
    "wof:name":"Cloghmore",
    "wof:placetype":"locality"
},
  "geometry": {"coordinates":[-9.95111,53.87444],"type":"Point"}
}