{
  "type": "Feature",
  "properties": {
    "gn:admin1_code":"L",
    "gn:admin2_code":"21.0",
    "gn:asciiname":"Kilcloon",
    "gn:country_code":"IE",
    "gn:dem":79,
    "gn:feature_class":"P",
    "gn:feature_code":"PPL",
    "gn:name":"Kilcloon",
    "gn:population":264,
    "gn:timezone":"Europe/Dublin",
    "iso:country":"IE",
    "name:ceb_x_preferred":[
        "Kilcloon"
    ],
    "name:eus_x_preferred":[
        "Kilcloon"
    ],
    "name:gle_x_preferred":[
        "Cill Chluain"
    ],
    "name:glv_x_preferred":[
        "Cill Chluain"
    ],
    "name:rus_x_preferred":[
        "\u041a\u0438\u043b\u043a\u043b\u043e\u043d"
    ],
    "name:spa_x_preferred":[
        "Kilcloon"
    ],
    "name:swe_x_preferred":[
        "Kilcloon"
    ],
    "wof:name":"Kilcloon",
    "wof:placetype":"locality",
    "wof:population":264
},
  "geometry": {"coordinates":[-6.57409,53.42414],"type":"Point"}
}