{
  "type": "Feature",
  "properties": {
    "gn:admin1_code":"M",
    "gn:admin2_code":"04",
    "gn:asciiname":"Garryduff",
    "gn:country_code":"IE",
    "gn:dem":152,
    "gn:feature_class":"P",
    "gn:feature_code":"PPL",
    "gn:name":"Garryduff",
    "gn:population":0,
    "gn:timezone":"Europe/Dublin",
    "iso:country":"IE",
    "wof:name":"Garryduff",
    "wof:placetype":"locality"
},
  "geometry": {"coordinates":[-8.11667,52.01667],"type":"Point"}
}