{
  "type": "Feature",
  "properties": {
    "gn:admin1_code":"U",
    "gn:admin2_code":"06",
    "gn:asciiname":"Burnfoot",
    "gn:country_code":"IE",
    "gn:dem":6,
    "gn:feature_class":"P",
    "gn:feature_code":"PPL",
    "gn:name":"Burnfoot",
    "gn:population":466,
    "gn:timezone":"Europe/Dublin",
    "iso:country":"IE",
    "name:eng_x_preferred":[
        "Burnfoot"
    ],
    "name:gle_x_preferred":[
        "Bun na hAbhann"
    ],
    "wof:name":"Burnfoot",
    "wof:placetype":"locality",
    "wof:population":466
},
  "geometry": {"coordinates":[-7.40302,55.05781999999999],"type":"Point"}
}