{
  "type": "Feature",
  "properties": {
    "gn:admin1_code":"L",
    "gn:admin2_code":"13",
    "gn:asciiname":"Clomantagh",
    "gn:country_code":"IE",
    "gn:dem":126,
    "gn:feature_class":"P",
    "gn:feature_code":"PPL",
    "gn:name":"Clomantagh",
    "gn:population":0,
    "gn:timezone":"Europe/Dublin",
    "iso:country":"IE",
    "wof:name":"Clomantagh",
    "wof:placetype":"locality"
},
  "geometry": {"coordinates":[-7.46889,52.72389],"type":"Point"}
}