{
  "type": "Feature",
  "properties": {
    "gn:admin1_code":"L",
    "gn:admin2_code":"13",
    "gn:asciiname":"Dungarvan",
    "gn:country_code":"IE",
    "gn:dem":63,
    "gn:feature_class":"P",
    "gn:feature_code":"PPL",
    "gn:name":"Dungarvan",
    "gn:population":0,
    "gn:timezone":"Europe/Dublin",
    "iso:country":"IE",
    "name:bar_x_preferred":[
        "Dungarven"
    ],
    "name:bul_x_preferred":[
        "\u0414\u044a\u043d\u0433\u0430\u0440\u0432\u0430\u043d"
    ],
    "name:cat_x_preferred":[
        "Dungarvan"
    ],
    "name:ceb_x_preferred":[
        "Dungarvan"
    ],
    "name:ces_x_preferred":[
        "Dungarvan"
    ],
    "name:dan_x_preferred":[
        "Dungarvan"
    ],
    "name:deu_x_preferred":[
        "Dungarvan"
    ],
    "name:eus_x_preferred":[
        "Dungarvan"
    ],
    "name:fas_x_preferred":[
        "\u062f\u0627\u0646\u06af\u0627\u0631\u0648\u0627\u0646"
    ],
    "name:fra_x_preferred":[
        "Dungarvan"
    ],
    "name:gle_x_preferred":[
        "D\u00fan Garbh\u00e1n"
    ],
    "name:glg_x_preferred":[
        "Dungarvan"
    ],
    "name:ind_x_preferred":[
        "Dungarvan"
    ],
    "name:ita_x_preferred":[
        "Dungarvan"
    ],
    "name:kat_x_preferred":[
        "\u10d3\u10d0\u10dc\u10d2\u10d0\u10e0\u10d5\u10d0\u10dc\u10d8"
    ],
    "name:kor_x_preferred":[
        "\ub358\uac00\ubc88"
    ],
    "name:nld_x_preferred":[
        "Dungarvan"
    ],
    "name:pol_x_preferred":[
        "Dungarvan"
    ],
    "name:rus_x_preferred":[
        "\u0414\u0430\u043d\u0433\u0430\u0440\u0432\u0430\u043d"
    ],
    "name:spa_x_preferred":[
        "Dungarvan"
    ],
    "name:srp_x_preferred":[
        "\u0414\u0430\u043d\u0433\u0430\u0440\u0432\u0430\u043d"
    ],
    "name:swe_x_preferred":[
        "Dungarvan"
    ],
    "name:urd_x_preferred":[
        "\u0688\u0646\u06af\u0627\u0631\u0648\u0646"
    ],
    "name:zho_x_preferred":[
        "\u9093\u52a0\u6587"
    ],
    "wof:name":"Dungarvan",
    "wof:placetype":"locality"
},
  "geometry": {"coordinates":[-7.08722,52.58971999999999],"type":"Point"}
}