{
  "type": "Feature",
  "properties": {
    "gn:admin1_code":"U",
    "gn:admin2_code":"22",
    "gn:asciiname":"Kiltybegs",
    "gn:country_code":"IE",
    "gn:dem":52,
    "gn:feature_class":"P",
    "gn:feature_code":"PPL",
    "gn:name":"Kiltybegs",
    "gn:population":0,
    "gn:timezone":"Europe/Dublin",
    "iso:country":"IE",
    "wof:name":"Kiltybegs",
    "wof:placetype":"locality"
},
  "geometry": {"coordinates":[-6.64167,53.9975],"type":"Point"}
}