{
  "type": "Feature",
  "properties": {
    "gn:admin1_code":"C",
    "gn:admin2_code":"10.0",
    "gn:asciiname":"Lough Nafurnace",
    "gn:country_code":"IE",
    "gn:dem":2,
    "gn:feature_class":"P",
    "gn:feature_code":"PPLL",
    "gn:name":"Lough Nafurnace",
    "gn:population":0,
    "gn:timezone":"Europe/Dublin",
    "iso:country":"IE",
    "wof:name":"Lough Nafurnace",
    "wof:placetype":"locality"
},
  "geometry": {"coordinates":[-9.5375,53.375],"type":"Point"}
}