{
  "type": "Feature",
  "properties": {
    "gn:admin1_code":"L",
    "gn:admin2_code":"15.0",
    "gn:asciiname":"Buddock Cross Roads",
    "gn:country_code":"IE",
    "gn:dem":102,
    "gn:feature_class":"P",
    "gn:feature_code":"PPL",
    "gn:name":"Buddock Cross Roads",
    "gn:population":0,
    "gn:timezone":"Europe/Dublin",
    "iso:country":"IE",
    "wof:name":"Buddock Cross Roads",
    "wof:placetype":"locality"
},
  "geometry": {"coordinates":[-7.16278,53.03471999999999],"type":"Point"}
}