{
  "type": "Feature",
  "properties": {
    "gn:admin1_code":"L",
    "gn:admin2_code":"29.0",
    "gn:asciiname":"Cloran and Corcullentry",
    "gn:country_code":"IE",
    "gn:dem":81,
    "gn:feature_class":"P",
    "gn:feature_code":"PPL",
    "gn:name":"Cloran and Corcullentry",
    "gn:population":0,
    "gn:timezone":"Europe/Dublin",
    "iso:country":"IE",
    "wof:name":"Cloran and Corcullentry",
    "wof:placetype":"locality"
},
  "geometry": {"coordinates":[-6.97729,53.64001],"type":"Point"}
}