{
  "type": "Feature",
  "properties": {
    "gn:country":"IE",
    "gn:fcode":"PPL",
    "gn:population":0,
    "iso:country":"IE",
    "name:bul_x_preferred":[
        "\u0411\u0430\u043b\u0438\u043d\u0433\u0435\u0430\u0440\u0439"
    ],
    "name:cat_x_preferred":[
        "B\u00e9al \u00c1tha an Ghaorthaidh"
    ],
    "name:ceb_x_preferred":[
        "Ballingeary"
    ],
    "name:deu_x_preferred":[
        "B\u00e9al \u00c1tha an Ghaorthaidh"
    ],
    "name:eng_x_preferred":[
        "Ballingeary"
    ],
    "name:eus_x_preferred":[
        "B\u00e9al \u00c1tha an Ghaorthaidh"
    ],
    "name:gle_x_preferred":[
        "B\u00e9al \u00c1tha an Ghaorthaidh"
    ],
    "name:ita_x_preferred":[
        "B\u00e9al \u00c1tha an Ghaorthaidh"
    ],
    "name:nld_x_preferred":[
        "Ballingeary"
    ],
    "name:rus_x_preferred":[
        "\u0411\u0430\u043b\u043b\u0438\u043d\u0433\u0438\u0440\u0438"
    ],
    "name:spa_x_preferred":[
        "Ballingeary"
    ],
    "name:swe_x_preferred":[
        "Ballingeary"
    ],
    "name:und_x_variant":[
        "B\u00e9al \u00c1tha An Ghaorthaidh"
    ],
    "qs_pg:aaroncc":"IE",
    "qs_pg:gn_country":"IE",
    "qs_pg:gn_fcode":"PPL",
    "qs_pg:gn_pop":0,
    "qs_pg:name":"Ballingeary",
    "qs_pg:name_adm0":"Ireland",
    "qs_pg:name_adm1":"Cork",
    "qs_pg:photos":160,
    "qs_pg:photos_1k":32,
    "qs_pg:photos_9k":1,
    "qs_pg:photos_9r":4,
    "qs_pg:photos_all":160,
    "qs_pg:photos_sr":4,
    "qs_pg:pop_sr":0,
    "qs_pg:qs_pg_placetype":"locality",
    "qs_pg:qs_pg_placetype_gp":"Town",
    "qs_pg:woe_adm0":23424803,
    "woe:adm0_id":23424803,
    "woe:name_adm0":"Ireland",
    "woe:name_adm1":"Cork",
    "woe:placetype":"Town",
    "wof:name":"Ballingeary",
    "wof:placetype":"locality",
    "wof:population":238
},
  "geometry": {"coordinates":[-9.23333,51.85],"type":"Point"}
}