{
  "type": "Feature",
  "properties": {
    "iso:country":"IE",
    "name:ceb_x_preferred":[
        "Churchtown"
    ],
    "name:deu_x_preferred":[
        "Churchtown"
    ],
    "name:eng_x_preferred":[
        "Churchtown"
    ],
    "name:nld_x_preferred":[
        "Churchtown"
    ],
    "name:pol_x_preferred":[
        "Churchtown"
    ],
    "name:swe_x_preferred":[
        "Churchtown"
    ],
    "qs:gn_adm0_cc":"IE",
    "qs:gn_local":2964574,
    "qs:gn_nam_loc":"Dublin, Dublin, IE",
    "qs:gn_namadm1":"L",
    "qs:local_max":52338,
    "qs:local_sum":267955,
    "qs:localhoods":62,
    "qs:name":"Churchtown",
    "qs:name_adm0":"Ireland",
    "qs:name_adm1":"Dublin",
    "qs:name_lau":"Churchtown-Woodlawn",
    "qs:name_local":"Dublin",
    "qs:photo_max":190,
    "qs:photo_sum":647,
    "qs:placetype":"Suburb",
    "qs:quad_count":28,
    "qs:woe_adm0":23424803,
    "qs:woe_adm1":2345254,
    "qs:woe_adm2":0,
    "qs:woe_lau":20072093,
    "qs:woe_local":560743,
    "qs:woe_ver":"7.10.0",
    "wd:wordcount":103,
    "wof:lang":[
        "eng"
    ],
    "wof:name":"Churchtown",
    "wof:placetype":"neighbourhood"
},
  "geometry": {"coordinates":[-6.257048,53.295293],"type":"Point"}
}