{
  "type": "Feature",
  "properties": {
    "gn:admin1_code":"L",
    "gn:admin2_code":"31.0",
    "gn:asciiname":"Knockandarragh",
    "gn:country_code":"IE",
    "gn:dem":198,
    "gn:feature_class":"P",
    "gn:feature_code":"PPL",
    "gn:name":"Knockandarragh",
    "gn:population":0,
    "gn:timezone":"Europe/Dublin",
    "iso:country":"IE",
    "wof:name":"Knockandarragh",
    "wof:placetype":"locality"
},
  "geometry": {"coordinates":[-6.605,53.00306],"type":"Point"}
}