{
  "type": "Feature",
  "properties": {
    "gn:admin1_code":"M",
    "gn:admin2_code":"04",
    "gn:asciiname":"Meens",
    "gn:country_code":"IE",
    "gn:dem":255,
    "gn:feature_class":"P",
    "gn:feature_code":"PPL",
    "gn:name":"Meens",
    "gn:population":0,
    "gn:timezone":"Europe/Dublin",
    "iso:country":"IE",
    "wof:name":"Meens",
    "wof:placetype":"locality"
},
  "geometry": {"coordinates":[-9.10083,52.19389],"type":"Point"}
}