{
  "type": "Feature",
  "properties": {
    "gn:admin1_code":"M",
    "gn:admin2_code":"42",
    "gn:asciiname":"Ballingaddy South",
    "gn:country_code":"IE",
    "gn:dem":112,
    "gn:feature_class":"P",
    "gn:feature_code":"PPL",
    "gn:name":"Ballingaddy South",
    "gn:population":0,
    "gn:timezone":"Europe/Dublin",
    "iso:country":"IE",
    "wof:name":"Ballingaddy South",
    "wof:placetype":"locality"
},
  "geometry": {"coordinates":[-8.56139,52.37944],"type":"Point"}
}