{
  "type": "Feature",
  "properties": {
    "gn:admin1_code":"M",
    "gn:admin2_code":"11",
    "gn:asciiname":"Crean's Cross Roads",
    "gn:country_code":"IE",
    "gn:dem":164,
    "gn:feature_class":"P",
    "gn:feature_code":"PPLL",
    "gn:name":"Crean\u2019s Cross Roads",
    "gn:population":0,
    "gn:timezone":"Europe/Dublin",
    "iso:country":"IE",
    "wof:name":"Crean's Cross Roads",
    "wof:placetype":"locality"
},
  "geometry": {"coordinates":[-8.7575,51.97167],"type":"Point"}
}