{
  "type": "Feature",
  "properties": {
    "gn:country":"IE",
    "gn:fcode":"PPL",
    "gn:population":0,
    "iso:country":"IE",
    "name:eng_x_preferred":[
        "Barnatra"
    ],
    "name:gle_x_preferred":[
        "Barr na Tr\u00e1"
    ],
    "qs_pg:aaroncc":"IE",
    "qs_pg:gn_country":"IE",
    "qs_pg:gn_fcode":"PPL",
    "qs_pg:gn_pop":0,
    "qs_pg:name":"Barnatra",
    "qs_pg:name_adm0":"Ireland",
    "qs_pg:name_adm1":"Mayo",
    "qs_pg:photos":27,
    "qs_pg:photos_1k":5,
    "qs_pg:photos_9k":1,
    "qs_pg:photos_9r":2,
    "qs_pg:photos_all":27,
    "qs_pg:photos_sr":2,
    "qs_pg:pop_sr":0,
    "qs_pg:qs_pg_placetype":"locality",
    "qs_pg:qs_pg_placetype_gp":"Town",
    "qs_pg:woe_adm0":23424803,
    "woe:adm0_id":23424803,
    "woe:name_adm0":"Ireland",
    "woe:name_adm1":"Mayo",
    "woe:placetype":"Town",
    "wof:name":"Barnatra",
    "wof:placetype":"locality"
},
  "geometry": {"coordinates":[-9.84361,54.22083],"type":"Point"}
}