{
  "type": "Feature",
  "properties": {
    "gn:admin1_code":"M",
    "gn:admin2_code":"11",
    "gn:asciiname":"Cliddaun",
    "gn:country_code":"IE",
    "gn:dem":29,
    "gn:feature_class":"P",
    "gn:feature_code":"PPLL",
    "gn:name":"Cliddaun",
    "gn:population":0,
    "gn:timezone":"Europe/Dublin",
    "iso:country":"IE",
    "name:eng_x_preferred":[
        "Cliddaun"
    ],
    "name:gle_x_preferred":[
        "An Clad\u00e1n"
    ],
    "wof:name":"Cliddaun",
    "wof:placetype":"locality"
},
  "geometry": {"coordinates":[-9.50639,52.20333],"type":"Point"}
}