{
  "type": "Feature",
  "properties": {
    "gn:admin1_code":"U",
    "gn:admin2_code":"2.0",
    "gn:asciiname":"Cloghoge",
    "gn:country_code":"IE",
    "gn:dem":87,
    "gn:feature_class":"P",
    "gn:feature_code":"PPLL",
    "gn:name":"Cloghoge",
    "gn:population":0,
    "gn:timezone":"Europe/Dublin",
    "iso:country":"IE",
    "wof:name":"Cloghoge",
    "wof:placetype":"locality"
},
  "geometry": {"coordinates":[-7.71333,54.20306],"type":"Point"}
}