{
  "type": "Feature",
  "properties": {
    "gn:admin1_code":"L",
    "gn:admin2_code":"30",
    "gn:asciiname":"Ballyhitt",
    "gn:country_code":"IE",
    "gn:dem":8,
    "gn:feature_class":"P",
    "gn:feature_code":"PPL",
    "gn:name":"Ballyhitt",
    "gn:population":0,
    "gn:timezone":"Europe/Dublin",
    "iso:country":"IE",
    "wof:name":"Ballyhitt",
    "wof:placetype":"locality"
},
  "geometry": {"coordinates":[-6.37134,52.21876],"type":"Point"}
}