{
  "type": "Feature",
  "properties": {
    "gn:admin1_code":"C",
    "gn:admin2_code":"24.0",
    "gn:asciiname":"Tarmonbarry",
    "gn:country_code":"IE",
    "gn:dem":39,
    "gn:feature_class":"P",
    "gn:feature_code":"PPL",
    "gn:name":"Tarmonbarry",
    "gn:population":366,
    "gn:timezone":"Europe/Dublin",
    "iso:country":"IE",
    "wof:name":"Tarmonbarry",
    "wof:placetype":"locality",
    "wof:population":366
},
  "geometry": {"coordinates":[-7.91925,53.74211],"type":"Point"}
}