{
  "type": "Feature",
  "properties": {
    "iso:country":"IE",
    "name:eng_x_preferred":[
        "Kilmore"
    ],
    "name:eus_x_preferred":[
        "Kilmore"
    ],
    "name:gle_x_preferred":[
        "An Chill Mh\u00f3r"
    ],
    "name:nld_x_preferred":[
        "Kilmore"
    ],
    "name:rus_x_preferred":[
        "\u041a\u0438\u043b\u043c\u043e\u0440"
    ],
    "name:spa_x_preferred":[
        "Kilmore"
    ],
    "qs:a0":"Ireland",
    "qs:a1":"*Wexford",
    "qs:a1r":"0",
    "qs:adm0":"Ireland",
    "qs:la_lc":"*",
    "qs:level":"locality",
    "qs:loc":"Kilmore",
    "qs:loc_alt":"Kilmore",
    "qs:pop":0,
    "qs:type":"buffered point",
    "wd:wordcount":138,
    "wof:name":"Kilmore",
    "wof:placetype":"locality"
},
  "geometry": {"coordinates":[-6.545727,52.205708],"type":"Point"}
}