{
  "type": "Feature",
  "properties": {
    "gn:admin1_code":"M",
    "gn:admin2_code":"11",
    "gn:asciiname":"Doonimlaghbeg",
    "gn:country_code":"IE",
    "gn:dem":24,
    "gn:feature_class":"P",
    "gn:feature_code":"PPL",
    "gn:name":"Doonimlaghbeg",
    "gn:population":0,
    "gn:timezone":"Europe/Dublin",
    "iso:country":"IE",
    "wof:name":"Doonimlaghbeg",
    "wof:placetype":"locality"
},
  "geometry": {"coordinates":[-9.61083,52.24278],"type":"Point"}
}