{
  "type": "Feature",
  "properties": {
    "gn:admin1_code":"L",
    "gn:admin2_code":"23.0",
    "gn:asciiname":"Ballyhugh",
    "gn:country_code":"IE",
    "gn:dem":74,
    "gn:feature_class":"P",
    "gn:feature_code":"PPL",
    "gn:name":"Ballyhugh",
    "gn:population":0,
    "gn:timezone":"Europe/Dublin",
    "iso:country":"IE",
    "wof:name":"Ballyhugh",
    "wof:placetype":"locality"
},
  "geometry": {"coordinates":[-7.23444,53.30972],"type":"Point"}
}