{
  "type": "Feature",
  "properties": {
    "gn:admin1_code":"C",
    "gn:admin2_code":"24.0",
    "gn:asciiname":"Grange Beg",
    "gn:country_code":"IE",
    "gn:dem":99,
    "gn:feature_class":"P",
    "gn:feature_code":"PPLL",
    "gn:name":"Grange Beg",
    "gn:population":0,
    "gn:timezone":"Europe/Dublin",
    "iso:country":"IE",
    "wof:name":"Grange Beg",
    "wof:placetype":"locality"
},
  "geometry": {"coordinates":[-8.31139,53.94833000000001],"type":"Point"}
}