{
  "type": "Feature",
  "properties": {
    "gn:admin1_code":"C",
    "gn:admin2_code":"25",
    "gn:asciiname":"Powellsborough Cross Roads",
    "gn:cc2":"IE",
    "gn:country_code":"IE",
    "gn:dem":107,
    "gn:feature_class":"P",
    "gn:feature_code":"PPL",
    "gn:name":"Powellsborough Cross Roads",
    "gn:population":0,
    "gn:timezone":"Europe/Dublin",
    "iso:country":"IE",
    "name:und_x_variant":[
        "Powellsborough",
        "Powellsborough Cross Roads"
    ],
    "wof:name":"Powellsborough Cross Roads",
    "wof:placetype":"locality"
},
  "geometry": {"coordinates":[-8.6875,54.04806],"type":"Point"}
}