{
  "type": "Feature",
  "properties": {
    "gn:admin1_code":"C",
    "gn:admin2_code":"25.0",
    "gn:asciiname":"Carrowreilly",
    "gn:country_code":"IE",
    "gn:dem":64,
    "gn:feature_class":"P",
    "gn:feature_code":"PPLL",
    "gn:name":"Carrowreilly",
    "gn:population":0,
    "gn:timezone":"Europe/Dublin",
    "iso:country":"IE",
    "wof:name":"Carrowreilly",
    "wof:placetype":"locality"
},
  "geometry": {"coordinates":[-8.63028,54.10833],"type":"Point"}
}