{
  "type": "Feature",
  "properties": {
    "gn:admin1_code":"M",
    "gn:admin2_code":"03",
    "gn:asciiname":"Mary Fort",
    "gn:country_code":"IE",
    "gn:dem":52,
    "gn:feature_class":"P",
    "gn:feature_code":"PPL",
    "gn:name":"Mary Fort",
    "gn:population":0,
    "gn:timezone":"Europe/Dublin",
    "iso:country":"IE",
    "wof:name":"Mary Fort",
    "wof:placetype":"locality"
},
  "geometry": {"coordinates":[-8.71722,52.87944],"type":"Point"}
}