{
  "type": "Feature",
  "properties": {
    "gn:admin1_code":"U",
    "gn:admin2_code":"22",
    "gn:asciiname":"Lisgillan",
    "gn:country_code":"IE",
    "gn:dem":104,
    "gn:feature_class":"P",
    "gn:feature_code":"PPLL",
    "gn:name":"Lisgillan",
    "gn:population":0,
    "gn:timezone":"Europe/Dublin",
    "iso:country":"IE",
    "wof:name":"Lisgillan",
    "wof:placetype":"locality"
},
  "geometry": {"coordinates":[-6.97528,54.12111],"type":"Point"}
}