{
  "type": "Feature",
  "properties": {
    "gn:admin1_code":"U",
    "gn:admin2_code":"06",
    "gn:asciiname":"Glenree",
    "gn:country_code":"IE",
    "gn:dem":7,
    "gn:feature_class":"P",
    "gn:feature_code":"PPLL",
    "gn:name":"Glenree",
    "gn:population":0,
    "gn:timezone":"Europe/Dublin",
    "iso:country":"IE",
    "wof:name":"Glenree",
    "wof:placetype":"locality"
},
  "geometry": {"coordinates":[-7.82639,55.15278000000001],"type":"Point"}
}