{
  "type": "Feature",
  "properties": {
    "gn:admin1_code":"L",
    "gn:admin2_code":"21.0",
    "gn:asciiname":"Basketstown",
    "gn:country_code":"IE",
    "gn:dem":78,
    "gn:feature_class":"P",
    "gn:feature_code":"PPL",
    "gn:name":"Basketstown",
    "gn:population":0,
    "gn:timezone":"Europe/Dublin",
    "iso:country":"IE",
    "wof:name":"Basketstown",
    "wof:placetype":"locality"
},
  "geometry": {"coordinates":[-6.71914,53.50516],"type":"Point"}
}