{
  "type": "Feature",
  "properties": {
    "gn:admin1_code":"L",
    "gn:admin2_code":"15.0",
    "gn:asciiname":"Long Island Well",
    "gn:country_code":"IE",
    "gn:dem":104,
    "gn:feature_class":"P",
    "gn:feature_code":"PPLL",
    "gn:name":"Long Island Well",
    "gn:population":0,
    "gn:timezone":"Europe/Dublin",
    "iso:country":"IE",
    "wof:name":"Long Island Well",
    "wof:placetype":"locality"
},
  "geometry": {"coordinates":[-7.49028,52.95528],"type":"Point"}
}