{
  "type": "Feature",
  "properties": {
    "gn:admin1_code":"M",
    "gn:admin2_code":"04",
    "gn:asciiname":"Ballynavar Bridge",
    "gn:country_code":"IE",
    "gn:dem":73,
    "gn:feature_class":"P",
    "gn:feature_code":"PPLL",
    "gn:name":"Ballynavar Bridge",
    "gn:population":0,
    "gn:timezone":"Europe/Dublin",
    "iso:country":"IE",
    "wof:name":"Ballynavar Bridge",
    "wof:placetype":"locality"
},
  "geometry": {"coordinates":[-8.97861,51.61639],"type":"Point"}
}