{
  "type": "Feature",
  "properties": {
    "gn:country":"IE",
    "gn:fcode":"PPL",
    "gn:population":0,
    "iso:country":"IE",
    "name:eng_x_preferred":[
        "Kilbaha"
    ],
    "name:epo_x_preferred":[
        "Kilbaha"
    ],
    "name:eus_x_preferred":[
        "Kilbaha"
    ],
    "name:fra_x_preferred":[
        "Kilbaha"
    ],
    "name:gle_x_preferred":[
        "Cill Bheathach"
    ],
    "name:nld_x_preferred":[
        "Kilbaha"
    ],
    "qs_pg:aaroncc":"IE",
    "qs_pg:gn_country":"IE",
    "qs_pg:gn_fcode":"PPL",
    "qs_pg:gn_pop":0,
    "qs_pg:name":"Kilbaha",
    "qs_pg:name_adm0":"Ireland",
    "qs_pg:name_adm1":"Clare",
    "qs_pg:photos":115,
    "qs_pg:photos_1k":23,
    "qs_pg:photos_9k":1,
    "qs_pg:photos_9r":3,
    "qs_pg:photos_all":115,
    "qs_pg:photos_sr":3,
    "qs_pg:pop_sr":0,
    "qs_pg:qs_pg_placetype":"locality",
    "qs_pg:qs_pg_placetype_gp":"Town",
    "qs_pg:woe_adm0":23424803,
    "woe:adm0_id":23424803,
    "woe:name_adm0":"Ireland",
    "woe:name_adm1":"Clare",
    "woe:placetype":"Town",
    "wof:name":"Kilbaha",
    "wof:placetype":"locality"
},
  "geometry": {"coordinates":[-9.86722,52.55],"type":"Point"}
}