{
  "type": "Feature",
  "properties": {
    "gn:admin1_code":"L",
    "gn:admin2_code":"21.0",
    "gn:asciiname":"Kilmainham",
    "gn:country_code":"IE",
    "gn:dem":54,
    "gn:feature_class":"P",
    "gn:feature_code":"PPL",
    "gn:name":"Kilmainham",
    "gn:population":0,
    "gn:timezone":"Europe/Dublin",
    "iso:country":"IE",
    "name:cat_x_preferred":[
        "Kilmainham"
    ],
    "name:eus_x_preferred":[
        "Kilmainham"
    ],
    "name:fra_x_preferred":[
        "Kilmainham"
    ],
    "name:gle_x_preferred":[
        "Cill Mhaighneann"
    ],
    "name:ita_x_preferred":[
        "Kilmainham"
    ],
    "name:rus_x_preferred":[
        "\u041a\u0438\u043b\u043c\u0435\u0439\u043d\u0435\u043c"
    ],
    "name:sco_x_preferred":[
        "Kilmainham"
    ],
    "name:spa_x_preferred":[
        "Kilmainham"
    ],
    "wof:name":"Kilmainham",
    "wof:placetype":"locality"
},
  "geometry": {"coordinates":[-6.83976,53.71339],"type":"Point"}
}