{
  "type": "Feature",
  "properties": {
    "gn:admin1_code":"L",
    "gn:admin2_code":"21.0",
    "gn:asciiname":"Kilmainham",
    "gn:country_code":"IE",
    "gn:dem":54,
    "gn:feature_class":"P",
    "gn:feature_code":"PPL",
    "gn:name":"Kilmainham",
    "gn:population":0,
    "gn:timezone":"Europe/Dublin",
    "iso:country":"IE",
    "wof:name":"Kilmainham",
    "wof:placetype":"locality"
},
  "geometry": {"coordinates":[-6.83976,53.71339],"type":"Point"}
}