{
  "type": "Feature",
  "properties": {
    "gn:admin1_code":"M",
    "gn:admin2_code":"42",
    "gn:asciiname":"Newbridge",
    "gn:country_code":"IE",
    "gn:dem":28,
    "gn:feature_class":"P",
    "gn:feature_code":"PPL",
    "gn:name":"Newbridge",
    "gn:population":0,
    "gn:timezone":"Europe/Dublin",
    "iso:country":"IE",
    "name:bul_x_preferred":[
        "\u041d\u044e\u0431\u0440\u0438\u0434\u0436"
    ],
    "name:ceb_x_preferred":[
        "Newbridge"
    ],
    "name:ces_x_preferred":[
        "Newbridge"
    ],
    "name:cym_x_preferred":[
        "Newbridge"
    ],
    "name:deu_x_preferred":[
        "Newbridge"
    ],
    "name:fra_x_preferred":[
        "Newbridge"
    ],
    "name:kor_x_preferred":[
        "\ub274\ube0c\ub9ac\uc9c0"
    ],
    "name:nld_x_preferred":[
        "Newbridge"
    ],
    "name:pol_x_preferred":[
        "Newbridge"
    ],
    "name:slk_x_preferred":[
        "Newbridge"
    ],
    "name:swe_x_preferred":[
        "Newbridge"
    ],
    "wof:name":"Newbridge",
    "wof:placetype":"locality"
},
  "geometry": {"coordinates":[-8.99139,52.55361],"type":"Point"}
}