{
  "type": "Feature",
  "properties": {
    "gn:admin1_code":"L",
    "gn:admin2_code":"01",
    "gn:asciiname":"Seskinryan",
    "gn:country_code":"IE",
    "gn:dem":78,
    "gn:feature_class":"P",
    "gn:feature_code":"PPL",
    "gn:name":"Seskinryan",
    "gn:population":0,
    "gn:timezone":"Europe/Dublin",
    "iso:country":"IE",
    "wof:name":"Seskinryan",
    "wof:placetype":"locality"
},
  "geometry": {"coordinates":[-6.93167,52.68222],"type":"Point"}
}