{
  "type": "Feature",
  "properties": {
    "gn:admin1_code":"C",
    "gn:admin2_code":"14",
    "gn:asciiname":"Lecarrow",
    "gn:country_code":"IE",
    "gn:dem":51,
    "gn:feature_class":"P",
    "gn:feature_code":"PPL",
    "gn:name":"Lecarrow",
    "gn:population":0,
    "gn:timezone":"Europe/Dublin",
    "iso:country":"IE",
    "name:eus_x_preferred":[
        "Lecarrow"
    ],
    "name:fry_x_preferred":[
        "Lecarrow"
    ],
    "name:gle_x_preferred":[
        "An Leithcheathr\u00fa"
    ],
    "name:kat_x_preferred":[
        "\u10da\u10d4\u10d9\u10d0\u10e0\u10dd\u10e3"
    ],
    "name:nld_x_preferred":[
        "Lecarrow"
    ],
    "name:rus_x_preferred":[
        "\u041b\u0435\u043a\u0430\u0440\u0440\u043e\u0443"
    ],
    "wof:name":"Lecarrow",
    "wof:placetype":"locality"
},
  "geometry": {"coordinates":[-8.09917,54.14471999999999],"type":"Point"}
}