{
  "type": "Feature",
  "properties": {
    "gn:admin1_code":"C",
    "gn:admin2_code":"20.0",
    "gn:asciiname":"Bocullin",
    "gn:country_code":"IE",
    "gn:dem":49,
    "gn:feature_class":"P",
    "gn:feature_code":"PPL",
    "gn:name":"Bocullin",
    "gn:population":0,
    "gn:timezone":"Europe/Dublin",
    "iso:country":"IE",
    "wof:name":"Bocullin",
    "wof:placetype":"locality"
},
  "geometry": {"coordinates":[-9.52868,53.82672],"type":"Point"}
}