{
  "type": "Feature",
  "properties": {
    "gn:admin1_code":"C",
    "gn:admin2_code":"20.0",
    "gn:asciiname":"Doogary",
    "gn:country_code":"IE",
    "gn:dem":40,
    "gn:feature_class":"P",
    "gn:feature_code":"PPL",
    "gn:name":"Doogary",
    "gn:population":0,
    "gn:timezone":"Europe/Dublin",
    "iso:country":"IE",
    "wof:name":"Doogary",
    "wof:placetype":"locality"
},
  "geometry": {"coordinates":[-9.25866,53.85495],"type":"Point"}
}