{
  "type": "Feature",
  "properties": {
    "gn:admin1_code":"L",
    "gn:admin2_code":"13",
    "gn:asciiname":"Ballygub",
    "gn:country_code":"IE",
    "gn:dem":143,
    "gn:feature_class":"P",
    "gn:feature_code":"PPL",
    "gn:name":"Ballygub",
    "gn:population":0,
    "gn:timezone":"Europe/Dublin",
    "iso:country":"IE",
    "wof:name":"Ballygub",
    "wof:placetype":"locality"
},
  "geometry": {"coordinates":[-6.9975,52.47944],"type":"Point"}
}