{
  "type": "Feature",
  "properties": {
    "iso:country":"IE",
    "name:eng_x_preferred":[
        "Donnybrook"
    ],
    "wof:name":"Donnybrook",
    "wof:placetype":"neighbourhood"
},
  "geometry": {"coordinates":[-6.231725,53.319255],"type":"Point"}
}