{
  "type": "Feature",
  "properties": {
    "gn:admin1_code":"M",
    "gn:admin2_code":"42",
    "gn:asciiname":"Barringtonsbridge",
    "gn:country_code":"IE",
    "gn:dem":33,
    "gn:feature_class":"P",
    "gn:feature_code":"PPL",
    "gn:name":"Barringtonsbridge",
    "gn:population":0,
    "gn:timezone":"Europe/Dublin",
    "iso:country":"IE",
    "wof:name":"Barringtonsbridge",
    "wof:placetype":"locality"
},
  "geometry": {"coordinates":[-8.47028,52.64444],"type":"Point"}
}