{
  "type": "Feature",
  "properties": {
    "gn:admin1_code":"M",
    "gn:admin2_code":"26.0",
    "gn:asciiname":"Newtown",
    "gn:country_code":"IE",
    "gn:dem":33,
    "gn:feature_class":"P",
    "gn:feature_code":"PPL",
    "gn:name":"Newtown",
    "gn:population":0,
    "gn:timezone":"Europe/Dublin",
    "iso:country":"IE",
    "name:bre_x_preferred":[
        "Newtown"
    ],
    "name:cat_x_preferred":[
        "Newtown"
    ],
    "name:ceb_x_preferred":[
        "Newtown"
    ],
    "name:ces_x_preferred":[
        "Newtown"
    ],
    "name:cym_x_preferred":[
        "Newtown"
    ],
    "name:dan_x_preferred":[
        "Newtown"
    ],
    "name:deu_x_preferred":[
        "Newtown"
    ],
    "name:est_x_preferred":[
        "Newtown"
    ],
    "name:fas_x_preferred":[
        "\u0646\u06cc\u0648\u062a\u0627\u0648\u0646"
    ],
    "name:fin_x_preferred":[
        "Newtown"
    ],
    "name:fra_x_preferred":[
        "Newtown"
    ],
    "name:heb_x_preferred":[
        "\u05e0\u05d9\u05d5\u05d8\u05d0\u05d5\u05df"
    ],
    "name:hun_x_preferred":[
        "Newtown"
    ],
    "name:ita_x_preferred":[
        "Newtown"
    ],
    "name:jpn_x_preferred":[
        "\u30cb\u30e5\u30fc\u30bf\u30a6\u30f3"
    ],
    "name:kor_x_preferred":[
        "\ub274\ud0c0\uc6b4"
    ],
    "name:mlg_x_preferred":[
        "Newtown"
    ],
    "name:nld_x_preferred":[
        "Newtown"
    ],
    "name:pol_x_preferred":[
        "Newtown"
    ],
    "name:rus_x_preferred":[
        "\u041d\u044c\u044e\u0442\u0430\u0443\u043d"
    ],
    "name:spa_x_preferred":[
        "Newtown"
    ],
    "name:srp_x_preferred":[
        "\u040a\u0443\u0442\u0430\u0443\u043d"
    ],
    "name:swe_x_preferred":[
        "Newtown"
    ],
    "name:urd_x_preferred":[
        "\u0646\u06cc\u0648 \u0679\u0627\u0624\u0646"
    ],
    "name:vol_x_preferred":[
        "Newtown"
    ],
    "wof:name":"Newtown",
    "wof:placetype":"locality"
},
  "geometry": {"coordinates":[-8.15,53.09444000000001],"type":"Point"}
}