{
  "type": "Feature",
  "properties": {
    "gn:admin1_code":"M",
    "gn:admin2_code":"26.0",
    "gn:asciiname":"Newtown",
    "gn:country_code":"IE",
    "gn:dem":33,
    "gn:feature_class":"P",
    "gn:feature_code":"PPL",
    "gn:name":"Newtown",
    "gn:population":0,
    "gn:timezone":"Europe/Dublin",
    "iso:country":"IE",
    "wof:name":"Newtown",
    "wof:placetype":"locality"
},
  "geometry": {"coordinates":[-8.15,53.09444000000001],"type":"Point"}
}