{
  "type": "Feature",
  "properties": {
    "gn:admin1_code":"L",
    "gn:admin2_code":"21",
    "gn:asciiname":"Teltown",
    "gn:country_code":"IE",
    "gn:dem":50,
    "gn:feature_class":"P",
    "gn:feature_code":"PPL",
    "gn:name":"Teltown",
    "gn:population":0,
    "gn:timezone":"Europe/Dublin",
    "iso:country":"IE",
    "name:amh_x_preferred":[
        "\u1273\u12ed\u120d\u1272\u1295"
    ],
    "name:gle_x_preferred":[
        "Tailtin"
    ],
    "name:ita_x_preferred":[
        "Teltown"
    ],
    "name:und_x_variant":[
        "Teltown House"
    ],
    "wof:name":"Teltown",
    "wof:placetype":"locality"
},
  "geometry": {"coordinates":[-6.7806,53.70321],"type":"Point"}
}