{
  "type": "Feature",
  "properties": {
    "gn:admin1_code":"L",
    "gn:admin2_code":"01",
    "gn:asciiname":"Flander's Cross Roads",
    "gn:country_code":"IE",
    "gn:dem":88,
    "gn:feature_class":"P",
    "gn:feature_code":"PPL",
    "gn:name":"Flander\u2019s Cross Roads",
    "gn:population":0,
    "gn:timezone":"Europe/Dublin",
    "iso:country":"IE",
    "wof:name":"Flander's Cross Roads",
    "wof:placetype":"locality"
},
  "geometry": {"coordinates":[-6.86361,52.655],"type":"Point"}
}