{
  "type": "Feature",
  "properties": {
    "gn:admin1_code":"C",
    "gn:admin2_code":"20.0",
    "gn:asciiname":"Lagduff More",
    "gn:country_code":"IE",
    "gn:dem":34,
    "gn:feature_class":"P",
    "gn:feature_code":"PPL",
    "gn:name":"Lagduff More",
    "gn:population":0,
    "gn:timezone":"Europe/Dublin",
    "iso:country":"IE",
    "wof:name":"Lagduff More",
    "wof:placetype":"locality"
},
  "geometry": {"coordinates":[-9.78703,54.07829],"type":"Point"}
}