{
  "type": "Feature",
  "properties": {
    "iso:country":"IE",
    "name:gle_x_preferred":[
        "Ros Tiall\u00e1in"
    ],
    "qs_pg:aaroncc":"IE",
    "qs_pg:name":"Rostellan",
    "qs_pg:name_adm0":"Ireland",
    "qs_pg:name_adm1":"Cork",
    "qs_pg:photos":2,
    "qs_pg:photos_1k":1,
    "qs_pg:photos_9k":1,
    "qs_pg:photos_9r":2,
    "qs_pg:photos_all":47,
    "qs_pg:photos_sr":1,
    "qs_pg:pop_sr":0,
    "qs_pg:qs_pg_placetype":"localadmin",
    "qs_pg:qs_pg_placetype_gp":"LocalAdmin",
    "qs_pg:woe_adm0":23424803,
    "woe:adm0_id":23424803,
    "woe:name_adm0":"Ireland",
    "woe:name_adm1":"Cork",
    "woe:placetype":"LocalAdmin",
    "wof:name":"Rostellan",
    "wof:placetype":"localadmin"
},
  "geometry": {"coordinates":[-8.19065,51.845548],"type":"Point"}
}