{
  "type": "Feature",
  "properties": {
    "gn:admin1_code":"M",
    "gn:admin2_code":"3.0",
    "gn:asciiname":"D'Esterre's Bridge",
    "gn:country_code":"IE",
    "gn:dem":1,
    "gn:feature_class":"P",
    "gn:feature_code":"PPL",
    "gn:name":"D\u2019Esterre\u2019s Bridge",
    "gn:population":0,
    "gn:timezone":"Europe/Dublin",
    "iso:country":"IE",
    "wof:name":"D'Esterre's Bridge",
    "wof:placetype":"locality"
},
  "geometry": {"coordinates":[-8.78083,52.71417],"type":"Point"}
}