{
  "type": "Feature",
  "properties": {
    "gn:country":"IE",
    "gn:fcode":"PPL",
    "gn:population":0,
    "iso:country":"IE",
    "name:ceb_x_preferred":[
        "Burren"
    ],
    "name:deu_x_preferred":[
        "Burren"
    ],
    "name:eng_x_preferred":[
        "Burren"
    ],
    "name:gle_x_preferred":[
        "Boirinn"
    ],
    "name:rus_x_preferred":[
        "\u0411\u0443\u0440\u0440\u0435\u043d"
    ],
    "name:swe_x_preferred":[
        "Burren"
    ],
    "qs_pg:aaroncc":"IE",
    "qs_pg:gn_country":"IE",
    "qs_pg:gn_fcode":"PPL",
    "qs_pg:gn_pop":0,
    "qs_pg:name":"Burren",
    "qs_pg:name_adm0":"Ireland",
    "qs_pg:name_adm1":"Clare",
    "qs_pg:photos":720,
    "qs_pg:photos_1k":146,
    "qs_pg:photos_9k":3,
    "qs_pg:photos_9r":5,
    "qs_pg:photos_all":720,
    "qs_pg:photos_sr":8,
    "qs_pg:pop_sr":0,
    "qs_pg:qs_pg_placetype":"locality",
    "qs_pg:qs_pg_placetype_gp":"Town",
    "qs_pg:woe_adm0":23424803,
    "woe:adm0_id":23424803,
    "woe:name_adm0":"Ireland",
    "woe:name_adm1":"Clare",
    "woe:placetype":"Town",
    "wof:name":"Burren",
    "wof:placetype":"locality"
},
  "geometry": {"coordinates":[-9.07556,53.14667],"type":"Point"}
}