{
  "type": "Feature",
  "properties": {
    "gn:admin1_code":"L",
    "gn:admin2_code":"13",
    "gn:asciiname":"Annaleck",
    "gn:country_code":"IE",
    "gn:dem":92,
    "gn:feature_class":"P",
    "gn:feature_code":"PPL",
    "gn:name":"Annaleck",
    "gn:population":0,
    "gn:timezone":"Europe/Dublin",
    "iso:country":"IE",
    "wof:name":"Annaleck",
    "wof:placetype":"locality"
},
  "geometry": {"coordinates":[-7.02333,52.58611],"type":"Point"}
}