{
  "type": "Feature",
  "properties": {
    "gn:admin1_code":"L",
    "gn:admin2_code":"30",
    "gn:asciiname":"Ballymoney",
    "gn:country_code":"IE",
    "gn:dem":32,
    "gn:feature_class":"P",
    "gn:feature_code":"PPL",
    "gn:name":"Ballymoney",
    "gn:population":0,
    "gn:timezone":"Europe/Dublin",
    "iso:country":"IE",
    "wof:name":"Ballymoney",
    "wof:placetype":"locality"
},
  "geometry": {"coordinates":[-6.21886,52.6725],"type":"Point"}
}