{
  "type": "Feature",
  "properties": {
    "gn:admin1_code":"L",
    "gn:admin2_code":"30",
    "gn:asciiname":"Ballymoney",
    "gn:country_code":"IE",
    "gn:dem":32,
    "gn:feature_class":"P",
    "gn:feature_code":"PPL",
    "gn:name":"Ballymoney",
    "gn:population":0,
    "gn:timezone":"Europe/Dublin",
    "iso:country":"IE",
    "name:afr_x_preferred":[
        "Ballymoney"
    ],
    "name:bul_x_preferred":[
        "\u0411\u0430\u043b\u0438\u043c\u044a\u043d\u0438"
    ],
    "name:cat_x_preferred":[
        "Ballymoney"
    ],
    "name:ceb_x_preferred":[
        "Ballymoney"
    ],
    "name:deu_x_preferred":[
        "Ballymoney"
    ],
    "name:eus_x_preferred":[
        "Ballymoney"
    ],
    "name:fas_x_preferred":[
        "\u0628\u0627\u0644\u06cc\u0645\u0627\u0646\u06cc"
    ],
    "name:fas_x_variant":[
        "\u0628\u0627\u0644\u06cc\u200c\u0645\u0627\u0646\u06cc"
    ],
    "name:fra_x_preferred":[
        "Ballymoney"
    ],
    "name:gla_x_preferred":[
        "Baile Monaidh"
    ],
    "name:gle_x_preferred":[
        "Baile Monaidh"
    ],
    "name:heb_x_preferred":[
        "\u05d1\u05d0\u05dc\u05d9\u05de\u05d5\u05e0\u05d9"
    ],
    "name:hin_x_preferred":[
        "\u092c\u0948\u0932\u0940\u092e\u0928\u0940"
    ],
    "name:hun_x_preferred":[
        "Ballymoney"
    ],
    "name:ind_x_preferred":[
        "Ballymoney"
    ],
    "name:ita_x_preferred":[
        "Ballymoney"
    ],
    "name:kor_x_preferred":[
        "\ubc38\ub9ac\uba38\ub2c8"
    ],
    "name:msa_x_preferred":[
        "Ballymoney"
    ],
    "name:nld_x_preferred":[
        "Ballymoney"
    ],
    "name:nor_x_preferred":[
        "Ballymoney"
    ],
    "name:pol_x_preferred":[
        "Ballymoney"
    ],
    "name:por_x_preferred":[
        "Ballymoney"
    ],
    "name:rus_x_preferred":[
        "\u0411\u0430\u043b\u043b\u0438\u043c\u043e\u043d\u0438"
    ],
    "name:spa_x_preferred":[
        "Ballymoney"
    ],
    "name:swe_x_preferred":[
        "Ballymoney"
    ],
    "name:tur_x_preferred":[
        "Ballymoney"
    ],
    "name:ukr_x_preferred":[
        "\u0411\u0430\u043b\u043b\u0456\u043c\u0430\u043d\u0456 "
    ],
    "name:urd_x_preferred":[
        "\u0628\u0627\u0644\u06cc\u0645\u0646\u06cc"
    ],
    "name:vie_x_preferred":[
        "Ballymoney"
    ],
    "wof:name":"Ballymoney",
    "wof:placetype":"locality"
},
  "geometry": {"coordinates":[-6.21886,52.6725],"type":"Point"}
}