{
  "type": "Feature",
  "properties": {
    "gn:admin1_code":"M",
    "gn:admin2_code":"04",
    "gn:asciiname":"Ballagheloghane Cross Roads",
    "gn:country_code":"IE",
    "gn:dem":111,
    "gn:feature_class":"P",
    "gn:feature_code":"PPLL",
    "gn:name":"Ballagheloghane Cross Roads",
    "gn:population":0,
    "gn:timezone":"Europe/Dublin",
    "iso:country":"IE",
    "wof:name":"Ballagheloghane Cross Roads",
    "wof:placetype":"locality"
},
  "geometry": {"coordinates":[-8.81889,51.76583],"type":"Point"}
}