{
  "type": "Feature",
  "properties": {
    "gn:admin1_code":"L",
    "gn:admin2_code":"35.0",
    "gn:asciiname":"Annfield",
    "gn:country_code":"IE",
    "gn:dem":64,
    "gn:feature_class":"P",
    "gn:feature_code":"PPL",
    "gn:name":"Annfield",
    "gn:population":0,
    "gn:timezone":"Europe/Dublin",
    "iso:country":"IE",
    "wof:name":"Annfield",
    "wof:placetype":"locality"
},
  "geometry": {"coordinates":[-6.40556,53.37444],"type":"Point"}
}