{
  "type": "Feature",
  "properties": {
    "gn:admin1_code":"U",
    "gn:admin2_code":"06",
    "gn:asciiname":"Effickmore",
    "gn:country_code":"IE",
    "gn:dem":161,
    "gn:feature_class":"P",
    "gn:feature_code":"PPLL",
    "gn:name":"Effickmore",
    "gn:population":0,
    "gn:timezone":"Europe/Dublin",
    "iso:country":"IE",
    "wof:name":"Effickmore",
    "wof:placetype":"locality"
},
  "geometry": {"coordinates":[-7.45667,55.23278000000001],"type":"Point"}
}