{
  "type": "Feature",
  "properties": {
    "gn:admin1_code":"L",
    "gn:admin2_code":"15",
    "gn:asciiname":"Guffsborough Cross Roads",
    "gn:country_code":"IE",
    "gn:dem":126,
    "gn:feature_class":"P",
    "gn:feature_code":"PPL",
    "gn:name":"Guffsborough Cross Roads",
    "gn:population":0,
    "gn:timezone":"Europe/Dublin",
    "iso:country":"IE",
    "wof:name":"Guffsborough Cross Roads",
    "wof:placetype":"locality"
},
  "geometry": {"coordinates":[-7.48333,52.89778],"type":"Point"}
}