{
  "type": "Feature",
  "properties": {
    "gn:admin1_code":"C",
    "gn:admin2_code":"25.0",
    "gn:asciiname":"Doonally",
    "gn:country_code":"IE",
    "gn:dem":59,
    "gn:feature_class":"P",
    "gn:feature_code":"PPLL",
    "gn:name":"Doonally",
    "gn:population":0,
    "gn:timezone":"Europe/Dublin",
    "iso:country":"IE",
    "wof:name":"Doonally",
    "wof:placetype":"locality"
},
  "geometry": {"coordinates":[-8.41944,54.18306],"type":"Point"}
}