{
  "type": "Feature",
  "properties": {
    "gn:admin1_code":"L",
    "gn:admin2_code":"19",
    "gn:asciiname":"Jenkinstown Cross",
    "gn:country_code":"IE",
    "gn:dem":18,
    "gn:feature_class":"P",
    "gn:feature_code":"PPLL",
    "gn:name":"Jenkinstown Cross",
    "gn:population":323,
    "gn:timezone":"Europe/Dublin",
    "iso:country":"IE",
    "name:und_x_variant":[
        "Jenkinstown",
        "Jenkinstown Cross"
    ],
    "wof:name":"Jenkinstown Cross",
    "wof:placetype":"locality",
    "wof:population":323
},
  "geometry": {"coordinates":[-6.30694,54.02083],"type":"Point"}
}