{
  "type": "Feature",
  "properties": {
    "iso:country":"IE",
    "name:eng_x_preferred":[
        "Castleknock"
    ],
    "wof:name":"Castleknock",
    "wof:placetype":"neighbourhood"
},
  "geometry": {"coordinates":[-6.362621,53.373001],"type":"Point"}
}