{
  "type": "Feature",
  "properties": {
    "gn:admin1_code":"M",
    "gn:admin2_code":"04",
    "gn:asciiname":"Boherbay Cross Roads",
    "gn:country_code":"IE",
    "gn:dem":88,
    "gn:feature_class":"P",
    "gn:feature_code":"PPLL",
    "gn:name":"Boherbay Cross Roads",
    "gn:population":0,
    "gn:timezone":"Europe/Dublin",
    "iso:country":"IE",
    "wof:name":"Boherbay Cross Roads",
    "wof:placetype":"locality"
},
  "geometry": {"coordinates":[-8.63111,52.23667],"type":"Point"}
}