{
  "type": "Feature",
  "properties": {
    "gn:admin1_code":"M",
    "gn:admin2_code":"3.0",
    "gn:asciiname":"Derryheena",
    "gn:country_code":"IE",
    "gn:dem":119,
    "gn:feature_class":"P",
    "gn:feature_code":"PPLL",
    "gn:name":"Derryheena",
    "gn:population":0,
    "gn:timezone":"Europe/Dublin",
    "iso:country":"IE",
    "wof:name":"Derryheena",
    "wof:placetype":"locality"
},
  "geometry": {"coordinates":[-8.83694,52.9275],"type":"Point"}
}