{
  "type": "Feature",
  "properties": {
    "gn:admin1_code":"L",
    "gn:admin2_code":"31.0",
    "gn:asciiname":"Tinoranhill Cross Roads",
    "gn:country_code":"IE",
    "gn:dem":170,
    "gn:feature_class":"P",
    "gn:feature_code":"PPL",
    "gn:name":"Tinoranhill Cross Roads",
    "gn:population":0,
    "gn:timezone":"Europe/Dublin",
    "iso:country":"IE",
    "wof:name":"Tinoranhill Cross Roads",
    "wof:placetype":"locality"
},
  "geometry": {"coordinates":[-6.74972,52.95806],"type":"Point"}
}