{
  "type": "Feature",
  "properties": {
    "iso:country":"IE",
    "name:eng_x_preferred":[
        "Mayfield"
    ],
    "wof:name":"Mayfield",
    "wof:placetype":"neighbourhood"
},
  "geometry": {"coordinates":[-8.43285,51.912367],"type":"Point"}
}