{
  "type": "Feature",
  "properties": {
    "iso:country":"IE",
    "name:dut_x_preferred":[
        "Pontoon"
    ],
    "name:eng_x_preferred":[
        "Pontoon"
    ],
    "name:fre_x_preferred":[
        "Pontoon"
    ],
    "name:geo_x_preferred":[
        "\u10de\u10dd\u10dc\u10e2\u10e3\u10dc\u10d8"
    ],
    "name:gle_x_preferred":[
        "Pont Abhann"
    ],
    "name:ita_x_preferred":[
        "Pontoon"
    ],
    "name:rus_x_preferred":[
        "\u041f\u043e\u043d\u0442\u0443\u043d"
    ],
    "qs_pg:aaroncc":"IE",
    "qs_pg:name":"Pontoon",
    "qs_pg:name_adm0":"Ireland",
    "qs_pg:name_adm1":"Mayo",
    "qs_pg:photos":152,
    "qs_pg:photos_1k":31,
    "qs_pg:photos_9k":1,
    "qs_pg:photos_9r":4,
    "qs_pg:photos_all":152,
    "qs_pg:photos_sr":4,
    "qs_pg:pop_sr":0,
    "qs_pg:qs_pg_placetype":"locality",
    "qs_pg:qs_pg_placetype_gp":"Town",
    "qs_pg:woe_adm0":23424803,
    "woe:adm0_id":23424803,
    "woe:name_adm0":"Ireland",
    "woe:name_adm1":"Mayo",
    "woe:placetype":"Town",
    "wof:name":"Pontoon",
    "wof:placetype":"locality"
},
  "geometry": {"coordinates":[-9.207487,53.9863255],"type":"Point"}
}