{
  "type": "Feature",
  "properties": {
    "gn:admin1_code":"M",
    "gn:admin2_code":"04",
    "gn:asciiname":"Glantane",
    "gn:country_code":"IE",
    "gn:dem":195,
    "gn:feature_class":"P",
    "gn:feature_code":"PPL",
    "gn:name":"Glantane",
    "gn:population":0,
    "gn:timezone":"Europe/Dublin",
    "iso:country":"IE",
    "wof:name":"Glantane",
    "wof:placetype":"locality"
},
  "geometry": {"coordinates":[-9.06139,51.99972],"type":"Point"}
}