{
  "type": "Feature",
  "properties": {
    "gn:admin1_code":"L",
    "gn:admin2_code":"12.0",
    "gn:asciiname":"Allenwood Cross Roads",
    "gn:country_code":"IE",
    "gn:dem":82,
    "gn:feature_class":"P",
    "gn:feature_code":"PPL",
    "gn:name":"Allenwood Cross Roads",
    "gn:population":845,
    "gn:timezone":"Europe/Dublin",
    "iso:country":"IE",
    "name:ceb_x_preferred":[
        "Allenwood"
    ],
    "name:deu_x_preferred":[
        "Allenwood"
    ],
    "name:gle_x_preferred":[
        "Fiodh Al\u00faine"
    ],
    "name:ita_x_preferred":[
        "Allenwood"
    ],
    "name:nld_x_preferred":[
        "Allenwood"
    ],
    "name:spa_x_preferred":[
        "Allenwood"
    ],
    "name:swe_x_preferred":[
        "Allenwood"
    ],
    "name:ukr_x_preferred":[
        "\u0410\u043b\u043b\u0435\u043d\u0432\u0443\u0434"
    ],
    "wof:name":"Allenwood Cross Roads",
    "wof:placetype":"locality",
    "wof:population":845
},
  "geometry": {"coordinates":[-6.86161,53.28392],"type":"Point"}
}