{
  "type": "Feature",
  "properties": {
    "gn:admin1_code":"L",
    "gn:admin2_code":"12.0",
    "gn:asciiname":"Allenwood Cross Roads",
    "gn:country_code":"IE",
    "gn:dem":82,
    "gn:feature_class":"P",
    "gn:feature_code":"PPL",
    "gn:name":"Allenwood Cross Roads",
    "gn:population":845,
    "gn:timezone":"Europe/Dublin",
    "iso:country":"IE",
    "name:gle_x_preferred":[
        "Fiodh Al\u00faine"
    ],
    "name:und_x_variant":[
        "Allenwood"
    ],
    "wof:name":"Allenwood Cross Roads",
    "wof:placetype":"locality",
    "wof:population":845
},
  "geometry": {"coordinates":[-6.86161,53.28392],"type":"Point"}
}