{
  "type": "Feature",
  "properties": {
    "gn:admin1_code":"L",
    "gn:admin2_code":"21",
    "gn:asciiname":"Black Bull",
    "gn:country_code":"IE",
    "gn:dem":80,
    "gn:feature_class":"P",
    "gn:feature_code":"PPL",
    "gn:name":"Black Bull",
    "gn:population":0,
    "gn:timezone":"Europe/Dublin",
    "iso:country":"IE",
    "wof:name":"Black Bull",
    "wof:placetype":"locality"
},
  "geometry": {"coordinates":[-6.47889,53.45083],"type":"Point"}
}