{
  "type": "Feature",
  "properties": {
    "gn:admin1_code":"U",
    "gn:admin2_code":"02",
    "gn:asciiname":"Ledonigan",
    "gn:country_code":"IE",
    "gn:dem":200,
    "gn:feature_class":"P",
    "gn:feature_code":"PPLL",
    "gn:name":"Ledonigan",
    "gn:population":0,
    "gn:timezone":"Europe/Dublin",
    "iso:country":"IE",
    "wof:name":"Ledonigan",
    "wof:placetype":"locality"
},
  "geometry": {"coordinates":[-7.075,53.94306],"type":"Point"}
}