{
  "type": "Feature",
  "properties": {
    "gn:country":"IE",
    "gn:fcode":"PPL",
    "gn:population":0,
    "iso:country":"IE",
    "name:bre_x_preferred":[
        "Gallach"
    ],
    "name:eng_x_preferred":[
        "Castleblakeney"
    ],
    "name:eus_x_preferred":[
        "Castleblakeney"
    ],
    "name:gle_x_preferred":[
        "Gallach"
    ],
    "name:heb_x_preferred":[
        "\u05e7\u05e1\u05dc\u05d1\u05dc\u05d9\u05d9\u05e7\u05e0\u05d9"
    ],
    "name:kat_x_preferred":[
        "\u10d9\u10d0\u10e1\u10da\u10d1\u10da\u10d4\u10d8\u10d9\u10dc\u10d8"
    ],
    "name:nld_x_preferred":[
        "Castleblakeney"
    ],
    "name:rus_x_preferred":[
        "\u041a\u0430\u0441\u043b\u0431\u043b\u0435\u0439\u043a\u043d\u0438"
    ],
    "name:und_x_variant":[
        "Castleblakeny"
    ],
    "qs_pg:aaroncc":"IE",
    "qs_pg:gn_country":"IE",
    "qs_pg:gn_fcode":"PPL",
    "qs_pg:gn_pop":0,
    "qs_pg:name":"Castleblakeney",
    "qs_pg:name_adm0":"Ireland",
    "qs_pg:name_adm1":"Galway",
    "qs_pg:photos_9r":0,
    "qs_pg:photos_sr":0,
    "qs_pg:pop_sr":0,
    "qs_pg:qs_pg_placetype":"locality",
    "qs_pg:qs_pg_placetype_gp":"Town",
    "qs_pg:woe_adm0":23424803,
    "woe:adm0_id":23424803,
    "woe:name_adm0":"Ireland",
    "woe:name_adm1":"Galway",
    "woe:placetype":"Town",
    "wof:name":"Castleblakeney",
    "wof:placetype":"locality"
},
  "geometry": {"coordinates":[-8.48333,53.43333],"type":"Point"}
}