{
  "type": "Feature",
  "properties": {
    "gn:admin1_code":"L",
    "gn:admin2_code":"13",
    "gn:asciiname":"Killamery",
    "gn:country_code":"IE",
    "gn:dem":103,
    "gn:feature_class":"P",
    "gn:feature_code":"PPL",
    "gn:name":"Killamery",
    "gn:population":0,
    "gn:timezone":"Europe/Dublin",
    "iso:country":"IE",
    "wof:name":"Killamery",
    "wof:placetype":"locality"
},
  "geometry": {"coordinates":[-7.44528,52.47583],"type":"Point"}
}