{
  "type": "Feature",
  "properties": {
    "gn:admin1_code":"U",
    "gn:admin2_code":"06",
    "gn:asciiname":"Kildoney",
    "gn:country_code":"IE",
    "gn:dem":31,
    "gn:feature_class":"P",
    "gn:feature_code":"PPL",
    "gn:name":"Kildoney",
    "gn:population":0,
    "gn:timezone":"Europe/Dublin",
    "iso:country":"IE",
    "wof:name":"Kildoney",
    "wof:placetype":"locality"
},
  "geometry": {"coordinates":[-8.25583,54.52306],"type":"Point"}
}