{
  "type": "Feature",
  "properties": {
    "gn:admin1_code":"U",
    "gn:admin2_code":"02",
    "gn:asciiname":"Lisagoan",
    "gn:country_code":"IE",
    "gn:dem":202,
    "gn:feature_class":"P",
    "gn:feature_code":"PPLL",
    "gn:name":"Lisagoan",
    "gn:population":0,
    "gn:timezone":"Europe/Dublin",
    "iso:country":"IE",
    "wof:name":"Lisagoan",
    "wof:placetype":"locality"
},
  "geometry": {"coordinates":[-6.87306,53.94944],"type":"Point"}
}