{
  "type": "Feature",
  "properties": {
    "gn:admin1_code":"M",
    "gn:admin2_code":"04",
    "gn:asciiname":"Geara Bridge",
    "gn:country_code":"IE",
    "gn:dem":122,
    "gn:feature_class":"P",
    "gn:feature_code":"PPLL",
    "gn:name":"Geara Bridge",
    "gn:population":0,
    "gn:timezone":"Europe/Dublin",
    "iso:country":"IE",
    "wof:name":"Geara Bridge",
    "wof:placetype":"locality"
},
  "geometry": {"coordinates":[-9.02389,51.79306],"type":"Point"}
}