{
  "type": "Feature",
  "properties": {
    "gn:admin1_code":"M",
    "gn:admin2_code":"11",
    "gn:asciiname":"Glena Bridge",
    "gn:country_code":"IE",
    "gn:dem":105,
    "gn:feature_class":"P",
    "gn:feature_code":"PPLL",
    "gn:name":"Glena Bridge",
    "gn:population":0,
    "gn:timezone":"Europe/Dublin",
    "iso:country":"IE",
    "wof:name":"Glena Bridge",
    "wof:placetype":"locality"
},
  "geometry": {"coordinates":[-9.365,52.34472],"type":"Point"}
}