{
  "type": "Feature",
  "properties": {
    "gn:admin1_code":"C",
    "gn:admin2_code":"20.0",
    "gn:asciiname":"Glenulra",
    "gn:country_code":"IE",
    "gn:dem":88,
    "gn:feature_class":"P",
    "gn:feature_code":"PPLL",
    "gn:name":"Glenulra",
    "gn:population":0,
    "gn:timezone":"Europe/Dublin",
    "iso:country":"IE",
    "wof:name":"Glenulra",
    "wof:placetype":"locality"
},
  "geometry": {"coordinates":[-9.44139,54.29944],"type":"Point"}
}