{
  "type": "Feature",
  "properties": {
    "gn:admin1_code":"C",
    "gn:admin2_code":"10.0",
    "gn:asciiname":"Boulard",
    "gn:country_code":"IE",
    "gn:dem":38,
    "gn:feature_class":"P",
    "gn:feature_code":"PPL",
    "gn:name":"Boulard",
    "gn:population":0,
    "gn:timezone":"Europe/Dublin",
    "iso:country":"IE",
    "wof:name":"Boulard",
    "wof:placetype":"locality"
},
  "geometry": {"coordinates":[-9.93246,53.39633000000001],"type":"Point"}
}