{
  "type": "Feature",
  "properties": {
    "gn:admin1_code":"C",
    "gn:admin2_code":"10.0",
    "gn:asciiname":"Shanvally",
    "gn:country_code":"IE",
    "gn:dem":71,
    "gn:feature_class":"P",
    "gn:feature_code":"PPLL",
    "gn:name":"Shanvally",
    "gn:population":0,
    "gn:timezone":"Europe/Dublin",
    "iso:country":"IE",
    "name:eng_x_preferred":[
        "Shanvally"
    ],
    "name:gle_x_preferred":[
        "An Seanbhaile"
    ],
    "wof:name":"Shanvally",
    "wof:placetype":"locality"
},
  "geometry": {"coordinates":[-9.49694,53.37917],"type":"Point"}
}