{
  "type": "Feature",
  "properties": {
    "gn:admin1_code":"U",
    "gn:admin2_code":"06",
    "gn:asciiname":"Sockar",
    "gn:country_code":"IE",
    "gn:dem":40,
    "gn:feature_class":"P",
    "gn:feature_code":"PPL",
    "gn:name":"Sockar",
    "gn:population":0,
    "gn:timezone":"Europe/Dublin",
    "iso:country":"IE",
    "wof:name":"Sockar",
    "wof:placetype":"locality"
},
  "geometry": {"coordinates":[-7.83778,54.98444],"type":"Point"}
}