{
  "type": "Feature",
  "properties": {
    "gn:admin1_code":"C",
    "gn:admin2_code":"25.0",
    "gn:asciiname":"Carrowneden",
    "gn:country_code":"IE",
    "gn:dem":107,
    "gn:feature_class":"P",
    "gn:feature_code":"PPLL",
    "gn:name":"Carrowneden",
    "gn:population":0,
    "gn:timezone":"Europe/Dublin",
    "iso:country":"IE",
    "wof:name":"Carrowneden",
    "wof:placetype":"locality"
},
  "geometry": {"coordinates":[-8.69778,54.13972],"type":"Point"}
}