{
  "type": "Feature",
  "properties": {
    "iso:country":"IE",
    "name:eng_x_preferred":[
        "Carnmore"
    ],
    "name:eus_x_preferred":[
        "Carnmore"
    ],
    "name:gle_x_preferred":[
        "An Carn M\u00f3r"
    ],
    "name:glg_x_preferred":[
        "Carnmore - An Car M\u00f3r"
    ],
    "name:kat_x_preferred":[
        "\u10d9\u10d0\u10e0\u10dc\u10db\u10dd\u10e0\u10d8"
    ],
    "name:nld_x_preferred":[
        "Carnmore"
    ],
    "name:nob_x_preferred":[
        "Carnmore"
    ],
    "name:rus_x_preferred":[
        "\u041a\u0430\u0440\u043d\u043c\u043e\u0440"
    ],
    "qs_pg:aaroncc":"IE",
    "qs_pg:name":"Carnmore",
    "qs_pg:name_adm0":"Ireland",
    "qs_pg:name_adm1":"Galway",
    "qs_pg:photos":33,
    "qs_pg:photos_1k":7,
    "qs_pg:photos_9k":1,
    "qs_pg:photos_9r":2,
    "qs_pg:photos_all":33,
    "qs_pg:photos_sr":2,
    "qs_pg:pop_sr":0,
    "qs_pg:qs_pg_placetype":"locality",
    "qs_pg:qs_pg_placetype_gp":"Town",
    "qs_pg:woe_adm0":23424803,
    "woe:adm0_id":23424803,
    "woe:name_adm0":"Ireland",
    "woe:name_adm1":"Galway",
    "woe:placetype":"Town",
    "wof:name":"Carnmore",
    "wof:placetype":"locality"
},
  "geometry": {"coordinates":[-8.899955,53.312108],"type":"Point"}
}