{
  "type": "Feature",
  "properties": {
    "gn:admin1_code":"L",
    "gn:admin2_code":"30",
    "gn:asciiname":"Johnstown",
    "gn:country_code":"IE",
    "gn:dem":82,
    "gn:feature_class":"P",
    "gn:feature_code":"PPL",
    "gn:name":"Johnstown",
    "gn:population":0,
    "gn:timezone":"Europe/Dublin",
    "iso:country":"IE",
    "name:cat_x_preferred":[
        "Johnstown"
    ],
    "name:ceb_x_preferred":[
        "Johnstown"
    ],
    "name:deu_x_preferred":[
        "Johnstown"
    ],
    "name:fra_x_preferred":[
        "Johnstown"
    ],
    "name:ita_x_preferred":[
        "Johnstown"
    ],
    "name:jpn_x_preferred":[
        "\u30b8\u30e7\u30f3\u30ba\u30bf\u30a6\u30f3"
    ],
    "name:kor_x_preferred":[
        "\uc874\uc2a4\ud0c0\uc6b4"
    ],
    "name:lav_x_preferred":[
        "D\u017eonstauna"
    ],
    "name:nld_x_preferred":[
        "Johnstown"
    ],
    "name:pol_x_preferred":[
        "Johnstown"
    ],
    "name:por_x_preferred":[
        "Johnstown"
    ],
    "name:rus_x_preferred":[
        "\u0414\u0436\u043e\u043d\u0441\u0442\u0430\u0443\u043d"
    ],
    "name:spa_x_preferred":[
        "Johnstown"
    ],
    "name:srp_x_preferred":[
        "\u040f\u043e\u043d\u0441\u0442\u0430\u0443\u043d"
    ],
    "name:swe_x_preferred":[
        "Johnstown"
    ],
    "name:ukr_x_preferred":[
        "\u0414\u0436\u043e\u043d\u0441\u0442\u0430\u0443\u043d"
    ],
    "name:vol_x_preferred":[
        "Johnstown"
    ],
    "name:zho_x_preferred":[
        "\u7d04\u7ff0\u57ce"
    ],
    "wof:name":"Johnstown",
    "wof:placetype":"locality"
},
  "geometry": {"coordinates":[-6.23389,52.78139],"type":"Point"}
}