{
  "type": "Feature",
  "properties": {
    "gn:admin1_code":"M",
    "gn:admin2_code":"42",
    "gn:asciiname":"Carrigeen Cross Roads",
    "gn:country_code":"IE",
    "gn:dem":214,
    "gn:feature_class":"P",
    "gn:feature_code":"PPL",
    "gn:name":"Carrigeen Cross Roads",
    "gn:population":0,
    "gn:timezone":"Europe/Dublin",
    "iso:country":"IE",
    "wof:name":"Carrigeen Cross Roads",
    "wof:placetype":"locality"
},
  "geometry": {"coordinates":[-8.47694,52.34778],"type":"Point"}
}