{
  "type": "Feature",
  "properties": {
    "gn:admin1_code":"C",
    "gn:admin2_code":"10",
    "gn:asciiname":"Mount Bellew Bridge",
    "gn:country_code":"IE",
    "gn:dem":61,
    "gn:feature_class":"P",
    "gn:feature_code":"PPL",
    "gn:name":"Mount Bellew Bridge",
    "gn:population":0,
    "gn:timezone":"Europe/Dublin",
    "iso:country":"IE",
    "name:eng_x_preferred":[
        "Mount Bellew Bridge"
    ],
    "name:gle_x_preferred":[
        "An Creag\u00e1n"
    ],
    "name:und_x_variant":[
        "Mount Bellew"
    ],
    "wof:name":"Mount Bellew Bridge",
    "wof:placetype":"locality"
},
  "geometry": {"coordinates":[-8.49689,53.46763000000001],"type":"Point"}
}