{
  "type": "Feature",
  "properties": {
    "gn:admin1_code":"C",
    "gn:admin2_code":"20.0",
    "gn:asciiname":"Knockshanbo",
    "gn:country_code":"IE",
    "gn:dem":14,
    "gn:feature_class":"P",
    "gn:feature_code":"PPLL",
    "gn:name":"Knockshanbo",
    "gn:population":0,
    "gn:timezone":"Europe/Dublin",
    "iso:country":"IE",
    "name:eng_x_preferred":[
        "Knockshanbo"
    ],
    "name:gle_x_preferred":[
        "Cnoc Seanbhotha"
    ],
    "wof:name":"Knockshanbo",
    "wof:placetype":"locality"
},
  "geometry": {"coordinates":[-9.92456,54.25165],"type":"Point"}
}