{
  "type": "Feature",
  "properties": {
    "gn:admin1_code":"M",
    "gn:admin2_code":"11",
    "gn:asciiname":"Kilderry",
    "gn:country_code":"IE",
    "gn:dem":24,
    "gn:feature_class":"P",
    "gn:feature_code":"PPL",
    "gn:name":"Kilderry",
    "gn:population":0,
    "gn:timezone":"Europe/Dublin",
    "iso:country":"IE",
    "name:ell_x_preferred":[
        "\u039a\u03af\u03bb\u03bd\u03c4\u03b5\u03c1\u03c5"
    ],
    "name:eus_x_preferred":[
        "Kilderry"
    ],
    "name:rus_x_preferred":[
        "\u041a\u0438\u043b\u0434\u0435\u0440\u0440\u0438"
    ],
    "wof:name":"Kilderry",
    "wof:placetype":"locality"
},
  "geometry": {"coordinates":[-9.74889,52.13722],"type":"Point"}
}