{
  "type": "Feature",
  "properties": {
    "gn:admin1_code":"L",
    "gn:admin2_code":"31.0",
    "gn:asciiname":"Stratford on Slaney",
    "gn:country_code":"IE",
    "gn:dem":140,
    "gn:feature_class":"P",
    "gn:feature_code":"PPL",
    "gn:name":"Stratford on Slaney",
    "gn:population":0,
    "gn:timezone":"Europe/Dublin",
    "iso:country":"IE",
    "wof:name":"Stratford on Slaney",
    "wof:placetype":"locality"
},
  "geometry": {"coordinates":[-6.6669,52.98079],"type":"Point"}
}