{
  "type": "Feature",
  "properties": {
    "gn:admin1_code":"L",
    "gn:admin2_code":"31.0",
    "gn:asciiname":"Stratford on Slaney",
    "gn:country_code":"IE",
    "gn:dem":140,
    "gn:feature_class":"P",
    "gn:feature_code":"PPL",
    "gn:name":"Stratford on Slaney",
    "gn:population":0,
    "gn:timezone":"Europe/Dublin",
    "iso:country":"IE",
    "name:eus_x_preferred":[
        "Stratford-on-Slaney"
    ],
    "name:gle_x_preferred":[
        "\u00c1th na Sr\u00e1ide"
    ],
    "name:rus_x_preferred":[
        "\u0421\u0442\u0440\u0430\u0442\u0444\u043e\u0440\u0434-\u043d\u0430-\u0421\u043b\u0435\u0439\u043d\u0438"
    ],
    "name:spa_x_preferred":[
        "Stratford-on-Slaney"
    ],
    "wof:name":"Stratford on Slaney",
    "wof:placetype":"locality"
},
  "geometry": {"coordinates":[-6.6669,52.98079],"type":"Point"}
}