{
  "type": "Feature",
  "properties": {
    "gn:admin1_code":"M",
    "gn:admin2_code":"26",
    "gn:asciiname":"Glenough Upper",
    "gn:country_code":"IE",
    "gn:dem":287,
    "gn:feature_class":"P",
    "gn:feature_code":"PPL",
    "gn:name":"Glenough Upper",
    "gn:population":0,
    "gn:timezone":"Europe/Dublin",
    "iso:country":"IE",
    "wof:name":"Glenough Upper",
    "wof:placetype":"locality"
},
  "geometry": {"coordinates":[-8.0675,52.63833],"type":"Point"}
}