{
  "type": "Feature",
  "properties": {
    "gn:admin1_code":"M",
    "gn:admin2_code":"04",
    "gn:asciiname":"Cullenagh Bridge",
    "gn:country_code":"IE",
    "gn:dem":282,
    "gn:feature_class":"P",
    "gn:feature_code":"PPLL",
    "gn:name":"Cullenagh Bridge",
    "gn:population":0,
    "gn:timezone":"Europe/Dublin",
    "iso:country":"IE",
    "wof:name":"Cullenagh Bridge",
    "wof:placetype":"locality"
},
  "geometry": {"coordinates":[-9.29833,51.81528],"type":"Point"}
}