{
  "type": "Feature",
  "properties": {
    "gn:admin1_code":"C",
    "gn:admin2_code":"14.0",
    "gn:asciiname":"Edergole",
    "gn:country_code":"IE",
    "gn:dem":55,
    "gn:feature_class":"P",
    "gn:feature_code":"PPLL",
    "gn:name":"Edergole",
    "gn:population":0,
    "gn:timezone":"Europe/Dublin",
    "iso:country":"IE",
    "wof:name":"Edergole",
    "wof:placetype":"locality"
},
  "geometry": {"coordinates":[-7.81417,53.96417],"type":"Point"}
}