{
  "type": "Feature",
  "properties": {
    "gn:admin1_code":"L",
    "gn:admin2_code":"21",
    "gn:asciiname":"Carnaross",
    "gn:country_code":"IE",
    "gn:dem":94,
    "gn:feature_class":"P",
    "gn:feature_code":"PPL",
    "gn:name":"Carnaross",
    "gn:population":0,
    "gn:timezone":"Europe/Dublin",
    "iso:country":"IE",
    "name:eus_x_preferred":[
        "Carnaross"
    ],
    "name:gle_x_preferred":[
        "Carn na Ros"
    ],
    "name:pol_x_preferred":[
        "Carnaross"
    ],
    "name:rus_x_preferred":[
        "\u041a\u0430\u0440\u043d\u0430\u0440\u043e\u0441\u0441"
    ],
    "wof:name":"Carnaross",
    "wof:placetype":"locality"
},
  "geometry": {"coordinates":[-6.95427,53.74977],"type":"Point"}
}