{
  "type": "Feature",
  "properties": {
    "gn:admin1_code":"U",
    "gn:admin2_code":"22",
    "gn:asciiname":"Ouvry Cross Roads",
    "gn:country_code":"IE",
    "gn:dem":169,
    "gn:feature_class":"P",
    "gn:feature_code":"PPLL",
    "gn:name":"Ouvry Cross Roads",
    "gn:population":0,
    "gn:timezone":"Europe/Dublin",
    "iso:country":"IE",
    "wof:name":"Ouvry Cross Roads",
    "wof:placetype":"locality"
},
  "geometry": {"coordinates":[-6.84361,54.01444],"type":"Point"}
}