{
  "type": "Feature",
  "properties": {
    "gn:admin1_code":"C",
    "gn:admin2_code":"25.0",
    "gn:asciiname":"Cuppanagh",
    "gn:country_code":"IE",
    "gn:dem":71,
    "gn:feature_class":"P",
    "gn:feature_code":"PPL",
    "gn:name":"Cuppanagh",
    "gn:population":0,
    "gn:timezone":"Europe/Dublin",
    "iso:country":"IE",
    "wof:name":"Cuppanagh",
    "wof:placetype":"locality"
},
  "geometry": {"coordinates":[-8.41806,53.96028],"type":"Point"}
}