{
  "type": "Feature",
  "properties": {
    "iso:country":"IE",
    "qs_pg:aaroncc":"IE",
    "qs_pg:name":"Newport East",
    "qs_pg:name_adm0":"Ireland",
    "qs_pg:name_adm1":"Mayo",
    "qs_pg:photos":132,
    "qs_pg:photos_1k":27,
    "qs_pg:photos_9k":2,
    "qs_pg:photos_9r":5,
    "qs_pg:photos_all":440,
    "qs_pg:photos_sr":3,
    "qs_pg:pop_sr":0,
    "qs_pg:qs_pg_placetype":"localadmin",
    "qs_pg:qs_pg_placetype_gp":"LocalAdmin",
    "qs_pg:woe_adm0":23424803,
    "woe:adm0_id":23424803,
    "woe:name_adm0":"Ireland",
    "woe:name_adm1":"Mayo",
    "woe:placetype":"LocalAdmin",
    "wof:name":"Newport East",
    "wof:placetype":"localadmin"
},
  "geometry": {"coordinates":[-9.552526,53.892706],"type":"Point"}
}