{
  "type": "Feature",
  "properties": {
    "gn:admin1_code":"M",
    "gn:admin2_code":"26",
    "gn:asciiname":"Lorrha",
    "gn:country_code":"IE",
    "gn:dem":38,
    "gn:feature_class":"P",
    "gn:feature_code":"PPL",
    "gn:name":"Lorrha",
    "gn:population":0,
    "gn:timezone":"Europe/Dublin",
    "iso:country":"IE",
    "name:deu_x_preferred":[
        "Lorrha"
    ],
    "name:eus_x_preferred":[
        "Lorrha"
    ],
    "name:fra_x_preferred":[
        "Lorrha"
    ],
    "name:gle_x_preferred":[
        "Lothra"
    ],
    "name:rus_x_preferred":[
        "\u041b\u043e\u0440\u0440\u0430"
    ],
    "wof:name":"Lorrha",
    "wof:placetype":"locality"
},
  "geometry": {"coordinates":[-8.12111,53.09056],"type":"Point"}
}