{
  "type": "Feature",
  "properties": {
    "gn:admin1_code":"L",
    "gn:admin2_code":"31",
    "gn:asciiname":"Ballyteige Bridge",
    "gn:country_code":"IE",
    "gn:dem":260,
    "gn:feature_class":"P",
    "gn:feature_code":"PPL",
    "gn:name":"Ballyteige Bridge",
    "gn:population":0,
    "gn:timezone":"Europe/Dublin",
    "iso:country":"IE",
    "wof:name":"Ballyteige Bridge",
    "wof:placetype":"locality"
},
  "geometry": {"coordinates":[-6.4075,52.88861],"type":"Point"}
}