{
  "type": "Feature",
  "properties": {
    "gn:admin1_code":"C",
    "gn:admin2_code":"10.0",
    "gn:asciiname":"Glennascaul",
    "gn:country_code":"IE",
    "gn:dem":14,
    "gn:feature_class":"P",
    "gn:feature_code":"PPL",
    "gn:name":"Glennascaul",
    "gn:population":0,
    "gn:timezone":"Europe/Dublin",
    "iso:country":"IE",
    "wof:name":"Glennascaul",
    "wof:placetype":"locality"
},
  "geometry": {"coordinates":[-8.92667,53.28722],"type":"Point"}
}