{
  "type": "Feature",
  "properties": {
    "gn:admin1_code":"C",
    "gn:admin2_code":"20.0",
    "gn:asciiname":"Cregganroe",
    "gn:country_code":"IE",
    "gn:dem":16,
    "gn:feature_class":"P",
    "gn:feature_code":"PPL",
    "gn:name":"Cregganroe",
    "gn:population":0,
    "gn:timezone":"Europe/Dublin",
    "iso:country":"IE",
    "wof:name":"Cregganroe",
    "wof:placetype":"locality"
},
  "geometry": {"coordinates":[-9.85871,54.05949],"type":"Point"}
}