{
  "type": "Feature",
  "properties": {
    "gn:admin1_code":"M",
    "gn:admin2_code":"03",
    "gn:asciiname":"Finavarra",
    "gn:country_code":"IE",
    "gn:dem":32,
    "gn:feature_class":"P",
    "gn:feature_code":"PPL",
    "gn:name":"Finavarra",
    "gn:population":0,
    "gn:timezone":"Europe/Dublin",
    "iso:country":"IE",
    "wof:name":"Finavarra",
    "wof:placetype":"locality"
},
  "geometry": {"coordinates":[-9.10056,53.15139],"type":"Point"}
}