{
  "type": "Feature",
  "properties": {
    "gn:admin1_code":"C",
    "gn:admin2_code":"20",
    "gn:asciiname":"Owenduff",
    "gn:country_code":"IE",
    "gn:dem":29,
    "gn:feature_class":"P",
    "gn:feature_code":"PPL",
    "gn:name":"Owenduff",
    "gn:population":0,
    "gn:timezone":"Europe/Dublin",
    "iso:country":"IE",
    "name:eng_x_preferred":[
        "Owenduff"
    ],
    "name:gle_x_preferred":[
        "An Abhainn Dubh"
    ],
    "wof:name":"Owenduff",
    "wof:placetype":"locality"
},
  "geometry": {"coordinates":[-9.83611,53.94806],"type":"Point"}
}