{
  "type": "Feature",
  "properties": {
    "gn:admin1_code":"M",
    "gn:admin2_code":"42",
    "gn:asciiname":"Cappamore",
    "gn:country_code":"IE",
    "gn:dem":57,
    "gn:feature_class":"P",
    "gn:feature_code":"PPL",
    "gn:name":"Cappamore",
    "gn:population":675,
    "gn:timezone":"Europe/Dublin",
    "iso:country":"IE",
    "name:ceb_x_preferred":[
        "Cappamore"
    ],
    "name:eng_x_preferred":[
        "Cappamore"
    ],
    "name:eus_x_preferred":[
        "Cappamore"
    ],
    "name:gle_x_preferred":[
        "An Cheapach Mh\u00f3r"
    ],
    "name:rus_x_preferred":[
        "\u041a\u0430\u043f\u043f\u0430\u043c\u043e\u0440"
    ],
    "name:spa_x_preferred":[
        "Cappamore"
    ],
    "name:swe_x_preferred":[
        "Cappamore"
    ],
    "wof:name":"Cappamore",
    "wof:placetype":"locality",
    "wof:population":675
},
  "geometry": {"coordinates":[-8.33556,52.61444],"type":"Point"}
}