{
  "type": "Feature",
  "properties": {
    "gn:admin1_code":"L",
    "gn:admin2_code":"29.0",
    "gn:asciiname":"Rahincuill",
    "gn:country_code":"IE",
    "gn:dem":102,
    "gn:feature_class":"P",
    "gn:feature_code":"PPL",
    "gn:name":"Rahincuill",
    "gn:population":0,
    "gn:timezone":"Europe/Dublin",
    "iso:country":"IE",
    "wof:name":"Rahincuill",
    "wof:placetype":"locality"
},
  "geometry": {"coordinates":[-7.33111,53.39167],"type":"Point"}
}