{
  "type": "Feature",
  "properties": {
    "gn:admin1_code":"M",
    "gn:admin2_code":"04",
    "gn:asciiname":"Ballyvodane Bridge",
    "gn:country_code":"IE",
    "gn:dem":106,
    "gn:feature_class":"P",
    "gn:feature_code":"PPLL",
    "gn:name":"Ballyvodane Bridge",
    "gn:population":0,
    "gn:timezone":"Europe/Dublin",
    "iso:country":"IE",
    "wof:name":"Ballyvodane Bridge",
    "wof:placetype":"locality"
},
  "geometry": {"coordinates":[-8.6875,51.97917],"type":"Point"}
}