{
  "type": "Feature",
  "properties": {
    "iso:country":"IE",
    "qs_pg:aaroncc":"IE",
    "qs_pg:name":"Innfield",
    "qs_pg:name_adm0":"Ireland",
    "qs_pg:name_adm1":"Meath",
    "qs_pg:photos":2,
    "qs_pg:photos_1k":1,
    "qs_pg:photos_9k":3,
    "qs_pg:photos_9r":5,
    "qs_pg:photos_all":675,
    "qs_pg:photos_sr":1,
    "qs_pg:pop_sr":0,
    "qs_pg:qs_pg_placetype":"localadmin",
    "qs_pg:qs_pg_placetype_gp":"LocalAdmin",
    "qs_pg:woe_adm0":23424803,
    "woe:adm0_id":23424803,
    "woe:name_adm0":"Ireland",
    "woe:name_adm1":"Meath",
    "woe:placetype":"LocalAdmin",
    "wof:name":"Innfield",
    "wof:placetype":"localadmin"
},
  "geometry": {"coordinates":[-6.854224,53.402867],"type":"Point"}
}