{
  "type": "Feature",
  "properties": {
    "gn:admin1_code":"M",
    "gn:admin2_code":"04",
    "gn:asciiname":"Bluebell",
    "gn:country_code":"IE",
    "gn:dem":72,
    "gn:feature_class":"P",
    "gn:feature_code":"PPL",
    "gn:name":"Bluebell",
    "gn:population":0,
    "gn:timezone":"Europe/Dublin",
    "iso:country":"IE",
    "name:ceb_x_preferred":[
        "Bluebell"
    ],
    "name:slv_x_preferred":[
        "Bluebell"
    ],
    "name:swe_x_preferred":[
        "Bluebell"
    ],
    "wof:name":"Bluebell",
    "wof:placetype":"locality"
},
  "geometry": {"coordinates":[-8.25778,52.05361],"type":"Point"}
}