{
  "type": "Feature",
  "properties": {
    "gn:admin1_code":"C",
    "gn:admin2_code":"20.0",
    "gn:asciiname":"Gorteen",
    "gn:country_code":"IE",
    "gn:dem":32,
    "gn:feature_class":"P",
    "gn:feature_code":"PPL",
    "gn:name":"Gorteen",
    "gn:population":0,
    "gn:timezone":"Europe/Dublin",
    "iso:country":"IE",
    "wof:name":"Gorteen",
    "wof:placetype":"locality"
},
  "geometry": {"coordinates":[-9.50372,53.84012],"type":"Point"}
}