{
  "type": "Feature",
  "properties": {
    "gn:admin1_code":"C",
    "gn:admin2_code":"10.0",
    "gn:asciiname":"Caraun",
    "gn:country_code":"IE",
    "gn:dem":64,
    "gn:feature_class":"P",
    "gn:feature_code":"PPL",
    "gn:name":"Caraun",
    "gn:population":0,
    "gn:timezone":"Europe/Dublin",
    "iso:country":"IE",
    "name:eng_x_preferred":[
        "Caraun"
    ],
    "name:gle_x_preferred":[
        "An C\u00e1r\u00e1n"
    ],
    "wof:name":"Caraun",
    "wof:placetype":"locality"
},
  "geometry": {"coordinates":[-8.54806,53.28167],"type":"Point"}
}