{
  "type": "Feature",
  "properties": {
    "gn:admin1_code":"C",
    "gn:admin2_code":"14.0",
    "gn:asciiname":"Gurteen",
    "gn:country_code":"IE",
    "gn:dem":90,
    "gn:feature_class":"P",
    "gn:feature_code":"PPL",
    "gn:name":"Gurteen",
    "gn:population":0,
    "gn:timezone":"Europe/Dublin",
    "iso:country":"IE",
    "name:spa_x_preferred":[
        "Gurteen"
    ],
    "wof:name":"Gurteen",
    "wof:placetype":"locality"
},
  "geometry": {"coordinates":[-8.31389,54.32583],"type":"Point"}
}