{
  "type": "Feature",
  "properties": {
    "gn:admin1_code":"C",
    "gn:admin2_code":"20.0",
    "gn:asciiname":"Moyrahan",
    "gn:country_code":"IE",
    "gn:dem":36,
    "gn:feature_class":"P",
    "gn:feature_code":"PPLL",
    "gn:name":"Moyrahan",
    "gn:population":0,
    "gn:timezone":"Europe/Dublin",
    "iso:country":"IE",
    "name:eng_x_preferred":[
        "Moyrahan"
    ],
    "name:gle_x_preferred":[
        "Maigh Raithin"
    ],
    "wof:name":"Moyrahan",
    "wof:placetype":"locality"
},
  "geometry": {"coordinates":[-9.95479,54.23189],"type":"Point"}
}