{
  "type": "Feature",
  "properties": {
    "iso:country":"IE",
    "qs_pg:aaroncc":"IE",
    "qs_pg:name":"Achill",
    "qs_pg:name_adm0":"Ireland",
    "qs_pg:name_adm1":"Mayo",
    "qs_pg:photos":2,
    "qs_pg:photos_1k":1,
    "qs_pg:photos_9k":1,
    "qs_pg:photos_9r":4,
    "qs_pg:photos_all":205,
    "qs_pg:photos_sr":1,
    "qs_pg:pop_sr":0,
    "qs_pg:qs_pg_placetype":"localadmin",
    "qs_pg:qs_pg_placetype_gp":"LocalAdmin",
    "qs_pg:woe_adm0":23424803,
    "woe:adm0_id":23424803,
    "woe:name_adm0":"Ireland",
    "woe:name_adm1":"Mayo",
    "woe:placetype":"LocalAdmin",
    "wof:name":"Achill",
    "wof:placetype":"localadmin"
},
  "geometry": {"coordinates":[-9.948978,53.933352],"type":"Point"}
}