{
  "type": "Feature",
  "properties": {
    "gn:admin1_code":"C",
    "gn:admin2_code":"25.0",
    "gn:asciiname":"Billa",
    "gn:country_code":"IE",
    "gn:dem":60,
    "gn:feature_class":"P",
    "gn:feature_code":"PPLL",
    "gn:name":"Billa",
    "gn:population":0,
    "gn:timezone":"Europe/Dublin",
    "iso:country":"IE",
    "name:bar_x_preferred":[
        "Billa"
    ],
    "name:ceb_x_preferred":[
        "Billa"
    ],
    "name:deu_x_preferred":[
        "Billa"
    ],
    "name:fas_x_preferred":[
        "\u0628\u06cc\u0644\u0627"
    ],
    "name:fra_x_preferred":[
        "Billa"
    ],
    "name:ind_x_preferred":[
        "Billa"
    ],
    "name:nld_x_preferred":[
        "Billa"
    ],
    "name:swe_x_preferred":[
        "Billa"
    ],
    "wof:name":"Billa",
    "wof:placetype":"locality"
},
  "geometry": {"coordinates":[-8.55694,54.17556],"type":"Point"}
}