{
  "type": "Feature",
  "properties": {
    "gn:admin1_code":"C",
    "gn:admin2_code":"25.0",
    "gn:asciiname":"Billa",
    "gn:country_code":"IE",
    "gn:dem":60,
    "gn:feature_class":"P",
    "gn:feature_code":"PPLL",
    "gn:name":"Billa",
    "gn:population":0,
    "gn:timezone":"Europe/Dublin",
    "iso:country":"IE",
    "wof:name":"Billa",
    "wof:placetype":"locality"
},
  "geometry": {"coordinates":[-8.55694,54.17556],"type":"Point"}
}