{
  "type": "Feature",
  "properties": {
    "gn:admin1_code":"M",
    "gn:admin2_code":"04",
    "gn:asciiname":"Danesfort",
    "gn:country_code":"IE",
    "gn:dem":104,
    "gn:feature_class":"P",
    "gn:feature_code":"PPL",
    "gn:name":"Danesfort",
    "gn:population":0,
    "gn:timezone":"Europe/Dublin",
    "iso:country":"IE",
    "name:gle_x_preferred":[
        "D\u00fan Feart"
    ],
    "wof:name":"Danesfort",
    "wof:placetype":"locality"
},
  "geometry": {"coordinates":[-8.72361,52.09944],"type":"Point"}
}