{
  "type": "Feature",
  "properties": {
    "gn:admin1_code":"M",
    "gn:admin2_code":"04",
    "gn:asciiname":"Knock",
    "gn:country_code":"IE",
    "gn:dem":147,
    "gn:feature_class":"P",
    "gn:feature_code":"PPLL",
    "gn:name":"Knock",
    "gn:population":0,
    "gn:timezone":"Europe/Dublin",
    "iso:country":"IE",
    "name:ceb_x_preferred":[
        "Knock"
    ],
    "name:deu_x_preferred":[
        "Knock"
    ],
    "name:fra_x_preferred":[
        "Knock"
    ],
    "name:ido_x_preferred":[
        "Knock"
    ],
    "name:ita_x_preferred":[
        "Knock"
    ],
    "name:jpn_x_preferred":[
        "\u30ce\u30c3\u30af"
    ],
    "name:nld_x_preferred":[
        "Knock"
    ],
    "name:pol_x_preferred":[
        "Knock"
    ],
    "name:swe_x_preferred":[
        "Knock"
    ],
    "wof:name":"Knock",
    "wof:placetype":"locality"
},
  "geometry": {"coordinates":[-8.95306,51.68833],"type":"Point"}
}