{
  "type": "Feature",
  "properties": {
    "gn:gn_country":"IE",
    "gn:gn_fcode":"PPL",
    "gn:gn_pop":0,
    "iso:country":"IE",
    "qs_pg:aaroncc":"IE",
    "qs_pg:gn_country":"IE",
    "qs_pg:gn_fcode":"PPL",
    "qs_pg:gn_pop":0,
    "qs_pg:name":"Ballyhar",
    "qs_pg:name_adm0":"Ireland",
    "qs_pg:name_adm1":"Kerry",
    "qs_pg:photos":68,
    "qs_pg:photos_1k":14,
    "qs_pg:photos_9k":1,
    "qs_pg:photos_9r":2,
    "qs_pg:photos_all":68,
    "qs_pg:photos_sr":2,
    "qs_pg:pop_sr":0,
    "qs_pg:qs_pg_placetype":"locality",
    "qs_pg:qs_pg_placetype_gp":"Town",
    "qs_pg:woe_adm0":23424803,
    "woe:adm0_id":23424803,
    "woe:name_adm0":"Ireland",
    "woe:name_adm1":"Kerry",
    "woe:placetype":"Town",
    "wof:name":"Ballyhar",
    "wof:placetype":"locality"
},
  "geometry": {"coordinates":[-9.56667,52.11667],"type":"Point"}
}