{
  "type": "Feature",
  "properties": {
    "gn:country":"IE",
    "gn:fcode":"PPL",
    "gn:population":0,
    "iso:country":"IE",
    "name:eus_x_preferred":[
        "Woodstown"
    ],
    "name:fra_x_preferred":[
        "Woodstown"
    ],
    "qs_pg:aaroncc":"IE",
    "qs_pg:gn_country":"IE",
    "qs_pg:gn_fcode":"PPL",
    "qs_pg:gn_pop":0,
    "qs_pg:name":"Woodstown",
    "qs_pg:name_adm0":"Ireland",
    "qs_pg:name_adm1":"Waterford",
    "qs_pg:photos":23,
    "qs_pg:photos_1k":5,
    "qs_pg:photos_9k":1,
    "qs_pg:photos_9r":2,
    "qs_pg:photos_all":66,
    "qs_pg:photos_sr":1,
    "qs_pg:pop_sr":0,
    "qs_pg:qs_pg_placetype":"localadmin",
    "qs_pg:qs_pg_placetype_gp":"LocalAdmin",
    "qs_pg:woe_adm0":23424803,
    "woe:adm0_id":23424803,
    "woe:name_adm0":"Ireland",
    "woe:name_adm1":"Waterford",
    "woe:placetype":"LocalAdmin",
    "wof:name":"Woodstown",
    "wof:placetype":"localadmin"
},
  "geometry": {"coordinates":[-7.01,52.19667],"type":"Point"}
}