{
  "type": "Feature",
  "properties": {
    "gn:admin1_code":"M",
    "gn:admin2_code":"03",
    "gn:asciiname":"Ballyvorney",
    "gn:country_code":"IE",
    "gn:dem":74,
    "gn:feature_class":"P",
    "gn:feature_code":"PPL",
    "gn:name":"Ballyvorney",
    "gn:population":0,
    "gn:timezone":"Europe/Dublin",
    "iso:country":"IE",
    "wof:name":"Ballyvorney",
    "wof:placetype":"locality"
},
  "geometry": {"coordinates":[-8.48278,52.7875],"type":"Point"}
}