{
  "type": "Feature",
  "properties": {
    "gn:admin1_code":"C",
    "gn:admin2_code":"10.0",
    "gn:asciiname":"Cloonascragh",
    "gn:country_code":"IE",
    "gn:dem":34,
    "gn:feature_class":"P",
    "gn:feature_code":"PPL",
    "gn:name":"Cloonascragh",
    "gn:population":0,
    "gn:timezone":"Europe/Dublin",
    "iso:country":"IE",
    "wof:name":"Cloonascragh",
    "wof:placetype":"locality"
},
  "geometry": {"coordinates":[-8.20028,53.28167],"type":"Point"}
}