{
  "type": "Feature",
  "properties": {
    "gn:admin1_code":"L",
    "gn:admin2_code":"12",
    "gn:asciiname":"Maganey",
    "gn:cc2":"IE",
    "gn:country_code":"IE",
    "gn:dem":57,
    "gn:feature_class":"P",
    "gn:feature_code":"PPL",
    "gn:name":"Maganey",
    "gn:population":0,
    "gn:timezone":"Europe/Dublin",
    "iso:country":"IE",
    "name:und_x_variant":[
        "Mageny",
        "Maganey"
    ],
    "wof:name":"Maganey",
    "wof:placetype":"locality"
},
  "geometry": {"coordinates":[-6.93083,52.90667],"type":"Point"}
}