{
  "type": "Feature",
  "properties": {
    "gn:admin1_code":"M",
    "gn:admin2_code":"11",
    "gn:asciiname":"Newmarket Cross Roads",
    "gn:country_code":"IE",
    "gn:dem":237,
    "gn:feature_class":"P",
    "gn:feature_code":"PPLL",
    "gn:name":"Newmarket Cross Roads",
    "gn:population":0,
    "gn:timezone":"Europe/Dublin",
    "iso:country":"IE",
    "wof:name":"Newmarket Cross Roads",
    "wof:placetype":"locality"
},
  "geometry": {"coordinates":[-9.32278,52.20056],"type":"Point"}
}