{
  "type": "Feature",
  "properties": {
    "gn:admin1_code":"C",
    "gn:admin2_code":"10.0",
    "gn:asciiname":"Shancroagh",
    "gn:country_code":"IE",
    "gn:dem":6,
    "gn:feature_class":"P",
    "gn:feature_code":"PPL",
    "gn:name":"Shancroagh",
    "gn:population":0,
    "gn:timezone":"Europe/Dublin",
    "iso:country":"IE",
    "wof:name":"Shancroagh",
    "wof:placetype":"locality"
},
  "geometry": {"coordinates":[-9.04667,53.28389],"type":"Point"}
}