{
  "type": "Feature",
  "properties": {
    "gn:admin1_code":"M",
    "gn:admin2_code":"11",
    "gn:asciiname":"Bunaw",
    "gn:cc2":"IE",
    "gn:country_code":"IE",
    "gn:dem":26,
    "gn:feature_class":"P",
    "gn:feature_code":"PPL",
    "gn:name":"Bunaw",
    "gn:population":0,
    "gn:timezone":"Europe/Dublin",
    "iso:country":"IE",
    "name:und_x_variant":[
        "Bunnow",
        "Bunaw"
    ],
    "wof:name":"Bunaw",
    "wof:placetype":"locality"
},
  "geometry": {"coordinates":[-9.81222,51.79],"type":"Point"}
}