{
  "type": "Feature",
  "properties": {
    "gn:gn_country":"IE",
    "gn:gn_fcode":"PPL",
    "gn:gn_pop":0,
    "gn:population":1161,
    "iso:country":"IE",
    "name:baq_x_preferred":[
        "Watergrasshill"
    ],
    "name:dut_x_preferred":[
        "Watergrasshill"
    ],
    "name:eng_x_preferred":[
        "Watergrasshill"
    ],
    "name:gle_x_preferred":[
        "Cnoc\u00e1n na Biolra\u00ed"
    ],
    "name:rus_x_preferred":[
        "\u0423\u043e\u0442\u0435\u0440\u0433\u0440\u0430\u0441\u0445\u0438\u043b\u043b"
    ],
    "name:swe_x_preferred":[
        "Watergrasshill"
    ],
    "qs_pg:aaroncc":"IE",
    "qs_pg:gn_country":"IE",
    "qs_pg:gn_fcode":"PPL",
    "qs_pg:gn_pop":0,
    "qs_pg:name":"Watergrasshill",
    "qs_pg:name_adm0":"Ireland",
    "qs_pg:name_adm1":"Cork",
    "qs_pg:photos":381,
    "qs_pg:photos_1k":77,
    "qs_pg:photos_9k":2,
    "qs_pg:photos_9r":5,
    "qs_pg:photos_all":381,
    "qs_pg:photos_sr":6,
    "qs_pg:pop_sr":0,
    "qs_pg:qs_pg_placetype":"locality",
    "qs_pg:qs_pg_placetype_gp":"Town",
    "qs_pg:woe_adm0":23424803,
    "woe:adm0_id":23424803,
    "woe:name_adm0":"Ireland",
    "woe:name_adm1":"Cork",
    "woe:placetype":"Town",
    "wof:name":"Watergrasshill",
    "wof:placetype":"locality",
    "wof:population":1161
},
  "geometry": {"coordinates":[-8.34417,52.01139],"type":"Point"}
}