{
  "type": "Feature",
  "properties": {
    "gn:admin1_code":"U",
    "gn:admin2_code":"22",
    "gn:asciiname":"Sheetrim",
    "gn:country_code":"IE",
    "gn:dem":139,
    "gn:feature_class":"P",
    "gn:feature_code":"PPL",
    "gn:name":"Sheetrim",
    "gn:population":0,
    "gn:timezone":"Europe/Dublin",
    "iso:country":"IE",
    "wof:name":"Sheetrim",
    "wof:placetype":"locality"
},
  "geometry": {"coordinates":[-6.78611,54.09611],"type":"Point"}
}