{
  "type": "Feature",
  "properties": {
    "gn:admin1_code":"C",
    "gn:admin2_code":"10.0",
    "gn:asciiname":"Kilcolgan",
    "gn:country_code":"IE",
    "gn:dem":15,
    "gn:feature_class":"P",
    "gn:feature_code":"PPLL",
    "gn:name":"Kilcolgan",
    "gn:population":0,
    "gn:timezone":"Europe/Dublin",
    "iso:country":"IE",
    "name:eus_x_preferred":[
        "Kilcolgan"
    ],
    "name:gle_x_preferred":[
        "Cill Cholg\u00e1in"
    ],
    "name:kat_x_preferred":[
        "\u10d9\u10d8\u10da\u10d9\u10dd\u10da\u10d2\u10d0\u10dc\u10d8"
    ],
    "name:nld_x_preferred":[
        "Kilcolgan"
    ],
    "name:rus_x_preferred":[
        "\u041a\u0438\u043b\u043a\u043e\u043b\u0433\u0430\u043d"
    ],
    "name:spa_x_preferred":[
        "Kilcolgan"
    ],
    "wof:name":"Kilcolgan",
    "wof:placetype":"locality"
},
  "geometry": {"coordinates":[-8.8663,53.20987],"type":"Point"}
}