{
  "type": "Feature",
  "properties": {
    "gn:admin1_code":"M",
    "gn:admin2_code":"44",
    "gn:asciiname":"Garrarus Cross Roads",
    "gn:country_code":"IE",
    "gn:dem":60,
    "gn:feature_class":"P",
    "gn:feature_code":"PPL",
    "gn:name":"Garrarus Cross Roads",
    "gn:population":0,
    "gn:timezone":"Europe/Dublin",
    "iso:country":"IE",
    "wof:name":"Garrarus Cross Roads",
    "wof:placetype":"locality"
},
  "geometry": {"coordinates":[-7.18694,52.14111],"type":"Point"}
}