{
  "type": "Feature",
  "properties": {
    "gn:gn_country":"IE",
    "iso:country":"IE",
    "name:eng_x_preferred":[
        "Dunree"
    ],
    "name:nld_x_preferred":[
        "Dunree"
    ],
    "qs_pg:aaroncc":"IE",
    "qs_pg:gn_country":"IE",
    "qs_pg:name":"Dunree",
    "qs_pg:name_adm0":"Ireland",
    "qs_pg:name_adm1":"Donegal",
    "qs_pg:photos":406,
    "qs_pg:photos_1k":82,
    "qs_pg:photos_9k":2,
    "qs_pg:photos_9r":5,
    "qs_pg:photos_all":406,
    "qs_pg:photos_sr":6,
    "qs_pg:pop_sr":0,
    "qs_pg:qs_pg_placetype":"locality",
    "qs_pg:qs_pg_placetype_gp":"Town",
    "qs_pg:woe_adm0":23424803,
    "woe:adm0_id":23424803,
    "woe:name_adm0":"Ireland",
    "woe:name_adm1":"Donegal",
    "woe:placetype":"Town",
    "wof:name":"Dunree",
    "wof:placetype":"locality"
},
  "geometry": {"coordinates":[-7.547435,55.196311],"type":"Point"}
}