{
  "type": "Feature",
  "properties": {
    "gn:country":"IE",
    "gn:fcode":"PPL",
    "gn:population":0,
    "iso:country":"IE",
    "name:bul_x_preferred":[
        "\u0428\u0430\u043d\u043e\u043d\u0431\u0440\u0438\u0434\u0433\u0435"
    ],
    "name:cat_x_preferred":[
        "Shannonbridge"
    ],
    "name:ceb_x_preferred":[
        "Shannonbridge"
    ],
    "name:deu_x_preferred":[
        "Shannonbridge"
    ],
    "name:eng_x_preferred":[
        "Shannonbridge"
    ],
    "name:eus_x_preferred":[
        "Shannonbridge"
    ],
    "name:fra_x_preferred":[
        "Shannonbridge"
    ],
    "name:gle_x_preferred":[
        "Droichead na Sionainne"
    ],
    "name:nld_x_preferred":[
        "Shannonbridge"
    ],
    "name:rus_x_preferred":[
        "\u0428\u0430\u043d\u043d\u043e\u043d\u0431\u0440\u0438\u0434\u0436"
    ],
    "name:spa_x_preferred":[
        "Shannonbridge"
    ],
    "name:swe_x_preferred":[
        "Shannonbridge"
    ],
    "qs_pg:aaroncc":"IE",
    "qs_pg:gn_country":"IE",
    "qs_pg:gn_fcode":"PPL",
    "qs_pg:gn_pop":0,
    "qs_pg:name":"Shannonbridge",
    "qs_pg:name_adm0":"Ireland",
    "qs_pg:name_adm1":"Offaly",
    "qs_pg:photos":228,
    "qs_pg:photos_1k":46,
    "qs_pg:photos_9k":1,
    "qs_pg:photos_9r":4,
    "qs_pg:photos_all":228,
    "qs_pg:photos_sr":4,
    "qs_pg:pop_sr":0,
    "qs_pg:qs_pg_placetype":"locality",
    "qs_pg:qs_pg_placetype_gp":"Town",
    "qs_pg:woe_adm0":23424803,
    "woe:adm0_id":23424803,
    "woe:name_adm0":"Ireland",
    "woe:name_adm1":"Offaly",
    "woe:placetype":"Town",
    "wof:name":"Shannonbridge",
    "wof:placetype":"locality",
    "wof:population":206
},
  "geometry": {"coordinates":[-8.03722,53.27778],"type":"Point"}
}