{
  "type": "Feature",
  "properties": {
    "gn:admin1_code":"L",
    "gn:admin2_code":"13",
    "gn:asciiname":"Scogh",
    "gn:country_code":"IE",
    "gn:dem":63,
    "gn:feature_class":"P",
    "gn:feature_code":"PPLL",
    "gn:name":"Scogh",
    "gn:population":0,
    "gn:timezone":"Europe/Dublin",
    "iso:country":"IE",
    "wof:name":"Scogh",
    "wof:placetype":"locality"
},
  "geometry": {"coordinates":[-7.38472,52.39889],"type":"Point"}
}