{
  "type": "Feature",
  "properties": {
    "gn:admin1_code":"L",
    "gn:admin2_code":"12.0",
    "gn:asciiname":"Laragh",
    "gn:country_code":"IE",
    "gn:dem":66,
    "gn:feature_class":"P",
    "gn:feature_code":"PPL",
    "gn:name":"Laragh",
    "gn:population":0,
    "gn:timezone":"Europe/Dublin",
    "iso:country":"IE",
    "name:fra_x_preferred":[
        "Laragh"
    ],
    "wof:name":"Laragh",
    "wof:placetype":"locality"
},
  "geometry": {"coordinates":[-6.66417,53.38],"type":"Point"}
}