{
  "type": "Feature",
  "properties": {
    "gn:admin1_code":"M",
    "gn:admin2_code":"26",
    "gn:asciiname":"Clocully",
    "gn:country_code":"IE",
    "gn:dem":28,
    "gn:feature_class":"P",
    "gn:feature_code":"PPL",
    "gn:name":"Clocully",
    "gn:population":0,
    "gn:timezone":"Europe/Dublin",
    "iso:country":"IE",
    "wof:name":"Clocully",
    "wof:placetype":"locality"
},
  "geometry": {"coordinates":[-7.84833,52.29167],"type":"Point"}
}