{
  "type": "Feature",
  "properties": {
    "iso:country":"IE",
    "name:pol_x_preferred":[
        "Swineford"
    ],
    "qs_pg:aaroncc":"IE",
    "qs_pg:name":"Swineford",
    "qs_pg:name_adm0":"Ireland",
    "qs_pg:name_adm1":"Mayo",
    "qs_pg:photos":1,
    "qs_pg:photos_1k":1,
    "qs_pg:photos_9k":1,
    "qs_pg:photos_9r":3,
    "qs_pg:photos_all":120,
    "qs_pg:photos_sr":1,
    "qs_pg:pop_sr":0,
    "qs_pg:qs_pg_placetype":"localadmin",
    "qs_pg:qs_pg_placetype_gp":"LocalAdmin",
    "qs_pg:woe_adm0":23424803,
    "woe:adm0_id":23424803,
    "woe:name_adm0":"Ireland",
    "woe:name_adm1":"Mayo",
    "woe:placetype":"LocalAdmin",
    "wof:name":"Swineford",
    "wof:placetype":"localadmin"
},
  "geometry": {"coordinates":[-8.950939,53.944518],"type":"Point"}
}