{
  "type": "Feature",
  "properties": {
    "gn:admin1_code":"C",
    "gn:admin2_code":"10.0",
    "gn:asciiname":"Corballymore",
    "gn:country_code":"IE",
    "gn:dem":104,
    "gn:feature_class":"P",
    "gn:feature_code":"PPL",
    "gn:name":"Corballymore",
    "gn:population":0,
    "gn:timezone":"Europe/Dublin",
    "iso:country":"IE",
    "wof:name":"Corballymore",
    "wof:placetype":"locality"
},
  "geometry": {"coordinates":[-8.41639,53.23389],"type":"Point"}
}