{
  "type": "Feature",
  "properties": {
    "gn:admin1_code":"C",
    "gn:admin2_code":"10.0",
    "gn:asciiname":"Mira",
    "gn:country_code":"IE",
    "gn:dem":46,
    "gn:feature_class":"P",
    "gn:feature_code":"PPLL",
    "gn:name":"Mira",
    "gn:population":0,
    "gn:timezone":"Europe/Dublin",
    "iso:country":"IE",
    "wof:name":"Mira",
    "wof:placetype":"locality"
},
  "geometry": {"coordinates":[-8.81,53.37889000000001],"type":"Point"}
}