{
  "type": "Feature",
  "properties": {
    "gn:admin1_code":"L",
    "gn:admin2_code":"15.0",
    "gn:asciiname":"Shanavolla",
    "gn:country_code":"IE",
    "gn:dem":94,
    "gn:feature_class":"P",
    "gn:feature_code":"PPL",
    "gn:name":"Shanavolla",
    "gn:population":0,
    "gn:timezone":"Europe/Dublin",
    "iso:country":"IE",
    "wof:name":"Shanavolla",
    "wof:placetype":"locality"
},
  "geometry": {"coordinates":[-7.43028,52.9725],"type":"Point"}
}