{
  "type": "Feature",
  "properties": {
    "gn:admin1_code":"L",
    "gn:admin2_code":"31.0",
    "gn:asciiname":"Ballinteskin Cross Roads",
    "gn:country_code":"IE",
    "gn:dem":52,
    "gn:feature_class":"P",
    "gn:feature_code":"PPL",
    "gn:name":"Ballinteskin Cross Roads",
    "gn:population":0,
    "gn:timezone":"Europe/Dublin",
    "iso:country":"IE",
    "wof:name":"Ballinteskin Cross Roads",
    "wof:placetype":"locality"
},
  "geometry": {"coordinates":[-6.075,52.9425],"type":"Point"}
}