{
  "type": "Feature",
  "properties": {
    "gn:admin1_code":"M",
    "gn:admin2_code":"04",
    "gn:asciiname":"Bofickil",
    "gn:country_code":"IE",
    "gn:dem":6,
    "gn:feature_class":"P",
    "gn:feature_code":"PPL",
    "gn:name":"Bofickil",
    "gn:population":0,
    "gn:timezone":"Europe/Dublin",
    "iso:country":"IE",
    "wof:name":"Bofickil",
    "wof:placetype":"locality"
},
  "geometry": {"coordinates":[-9.95417,51.70778],"type":"Point"}
}