{
  "type": "Feature",
  "properties": {
    "gn:admin1_code":"M",
    "gn:admin2_code":"04",
    "gn:asciiname":"Seafort",
    "gn:country_code":"IE",
    "gn:dem":0,
    "gn:feature_class":"P",
    "gn:feature_code":"PPL",
    "gn:name":"Seafort",
    "gn:population":0,
    "gn:timezone":"Europe/Dublin",
    "iso:country":"IE",
    "wof:name":"Seafort",
    "wof:placetype":"locality"
},
  "geometry": {"coordinates":[-9.585,51.51139000000001],"type":"Point"}
}