{
  "type": "Feature",
  "properties": {
    "gn:admin1_code":"M",
    "gn:admin2_code":"11",
    "gn:asciiname":"Caherbullig",
    "gn:country_code":"IE",
    "gn:dem":77,
    "gn:feature_class":"P",
    "gn:feature_code":"PPL",
    "gn:name":"Caherbullig",
    "gn:population":0,
    "gn:timezone":"Europe/Dublin",
    "iso:country":"IE",
    "name:eng_x_preferred":[
        "Caherbullig"
    ],
    "name:gle_x_preferred":[
        "Cathair Boilg"
    ],
    "wof:name":"Caherbullig",
    "wof:placetype":"locality"
},
  "geometry": {"coordinates":[-10.40333,52.1175],"type":"Point"}
}