{
  "type": "Feature",
  "properties": {
    "gn:admin1_code":"M",
    "gn:admin2_code":"04",
    "gn:asciiname":"Graigue Bridge",
    "gn:country_code":"IE",
    "gn:dem":183,
    "gn:feature_class":"P",
    "gn:feature_code":"PPLL",
    "gn:name":"Graigue Bridge",
    "gn:population":0,
    "gn:timezone":"Europe/Dublin",
    "iso:country":"IE",
    "wof:name":"Graigue Bridge",
    "wof:placetype":"locality"
},
  "geometry": {"coordinates":[-9.16611,51.85694],"type":"Point"}
}