{
  "type": "Feature",
  "properties": {
    "gn:admin1_code":"C",
    "gn:admin2_code":"20.0",
    "gn:asciiname":"Ballynarick",
    "gn:country_code":"IE",
    "gn:dem":17,
    "gn:feature_class":"P",
    "gn:feature_code":"PPLL",
    "gn:name":"Ballynarick",
    "gn:population":0,
    "gn:timezone":"Europe/Dublin",
    "iso:country":"IE",
    "wof:name":"Ballynarick",
    "wof:placetype":"locality"
},
  "geometry": {"coordinates":[-9.21472,54.23528],"type":"Point"}
}