{
  "type": "Feature",
  "properties": {
    "gn:admin1_code":"L",
    "gn:admin2_code":"21.0",
    "gn:asciiname":"Arlonstown",
    "gn:country_code":"IE",
    "gn:dem":106,
    "gn:feature_class":"P",
    "gn:feature_code":"PPL",
    "gn:name":"Arlonstown",
    "gn:population":0,
    "gn:timezone":"Europe/Dublin",
    "iso:country":"IE",
    "wof:name":"Arlonstown",
    "wof:placetype":"locality"
},
  "geometry": {"coordinates":[-6.62519,53.5552],"type":"Point"}
}