{
  "type": "Feature",
  "properties": {
    "gn:gn_country":"IE",
    "gn:gn_fcode":"PPL",
    "gn:gn_pop":0,
    "gn:population":491,
    "iso:country":"IE",
    "name:ceb_x_preferred":[
        "Clogheen"
    ],
    "name:eng_x_preferred":[
        "Clogheen"
    ],
    "name:eus_x_preferred":[
        "Clogheen"
    ],
    "name:gle_x_preferred":[
        "An Cloich\u00edn"
    ],
    "name:gle_x_variant":[
        "An Chloich\u00edn"
    ],
    "name:jpn_x_preferred":[
        "\u30af\u30ed\u30b8\u30fc\u30f3\u30fb\u30ec\u30c7\u30a3\u30fc\u30ba"
    ],
    "name:nld_x_preferred":[
        "Clogheen"
    ],
    "name:por_x_preferred":[
        "Clogheen"
    ],
    "name:rus_x_preferred":[
        "\u041a\u043b\u043e\u0445\u0438\u043d"
    ],
    "name:spa_x_preferred":[
        "Clogheen"
    ],
    "name:swe_x_preferred":[
        "Clogheen"
    ],
    "name:szl_x_preferred":[
        "Clogheen"
    ],
    "qs_pg:aaroncc":"IE",
    "qs_pg:gn_country":"IE",
    "qs_pg:gn_fcode":"PPL",
    "qs_pg:gn_pop":0,
    "qs_pg:name":"Clogheen",
    "qs_pg:name_adm0":"Ireland",
    "qs_pg:name_adm1":"Tipperary",
    "qs_pg:photos":175,
    "qs_pg:photos_1k":35,
    "qs_pg:photos_9k":1,
    "qs_pg:photos_9r":4,
    "qs_pg:photos_all":175,
    "qs_pg:photos_sr":4,
    "qs_pg:pop_sr":0,
    "qs_pg:qs_pg_placetype":"locality",
    "qs_pg:qs_pg_placetype_gp":"Town",
    "qs_pg:woe_adm0":23424803,
    "woe:adm0_id":23424803,
    "woe:name_adm0":"Ireland",
    "woe:name_adm1":"Tipperary",
    "woe:placetype":"Town",
    "wof:name":"Clogheen",
    "wof:placetype":"locality",
    "wof:population":491
},
  "geometry": {"coordinates":[-7.99222,52.27583],"type":"Point"}
}