{
  "type": "Feature",
  "properties": {
    "gn:admin1_code":"L",
    "gn:admin2_code":"21.0",
    "gn:asciiname":"Fordstown",
    "gn:country_code":"IE",
    "gn:dem":76,
    "gn:feature_class":"P",
    "gn:feature_code":"PPL",
    "gn:name":"Fordstown",
    "gn:population":0,
    "gn:timezone":"Europe/Dublin",
    "iso:country":"IE",
    "name:und_x_variant":[
        "Ballaghboy"
    ],
    "wof:name":"Fordstown",
    "wof:placetype":"locality"
},
  "geometry": {"coordinates":[-6.90314,53.68711999999999],"type":"Point"}
}