{
  "type": "Feature",
  "properties": {
    "gn:admin1_code":"L",
    "gn:admin2_code":"19.0",
    "gn:asciiname":"Dowdallshill",
    "gn:country_code":"IE",
    "gn:dem":11,
    "gn:feature_class":"P",
    "gn:feature_code":"PPL",
    "gn:name":"Dowdallshill",
    "gn:population":0,
    "gn:timezone":"Europe/Dublin",
    "iso:country":"IE",
    "wof:name":"Dowdallshill",
    "wof:placetype":"locality"
},
  "geometry": {"coordinates":[-6.39472,54.02139],"type":"Point"}
}