{
  "type": "Feature",
  "properties": {
    "gn:admin1_code":"L",
    "gn:admin2_code":"15.0",
    "gn:asciiname":"Huntington",
    "gn:country_code":"IE",
    "gn:dem":85,
    "gn:feature_class":"P",
    "gn:feature_code":"PPL",
    "gn:name":"Huntington",
    "gn:population":0,
    "gn:timezone":"Europe/Dublin",
    "iso:country":"IE",
    "wof:name":"Huntington",
    "wof:placetype":"locality"
},
  "geometry": {"coordinates":[-7.16806,53.12778],"type":"Point"}
}