{
  "type": "Feature",
  "properties": {
    "gn:admin1_code":"C",
    "gn:admin2_code":"20",
    "gn:asciiname":"Srah",
    "gn:country_code":"IE",
    "gn:dem":43,
    "gn:feature_class":"P",
    "gn:feature_code":"PPL",
    "gn:name":"Srah",
    "gn:population":0,
    "gn:timezone":"Europe/Dublin",
    "iso:country":"IE",
    "name:eng_x_preferred":[
        "Srah"
    ],
    "name:gle_x_preferred":[
        "An tSraith"
    ],
    "wof:name":"Srah",
    "wof:placetype":"locality"
},
  "geometry": {"coordinates":[-9.93349,54.17196],"type":"Point"}
}