{
  "type": "Feature",
  "properties": {
    "gn:admin1_code":"M",
    "gn:admin2_code":"11",
    "gn:asciiname":"Letterfinish",
    "gn:country_code":"IE",
    "gn:dem":130,
    "gn:feature_class":"P",
    "gn:feature_code":"PPL",
    "gn:name":"Letterfinish",
    "gn:population":0,
    "gn:timezone":"Europe/Dublin",
    "iso:country":"IE",
    "wof:name":"Letterfinish",
    "wof:placetype":"locality"
},
  "geometry": {"coordinates":[-9.81667,51.86667],"type":"Point"}
}