{
  "type": "Feature",
  "properties": {
    "gn:admin1_code":"C",
    "gn:admin2_code":"10",
    "gn:asciiname":"Ballinamore Bridge",
    "gn:country_code":"IE",
    "gn:dem":51,
    "gn:feature_class":"P",
    "gn:feature_code":"PPL",
    "gn:name":"Ballinamore Bridge",
    "gn:population":0,
    "gn:timezone":"Europe/Dublin",
    "iso:country":"IE",
    "name:und_x_variant":[
        "Ballinamore",
        "Ballinamore Bridge"
    ],
    "wof:name":"Ballinamore Bridge",
    "wof:placetype":"locality"
},
  "geometry": {"coordinates":[-8.36667,53.48333],"type":"Point"}
}