{
  "type": "Feature",
  "properties": {
    "gn:admin1_code":"L",
    "gn:admin2_code":"12.0",
    "gn:asciiname":"Dysart",
    "gn:country_code":"IE",
    "gn:dem":73,
    "gn:feature_class":"P",
    "gn:feature_code":"PPLL",
    "gn:name":"Dysart",
    "gn:population":0,
    "gn:timezone":"Europe/Dublin",
    "iso:country":"IE",
    "name:ceb_x_preferred":[
        "Dysart"
    ],
    "name:deu_x_preferred":[
        "Dysart"
    ],
    "name:fra_x_preferred":[
        "Dysart"
    ],
    "name:swe_x_preferred":[
        "Dysart"
    ],
    "wof:name":"Dysart",
    "wof:placetype":"locality"
},
  "geometry": {"coordinates":[-6.80611,53.38916999999999],"type":"Point"}
}