{
  "type": "Feature",
  "properties": {
    "gn:admin1_code":"U",
    "gn:admin2_code":"22",
    "gn:asciiname":"Knocks",
    "gn:country_code":"IE",
    "gn:dem":124,
    "gn:feature_class":"P",
    "gn:feature_code":"PPLL",
    "gn:name":"Knocks",
    "gn:population":0,
    "gn:timezone":"Europe/Dublin",
    "iso:country":"IE",
    "name:deu_x_preferred":[
        "Knocks"
    ],
    "wof:name":"Knocks",
    "wof:placetype":"locality"
},
  "geometry": {"coordinates":[-7.25222,54.09806],"type":"Point"}
}