{
  "type": "Feature",
  "properties": {
    "gn:admin1_code":"U",
    "gn:admin2_code":"06",
    "gn:asciiname":"Garrynabullogy",
    "gn:country_code":"IE",
    "gn:dem":56,
    "gn:feature_class":"P",
    "gn:feature_code":"PPL",
    "gn:name":"Garrynabullogy",
    "gn:population":0,
    "gn:timezone":"Europe/Dublin",
    "iso:country":"IE",
    "wof:name":"Garrynabullogy",
    "wof:placetype":"locality"
},
  "geometry": {"coordinates":[-7.47194,55.16056],"type":"Point"}
}