{
  "type": "Feature",
  "properties": {
    "gn:admin1_code":"M",
    "gn:admin2_code":"04",
    "gn:asciiname":"Bealahareagh Bridge",
    "gn:country_code":"IE",
    "gn:dem":35,
    "gn:feature_class":"P",
    "gn:feature_code":"PPLL",
    "gn:name":"Bealahareagh Bridge",
    "gn:population":0,
    "gn:timezone":"Europe/Dublin",
    "iso:country":"IE",
    "wof:name":"Bealahareagh Bridge",
    "wof:placetype":"locality"
},
  "geometry": {"coordinates":[-8.46278,51.82389000000001],"type":"Point"}
}