{
  "type": "Feature",
  "properties": {
    "gn:admin1_code":"L",
    "gn:admin2_code":"30",
    "gn:asciiname":"Ballynamona",
    "gn:country_code":"IE",
    "gn:dem":58,
    "gn:feature_class":"P",
    "gn:feature_code":"PPL",
    "gn:name":"Ballynamona",
    "gn:population":0,
    "gn:timezone":"Europe/Dublin",
    "iso:country":"IE",
    "wof:name":"Ballynamona",
    "wof:placetype":"locality"
},
  "geometry": {"coordinates":[-6.79583,52.31778],"type":"Point"}
}