{
  "type": "Feature",
  "properties": {
    "gn:gn_country":"IE",
    "gn:gn_fcode":"PPL",
    "gn:gn_pop":1961,
    "gn:population":2374,
    "iso:country":"IE",
    "name:eng_x_preferred":[
        "Rathangan"
    ],
    "name:gle_x_preferred":[
        "R\u00e1th Iomgh\u00e1in"
    ],
    "qs_pg:aaroncc":"IE",
    "qs_pg:gn_country":"IE",
    "qs_pg:gn_fcode":"PPL",
    "qs_pg:gn_pop":1961,
    "qs_pg:name":"Rathangan",
    "qs_pg:name_adm0":"Ireland",
    "qs_pg:name_adm1":"Kildare",
    "qs_pg:photos":157,
    "qs_pg:photos_1k":32,
    "qs_pg:photos_9k":2,
    "qs_pg:photos_9r":5,
    "qs_pg:photos_all":344,
    "qs_pg:photos_sr":4,
    "qs_pg:pop_sr":3,
    "qs_pg:qs_pg_placetype":"localadmin",
    "qs_pg:qs_pg_placetype_gp":"LocalAdmin",
    "qs_pg:woe_adm0":23424803,
    "woe:adm0_id":23424803,
    "woe:name_adm0":"Ireland",
    "woe:name_adm1":"Kildare",
    "woe:placetype":"LocalAdmin",
    "wof:name":"Rathangan",
    "wof:placetype":"localadmin",
    "wof:population":2374
},
  "geometry": {"coordinates":[-6.995,53.22139],"type":"Point"}
}