{
  "type": "Feature",
  "properties": {
    "gn:admin1_code":"L",
    "gn:admin2_code":"30",
    "gn:asciiname":"Barry's Cross Roads",
    "gn:country_code":"IE",
    "gn:dem":74,
    "gn:feature_class":"P",
    "gn:feature_code":"PPL",
    "gn:name":"Barry\u2019s Cross Roads",
    "gn:population":0,
    "gn:timezone":"Europe/Dublin",
    "iso:country":"IE",
    "wof:name":"Barry's Cross Roads",
    "wof:placetype":"locality"
},
  "geometry": {"coordinates":[-6.64917,52.35361],"type":"Point"}
}