{
  "type": "Feature",
  "properties": {
    "iso:country":"IE",
    "name:eng_x_preferred":[
        "Willbrook"
    ],
    "qs:gn_adm0_cc":"IE",
    "qs:gn_local":2964574,
    "qs:gn_nam_loc":"Dublin, Dublin, IE",
    "qs:gn_namadm1":"L",
    "qs:local_max":52338,
    "qs:local_sum":267955,
    "qs:localhoods":62,
    "qs:name":"Willbrook",
    "qs:name_adm0":"Ireland",
    "qs:name_adm1":"Dublin",
    "qs:name_lau":"Rathfarnham-Butterfield",
    "qs:name_local":"Dublin",
    "qs:photo_max":46,
    "qs:photo_sum":137,
    "qs:placetype":"Suburb",
    "qs:quad_count":16,
    "qs:woe_adm0":23424803,
    "qs:woe_adm1":2345254,
    "qs:woe_adm2":0,
    "qs:woe_lau":20072248,
    "qs:woe_local":560743,
    "qs:woe_ver":"7.10.0",
    "wof:lang":[
        "eng"
    ],
    "wof:name":"Willbrook",
    "wof:placetype":"neighbourhood"
},
  "geometry": {"coordinates":[-6.287802,53.293018],"type":"Point"}
}