{
  "type": "Feature",
  "properties": {
    "gn:admin1_code":"L",
    "gn:admin2_code":"13",
    "gn:asciiname":"Lanoge",
    "gn:country_code":"IE",
    "gn:dem":161,
    "gn:feature_class":"P",
    "gn:feature_code":"PPL",
    "gn:name":"Lanoge",
    "gn:population":0,
    "gn:timezone":"Europe/Dublin",
    "iso:country":"IE",
    "wof:name":"Lanoge",
    "wof:placetype":"locality"
},
  "geometry": {"coordinates":[-7.36639,52.44611],"type":"Point"}
}