{
  "type": "Feature",
  "properties": {
    "iso:country":"IE",
    "name:bar_x_preferred":[
        "Connemara"
    ],
    "name:bre_x_preferred":[
        "Conamara"
    ],
    "name:cat_x_preferred":[
        "Conamara"
    ],
    "name:ces_x_preferred":[
        "Connemara"
    ],
    "name:dan_x_preferred":[
        "Connemara"
    ],
    "name:deu_x_preferred":[
        "Connemara"
    ],
    "name:epo_x_preferred":[
        "Connemara"
    ],
    "name:eus_x_preferred":[
        "Connemara"
    ],
    "name:fin_x_preferred":[
        "Connemara"
    ],
    "name:fra_x_preferred":[
        "Connemara"
    ],
    "name:gle_x_preferred":[
        "Conamara"
    ],
    "name:glv_x_preferred":[
        "Conamara"
    ],
    "name:heb_x_preferred":[
        "\u05e7\u05d5\u05e0\u05de\u05d0\u05e8\u05d4"
    ],
    "name:ita_x_preferred":[
        "Connemara"
    ],
    "name:jpn_x_preferred":[
        "\u30b3\u30cd\u30de\u30e9\u5c71\u5730"
    ],
    "name:lit_x_preferred":[
        "Konamara"
    ],
    "name:nld_x_preferred":[
        "Connemara"
    ],
    "name:nor_x_preferred":[
        "Connemara"
    ],
    "name:pol_x_preferred":[
        "Connemara"
    ],
    "name:por_x_preferred":[
        "Connemara"
    ],
    "name:ron_x_preferred":[
        "Connemara"
    ],
    "name:rus_x_preferred":[
        "\u041a\u043e\u043d\u043d\u0435\u043c\u0430\u0440\u0430"
    ],
    "name:slv_x_preferred":[
        "Connemara"
    ],
    "name:spa_x_preferred":[
        "Connemara"
    ],
    "name:swe_x_preferred":[
        "Connemara"
    ],
    "name:ukr_x_preferred":[
        "\u041a\u043e\u043d\u043d\u0435\u043c\u0430\u0440\u0430"
    ],
    "qs_pg:aaroncc":"IE",
    "qs_pg:name":"Connemara",
    "qs_pg:name_adm0":"Ireland",
    "qs_pg:name_adm1":"Galway",
    "qs_pg:photos":1169,
    "qs_pg:photos_1k":237,
    "qs_pg:photos_9k":5,
    "qs_pg:photos_9r":7,
    "qs_pg:photos_all":1169,
    "qs_pg:photos_sr":11,
    "qs_pg:pop_sr":0,
    "qs_pg:qs_pg_placetype":"locality",
    "qs_pg:qs_pg_placetype_gp":"Town",
    "qs_pg:woe_adm0":23424803,
    "woe:adm0_id":23424803,
    "woe:name_adm0":"Ireland",
    "woe:name_adm1":"Galway",
    "woe:placetype":"Town",
    "wof:name":"Connemara",
    "wof:placetype":"locality"
},
  "geometry": {"coordinates":[-9.75018,53.500049],"type":"Point"}
}