{
  "type": "Feature",
  "properties": {
    "gn:admin1_code":"L",
    "gn:admin2_code":"15.0",
    "gn:asciiname":"Ballydavis",
    "gn:country_code":"IE",
    "gn:dem":119,
    "gn:feature_class":"P",
    "gn:feature_code":"PPL",
    "gn:name":"Ballydavis",
    "gn:population":0,
    "gn:timezone":"Europe/Dublin",
    "iso:country":"IE",
    "wof:name":"Ballydavis",
    "wof:placetype":"locality"
},
  "geometry": {"coordinates":[-7.24556,53.04722],"type":"Point"}
}