{
  "type": "Feature",
  "properties": {
    "gn:admin1_code":"M",
    "gn:admin2_code":"42",
    "gn:asciiname":"Coolygorman",
    "gn:country_code":"IE",
    "gn:dem":93,
    "gn:feature_class":"P",
    "gn:feature_code":"PPL",
    "gn:name":"Coolygorman",
    "gn:population":0,
    "gn:timezone":"Europe/Dublin",
    "iso:country":"IE",
    "wof:name":"Coolygorman",
    "wof:placetype":"locality"
},
  "geometry": {"coordinates":[-8.99611,52.36389000000001],"type":"Point"}
}