{
  "type": "Feature",
  "properties": {
    "gn:admin1_code":"U",
    "gn:admin2_code":"06",
    "gn:asciiname":"Shalwy",
    "gn:country_code":"IE",
    "gn:dem":61,
    "gn:feature_class":"P",
    "gn:feature_code":"PPL",
    "gn:name":"Shalwy",
    "gn:population":0,
    "gn:timezone":"Europe/Dublin",
    "iso:country":"IE",
    "wof:name":"Shalwy",
    "wof:placetype":"locality"
},
  "geometry": {"coordinates":[-8.53139,54.62416999999999],"type":"Point"}
}