{
  "type": "Feature",
  "properties": {
    "gn:admin1_code":"M",
    "gn:admin2_code":"44",
    "gn:asciiname":"Hacketstown",
    "gn:country_code":"IE",
    "gn:dem":107,
    "gn:feature_class":"P",
    "gn:feature_code":"PPL",
    "gn:name":"Hacketstown",
    "gn:population":0,
    "gn:timezone":"Europe/Dublin",
    "iso:country":"IE",
    "name:ceb_x_preferred":[
        "Hacketstown"
    ],
    "name:eng_x_preferred":[
        "Hacketstown"
    ],
    "name:eus_x_preferred":[
        "Hacketstown"
    ],
    "name:gle_x_preferred":[
        "Baile an Aic\u00e9adaigh"
    ],
    "name:gle_x_variant":[
        "Baile Haic\u00e9id"
    ],
    "name:kat_x_preferred":[
        "\u10f0\u10d0\u10d9\u10d4\u10e2\u10e1\u10e2\u10d0\u10e3\u10dc\u10d8"
    ],
    "name:nld_x_preferred":[
        "Hacketstown"
    ],
    "name:rus_x_preferred":[
        "\u0425\u0430\u043a\u0435\u0442\u0441\u0442\u0430\u0443\u043d"
    ],
    "name:spa_x_preferred":[
        "Hacketstown"
    ],
    "name:swe_x_preferred":[
        "Hacketstown"
    ],
    "wof:name":"Hacketstown",
    "wof:placetype":"locality"
},
  "geometry": {"coordinates":[-7.33111,52.24389],"type":"Point"}
}