{
  "type": "Feature",
  "properties": {
    "gn:admin1_code":"M",
    "gn:admin2_code":"04",
    "gn:asciiname":"Gyleen",
    "gn:country_code":"IE",
    "gn:dem":37,
    "gn:feature_class":"P",
    "gn:feature_code":"PPL",
    "gn:name":"Gyleen",
    "gn:population":0,
    "gn:timezone":"Europe/Dublin",
    "iso:country":"IE",
    "wof:name":"Gyleen",
    "wof:placetype":"locality"
},
  "geometry": {"coordinates":[-8.1875,51.79778],"type":"Point"}
}