{
  "type": "Feature",
  "properties": {
    "gn:admin1_code":"L",
    "gn:admin2_code":"31.0",
    "gn:asciiname":"Ballardbeg",
    "gn:country_code":"IE",
    "gn:dem":91,
    "gn:feature_class":"P",
    "gn:feature_code":"PPL",
    "gn:name":"Ballardbeg",
    "gn:population":0,
    "gn:timezone":"Europe/Dublin",
    "iso:country":"IE",
    "wof:name":"Ballardbeg",
    "wof:placetype":"locality"
},
  "geometry": {"coordinates":[-6.15611,53.00722],"type":"Point"}
}