{
  "type": "Feature",
  "properties": {
    "gn:country":"IE",
    "gn:fcode":"PPL",
    "gn:population":1241,
    "iso:country":"IE",
    "name:bre_x_preferred":[
        "B\u00e9al \u00c1tha na Muice"
    ],
    "name:ceb_x_preferred":[
        "Swinford"
    ],
    "name:deu_x_preferred":[
        "Swinford"
    ],
    "name:eng_x_preferred":[
        "Swinford"
    ],
    "name:eus_x_preferred":[
        "Swinford"
    ],
    "name:fra_x_preferred":[
        "Swinford"
    ],
    "name:gla_x_preferred":[
        "B\u00e9al \u00c0tha na Muice"
    ],
    "name:gle_x_preferred":[
        "B\u00e9al \u00c1tha na Muice"
    ],
    "name:ita_x_preferred":[
        "Swinford"
    ],
    "name:kat_x_preferred":[
        "\u10e1\u10d5\u10d8\u10dc\u10e4\u10dd\u10e0\u10d3\u10d8"
    ],
    "name:lit_x_preferred":[
        "Svinfordas"
    ],
    "name:nld_x_preferred":[
        "Swinford"
    ],
    "name:pol_x_preferred":[
        "Swinford"
    ],
    "name:rus_x_preferred":[
        "\u0421\u0443\u0438\u043d\u0444\u043e\u0440\u0434"
    ],
    "name:slv_x_preferred":[
        "Swinford"
    ],
    "name:spa_x_preferred":[
        "Swinford"
    ],
    "name:swe_x_preferred":[
        "Swinford"
    ],
    "name:und_x_variant":[
        "Swineford"
    ],
    "qs_pg:aaroncc":"IE",
    "qs_pg:gn_country":"IE",
    "qs_pg:gn_fcode":"PPL",
    "qs_pg:gn_pop":1241,
    "qs_pg:name":"Swinford",
    "qs_pg:name_adm0":"Ireland",
    "qs_pg:name_adm1":"Mayo",
    "qs_pg:photos":119,
    "qs_pg:photos_1k":24,
    "qs_pg:photos_9k":1,
    "qs_pg:photos_9r":3,
    "qs_pg:photos_all":119,
    "qs_pg:photos_sr":3,
    "qs_pg:pop_sr":3,
    "qs_pg:qs_pg_placetype":"locality",
    "qs_pg:qs_pg_placetype_gp":"Town",
    "qs_pg:woe_adm0":23424803,
    "woe:adm0_id":23424803,
    "woe:name_adm0":"Ireland",
    "woe:name_adm1":"Mayo",
    "woe:placetype":"Town",
    "wof:name":"Swinford",
    "wof:placetype":"locality",
    "wof:population":1435
},
  "geometry": {"coordinates":[-8.95,53.95],"type":"Point"}
}