{
  "type": "Feature",
  "properties": {
    "gn:admin1_code":"M",
    "gn:admin2_code":"03",
    "gn:asciiname":"Moyasta",
    "gn:country_code":"IE",
    "gn:dem":5,
    "gn:feature_class":"P",
    "gn:feature_code":"PPL",
    "gn:name":"Moyasta",
    "gn:population":0,
    "gn:timezone":"Europe/Dublin",
    "iso:country":"IE",
    "name:eus_x_preferred":[
        "Moyasta"
    ],
    "wof:name":"Moyasta",
    "wof:placetype":"locality"
},
  "geometry": {"coordinates":[-9.53833,52.67139],"type":"Point"}
}