{
  "type": "Feature",
  "properties": {
    "gn:admin1_code":"L",
    "gn:admin2_code":"12",
    "gn:asciiname":"Newberry",
    "gn:country_code":"IE",
    "gn:dem":103,
    "gn:feature_class":"P",
    "gn:feature_code":"PPL",
    "gn:name":"Newberry",
    "gn:population":0,
    "gn:timezone":"Europe/Dublin",
    "iso:country":"IE",
    "name:deu_x_preferred":[
        "Newberry"
    ],
    "name:fra_x_preferred":[
        "Newberry"
    ],
    "name:nld_x_preferred":[
        "Newberry"
    ],
    "name:pol_x_preferred":[
        "Newberry"
    ],
    "name:por_x_preferred":[
        "Newberry"
    ],
    "name:swe_x_preferred":[
        "Newberry"
    ],
    "name:vol_x_preferred":[
        "Newberry"
    ],
    "wof:name":"Newberry",
    "wof:placetype":"locality"
},
  "geometry": {"coordinates":[-6.725,53.13361],"type":"Point"}
}