{
  "type": "Feature",
  "properties": {
    "gn:admin1_code":"U",
    "gn:admin2_code":"22",
    "gn:asciiname":"Creevelands",
    "gn:country_code":"IE",
    "gn:dem":161,
    "gn:feature_class":"P",
    "gn:feature_code":"PPLL",
    "gn:name":"Creevelands",
    "gn:population":0,
    "gn:timezone":"Europe/Dublin",
    "iso:country":"IE",
    "wof:name":"Creevelands",
    "wof:placetype":"locality"
},
  "geometry": {"coordinates":[-6.895,54.10278],"type":"Point"}
}