{
  "type": "Feature",
  "properties": {
    "gn:admin1_code":"L",
    "gn:admin2_code":"21",
    "gn:asciiname":"Irishford",
    "gn:country_code":"IE",
    "gn:dem":76,
    "gn:feature_class":"P",
    "gn:feature_code":"PPL",
    "gn:name":"Irishford",
    "gn:population":0,
    "gn:timezone":"Europe/Dublin",
    "iso:country":"IE",
    "wof:name":"Irishford",
    "wof:placetype":"locality"
},
  "geometry": {"coordinates":[-6.67798,53.75561],"type":"Point"}
}