{
  "type": "Feature",
  "properties": {
    "gn:country":"IE",
    "gn:fcode":"PPL",
    "gn:population":0,
    "iso:country":"IE",
    "name:eng_x_preferred":[
        "Ballinascarty"
    ],
    "name:eus_x_preferred":[
        "Ballinascarty"
    ],
    "name:gle_x_preferred":[
        "B\u00e9al na Scairte"
    ],
    "name:nld_x_preferred":[
        "Ballinascarty"
    ],
    "name:rus_x_preferred":[
        "\u0411\u0430\u043b\u043b\u0438\u043d\u0430\u0441\u043a\u0430\u0440\u0442\u0438"
    ],
    "name:und_x_variant":[
        "Ballinascarthy"
    ],
    "qs_pg:aaroncc":"IE",
    "qs_pg:gn_country":"IE",
    "qs_pg:gn_fcode":"PPL",
    "qs_pg:gn_pop":0,
    "qs_pg:name":"Ballinascarty",
    "qs_pg:name_adm0":"Ireland",
    "qs_pg:name_adm1":"Cork",
    "qs_pg:photos":57,
    "qs_pg:photos_1k":12,
    "qs_pg:photos_9k":1,
    "qs_pg:photos_9r":2,
    "qs_pg:photos_all":57,
    "qs_pg:photos_sr":2,
    "qs_pg:pop_sr":0,
    "qs_pg:qs_pg_placetype":"locality",
    "qs_pg:qs_pg_placetype_gp":"Town",
    "qs_pg:woe_adm0":23424803,
    "woe:adm0_id":23424803,
    "woe:name_adm0":"Ireland",
    "woe:name_adm1":"Cork",
    "woe:placetype":"Town",
    "wof:name":"Ballinascarty",
    "wof:placetype":"locality"
},
  "geometry": {"coordinates":[-8.90528,51.67222],"type":"Point"}
}