{
  "type": "Feature",
  "properties": {
    "gn:admin1_code":"C",
    "gn:admin2_code":"25.0",
    "gn:asciiname":"Claragh Scotch",
    "gn:country_code":"IE",
    "gn:dem":129,
    "gn:feature_class":"P",
    "gn:feature_code":"PPLL",
    "gn:name":"Claragh Scotch",
    "gn:population":0,
    "gn:timezone":"Europe/Dublin",
    "iso:country":"IE",
    "wof:name":"Claragh Scotch",
    "wof:placetype":"locality"
},
  "geometry": {"coordinates":[-8.64528,54.12111],"type":"Point"}
}