{
  "type": "Feature",
  "properties": {
    "gn:admin1_code":"L",
    "gn:admin2_code":"29.0",
    "gn:asciiname":"Killogeenaghan",
    "gn:country_code":"IE",
    "gn:dem":76,
    "gn:feature_class":"P",
    "gn:feature_code":"PPL",
    "gn:name":"Killogeenaghan",
    "gn:population":0,
    "gn:timezone":"Europe/Dublin",
    "iso:country":"IE",
    "wof:name":"Killogeenaghan",
    "wof:placetype":"locality"
},
  "geometry": {"coordinates":[-7.82972,53.39333000000001],"type":"Point"}
}