{
  "type": "Feature",
  "properties": {
    "gn:admin1_code":"L",
    "gn:admin2_code":"21.0",
    "gn:asciiname":"Philipstown",
    "gn:country_code":"IE",
    "gn:dem":114,
    "gn:feature_class":"P",
    "gn:feature_code":"PPL",
    "gn:name":"Philipstown",
    "gn:population":0,
    "gn:timezone":"Europe/Dublin",
    "iso:country":"IE",
    "name:ceb_x_preferred":[
        "Philipstown"
    ],
    "name:swe_x_preferred":[
        "Philipstown"
    ],
    "wof:name":"Philipstown",
    "wof:placetype":"locality"
},
  "geometry": {"coordinates":[-7.05907,53.72704],"type":"Point"}
}