{
  "type": "Feature",
  "properties": {
    "gn:admin1_code":"M",
    "gn:admin2_code":"4.0",
    "gn:asciiname":"Laghtneill",
    "gn:country_code":"IE",
    "gn:dem":65,
    "gn:feature_class":"P",
    "gn:feature_code":"PPL",
    "gn:name":"Laghtneill",
    "gn:population":0,
    "gn:timezone":"Europe/Dublin",
    "iso:country":"IE",
    "wof:name":"Laghtneill",
    "wof:placetype":"locality"
},
  "geometry": {"coordinates":[-9.33559,51.47847],"type":"Point"}
}