{
  "type": "Feature",
  "properties": {
    "gn:admin1_code":"L",
    "gn:admin2_code":"12",
    "gn:asciiname":"Sheriffhill",
    "gn:country_code":"IE",
    "gn:dem":162,
    "gn:feature_class":"P",
    "gn:feature_code":"PPL",
    "gn:name":"Sheriffhill",
    "gn:population":0,
    "gn:timezone":"Europe/Dublin",
    "iso:country":"IE",
    "wof:name":"Sheriffhill",
    "wof:placetype":"locality"
},
  "geometry": {"coordinates":[-6.80278,52.95],"type":"Point"}
}