{
  "type": "Feature",
  "properties": {
    "gn:admin1_code":"C",
    "gn:admin2_code":"24.0",
    "gn:asciiname":"Largan",
    "gn:country_code":"IE",
    "gn:dem":134,
    "gn:feature_class":"P",
    "gn:feature_code":"PPLL",
    "gn:name":"Largan",
    "gn:population":0,
    "gn:timezone":"Europe/Dublin",
    "iso:country":"IE",
    "wof:name":"Largan",
    "wof:placetype":"locality"
},
  "geometry": {"coordinates":[-8.54694,53.94806],"type":"Point"}
}