{
  "type": "Feature",
  "properties": {
    "gn:gn_country":"IE",
    "gn:gn_fcode":"PPL",
    "gn:gn_pop":0,
    "gn:population":144,
    "iso:country":"IE",
    "name:baq_x_preferred":[
        "Knocktopher"
    ],
    "name:dut_x_preferred":[
        "Knocktopher"
    ],
    "name:eng_x_preferred":[
        "Knocktopher"
    ],
    "name:fre_x_preferred":[
        "Knocktopher"
    ],
    "name:ger_x_preferred":[
        "Knocktopher"
    ],
    "name:gle_x_preferred":[
        "Cnoc an T\u00f3chair"
    ],
    "name:rus_x_preferred":[
        "\u041d\u043e\u043a\u0442\u043e\u0444\u0435\u0440"
    ],
    "name:swe_x_preferred":[
        "Knocktopher"
    ],
    "name:unk_x_variant":[
        "Knockstopher"
    ],
    "qs_pg:aaroncc":"IE",
    "qs_pg:gn_country":"IE",
    "qs_pg:gn_fcode":"PPL",
    "qs_pg:gn_pop":0,
    "qs_pg:name":"Knocktopher",
    "qs_pg:name_adm0":"Ireland",
    "qs_pg:name_adm1":"Kilkenny",
    "qs_pg:photos_9k":1,
    "qs_pg:photos_9r":2,
    "qs_pg:photos_all":26,
    "qs_pg:photos_sr":0,
    "qs_pg:pop_sr":0,
    "qs_pg:qs_pg_placetype":"locality",
    "qs_pg:qs_pg_placetype_gp":"Town",
    "qs_pg:woe_adm0":23424803,
    "woe:adm0_id":23424803,
    "woe:name_adm0":"Ireland",
    "woe:name_adm1":"Kilkenny",
    "woe:placetype":"Town",
    "wof:name":"Knocktopher",
    "wof:placetype":"locality",
    "wof:population":144
},
  "geometry": {"coordinates":[-7.21194,52.48361],"type":"Point"}
}