{
  "type": "Feature",
  "properties": {
    "gn:admin1_code":"C",
    "gn:admin2_code":"10.0",
    "gn:asciiname":"Caherphuca",
    "gn:country_code":"IE",
    "gn:dem":54,
    "gn:feature_class":"P",
    "gn:feature_code":"PPL",
    "gn:name":"Caherphuca",
    "gn:population":0,
    "gn:timezone":"Europe/Dublin",
    "iso:country":"IE",
    "wof:name":"Caherphuca",
    "wof:placetype":"locality"
},
  "geometry": {"coordinates":[-8.78056,53.41389],"type":"Point"}
}