{
  "type": "Feature",
  "properties": {
    "gn:admin1_code":"C",
    "gn:admin2_code":"14",
    "gn:asciiname":"Kiltoghert",
    "gn:country_code":"IE",
    "gn:dem":72,
    "gn:feature_class":"P",
    "gn:feature_code":"PPL",
    "gn:name":"Kiltoghert",
    "gn:population":0,
    "gn:timezone":"Europe/Dublin",
    "iso:country":"IE",
    "wof:name":"Kiltoghert",
    "wof:placetype":"locality"
},
  "geometry": {"coordinates":[-8.03611,53.98],"type":"Point"}
}