{
  "type": "Feature",
  "properties": {
    "gn:admin1_code":"L",
    "gn:admin2_code":"30",
    "gn:asciiname":"Screen",
    "gn:cc2":"IE",
    "gn:country_code":"IE",
    "gn:dem":39,
    "gn:feature_class":"P",
    "gn:feature_code":"PPL",
    "gn:name":"Screen",
    "gn:population":0,
    "gn:timezone":"Europe/Dublin",
    "iso:country":"IE",
    "name:und_x_variant":[
        "Skreen",
        "Screen"
    ],
    "wof:name":"Screen",
    "wof:placetype":"locality"
},
  "geometry": {"coordinates":[-6.4125,52.41361],"type":"Point"}
}