{
  "type": "Feature",
  "properties": {
    "gn:admin1_code":"M",
    "gn:admin2_code":"04",
    "gn:asciiname":"Garrane",
    "gn:country_code":"IE",
    "gn:dem":82,
    "gn:feature_class":"P",
    "gn:feature_code":"PPL",
    "gn:name":"Garrane",
    "gn:population":0,
    "gn:timezone":"Europe/Dublin",
    "iso:country":"IE",
    "wof:name":"Garrane",
    "wof:placetype":"locality"
},
  "geometry": {"coordinates":[-8.93,52.11917],"type":"Point"}
}