{
  "type": "Feature",
  "properties": {
    "gn:admin1_code":"C",
    "gn:admin2_code":"20",
    "gn:asciiname":"Carrowmore",
    "gn:country_code":"IE",
    "gn:dem":36,
    "gn:feature_class":"P",
    "gn:feature_code":"PPL",
    "gn:name":"Carrowmore",
    "gn:population":0,
    "gn:timezone":"Europe/Dublin",
    "iso:country":"IE",
    "name:eng_x_preferred":[
        "Carrowmore"
    ],
    "name:gle_x_preferred":[
        "An Cheathr\u00fa Mh\u00f3r"
    ],
    "wof:name":"Carrowmore",
    "wof:placetype":"locality"
},
  "geometry": {"coordinates":[-9.28333,54.25],"type":"Point"}
}