{
  "type": "Feature",
  "properties": {
    "gn:admin1_code":"L",
    "gn:admin2_code":"29.0",
    "gn:asciiname":"Scurlockstown",
    "gn:country_code":"IE",
    "gn:dem":99,
    "gn:feature_class":"P",
    "gn:feature_code":"PPL",
    "gn:name":"Scurlockstown",
    "gn:population":0,
    "gn:timezone":"Europe/Dublin",
    "iso:country":"IE",
    "wof:name":"Scurlockstown",
    "wof:placetype":"locality"
},
  "geometry": {"coordinates":[-7.14154,53.64589],"type":"Point"}
}