{
  "type": "Feature",
  "properties": {
    "gn:admin1_code":"M",
    "gn:admin2_code":"26",
    "gn:asciiname":"Ballyporeen",
    "gn:country_code":"IE",
    "gn:dem":82,
    "gn:feature_class":"P",
    "gn:feature_code":"PPL",
    "gn:name":"Ballyporeen",
    "gn:population":313,
    "gn:timezone":"Europe/Dublin",
    "iso:country":"IE",
    "name:ceb_x_preferred":[
        "Ballyporeen"
    ],
    "name:eng_x_preferred":[
        "Ballyporeen"
    ],
    "name:eus_x_preferred":[
        "Ballyporeen"
    ],
    "name:gle_x_preferred":[
        "B\u00e9al \u00c1tha P\u00f3irin"
    ],
    "name:hun_x_preferred":[
        "Ballyporeen"
    ],
    "name:ita_x_preferred":[
        "Ballyporeen"
    ],
    "name:rus_x_preferred":[
        "\u0411\u0430\u043b\u043b\u0438\u043f\u043e\u0440\u0438\u043d"
    ],
    "name:spa_x_preferred":[
        "Ballyporeen"
    ],
    "name:swe_x_preferred":[
        "Ballyporeen"
    ],
    "wof:name":"Ballyporeen",
    "wof:placetype":"locality",
    "wof:population":313
},
  "geometry": {"coordinates":[-8.10028,52.26917],"type":"Point"}
}