{
  "type": "Feature",
  "properties": {
    "iso:country":"IE",
    "name:eng_x_preferred":[
        "Chapelizod"
    ],
    "wof:name":"Chapelizod",
    "wof:placetype":"neighbourhood"
},
  "geometry": {"coordinates":[-6.342552,53.34828],"type":"Point"}
}