{
  "type": "Feature",
  "properties": {
    "iso:country":"IE",
    "qs_pg:aaroncc":"IE",
    "qs_pg:name":"Connahy",
    "qs_pg:name_adm0":"Ireland",
    "qs_pg:name_adm1":"Kilkenny",
    "qs_pg:photos":122,
    "qs_pg:photos_1k":25,
    "qs_pg:photos_9k":1,
    "qs_pg:photos_9r":3,
    "qs_pg:photos_all":122,
    "qs_pg:photos_sr":3,
    "qs_pg:pop_sr":0,
    "qs_pg:qs_pg_placetype":"locality",
    "qs_pg:qs_pg_placetype_gp":"Town",
    "qs_pg:woe_adm0":23424803,
    "woe:adm0_id":23424803,
    "woe:name_adm0":"Ireland",
    "woe:name_adm1":"Kilkenny",
    "woe:placetype":"Town",
    "wof:name":"Connahy",
    "wof:placetype":"locality"
},
  "geometry": {"coordinates":[-7.291231,52.725025],"type":"Point"}
}