{
  "type": "Feature",
  "properties": {
    "gn:admin1_code":"M",
    "gn:admin2_code":"26",
    "gn:asciiname":"Grangemockler",
    "gn:country_code":"IE",
    "gn:dem":201,
    "gn:feature_class":"P",
    "gn:feature_code":"PPL",
    "gn:name":"Grangemockler",
    "gn:population":0,
    "gn:timezone":"Europe/Dublin",
    "iso:country":"IE",
    "wof:name":"Grangemockler",
    "wof:placetype":"locality"
},
  "geometry": {"coordinates":[-7.49417,52.45639],"type":"Point"}
}