{
  "type": "Feature",
  "properties": {
    "gn:admin1_code":"U",
    "gn:admin2_code":"2.0",
    "gn:asciiname":"Teeboy",
    "gn:country_code":"IE",
    "gn:dem":66,
    "gn:feature_class":"P",
    "gn:feature_code":"PPLL",
    "gn:name":"Teeboy",
    "gn:population":0,
    "gn:timezone":"Europe/Dublin",
    "iso:country":"IE",
    "wof:name":"Teeboy",
    "wof:placetype":"locality"
},
  "geometry": {"coordinates":[-7.72917,54.11472],"type":"Point"}
}