{
  "type": "Feature",
  "properties": {
    "gn:admin1_code":"L",
    "gn:admin2_code":"31",
    "gn:asciiname":"Kilcommon Bridge",
    "gn:country_code":"IE",
    "gn:dem":115,
    "gn:feature_class":"P",
    "gn:feature_code":"PPL",
    "gn:name":"Kilcommon Bridge",
    "gn:population":0,
    "gn:timezone":"Europe/Dublin",
    "iso:country":"IE",
    "wof:name":"Kilcommon Bridge",
    "wof:placetype":"locality"
},
  "geometry": {"coordinates":[-6.45611,52.78639],"type":"Point"}
}