{
  "type": "Feature",
  "properties": {
    "gn:admin1_code":"M",
    "gn:admin2_code":"03",
    "gn:asciiname":"Blackweir Bridge",
    "gn:country_code":"IE",
    "gn:dem":1,
    "gn:feature_class":"P",
    "gn:feature_code":"PPL",
    "gn:name":"Blackweir Bridge",
    "gn:population":0,
    "gn:timezone":"Europe/Dublin",
    "iso:country":"IE",
    "wof:name":"Blackweir Bridge",
    "wof:placetype":"locality"
},
  "geometry": {"coordinates":[-9.58833,52.66694],"type":"Point"}
}