{
  "type": "Feature",
  "properties": {
    "gn:admin1_code":"L",
    "gn:admin2_code":"19.0",
    "gn:asciiname":"Beaulieu Cross",
    "gn:country_code":"IE",
    "gn:dem":17,
    "gn:feature_class":"P",
    "gn:feature_code":"PPL",
    "gn:name":"Beaulieu Cross",
    "gn:population":221,
    "gn:timezone":"Europe/Dublin",
    "iso:country":"IE",
    "wof:name":"Beaulieu Cross",
    "wof:placetype":"locality",
    "wof:population":221
},
  "geometry": {"coordinates":[-6.30671,53.73823],"type":"Point"}
}