{
  "type": "Feature",
  "properties": {
    "gn:admin1_code":"L",
    "gn:admin2_code":"19",
    "gn:asciiname":"Salterstown",
    "gn:country_code":"IE",
    "gn:dem":12,
    "gn:feature_class":"P",
    "gn:feature_code":"PPL",
    "gn:name":"Salterstown",
    "gn:population":0,
    "gn:timezone":"Europe/Dublin",
    "iso:country":"IE",
    "wof:name":"Salterstown",
    "wof:placetype":"locality"
},
  "geometry": {"coordinates":[-6.30694,53.87167],"type":"Point"}
}