{
  "type": "Feature",
  "properties": {
    "gn:admin1_code":"M",
    "gn:admin2_code":"04",
    "gn:asciiname":"Ballinadee",
    "gn:country_code":"IE",
    "gn:dem":27,
    "gn:feature_class":"P",
    "gn:feature_code":"PPL",
    "gn:name":"Ballinadee",
    "gn:population":0,
    "gn:timezone":"Europe/Dublin",
    "iso:country":"IE",
    "name:eus_x_preferred":[
        "Ballinadee"
    ],
    "name:rus_x_preferred":[
        "\u0411\u0430\u043b\u043b\u0438\u043d\u0430\u0434\u0438"
    ],
    "wof:name":"Ballinadee",
    "wof:placetype":"locality"
},
  "geometry": {"coordinates":[-8.63444,51.71278],"type":"Point"}
}