{
  "type": "Feature",
  "properties": {
    "gn:admin1_code":"C",
    "gn:admin2_code":"20.0",
    "gn:asciiname":"Glencastle",
    "gn:country_code":"IE",
    "gn:dem":51,
    "gn:feature_class":"P",
    "gn:feature_code":"PPL",
    "gn:name":"Glencastle",
    "gn:population":0,
    "gn:timezone":"Europe/Dublin",
    "iso:country":"IE",
    "name:eng_x_preferred":[
        "Glencastle"
    ],
    "name:eus_x_preferred":[
        "Glencastle"
    ],
    "name:gle_x_preferred":[
        "Gleann Chaisell"
    ],
    "name:gle_x_variant":[
        "Gleann Chaisil"
    ],
    "wof:name":"Glencastle",
    "wof:placetype":"locality"
},
  "geometry": {"coordinates":[-9.87668,54.1818],"type":"Point"}
}