{
  "type": "Feature",
  "properties": {
    "gn:admin1_code":"C",
    "gn:admin2_code":"25.0",
    "gn:asciiname":"Doonbeakin",
    "gn:country_code":"IE",
    "gn:dem":86,
    "gn:feature_class":"P",
    "gn:feature_code":"PPLL",
    "gn:name":"Doonbeakin",
    "gn:population":0,
    "gn:timezone":"Europe/Dublin",
    "iso:country":"IE",
    "wof:name":"Doonbeakin",
    "wof:placetype":"locality"
},
  "geometry": {"coordinates":[-8.83333,54.23194],"type":"Point"}
}