{
  "type": "Feature",
  "properties": {
    "gn:admin1_code":"C",
    "gn:admin2_code":"10.0",
    "gn:asciiname":"Terryland",
    "gn:country_code":"IE",
    "gn:dem":16,
    "gn:feature_class":"P",
    "gn:feature_code":"PPL",
    "gn:name":"Terryland",
    "gn:population":0,
    "gn:timezone":"Europe/Dublin",
    "iso:country":"IE",
    "name:eng_x_preferred":[
        "Terryland"
    ],
    "name:gle_x_preferred":[
        "T\u00edr Oile\u00e1in"
    ],
    "wof:name":"Terryland",
    "wof:placetype":"locality"
},
  "geometry": {"coordinates":[-9.05472,53.28889],"type":"Point"}
}