{
  "type": "Feature",
  "properties": {
    "gn:admin1_code":"C",
    "gn:admin2_code":"20",
    "gn:asciiname":"Carn",
    "gn:country_code":"IE",
    "gn:dem":27,
    "gn:feature_class":"P",
    "gn:feature_code":"PPL",
    "gn:name":"Carn",
    "gn:population":0,
    "gn:timezone":"Europe/Dublin",
    "iso:country":"IE",
    "name:eng_x_preferred":[
        "Carn"
    ],
    "name:gle_x_preferred":[
        "An Carn"
    ],
    "wof:name":"Carn",
    "wof:placetype":"locality"
},
  "geometry": {"coordinates":[-9.29222,54.23222],"type":"Point"}
}