{
  "type": "Feature",
  "properties": {
    "gn:admin1_code":"M",
    "gn:admin2_code":"26",
    "gn:asciiname":"Curreeny Cross",
    "gn:country_code":"IE",
    "gn:dem":303,
    "gn:feature_class":"P",
    "gn:feature_code":"PPL",
    "gn:name":"Curreeny Cross",
    "gn:population":0,
    "gn:timezone":"Europe/Dublin",
    "iso:country":"IE",
    "wof:name":"Curreeny Cross",
    "wof:placetype":"locality"
},
  "geometry": {"coordinates":[-8.14333,52.73361],"type":"Point"}
}