{
  "type": "Feature",
  "properties": {
    "gn:admin1_code":"M",
    "gn:admin2_code":"26",
    "gn:asciiname":"Gortnahoe",
    "gn:country_code":"IE",
    "gn:dem":140,
    "gn:feature_class":"P",
    "gn:feature_code":"PPL",
    "gn:name":"Gortnahoe",
    "gn:population":304,
    "gn:timezone":"Europe/Dublin",
    "iso:country":"IE",
    "name:und_x_variant":[
        "Gortnahoo"
    ],
    "wof:name":"Gortnahoe",
    "wof:placetype":"locality",
    "wof:population":304
},
  "geometry": {"coordinates":[-7.59917,52.67667],"type":"Point"}
}