{
  "type": "Feature",
  "properties": {
    "gn:admin1_code":"M",
    "gn:admin2_code":"26",
    "gn:asciiname":"Gortnahoe",
    "gn:country_code":"IE",
    "gn:dem":140,
    "gn:feature_class":"P",
    "gn:feature_code":"PPL",
    "gn:name":"Gortnahoe",
    "gn:population":304,
    "gn:timezone":"Europe/Dublin",
    "iso:country":"IE",
    "name:ceb_x_preferred":[
        "Gortnahoe"
    ],
    "name:cym_x_preferred":[
        "Gortnahoe"
    ],
    "name:eus_x_preferred":[
        "Gortnahoe"
    ],
    "name:rus_x_preferred":[
        "\u0413\u043e\u0440\u0442\u043d\u0430\u0445\u0443"
    ],
    "name:spa_x_preferred":[
        "Gortnahoo"
    ],
    "name:swe_x_preferred":[
        "Gortnahoe"
    ],
    "wof:name":"Gortnahoe",
    "wof:placetype":"locality",
    "wof:population":304
},
  "geometry": {"coordinates":[-7.59917,52.67667],"type":"Point"}
}