{
  "type": "Feature",
  "properties": {
    "gn:admin1_code":"L",
    "gn:admin2_code":"30",
    "gn:asciiname":"Howlan's Cross Roads",
    "gn:country_code":"IE",
    "gn:dem":55,
    "gn:feature_class":"P",
    "gn:feature_code":"PPL",
    "gn:name":"Howlan\u2019s Cross Roads",
    "gn:population":0,
    "gn:timezone":"Europe/Dublin",
    "iso:country":"IE",
    "wof:name":"Howlan's Cross Roads",
    "wof:placetype":"locality"
},
  "geometry": {"coordinates":[-6.6725,52.30667],"type":"Point"}
}