{
  "type": "Feature",
  "properties": {
    "gn:admin1_code":"C",
    "gn:admin2_code":"14.0",
    "gn:asciiname":"Dawn of Hope Bridge",
    "gn:country_code":"IE",
    "gn:dem":261,
    "gn:feature_class":"P",
    "gn:feature_code":"PPLL",
    "gn:name":"Dawn of Hope Bridge",
    "gn:population":0,
    "gn:timezone":"Europe/Dublin",
    "iso:country":"IE",
    "wof:name":"Dawn of Hope Bridge",
    "wof:placetype":"locality"
},
  "geometry": {"coordinates":[-8.08444,54.20306],"type":"Point"}
}