{
  "type": "Feature",
  "properties": {
    "gn:admin1_code":"L",
    "gn:admin2_code":"21.0",
    "gn:asciiname":"Knightstown",
    "gn:country_code":"IE",
    "gn:dem":71,
    "gn:feature_class":"P",
    "gn:feature_code":"PPL",
    "gn:name":"Knightstown",
    "gn:population":0,
    "gn:timezone":"Europe/Dublin",
    "iso:country":"IE",
    "name:ceb_x_preferred":[
        "Knightstown"
    ],
    "name:fra_x_preferred":[
        "Knightstown"
    ],
    "name:swe_x_preferred":[
        "Knightstown"
    ],
    "wof:name":"Knightstown",
    "wof:placetype":"locality"
},
  "geometry": {"coordinates":[-6.7181,53.74786],"type":"Point"}
}