{
  "type": "Feature",
  "properties": {
    "gn:admin1_code":"L",
    "gn:admin2_code":"15.0",
    "gn:asciiname":"Farmleigh",
    "gn:country_code":"IE",
    "gn:dem":86,
    "gn:feature_class":"P",
    "gn:feature_code":"PPL",
    "gn:name":"Farmleigh",
    "gn:population":0,
    "gn:timezone":"Europe/Dublin",
    "iso:country":"IE",
    "wof:name":"Farmleigh",
    "wof:placetype":"locality"
},
  "geometry": {"coordinates":[-7.39806,52.90221999999999],"type":"Point"}
}