{
  "type": "Feature",
  "properties": {
    "gn:admin1_code":"C",
    "gn:admin2_code":"20.0",
    "gn:asciiname":"Ballina",
    "gn:country_code":"IE",
    "gn:dem":4,
    "gn:feature_class":"P",
    "gn:feature_code":"PPL",
    "gn:name":"Ballina",
    "gn:population":0,
    "gn:timezone":"Europe/Dublin",
    "iso:country":"IE",
    "name:ceb_x_preferred":[
        "Ballina"
    ],
    "name:deu_x_preferred":[
        "Ballina"
    ],
    "name:fra_x_preferred":[
        "Ballina"
    ],
    "name:glg_x_preferred":[
        "Ballina"
    ],
    "name:ind_x_preferred":[
        "Ballina"
    ],
    "name:ita_x_preferred":[
        "Ballina"
    ],
    "name:kat_x_preferred":[
        "\u10d1\u10d0\u10da\u10d8\u10dc\u10d0"
    ],
    "name:kor_x_preferred":[
        "\ubc1c\ub9ac\ub098"
    ],
    "name:kor_x_variant":[
        "\ubc38\ub9ac\ub098"
    ],
    "name:mlg_x_preferred":[
        "Ballina"
    ],
    "name:nld_x_preferred":[
        "Ballina"
    ],
    "name:pol_x_preferred":[
        "Ballina"
    ],
    "name:por_x_preferred":[
        "Ballina"
    ],
    "name:rus_x_preferred":[
        "\u0411\u0430\u043b\u043b\u0438\u043d\u0430"
    ],
    "name:swe_x_preferred":[
        "Ballina"
    ],
    "name:tur_x_preferred":[
        "Ballina"
    ],
    "name:ukr_x_preferred":[
        "\u0411\u0430\u043b\u043b\u0456\u043d\u0430"
    ],
    "name:urd_x_preferred":[
        "\u0628\u0644\u06cc\u0646\u0627"
    ],
    "name:vie_x_preferred":[
        "Ballina"
    ],
    "wof:name":"Ballina",
    "wof:placetype":"locality"
},
  "geometry": {"coordinates":[-9.81425,54.13376],"type":"Point"}
}