{
  "type": "Feature",
  "properties": {
    "gn:admin1_code":"C",
    "gn:admin2_code":"20.0",
    "gn:asciiname":"Carrownurlaur",
    "gn:country_code":"IE",
    "gn:dem":41,
    "gn:feature_class":"P",
    "gn:feature_code":"PPL",
    "gn:name":"Carrownurlaur",
    "gn:population":0,
    "gn:timezone":"Europe/Dublin",
    "iso:country":"IE",
    "wof:name":"Carrownurlaur",
    "wof:placetype":"locality"
},
  "geometry": {"coordinates":[-9.24575,53.85238],"type":"Point"}
}