{
  "type": "Feature",
  "properties": {
    "gn:admin1_code":"M",
    "gn:admin2_code":"11",
    "gn:asciiname":"Lisselton Cross Roads",
    "gn:country_code":"IE",
    "gn:dem":25,
    "gn:feature_class":"P",
    "gn:feature_code":"PPL",
    "gn:name":"Lisselton Cross Roads",
    "gn:population":0,
    "gn:timezone":"Europe/Dublin",
    "iso:country":"IE",
    "wof:name":"Lisselton Cross Roads",
    "wof:placetype":"locality"
},
  "geometry": {"coordinates":[-9.57556,52.48833000000001],"type":"Point"}
}