{
  "type": "Feature",
  "properties": {
    "gn:admin1_code":"L",
    "gn:admin2_code":"15.0",
    "gn:asciiname":"Carrowreagh",
    "gn:country_code":"IE",
    "gn:dem":142,
    "gn:feature_class":"P",
    "gn:feature_code":"PPL",
    "gn:name":"Carrowreagh",
    "gn:population":0,
    "gn:timezone":"Europe/Dublin",
    "iso:country":"IE",
    "wof:name":"Carrowreagh",
    "wof:placetype":"locality"
},
  "geometry": {"coordinates":[-7.56389,52.92861],"type":"Point"}
}