{
  "type": "Feature",
  "properties": {
    "gn:admin1_code":"L",
    "gn:admin2_code":"01",
    "gn:asciiname":"Ballyhacket",
    "gn:country_code":"IE",
    "gn:dem":115,
    "gn:feature_class":"P",
    "gn:feature_code":"PPL",
    "gn:name":"Ballyhacket",
    "gn:population":0,
    "gn:timezone":"Europe/Dublin",
    "iso:country":"IE",
    "wof:name":"Ballyhacket",
    "wof:placetype":"locality"
},
  "geometry": {"coordinates":[-6.75278,52.86389000000001],"type":"Point"}
}