{
  "type": "Feature",
  "properties": {
    "gn:admin1_code":"C",
    "gn:admin2_code":"10",
    "gn:asciiname":"Gowla",
    "gn:country_code":"IE",
    "gn:dem":12,
    "gn:feature_class":"P",
    "gn:feature_code":"PPL",
    "gn:name":"Gowla",
    "gn:population":0,
    "gn:timezone":"Europe/Dublin",
    "iso:country":"IE",
    "name:eng_x_preferred":[
        "Gowla"
    ],
    "name:gle_x_preferred":[
        "Gabhla"
    ],
    "wof:name":"Gowla",
    "wof:placetype":"locality"
},
  "geometry": {"coordinates":[-9.77806,53.39611],"type":"Point"}
}