{
  "type": "Feature",
  "properties": {
    "gn:country":"IE",
    "gn:fcode":"PPL",
    "gn:population":0,
    "iso:country":"IE",
    "name:ceb_x_preferred":[
        "Rockhill"
    ],
    "name:deu_x_preferred":[
        "Rockhill"
    ],
    "name:fra_x_preferred":[
        "Rockhill"
    ],
    "name:ita_x_preferred":[
        "Rockhill"
    ],
    "name:spa_x_preferred":[
        "Rockhill"
    ],
    "name:swe_x_preferred":[
        "Rockhill"
    ],
    "qs_pg:aaroncc":"IE",
    "qs_pg:gn_country":"IE",
    "qs_pg:gn_fcode":"PPL",
    "qs_pg:gn_pop":0,
    "qs_pg:name":"Rockhill",
    "qs_pg:name_adm0":"Ireland",
    "qs_pg:name_adm1":"Roscommon",
    "qs_pg:photos":1,
    "qs_pg:photos_1k":1,
    "qs_pg:photos_9k":1,
    "qs_pg:photos_9r":1,
    "qs_pg:photos_all":1,
    "qs_pg:photos_sr":1,
    "qs_pg:pop_sr":0,
    "qs_pg:qs_pg_placetype":"localadmin",
    "qs_pg:qs_pg_placetype_gp":"LocalAdmin",
    "qs_pg:woe_adm0":23424803,
    "woe:adm0_id":23424803,
    "woe:name_adm0":"Ireland",
    "woe:name_adm1":"Roscommon",
    "woe:placetype":"LocalAdmin",
    "wof:name":"Rockhill",
    "wof:placetype":"localadmin"
},
  "geometry": {"coordinates":[-8.15,54.06667],"type":"Point"}
}