{
  "type": "Feature",
  "properties": {
    "gn:gn_country":"IE",
    "gn:gn_fcode":"PPL",
    "gn:gn_pop":0,
    "gn:population":296,
    "iso:country":"IE",
    "name:bul_x_preferred":[
        "\u041c\u043e\u043d\u0438\u0432\u0435\u0430"
    ],
    "name:ceb_x_preferred":[
        "Monivea"
    ],
    "name:eng_x_preferred":[
        "Monivea"
    ],
    "name:eus_x_preferred":[
        "Monivea"
    ],
    "name:fra_x_preferred":[
        "Monivea"
    ],
    "name:gle_x_preferred":[
        "Muine Mhe\u00e1"
    ],
    "name:jpn_x_preferred":[
        "\u30e2\u30cb\u30f4\u30a3\u30a2"
    ],
    "name:kat_x_preferred":[
        "\u10db\u10dd\u10dc\u10d8\u10d5\u10d4\u10d8"
    ],
    "name:nld_x_preferred":[
        "Monivea"
    ],
    "name:pol_x_preferred":[
        "Monivea"
    ],
    "name:rus_x_preferred":[
        "\u041c\u043e\u043d\u0438\u0432\u0435\u0439"
    ],
    "name:spa_x_preferred":[
        "Monivea"
    ],
    "name:swe_x_preferred":[
        "Monivea"
    ],
    "qs_pg:aaroncc":"IE",
    "qs_pg:gn_country":"IE",
    "qs_pg:gn_fcode":"PPL",
    "qs_pg:gn_pop":0,
    "qs_pg:name":"Monivea",
    "qs_pg:name_adm0":"Ireland",
    "qs_pg:name_adm1":"Galway",
    "qs_pg:photos":25,
    "qs_pg:photos_1k":5,
    "qs_pg:photos_9k":1,
    "qs_pg:photos_9r":1,
    "qs_pg:photos_all":25,
    "qs_pg:photos_sr":1,
    "qs_pg:pop_sr":0,
    "qs_pg:qs_pg_placetype":"locality",
    "qs_pg:qs_pg_placetype_gp":"Town",
    "qs_pg:woe_adm0":23424803,
    "woe:adm0_id":23424803,
    "woe:name_adm0":"Ireland",
    "woe:name_adm1":"Galway",
    "woe:placetype":"Town",
    "wof:name":"Monivea",
    "wof:placetype":"locality",
    "wof:population":296
},
  "geometry": {"coordinates":[-8.69778,53.36778],"type":"Point"}
}