{
  "type": "Feature",
  "properties": {
    "gn:admin1_code":"M",
    "gn:admin2_code":"26",
    "gn:asciiname":"Ballytarsna",
    "gn:country_code":"IE",
    "gn:dem":113,
    "gn:feature_class":"P",
    "gn:feature_code":"PPL",
    "gn:name":"Ballytarsna",
    "gn:population":0,
    "gn:timezone":"Europe/Dublin",
    "iso:country":"IE",
    "wof:name":"Ballytarsna",
    "wof:placetype":"locality"
},
  "geometry": {"coordinates":[-7.82583,52.57639],"type":"Point"}
}