{
  "type": "Feature",
  "properties": {
    "gn:admin1_code":"M",
    "gn:admin2_code":"44",
    "gn:asciiname":"Soldiers Cross Roads",
    "gn:country_code":"IE",
    "gn:dem":129,
    "gn:feature_class":"P",
    "gn:feature_code":"PPL",
    "gn:name":"Soldiers Cross Roads",
    "gn:population":0,
    "gn:timezone":"Europe/Dublin",
    "iso:country":"IE",
    "wof:name":"Soldiers Cross Roads",
    "wof:placetype":"locality"
},
  "geometry": {"coordinates":[-7.72083,52.15056],"type":"Point"}
}