{
  "type": "Feature",
  "properties": {
    "iso:country":"IE",
    "qs_pg:aaroncc":"IE",
    "qs_pg:name":"Baltinglass",
    "qs_pg:name_adm0":"Ireland",
    "qs_pg:name_adm1":"Wicklow",
    "qs_pg:photos":185,
    "qs_pg:photos_1k":37,
    "qs_pg:photos_9k":2,
    "qs_pg:photos_9r":5,
    "qs_pg:photos_all":464,
    "qs_pg:photos_sr":4,
    "qs_pg:pop_sr":0,
    "qs_pg:qs_pg_placetype":"localadmin",
    "qs_pg:qs_pg_placetype_gp":"LocalAdmin",
    "qs_pg:woe_adm0":23424803,
    "woe:adm0_id":23424803,
    "woe:name_adm0":"Ireland",
    "woe:name_adm1":"Wicklow",
    "woe:placetype":"LocalAdmin",
    "wof:name":"Baltinglass",
    "wof:placetype":"localadmin"
},
  "geometry": {"coordinates":[-6.7096045,52.941332],"type":"Point"}
}