{
  "type": "Feature",
  "properties": {
    "gn:admin1_code":"L",
    "gn:admin2_code":"12.0",
    "gn:asciiname":"Walterstown",
    "gn:country_code":"IE",
    "gn:dem":114,
    "gn:feature_class":"P",
    "gn:feature_code":"PPL",
    "gn:name":"Walterstown",
    "gn:population":0,
    "gn:timezone":"Europe/Dublin",
    "iso:country":"IE",
    "wof:name":"Walterstown",
    "wof:placetype":"locality"
},
  "geometry": {"coordinates":[-6.72556,53.16],"type":"Point"}
}