{
  "type": "Feature",
  "properties": {
    "gn:country":"IE",
    "gn:fcode":"PPL",
    "gn:population":0,
    "iso:country":"IE",
    "name:eng_x_preferred":[
        "Ballykeeran"
    ],
    "name:eus_x_preferred":[
        "Ballykeeran"
    ],
    "name:gle_x_preferred":[
        "Bealach Caorthainn"
    ],
    "name:nld_x_preferred":[
        "Ballykeeran"
    ],
    "name:rus_x_preferred":[
        "\u0411\u0430\u043b\u043b\u0438\u043a\u0438\u0440\u0430\u043d"
    ],
    "qs_pg:aaroncc":"IE",
    "qs_pg:gn_country":"IE",
    "qs_pg:gn_fcode":"PPL",
    "qs_pg:gn_pop":0,
    "qs_pg:name":"Ballykerran",
    "qs_pg:name_adm0":"Ireland",
    "qs_pg:name_adm1":"Westmeath",
    "qs_pg:photos":242,
    "qs_pg:photos_1k":49,
    "qs_pg:photos_9k":1,
    "qs_pg:photos_9r":4,
    "qs_pg:photos_all":242,
    "qs_pg:photos_sr":4,
    "qs_pg:pop_sr":0,
    "qs_pg:qs_pg_placetype":"locality",
    "qs_pg:qs_pg_placetype_gp":"Town",
    "qs_pg:woe_adm0":23424803,
    "woe:adm0_id":23424803,
    "woe:name_adm0":"Ireland",
    "woe:name_adm1":"Westmeath",
    "woe:placetype":"Town",
    "wof:name":"Ballykerran",
    "wof:placetype":"locality"
},
  "geometry": {"coordinates":[-7.88333,53.45],"type":"Point"}
}