{
  "type": "Feature",
  "properties": {
    "gn:admin1_code":"L",
    "gn:admin2_code":"01",
    "gn:asciiname":"Bilboa",
    "gn:country_code":"IE",
    "gn:dem":258,
    "gn:feature_class":"P",
    "gn:feature_code":"PPL",
    "gn:name":"Bilboa",
    "gn:population":0,
    "gn:timezone":"Europe/Dublin",
    "iso:country":"IE",
    "wof:name":"Bilboa",
    "wof:placetype":"locality"
},
  "geometry": {"coordinates":[-7.03806,52.79667],"type":"Point"}
}