{
  "type": "Feature",
  "properties": {
    "gn:admin1_code":"L",
    "gn:admin2_code":"30",
    "gn:asciiname":"Clonevin Cross Roads",
    "gn:cc2":"IE",
    "gn:country_code":"IE",
    "gn:dem":18,
    "gn:feature_class":"P",
    "gn:feature_code":"PPL",
    "gn:name":"Clonevin Cross Roads",
    "gn:population":0,
    "gn:timezone":"Europe/Dublin",
    "iso:country":"IE",
    "name:und_x_variant":[
        "Clonevan",
        "Clonevin Cross Roads"
    ],
    "wof:name":"Clonevin Cross Roads",
    "wof:placetype":"locality"
},
  "geometry": {"coordinates":[-6.23111,52.55694],"type":"Point"}
}