{
  "type": "Feature",
  "properties": {
    "gn:admin1_code":"L",
    "gn:admin2_code":"12.0",
    "gn:asciiname":"Bray",
    "gn:country_code":"IE",
    "gn:dem":62,
    "gn:feature_class":"P",
    "gn:feature_code":"PPL",
    "gn:name":"Bray",
    "gn:population":0,
    "gn:timezone":"Europe/Dublin",
    "iso:country":"IE",
    "name:bre_x_preferred":[
        "Bray"
    ],
    "name:cat_x_preferred":[
        "Bray"
    ],
    "name:ceb_x_preferred":[
        "Bray"
    ],
    "name:deu_x_preferred":[
        "Bray"
    ],
    "name:eus_x_preferred":[
        "Bray"
    ],
    "name:fra_x_preferred":[
        "Bray"
    ],
    "name:heb_x_preferred":[
        "\u05d1\u05e8\u05d9\u05d9"
    ],
    "name:ita_x_preferred":[
        "Bray"
    ],
    "name:nds_x_preferred":[
        "Bray"
    ],
    "name:nld_x_preferred":[
        "Bray"
    ],
    "name:pms_x_preferred":[
        "Bray"
    ],
    "name:pol_x_preferred":[
        "Bray"
    ],
    "name:por_x_preferred":[
        "Bray"
    ],
    "name:rus_x_preferred":[
        "\u0411\u0440\u0435"
    ],
    "name:slk_x_preferred":[
        "Bray"
    ],
    "name:spa_x_preferred":[
        "Bray"
    ],
    "name:swe_x_preferred":[
        "Bray"
    ],
    "name:vol_x_preferred":[
        "Bray"
    ],
    "wof:name":"Bray",
    "wof:placetype":"locality"
},
  "geometry": {"coordinates":[-6.94444,52.9825],"type":"Point"}
}