{
  "type": "Feature",
  "properties": {
    "gn:gn_country":"IE",
    "gn:gn_fcode":"PPL",
    "gn:gn_pop":0,
    "gn:population":742,
    "iso:country":"IE",
    "name:eng_x_preferred":[
        "Gowran"
    ],
    "name:eus_x_preferred":[
        "Gowran"
    ],
    "name:fra_x_preferred":[
        "Gowran"
    ],
    "name:gle_x_preferred":[
        "Gabhr\u00e1n"
    ],
    "name:ita_x_preferred":[
        "Gowran"
    ],
    "name:nld_x_preferred":[
        "Gowran"
    ],
    "name:rus_x_preferred":[
        "\u0413\u0430\u0443\u0440\u0430\u043d"
    ],
    "name:swe_x_preferred":[
        "Gowran"
    ],
    "qs_pg:aaroncc":"IE",
    "qs_pg:gn_country":"IE",
    "qs_pg:gn_fcode":"PPL",
    "qs_pg:gn_pop":0,
    "qs_pg:name":"Gowran",
    "qs_pg:name_adm0":"Ireland",
    "qs_pg:name_adm1":"Kilkenny",
    "qs_pg:photos":92,
    "qs_pg:photos_1k":19,
    "qs_pg:photos_9k":1,
    "qs_pg:photos_9r":3,
    "qs_pg:photos_all":92,
    "qs_pg:photos_sr":3,
    "qs_pg:pop_sr":0,
    "qs_pg:qs_pg_placetype":"locality",
    "qs_pg:qs_pg_placetype_gp":"Town",
    "qs_pg:woe_adm0":23424803,
    "woe:adm0_id":23424803,
    "woe:name_adm0":"Ireland",
    "woe:name_adm1":"Kilkenny",
    "woe:placetype":"Town",
    "wof:name":"Gowran",
    "wof:placetype":"locality",
    "wof:population":742
},
  "geometry": {"coordinates":[-7.07333,52.62944],"type":"Point"}
}