{
  "type": "Feature",
  "properties": {
    "gn:admin1_code":"L",
    "gn:admin2_code":"31.0",
    "gn:asciiname":"Glendarragh",
    "gn:country_code":"IE",
    "gn:dem":245,
    "gn:feature_class":"P",
    "gn:feature_code":"PPLL",
    "gn:name":"Glendarragh",
    "gn:population":0,
    "gn:timezone":"Europe/Dublin",
    "iso:country":"IE",
    "wof:name":"Glendarragh",
    "wof:placetype":"locality"
},
  "geometry": {"coordinates":[-6.17361,53.09721999999999],"type":"Point"}
}