{
  "type": "Feature",
  "properties": {
    "gn:gn_country":"IE",
    "gn:gn_fcode":"PPL",
    "gn:gn_pop":0,
    "iso:country":"IE",
    "name:eng_x_preferred":[
        "Bunmahon"
    ],
    "name:eus_x_preferred":[
        "Bunmahon"
    ],
    "name:gle_x_preferred":[
        "Bun Machan"
    ],
    "name:nld_x_preferred":[
        "Bunmahon"
    ],
    "name:rus_x_preferred":[
        "\u0411\u0430\u043d\u043c\u0430\u0445\u043e\u043d"
    ],
    "qs_pg:aaroncc":"IE",
    "qs_pg:gn_country":"IE",
    "qs_pg:gn_fcode":"PPL",
    "qs_pg:gn_pop":0,
    "qs_pg:name":"Bunmahon",
    "qs_pg:name_adm0":"Ireland",
    "qs_pg:name_adm1":"Waterford",
    "qs_pg:photos":273,
    "qs_pg:photos_1k":55,
    "qs_pg:photos_9k":1,
    "qs_pg:photos_9r":4,
    "qs_pg:photos_all":273,
    "qs_pg:photos_sr":5,
    "qs_pg:pop_sr":0,
    "qs_pg:qs_pg_placetype":"locality",
    "qs_pg:qs_pg_placetype_gp":"Town",
    "qs_pg:woe_adm0":23424803,
    "woe:adm0_id":23424803,
    "woe:name_adm0":"Ireland",
    "woe:name_adm1":"Waterford",
    "woe:placetype":"Town",
    "wof:name":"Bunmahon",
    "wof:placetype":"locality"
},
  "geometry": {"coordinates":[-7.37444,52.14028],"type":"Point"}
}