{
  "type": "Feature",
  "properties": {
    "gn:admin1_code":"L",
    "gn:admin2_code":"12.0",
    "gn:asciiname":"Clonegath Cross Roads",
    "gn:country_code":"IE",
    "gn:dem":104,
    "gn:feature_class":"P",
    "gn:feature_code":"PPL",
    "gn:name":"Clonegath Cross Roads",
    "gn:population":0,
    "gn:timezone":"Europe/Dublin",
    "iso:country":"IE",
    "wof:name":"Clonegath Cross Roads",
    "wof:placetype":"locality"
},
  "geometry": {"coordinates":[-7.04333,53.12028000000001],"type":"Point"}
}