{
  "type": "Feature",
  "properties": {
    "gn:gn_country":"IE",
    "gn:gn_fcode":"PPL",
    "gn:gn_pop":0,
    "gn:population":166,
    "iso:country":"IE",
    "name:ceb_x_preferred":[
        "Kilmaine"
    ],
    "name:eus_x_preferred":[
        "Kilmaine"
    ],
    "name:gle_x_preferred":[
        "Cill Mhe\u00e1in"
    ],
    "name:kat_x_preferred":[
        "\u10d9\u10d8\u10da\u10db\u10d4\u10dc\u10d8"
    ],
    "name:rus_x_preferred":[
        "\u041a\u0438\u043b\u043c\u0435\u0439\u043d"
    ],
    "name:spa_x_preferred":[
        "Kilmaine"
    ],
    "name:swe_x_preferred":[
        "Kilmaine"
    ],
    "qs_pg:aaroncc":"IE",
    "qs_pg:gn_country":"IE",
    "qs_pg:gn_fcode":"PPL",
    "qs_pg:gn_pop":0,
    "qs_pg:name":"Kilmaine",
    "qs_pg:name_adm0":"Ireland",
    "qs_pg:name_adm1":"Mayo",
    "qs_pg:photos":1,
    "qs_pg:photos_1k":1,
    "qs_pg:photos_9k":1,
    "qs_pg:photos_9r":1,
    "qs_pg:photos_all":1,
    "qs_pg:photos_sr":1,
    "qs_pg:pop_sr":0,
    "qs_pg:qs_pg_placetype":"localadmin",
    "qs_pg:qs_pg_placetype_gp":"LocalAdmin",
    "qs_pg:woe_adm0":23424803,
    "woe:adm0_id":23424803,
    "woe:name_adm0":"Ireland",
    "woe:name_adm1":"Mayo",
    "woe:placetype":"LocalAdmin",
    "wof:name":"Kilmaine",
    "wof:placetype":"localadmin",
    "wof:population":166
},
  "geometry": {"coordinates":[-9.11667,53.58333],"type":"Point"}
}