{
  "type": "Feature",
  "properties": {
    "gn:country":"IE",
    "gn:fcode":"PPL",
    "gn:population":0,
    "iso:country":"IE",
    "name:ceb_x_preferred":[
        "Killaloe"
    ],
    "name:deu_x_preferred":[
        "Killaloe"
    ],
    "name:eng_x_preferred":[
        "Killaloe"
    ],
    "name:gle_x_preferred":[
        "Cill Dalua"
    ],
    "name:rus_x_preferred":[
        "\u041a\u0438\u043b\u043b\u0430\u043b\u043e"
    ],
    "name:swe_x_preferred":[
        "Killaloe"
    ],
    "qs_pg:aaroncc":"IE",
    "qs_pg:gn_country":"IE",
    "qs_pg:gn_fcode":"PPL",
    "qs_pg:gn_pop":0,
    "qs_pg:name":"Killaloe",
    "qs_pg:name_adm0":"Ireland",
    "qs_pg:name_adm1":"Clare",
    "qs_pg:photos":3,
    "qs_pg:photos_1k":1,
    "qs_pg:photos_9k":2,
    "qs_pg:photos_9r":5,
    "qs_pg:photos_all":543,
    "qs_pg:photos_sr":1,
    "qs_pg:pop_sr":0,
    "qs_pg:qs_pg_placetype":"localadmin",
    "qs_pg:qs_pg_placetype_gp":"LocalAdmin",
    "qs_pg:woe_adm0":23424803,
    "woe:adm0_id":23424803,
    "woe:name_adm0":"Ireland",
    "woe:name_adm1":"Clare",
    "woe:placetype":"LocalAdmin",
    "wof:name":"Killaloe",
    "wof:placetype":"localadmin",
    "wof:population":1292
},
  "geometry": {"coordinates":[-8.44361,52.80667],"type":"Point"}
}