{
  "type": "Feature",
  "properties": {
    "gn:admin1_code":"M",
    "gn:admin2_code":"03",
    "gn:asciiname":"Drehidnaraga Bridge",
    "gn:country_code":"IE",
    "gn:dem":48,
    "gn:feature_class":"P",
    "gn:feature_code":"PPL",
    "gn:name":"Drehidnaraga Bridge",
    "gn:population":0,
    "gn:timezone":"Europe/Dublin",
    "iso:country":"IE",
    "wof:name":"Drehidnaraga Bridge",
    "wof:placetype":"locality"
},
  "geometry": {"coordinates":[-9.38139,52.80611],"type":"Point"}
}