{
  "type": "Feature",
  "properties": {
    "gn:admin1_code":"U",
    "gn:admin2_code":"06",
    "gn:asciiname":"Saint Catherines",
    "gn:country_code":"IE",
    "gn:dem":59,
    "gn:feature_class":"P",
    "gn:feature_code":"PPLL",
    "gn:name":"Saint Catherines",
    "gn:population":0,
    "gn:timezone":"Europe/Dublin",
    "iso:country":"IE",
    "wof:name":"Saint Catherines",
    "wof:placetype":"locality"
},
  "geometry": {"coordinates":[-8.46278,54.62416999999999],"type":"Point"}
}