{
  "type": "Feature",
  "properties": {
    "gn:admin1_code":"M",
    "gn:admin2_code":"04",
    "gn:asciiname":"Kippagh",
    "gn:country_code":"IE",
    "gn:dem":246,
    "gn:feature_class":"P",
    "gn:feature_code":"PPL",
    "gn:name":"Kippagh",
    "gn:population":0,
    "gn:timezone":"Europe/Dublin",
    "iso:country":"IE",
    "wof:name":"Kippagh",
    "wof:placetype":"locality"
},
  "geometry": {"coordinates":[-9.13417,52.04139],"type":"Point"}
}