{
  "type": "Feature",
  "properties": {
    "gn:admin1_code":"C",
    "gn:admin2_code":"20.0",
    "gn:asciiname":"Doonaroya",
    "gn:country_code":"IE",
    "gn:dem":120,
    "gn:feature_class":"P",
    "gn:feature_code":"PPL",
    "gn:name":"Doonaroya",
    "gn:population":0,
    "gn:timezone":"Europe/Dublin",
    "iso:country":"IE",
    "wof:name":"Doonaroya",
    "wof:placetype":"locality"
},
  "geometry": {"coordinates":[-9.40356,54.01377],"type":"Point"}
}