{
  "type": "Feature",
  "properties": {
    "gn:admin1_code":"C",
    "gn:admin2_code":"25.0",
    "gn:asciiname":"Glen",
    "gn:country_code":"IE",
    "gn:dem":239,
    "gn:feature_class":"P",
    "gn:feature_code":"PPLL",
    "gn:name":"Glen",
    "gn:population":0,
    "gn:timezone":"Europe/Dublin",
    "iso:country":"IE",
    "name:afr_x_preferred":[
        "Glen"
    ],
    "name:eus_x_preferred":[
        "Glen"
    ],
    "name:fra_x_preferred":[
        "Glen"
    ],
    "name:ita_x_preferred":[
        "Glen"
    ],
    "name:mkd_x_preferred":[
        "\u0413\u043b\u0435\u043d"
    ],
    "name:nld_x_preferred":[
        "Glen"
    ],
    "name:rus_x_preferred":[
        "\u0420\u0430\u0441\u043f\u0430\u0434\u043e\u043a"
    ],
    "name:sco_x_preferred":[
        "Glen"
    ],
    "wof:name":"Glen",
    "wof:placetype":"locality"
},
  "geometry": {"coordinates":[-8.17667,54.10389],"type":"Point"}
}