{
  "type": "Feature",
  "properties": {
    "gn:admin1_code":"L",
    "gn:admin2_code":"18",
    "gn:asciiname":"Esker South",
    "gn:country_code":"IE",
    "gn:dem":87,
    "gn:feature_class":"P",
    "gn:feature_code":"PPL",
    "gn:name":"Esker South",
    "gn:population":0,
    "gn:timezone":"Europe/Dublin",
    "iso:country":"IE",
    "name:und_x_variant":[
        "Esker",
        "Esker South"
    ],
    "wof:name":"Esker South",
    "wof:placetype":"locality"
},
  "geometry": {"coordinates":[-7.71667,53.78333000000001],"type":"Point"}
}