{
  "type": "Feature",
  "properties": {
    "gn:admin1_code":"C",
    "gn:admin2_code":"24.0",
    "gn:asciiname":"Mullaun",
    "gn:country_code":"IE",
    "gn:dem":58,
    "gn:feature_class":"P",
    "gn:feature_code":"PPLL",
    "gn:name":"Mullaun",
    "gn:population":0,
    "gn:timezone":"Europe/Dublin",
    "iso:country":"IE",
    "wof:name":"Mullaun",
    "wof:placetype":"locality"
},
  "geometry": {"coordinates":[-8.09444,54.06306],"type":"Point"}
}