{
  "type": "Feature",
  "properties": {
    "gn:admin1_code":"C",
    "gn:admin2_code":"25.0",
    "gn:asciiname":"Ballynamona",
    "gn:country_code":"IE",
    "gn:dem":66,
    "gn:feature_class":"P",
    "gn:feature_code":"PPLL",
    "gn:name":"Ballynamona",
    "gn:population":0,
    "gn:timezone":"Europe/Dublin",
    "iso:country":"IE",
    "wof:name":"Ballynamona",
    "wof:placetype":"locality"
},
  "geometry": {"coordinates":[-9.02694,54.20972],"type":"Point"}
}