{
  "type": "Feature",
  "properties": {
    "gn:country":"IE",
    "gn:fcode":"PPL",
    "gn:population":0,
    "iso:country":"IE",
    "name:bre_x_preferred":[
        "Ard Fhearta"
    ],
    "name:bul_x_preferred":[
        "\u0410\u0440\u0434\u0444\u0435\u0440\u0442"
    ],
    "name:ceb_x_preferred":[
        "Ardfert"
    ],
    "name:eng_x_preferred":[
        "Ardfert"
    ],
    "name:eus_x_preferred":[
        "Ardfert"
    ],
    "name:gle_x_preferred":[
        "Ard Fhearta"
    ],
    "name:jpn_x_preferred":[
        "\u30a2\u30fc\u30c9\u30d5\u30a1\u30fc\u30c8"
    ],
    "name:lit_x_preferred":[
        "Ardfertas"
    ],
    "name:nld_x_preferred":[
        "Ardfert"
    ],
    "name:por_x_preferred":[
        "Ardfert"
    ],
    "name:rus_x_preferred":[
        "\u0410\u0440\u0434\u0444\u0435\u0440\u0442"
    ],
    "name:spa_x_preferred":[
        "Ardfert"
    ],
    "name:swe_x_preferred":[
        "Ardfert"
    ],
    "qs_pg:aaroncc":"IE",
    "qs_pg:gn_country":"IE",
    "qs_pg:gn_fcode":"PPL",
    "qs_pg:gn_pop":0,
    "qs_pg:name":"Ardfert",
    "qs_pg:name_adm0":"Ireland",
    "qs_pg:name_adm1":"Kerry",
    "qs_pg:photos":335,
    "qs_pg:photos_1k":68,
    "qs_pg:photos_9k":1,
    "qs_pg:photos_9r":5,
    "qs_pg:photos_all":335,
    "qs_pg:photos_sr":5,
    "qs_pg:pop_sr":0,
    "qs_pg:qs_pg_placetype":"locality",
    "qs_pg:qs_pg_placetype_gp":"Town",
    "qs_pg:woe_adm0":23424803,
    "woe:adm0_id":23424803,
    "woe:name_adm0":"Ireland",
    "woe:name_adm1":"Kerry",
    "woe:placetype":"Town",
    "wof:name":"Ardfert",
    "wof:placetype":"locality",
    "wof:population":800
},
  "geometry": {"coordinates":[-9.78333,52.33333],"type":"Point"}
}