{
  "type": "Feature",
  "properties": {
    "gn:admin1_code":"C",
    "gn:admin2_code":"10.0",
    "gn:asciiname":"Cloonkeen",
    "gn:country_code":"IE",
    "gn:dem":82,
    "gn:feature_class":"P",
    "gn:feature_code":"PPL",
    "gn:name":"Cloonkeen",
    "gn:population":0,
    "gn:timezone":"Europe/Dublin",
    "iso:country":"IE",
    "wof:name":"Cloonkeen",
    "wof:placetype":"locality"
},
  "geometry": {"coordinates":[-8.34167,53.27028000000001],"type":"Point"}
}