{
  "type": "Feature",
  "properties": {
    "gn:admin1_code":"L",
    "gn:admin2_code":"21.0",
    "gn:asciiname":"Castletown",
    "gn:country_code":"IE",
    "gn:dem":66,
    "gn:feature_class":"P",
    "gn:feature_code":"PPL",
    "gn:name":"Castletown",
    "gn:population":0,
    "gn:timezone":"Europe/Dublin",
    "iso:country":"IE",
    "name:ceb_x_preferred":[
        "Castletown"
    ],
    "name:cym_x_preferred":[
        "Castletown"
    ],
    "name:fra_x_preferred":[
        "Castletown"
    ],
    "name:ita_x_preferred":[
        "Castletown"
    ],
    "name:nld_x_preferred":[
        "Castletown"
    ],
    "name:nor_x_preferred":[
        "Castletown"
    ],
    "name:pol_x_preferred":[
        "Castletown"
    ],
    "name:rus_x_preferred":[
        "\u041a\u0430\u0441\u043b\u0442\u0430\u0443\u043d"
    ],
    "name:slk_x_preferred":[
        "Castletown"
    ],
    "name:spa_x_preferred":[
        "Castletown"
    ],
    "name:swe_x_preferred":[
        "Castletown"
    ],
    "wof:name":"Castletown",
    "wof:placetype":"locality"
},
  "geometry": {"coordinates":[-6.8303,53.50616],"type":"Point"}
}