{
  "type": "Feature",
  "properties": {
    "gn:admin1_code":"M",
    "gn:admin2_code":"44",
    "gn:asciiname":"Furraleigh",
    "gn:country_code":"IE",
    "gn:dem":90,
    "gn:feature_class":"P",
    "gn:feature_code":"PPL",
    "gn:name":"Furraleigh",
    "gn:population":0,
    "gn:timezone":"Europe/Dublin",
    "iso:country":"IE",
    "wof:name":"Furraleigh",
    "wof:placetype":"locality"
},
  "geometry": {"coordinates":[-7.49861,52.20583],"type":"Point"}
}