{
  "type": "Feature",
  "properties": {
    "gn:admin1_code":"L",
    "gn:admin2_code":"30",
    "gn:asciiname":"Boleany Cross Roads",
    "gn:country_code":"IE",
    "gn:dem":41,
    "gn:feature_class":"P",
    "gn:feature_code":"PPL",
    "gn:name":"Boleany Cross Roads",
    "gn:population":0,
    "gn:timezone":"Europe/Dublin",
    "iso:country":"IE",
    "wof:name":"Boleany Cross Roads",
    "wof:placetype":"locality"
},
  "geometry": {"coordinates":[-6.26194,52.6375],"type":"Point"}
}