{
  "type": "Feature",
  "properties": {
    "gn:admin1_code":"L",
    "gn:admin2_code":"21.0",
    "gn:asciiname":"Clonalvy",
    "gn:country_code":"IE",
    "gn:dem":114,
    "gn:feature_class":"P",
    "gn:feature_code":"PPL",
    "gn:name":"Clonalvy",
    "gn:population":0,
    "gn:timezone":"Europe/Dublin",
    "iso:country":"IE",
    "name:gle_x_preferred":[
        "Cluain Ailbhe"
    ],
    "wof:name":"Clonalvy",
    "wof:placetype":"locality"
},
  "geometry": {"coordinates":[-6.33667,53.58971999999999],"type":"Point"}
}