{
  "type": "Feature",
  "properties": {
    "gn:admin1_code":"M",
    "gn:admin2_code":"11",
    "gn:asciiname":"Cappagh",
    "gn:country_code":"IE",
    "gn:dem":119,
    "gn:feature_class":"P",
    "gn:feature_code":"PPL",
    "gn:name":"Cappagh",
    "gn:population":0,
    "gn:timezone":"Europe/Dublin",
    "iso:country":"IE",
    "name:eng_x_preferred":[
        "Cappagh"
    ],
    "name:gle_x_preferred":[
        "An Cheapaigh"
    ],
    "wof:name":"Cappagh",
    "wof:placetype":"locality"
},
  "geometry": {"coordinates":[-9.605,52.33583],"type":"Point"}
}