{
  "type": "Feature",
  "properties": {
    "iso:country":"IE",
    "name:ceb_x_preferred":[
        "Ballintra"
    ],
    "name:eus_x_preferred":[
        "Ballintra"
    ],
    "name:nld_x_preferred":[
        "Ballintra"
    ],
    "name:rus_x_preferred":[
        "\u0411\u0430\u043b\u043b\u0438\u043d\u0442\u0440\u0430"
    ],
    "name:spa_x_preferred":[
        "Ballintra"
    ],
    "name:swe_x_preferred":[
        "Ballintra"
    ],
    "name:ukr_x_preferred":[
        "\u0411\u0430\u043b\u043b\u0456\u043d\u0442\u0440\u0430"
    ],
    "qs_pg:aaroncc":"IE",
    "qs_pg:name":"Ballintra",
    "qs_pg:name_adm0":"Ireland",
    "qs_pg:name_adm1":"Donegal",
    "qs_pg:photos":482,
    "qs_pg:photos_1k":98,
    "qs_pg:photos_9k":6,
    "qs_pg:photos_9r":7,
    "qs_pg:photos_all":1417,
    "qs_pg:photos_sr":7,
    "qs_pg:pop_sr":0,
    "qs_pg:qs_pg_placetype":"localadmin",
    "qs_pg:qs_pg_placetype_gp":"LocalAdmin",
    "qs_pg:woe_adm0":23424803,
    "woe:adm0_id":23424803,
    "woe:name_adm0":"Ireland",
    "woe:name_adm1":"Donegal",
    "woe:placetype":"LocalAdmin",
    "wof:name":"Ballintra",
    "wof:placetype":"localadmin"
},
  "geometry": {"coordinates":[-8.151082,54.563801],"type":"Point"}
}