{
  "type": "Feature",
  "properties": {
    "gn:admin1_code":"M",
    "gn:admin2_code":"44",
    "gn:asciiname":"Ballynoe",
    "gn:country_code":"IE",
    "gn:dem":47,
    "gn:feature_class":"P",
    "gn:feature_code":"PPL",
    "gn:name":"Ballynoe",
    "gn:population":0,
    "gn:timezone":"Europe/Dublin",
    "iso:country":"IE",
    "wof:name":"Ballynoe",
    "wof:placetype":"locality"
},
  "geometry": {"coordinates":[-8.08333,52.15],"type":"Point"}
}