{
  "type": "Feature",
  "properties": {
    "gn:admin1_code":"C",
    "gn:admin2_code":"14.0",
    "gn:asciiname":"Oghill Cross Roads",
    "gn:country_code":"IE",
    "gn:dem":58,
    "gn:feature_class":"P",
    "gn:feature_code":"PPLL",
    "gn:name":"Oghill Cross Roads",
    "gn:population":0,
    "gn:timezone":"Europe/Dublin",
    "iso:country":"IE",
    "wof:name":"Oghill Cross Roads",
    "wof:placetype":"locality"
},
  "geometry": {"coordinates":[-7.89444,53.96583],"type":"Point"}
}