{
  "type": "Feature",
  "properties": {
    "gn:admin1_code":"U",
    "gn:admin2_code":"06",
    "gn:asciiname":"Altadoo",
    "gn:country_code":"IE",
    "gn:dem":94,
    "gn:feature_class":"P",
    "gn:feature_code":"PPLL",
    "gn:name":"Altadoo",
    "gn:population":0,
    "gn:timezone":"Europe/Dublin",
    "iso:country":"IE",
    "wof:name":"Altadoo",
    "wof:placetype":"locality"
},
  "geometry": {"coordinates":[-8.17167,54.68222],"type":"Point"}
}