{
  "type": "Feature",
  "properties": {
    "gn:gn_country":"IE",
    "gn:gn_fcode":"PPL",
    "gn:gn_pop":0,
    "iso:country":"IE",
    "name:baq_x_preferred":[
        "Ardgroom"
    ],
    "name:bul_x_preferred":[
        "\u0410\u0440\u0434\u0433\u0440\u043e\u043c"
    ],
    "name:cat_x_preferred":[
        "Ardgroom"
    ],
    "name:dut_x_preferred":[
        "Ardgroom"
    ],
    "name:eng_x_preferred":[
        "Ardgroom"
    ],
    "name:fre_x_preferred":[
        "Ardgroom"
    ],
    "name:ger_x_preferred":[
        "Ardgroom"
    ],
    "name:gle_x_preferred":[
        "Dh\u00e1 Dhroim"
    ],
    "name:por_x_preferred":[
        "Ardgroom"
    ],
    "name:rus_x_preferred":[
        "\u0410\u0440\u0434\u0433\u0440\u0443\u043c"
    ],
    "name:swe_x_preferred":[
        "Ardgroom"
    ],
    "qs_pg:aaroncc":"IE",
    "qs_pg:gn_country":"IE",
    "qs_pg:gn_fcode":"PPL",
    "qs_pg:gn_pop":0,
    "qs_pg:name":"Ardgroom",
    "qs_pg:name_adm0":"Ireland",
    "qs_pg:name_adm1":"Cork",
    "qs_pg:photos":141,
    "qs_pg:photos_1k":29,
    "qs_pg:photos_9k":1,
    "qs_pg:photos_9r":3,
    "qs_pg:photos_all":141,
    "qs_pg:photos_sr":3,
    "qs_pg:pop_sr":0,
    "qs_pg:qs_pg_placetype":"locality",
    "qs_pg:qs_pg_placetype_gp":"Town",
    "qs_pg:woe_adm0":23424803,
    "woe:adm0_id":23424803,
    "woe:name_adm0":"Ireland",
    "woe:name_adm1":"Cork",
    "woe:placetype":"Town",
    "wof:name":"Ardgroom",
    "wof:placetype":"locality"
},
  "geometry": {"coordinates":[-9.89556,51.74056],"type":"Point"}
}