{
  "type": "Feature",
  "properties": {
    "gn:admin1_code":"L",
    "gn:admin2_code":"21.0",
    "gn:asciiname":"Balrathboyne Glebe",
    "gn:country_code":"IE",
    "gn:dem":74,
    "gn:feature_class":"P",
    "gn:feature_code":"PPL",
    "gn:name":"Balrathboyne Glebe",
    "gn:population":0,
    "gn:timezone":"Europe/Dublin",
    "iso:country":"IE",
    "wof:name":"Balrathboyne Glebe",
    "wof:placetype":"locality"
},
  "geometry": {"coordinates":[-6.8707,53.67395],"type":"Point"}
}