{
  "type": "Feature",
  "properties": {
    "gn:admin1_code":"M",
    "gn:admin2_code":"44",
    "gn:asciiname":"Lisnakill Cross",
    "gn:country_code":"IE",
    "gn:dem":98,
    "gn:feature_class":"P",
    "gn:feature_code":"PPL",
    "gn:name":"Lisnakill Cross",
    "gn:population":0,
    "gn:timezone":"Europe/Dublin",
    "iso:country":"IE",
    "wof:name":"Lisnakill Cross",
    "wof:placetype":"locality"
},
  "geometry": {"coordinates":[-7.1975,52.20833],"type":"Point"}
}