{
  "type": "Feature",
  "properties": {
    "gn:admin1_code":"L",
    "gn:admin2_code":"31.0",
    "gn:asciiname":"Crehelp",
    "gn:country_code":"IE",
    "gn:dem":205,
    "gn:feature_class":"P",
    "gn:feature_code":"PPL",
    "gn:name":"Crehelp",
    "gn:population":0,
    "gn:timezone":"Europe/Dublin",
    "iso:country":"IE",
    "wof:name":"Crehelp",
    "wof:placetype":"locality"
},
  "geometry": {"coordinates":[-6.65139,53.06556],"type":"Point"}
}