{
  "type": "Feature",
  "properties": {
    "gn:admin1_code":"C",
    "gn:admin2_code":"10.0",
    "gn:asciiname":"Derraheeda",
    "gn:country_code":"IE",
    "gn:dem":23,
    "gn:feature_class":"P",
    "gn:feature_code":"PPL",
    "gn:name":"Derraheeda",
    "gn:population":0,
    "gn:timezone":"Europe/Dublin",
    "iso:country":"IE",
    "wof:name":"Derraheeda",
    "wof:placetype":"locality"
},
  "geometry": {"coordinates":[-9.69505,53.59388000000001],"type":"Point"}
}