{
  "type": "Feature",
  "properties": {
    "gn:admin1_code":"C",
    "gn:admin2_code":"24",
    "gn:asciiname":"Moore",
    "gn:country_code":"IE",
    "gn:dem":39,
    "gn:feature_class":"P",
    "gn:feature_code":"PPL",
    "gn:name":"Moore",
    "gn:population":0,
    "gn:timezone":"Europe/Dublin",
    "iso:country":"IE",
    "wof:name":"Moore",
    "wof:placetype":"locality"
},
  "geometry": {"coordinates":[-8.06611,53.33194],"type":"Point"}
}