{
  "type": "Feature",
  "properties": {
    "gn:admin1_code":"C",
    "gn:admin2_code":"24",
    "gn:asciiname":"Moore",
    "gn:country_code":"IE",
    "gn:dem":39,
    "gn:feature_class":"P",
    "gn:feature_code":"PPL",
    "gn:name":"Moore",
    "gn:population":0,
    "gn:timezone":"Europe/Dublin",
    "iso:country":"IE",
    "name:cat_x_preferred":[
        "Moore"
    ],
    "name:ceb_x_preferred":[
        "Moore"
    ],
    "name:ces_x_preferred":[
        "Moore"
    ],
    "name:deu_x_preferred":[
        "Moore"
    ],
    "name:epo_x_preferred":[
        "Moore"
    ],
    "name:fas_x_preferred":[
        "\u0645\u0648\u0631"
    ],
    "name:fin_x_preferred":[
        "Moore"
    ],
    "name:fra_x_preferred":[
        "Moore"
    ],
    "name:ita_x_preferred":[
        "Moore"
    ],
    "name:jpn_x_preferred":[
        "\u30e0\u30fc\u30a2"
    ],
    "name:kat_x_preferred":[
        "\u10db\u10e3\u10e0\u10d8"
    ],
    "name:lav_x_preferred":[
        "M\u016brs"
    ],
    "name:lit_x_preferred":[
        "Moore"
    ],
    "name:nld_x_preferred":[
        "Moore"
    ],
    "name:pol_x_preferred":[
        "Moore"
    ],
    "name:por_x_preferred":[
        "Moore"
    ],
    "name:ron_x_preferred":[
        "Moore"
    ],
    "name:slv_x_preferred":[
        "Moore"
    ],
    "name:spa_x_preferred":[
        "Moore"
    ],
    "name:swe_x_preferred":[
        "Moore"
    ],
    "name:tur_x_preferred":[
        "Moore"
    ],
    "name:vie_x_preferred":[
        "Moore"
    ],
    "name:vol_x_preferred":[
        "Moore"
    ],
    "wof:name":"Moore",
    "wof:placetype":"locality"
},
  "geometry": {"coordinates":[-8.06611,53.33194],"type":"Point"}
}