{
  "type": "Feature",
  "properties": {
    "gn:admin1_code":"C",
    "gn:admin2_code":"20.0",
    "gn:asciiname":"Lugganashiere",
    "gn:country_code":"IE",
    "gn:dem":31,
    "gn:feature_class":"P",
    "gn:feature_code":"PPL",
    "gn:name":"Lugganashiere",
    "gn:population":0,
    "gn:timezone":"Europe/Dublin",
    "iso:country":"IE",
    "wof:name":"Lugganashiere",
    "wof:placetype":"locality"
},
  "geometry": {"coordinates":[-9.19386,53.87198000000001],"type":"Point"}
}