{
  "type": "Feature",
  "properties": {
    "gn:admin1_code":"M",
    "gn:admin2_code":"11",
    "gn:asciiname":"Flemby",
    "gn:country_code":"IE",
    "gn:dem":37,
    "gn:feature_class":"P",
    "gn:feature_code":"PPL",
    "gn:name":"Flemby",
    "gn:population":0,
    "gn:timezone":"Europe/Dublin",
    "iso:country":"IE",
    "wof:name":"Flemby",
    "wof:placetype":"locality"
},
  "geometry": {"coordinates":[-9.59944,52.22944],"type":"Point"}
}