{
  "type": "Feature",
  "properties": {
    "iso:country":"IE",
    "name:eng_x_preferred":[
        "Blackrock"
    ],
    "wof:name":"Blackrock",
    "wof:placetype":"neighbourhood"
},
  "geometry": {"coordinates":[-8.416936,51.897037],"type":"Point"}
}