{
  "type": "Feature",
  "properties": {
    "gn:admin1_code":"M",
    "gn:admin2_code":"26",
    "gn:asciiname":"Curreeny",
    "gn:country_code":"IE",
    "gn:dem":317,
    "gn:feature_class":"P",
    "gn:feature_code":"PPL",
    "gn:name":"Curreeny",
    "gn:population":0,
    "gn:timezone":"Europe/Dublin",
    "iso:country":"IE",
    "name:gle_x_preferred":[
        "Na Coirr\u00edn\u00ed"
    ],
    "wof:name":"Curreeny",
    "wof:placetype":"locality"
},
  "geometry": {"coordinates":[-8.15028,52.72778],"type":"Point"}
}