{
  "type": "Feature",
  "properties": {
    "gn:admin1_code":"L",
    "gn:admin2_code":"15",
    "gn:asciiname":"Cannonswood Cross Roads",
    "gn:country_code":"IE",
    "gn:dem":83,
    "gn:feature_class":"P",
    "gn:feature_code":"PPL",
    "gn:name":"Cannonswood Cross Roads",
    "gn:population":0,
    "gn:timezone":"Europe/Dublin",
    "iso:country":"IE",
    "wof:name":"Cannonswood Cross Roads",
    "wof:placetype":"locality"
},
  "geometry": {"coordinates":[-7.49694,52.84083],"type":"Point"}
}