{
  "type": "Feature",
  "properties": {
    "gn:admin1_code":"L",
    "gn:admin2_code":"29.0",
    "gn:asciiname":"Cartron",
    "gn:country_code":"IE",
    "gn:dem":82,
    "gn:feature_class":"P",
    "gn:feature_code":"PPLL",
    "gn:name":"Cartron",
    "gn:population":0,
    "gn:timezone":"Europe/Dublin",
    "iso:country":"IE",
    "wof:name":"Cartron",
    "wof:placetype":"locality"
},
  "geometry": {"coordinates":[-7.40912,53.49647],"type":"Point"}
}