{
  "type": "Feature",
  "properties": {
    "gn:admin1_code":"U",
    "gn:admin2_code":"06",
    "gn:asciiname":"Kinnakillew",
    "gn:country_code":"IE",
    "gn:dem":122,
    "gn:feature_class":"P",
    "gn:feature_code":"PPLL",
    "gn:name":"Kinnakillew",
    "gn:population":0,
    "gn:timezone":"Europe/Dublin",
    "iso:country":"IE",
    "name:eng_x_preferred":[
        "Kinnakillew"
    ],
    "name:gle_x_preferred":[
        "Cionn na Coilleadh"
    ],
    "wof:name":"Kinnakillew",
    "wof:placetype":"locality"
},
  "geometry": {"coordinates":[-8.70111,54.71778000000001],"type":"Point"}
}