{
  "type": "Feature",
  "properties": {
    "gn:admin1_code":"L",
    "gn:admin2_code":"15",
    "gn:asciiname":"Ballaghmore",
    "gn:country_code":"IE",
    "gn:dem":109,
    "gn:feature_class":"P",
    "gn:feature_code":"PPL",
    "gn:name":"Ballaghmore",
    "gn:population":0,
    "gn:timezone":"Europe/Dublin",
    "iso:country":"IE",
    "wof:name":"Ballaghmore",
    "wof:placetype":"locality"
},
  "geometry": {"coordinates":[-7.72639,52.95916999999999],"type":"Point"}
}