{
  "type": "Feature",
  "properties": {
    "gn:admin1_code":"C",
    "gn:admin2_code":"10.0",
    "gn:asciiname":"Letter More",
    "gn:country_code":"IE",
    "gn:dem":64,
    "gn:feature_class":"P",
    "gn:feature_code":"PPLL",
    "gn:name":"Letter More",
    "gn:population":0,
    "gn:timezone":"Europe/Dublin",
    "iso:country":"IE",
    "name:eng_x_preferred":[
        "Letter More"
    ],
    "name:gle_x_preferred":[
        "Leitir M\u00f3ir"
    ],
    "wof:name":"Letter More",
    "wof:placetype":"locality"
},
  "geometry": {"coordinates":[-10.01583,53.57889],"type":"Point"}
}