{
  "type": "Feature",
  "properties": {
    "gn:admin1_code":"C",
    "gn:admin2_code":"25.0",
    "gn:asciiname":"Cloonkeevy",
    "gn:country_code":"IE",
    "gn:dem":64,
    "gn:feature_class":"P",
    "gn:feature_code":"PPL",
    "gn:name":"Cloonkeevy",
    "gn:population":0,
    "gn:timezone":"Europe/Dublin",
    "iso:country":"IE",
    "wof:name":"Cloonkeevy",
    "wof:placetype":"locality"
},
  "geometry": {"coordinates":[-8.56417,54.08361],"type":"Point"}
}