{
  "type": "Feature",
  "properties": {
    "gn:admin1_code":"U",
    "gn:admin2_code":"06",
    "gn:asciiname":"Cronkeeran",
    "gn:country_code":"IE",
    "gn:dem":125,
    "gn:feature_class":"P",
    "gn:feature_code":"PPLL",
    "gn:name":"Cronkeeran",
    "gn:population":0,
    "gn:timezone":"Europe/Dublin",
    "iso:country":"IE",
    "name:eng_x_preferred":[
        "Cronkeeran"
    ],
    "name:gle_x_preferred":[
        "Cr\u00f3 an Chaorthainn"
    ],
    "wof:name":"Cronkeeran",
    "wof:placetype":"locality"
},
  "geometry": {"coordinates":[-8.37667,54.74722],"type":"Point"}
}