{
  "type": "Feature",
  "properties": {
    "gn:admin1_code":"C",
    "gn:admin2_code":"14",
    "gn:asciiname":"Drumbrick",
    "gn:country_code":"IE",
    "gn:dem":56,
    "gn:feature_class":"P",
    "gn:feature_code":"PPL",
    "gn:name":"Drumbrick",
    "gn:population":0,
    "gn:timezone":"Europe/Dublin",
    "iso:country":"IE",
    "wof:name":"Drumbrick",
    "wof:placetype":"locality"
},
  "geometry": {"coordinates":[-7.64944,54.01221999999999],"type":"Point"}
}