{
  "type": "Feature",
  "properties": {
    "gn:admin1_code":"L",
    "gn:admin2_code":"12.0",
    "gn:asciiname":"Obelisks",
    "gn:country_code":"IE",
    "gn:dem":86,
    "gn:feature_class":"P",
    "gn:feature_code":"PPL",
    "gn:name":"Obelisks",
    "gn:population":0,
    "gn:timezone":"Europe/Dublin",
    "iso:country":"IE",
    "wof:name":"Obelisks",
    "wof:placetype":"locality"
},
  "geometry": {"coordinates":[-6.85167,52.96471999999999],"type":"Point"}
}