{
  "type": "Feature",
  "properties": {
    "gn:gn_country":"IE",
    "iso:country":"IE",
    "qs_pg:aaroncc":"IE",
    "qs_pg:gn_country":"IE",
    "qs_pg:name":"Cromane Upper",
    "qs_pg:name_adm0":"Ireland",
    "qs_pg:name_adm1":"Kerry",
    "qs_pg:photos":183,
    "qs_pg:photos_1k":37,
    "qs_pg:photos_9k":1,
    "qs_pg:photos_9r":4,
    "qs_pg:photos_all":183,
    "qs_pg:photos_sr":4,
    "qs_pg:pop_sr":0,
    "qs_pg:qs_pg_placetype":"locality",
    "qs_pg:qs_pg_placetype_gp":"Town",
    "qs_pg:woe_adm0":23424803,
    "woe:adm0_id":23424803,
    "woe:name_adm0":"Ireland",
    "woe:name_adm1":"Kerry",
    "woe:placetype":"Town",
    "wof:name":"Cromane Upper",
    "wof:placetype":"locality"
},
  "geometry": {"coordinates":[-9.925889,52.115466],"type":"Point"}
}