{
  "type": "Feature",
  "properties": {
    "iso:country":"IE",
    "name:eng_x_preferred":[
        "Bluebell"
    ],
    "wof:name":"Bluebell",
    "wof:placetype":"neighbourhood"
},
  "geometry": {"coordinates":[-6.343907,53.328598],"type":"Point"}
}