{
  "type": "Feature",
  "properties": {
    "gn:admin1_code":"C",
    "gn:admin2_code":"14.0",
    "gn:asciiname":"Castlecarra",
    "gn:country_code":"IE",
    "gn:dem":57,
    "gn:feature_class":"P",
    "gn:feature_code":"PPLL",
    "gn:name":"Castlecarra",
    "gn:population":0,
    "gn:timezone":"Europe/Dublin",
    "iso:country":"IE",
    "wof:name":"Castlecarra",
    "wof:placetype":"locality"
},
  "geometry": {"coordinates":[-8.06056,53.95417],"type":"Point"}
}