{
  "type": "Feature",
  "properties": {
    "gn:admin1_code":"M",
    "gn:admin2_code":"04",
    "gn:asciiname":"Cummernamart Cross Roads",
    "gn:country_code":"IE",
    "gn:dem":191,
    "gn:feature_class":"P",
    "gn:feature_code":"PPLL",
    "gn:name":"Cummernamart Cross Roads",
    "gn:population":0,
    "gn:timezone":"Europe/Dublin",
    "iso:country":"IE",
    "wof:name":"Cummernamart Cross Roads",
    "wof:placetype":"locality"
},
  "geometry": {"coordinates":[-9.13889,51.79056],"type":"Point"}
}