{
  "type": "Feature",
  "properties": {
    "gn:admin1_code":"L",
    "gn:admin2_code":"12.0",
    "gn:asciiname":"Grangemore",
    "gn:country_code":"IE",
    "gn:dem":123,
    "gn:feature_class":"P",
    "gn:feature_code":"PPL",
    "gn:name":"Grangemore",
    "gn:population":215,
    "gn:timezone":"Europe/Dublin",
    "iso:country":"IE",
    "wof:name":"Grangemore",
    "wof:placetype":"locality",
    "wof:population":215
},
  "geometry": {"coordinates":[-6.69278,53.11974],"type":"Point"}
}