{
  "type": "Feature",
  "properties": {
    "gn:admin1_code":"U",
    "gn:admin2_code":"22.0",
    "gn:asciiname":"Mullaloughan",
    "gn:country_code":"IE",
    "gn:dem":49,
    "gn:feature_class":"P",
    "gn:feature_code":"PPLL",
    "gn:name":"Mullaloughan",
    "gn:population":0,
    "gn:timezone":"Europe/Dublin",
    "iso:country":"IE",
    "wof:name":"Mullaloughan",
    "wof:placetype":"locality"
},
  "geometry": {"coordinates":[-6.93472,54.28917],"type":"Point"}
}