{
  "type": "Feature",
  "properties": {
    "gn:admin1_code":"L",
    "gn:admin2_code":"30",
    "gn:asciiname":"Oldcourt",
    "gn:country_code":"IE",
    "gn:dem":55,
    "gn:feature_class":"P",
    "gn:feature_code":"PPL",
    "gn:name":"Oldcourt",
    "gn:population":0,
    "gn:timezone":"Europe/Dublin",
    "iso:country":"IE",
    "wof:name":"Oldcourt",
    "wof:placetype":"locality"
},
  "geometry": {"coordinates":[-6.97528,52.34583],"type":"Point"}
}