{
  "type": "Feature",
  "properties": {
    "gn:admin1_code":"M",
    "gn:admin2_code":"4.0",
    "gn:asciiname":"Sanavalley",
    "gn:country_code":"IE",
    "gn:dem":9,
    "gn:feature_class":"P",
    "gn:feature_code":"PPL",
    "gn:name":"Sanavalley",
    "gn:population":0,
    "gn:timezone":"Europe/Dublin",
    "iso:country":"IE",
    "wof:name":"Sanavalley",
    "wof:placetype":"locality"
},
  "geometry": {"coordinates":[-9.70882,51.4805],"type":"Point"}
}