{
  "type": "Feature",
  "properties": {
    "gn:admin1_code":"L",
    "gn:admin2_code":"12.0",
    "gn:asciiname":"Littletown",
    "gn:country_code":"IE",
    "gn:dem":87,
    "gn:feature_class":"P",
    "gn:feature_code":"PPL",
    "gn:name":"Littletown",
    "gn:population":0,
    "gn:timezone":"Europe/Dublin",
    "iso:country":"IE",
    "name:deu_x_preferred":[
        "Littletown"
    ],
    "name:pol_x_preferred":[
        "Littletown"
    ],
    "name:srp_x_preferred":[
        "\u041b\u0438\u0442\u043b\u0442\u0430\u0443\u043d"
    ],
    "wof:name":"Littletown",
    "wof:placetype":"locality"
},
  "geometry": {"coordinates":[-6.84833,53.27],"type":"Point"}
}