{
  "type": "Feature",
  "properties": {
    "gn:admin1_code":"U",
    "gn:admin2_code":"06",
    "gn:asciiname":"Maas Upper",
    "gn:country_code":"IE",
    "gn:dem":24,
    "gn:feature_class":"P",
    "gn:feature_code":"PPL",
    "gn:name":"Maas Upper",
    "gn:population":0,
    "gn:timezone":"Europe/Dublin",
    "iso:country":"IE",
    "wof:name":"Maas Upper",
    "wof:placetype":"locality"
},
  "geometry": {"coordinates":[-8.35,54.83333],"type":"Point"}
}