{
  "type": "Feature",
  "properties": {
    "gn:admin1_code":"M",
    "gn:admin2_code":"3.0",
    "gn:asciiname":"Garrauncam Bridge",
    "gn:country_code":"IE",
    "gn:dem":41,
    "gn:feature_class":"P",
    "gn:feature_code":"PPL",
    "gn:name":"Garrauncam Bridge",
    "gn:population":0,
    "gn:timezone":"Europe/Dublin",
    "iso:country":"IE",
    "wof:name":"Garrauncam Bridge",
    "wof:placetype":"locality"
},
  "geometry": {"coordinates":[-8.69667,52.89972],"type":"Point"}
}