{
  "type": "Feature",
  "properties": {
    "gn:admin1_code":"L",
    "gn:admin2_code":"30",
    "gn:asciiname":"Turkyle",
    "gn:country_code":"IE",
    "gn:dem":58,
    "gn:feature_class":"P",
    "gn:feature_code":"PPL",
    "gn:name":"Turkyle",
    "gn:population":0,
    "gn:timezone":"Europe/Dublin",
    "iso:country":"IE",
    "wof:name":"Turkyle",
    "wof:placetype":"locality"
},
  "geometry": {"coordinates":[-6.44611,52.42528],"type":"Point"}
}