{
  "type": "Feature",
  "properties": {
    "gn:admin1_code":"M",
    "gn:admin2_code":"04",
    "gn:asciiname":"Fergus Cross Roads",
    "gn:country_code":"IE",
    "gn:dem":81,
    "gn:feature_class":"P",
    "gn:feature_code":"PPLL",
    "gn:name":"Fergus Cross Roads",
    "gn:population":0,
    "gn:timezone":"Europe/Dublin",
    "iso:country":"IE",
    "wof:name":"Fergus Cross Roads",
    "wof:placetype":"locality"
},
  "geometry": {"coordinates":[-8.74111,51.90417],"type":"Point"}
}