{
  "type": "Feature",
  "properties": {
    "gn:admin1_code":"L",
    "gn:admin2_code":"35.0",
    "gn:asciiname":"Rivermeade",
    "gn:country_code":"IE",
    "gn:dem":62,
    "gn:feature_class":"P",
    "gn:feature_code":"PPL",
    "gn:name":"Rivermeade",
    "gn:population":543,
    "gn:timezone":"Europe/Dublin",
    "iso:country":"IE",
    "name:ceb_x_preferred":[
        "Rivermeade"
    ],
    "name:swe_x_preferred":[
        "Rivermeade"
    ],
    "wof:name":"Rivermeade",
    "wof:placetype":"locality",
    "wof:population":543
},
  "geometry": {"coordinates":[-6.29115,53.45291],"type":"Point"}
}