{
  "type": "Feature",
  "properties": {
    "gn:admin1_code":"M",
    "gn:admin2_code":"11",
    "gn:asciiname":"Camp",
    "gn:country_code":"IE",
    "gn:dem":14,
    "gn:feature_class":"P",
    "gn:feature_code":"PPL",
    "gn:name":"Camp",
    "gn:population":0,
    "gn:timezone":"Europe/Dublin",
    "iso:country":"IE",
    "wof:name":"Camp",
    "wof:placetype":"locality"
},
  "geometry": {"coordinates":[-9.92222,52.22528],"type":"Point"}
}