{
  "type": "Feature",
  "properties": {
    "gn:admin1_code":"M",
    "gn:admin2_code":"11",
    "gn:asciiname":"Camp",
    "gn:country_code":"IE",
    "gn:dem":14,
    "gn:feature_class":"P",
    "gn:feature_code":"PPL",
    "gn:name":"Camp",
    "gn:population":0,
    "gn:timezone":"Europe/Dublin",
    "iso:country":"IE",
    "name:bul_x_preferred":[
        "\u041b\u0430\u0433\u0435\u0440"
    ],
    "name:cat_x_preferred":[
        "Camp"
    ],
    "name:ceb_x_preferred":[
        "Camp"
    ],
    "name:cym_x_preferred":[
        "Camp"
    ],
    "name:dan_x_preferred":[
        "Camp"
    ],
    "name:deu_x_preferred":[
        "Camp"
    ],
    "name:fin_x_preferred":[
        "Camp"
    ],
    "name:fra_x_preferred":[
        "Camp"
    ],
    "name:heb_x_preferred":[
        "\u05de\u05d7\u05e0\u05d4"
    ],
    "name:jpn_x_preferred":[
        "\u30ad\u30e3\u30f3\u30d7"
    ],
    "name:nld_x_preferred":[
        "Camp"
    ],
    "name:nor_x_preferred":[
        "Camp"
    ],
    "name:pol_x_preferred":[
        "Camp"
    ],
    "name:rus_x_preferred":[
        "\u041a\u0430\u043c\u043f"
    ],
    "name:ukr_x_preferred":[
        "\u0422\u0430\u0431\u0456\u0440"
    ],
    "wof:name":"Camp",
    "wof:placetype":"locality"
},
  "geometry": {"coordinates":[-9.92222,52.22528],"type":"Point"}
}