{
  "type": "Feature",
  "properties": {
    "gn:admin1_code":"L",
    "gn:admin2_code":"21.0",
    "gn:asciiname":"Martinstown",
    "gn:country_code":"IE",
    "gn:dem":72,
    "gn:feature_class":"P",
    "gn:feature_code":"PPL",
    "gn:name":"Martinstown",
    "gn:population":0,
    "gn:timezone":"Europe/Dublin",
    "iso:country":"IE",
    "name:deu_x_preferred":[
        "Martinstown"
    ],
    "wof:name":"Martinstown",
    "wof:placetype":"locality"
},
  "geometry": {"coordinates":[-6.6836,53.52012],"type":"Point"}
}