{
  "type": "Feature",
  "properties": {
    "gn:admin1_code":"U",
    "gn:admin2_code":"06",
    "gn:asciiname":"Glasmullan",
    "gn:country_code":"IE",
    "gn:dem":138,
    "gn:feature_class":"P",
    "gn:feature_code":"PPLL",
    "gn:name":"Glasmullan",
    "gn:population":0,
    "gn:timezone":"Europe/Dublin",
    "iso:country":"IE",
    "wof:name":"Glasmullan",
    "wof:placetype":"locality"
},
  "geometry": {"coordinates":[-7.41222,55.21444],"type":"Point"}
}