{
  "type": "Feature",
  "properties": {
    "gn:admin1_code":"L",
    "gn:admin2_code":"23.0",
    "gn:asciiname":"Jonestown Cross Roads",
    "gn:country_code":"IE",
    "gn:dem":67,
    "gn:feature_class":"P",
    "gn:feature_code":"PPL",
    "gn:name":"Jonestown Cross Roads",
    "gn:population":0,
    "gn:timezone":"Europe/Dublin",
    "iso:country":"IE",
    "wof:name":"Jonestown Cross Roads",
    "wof:placetype":"locality"
},
  "geometry": {"coordinates":[-7.05556,53.35471999999999],"type":"Point"}
}