{
  "type": "Feature",
  "properties": {
    "gn:admin1_code":"U",
    "gn:admin2_code":"06",
    "gn:asciiname":"Ardagh",
    "gn:country_code":"IE",
    "gn:dem":137,
    "gn:feature_class":"P",
    "gn:feature_code":"PPLL",
    "gn:name":"Ardagh",
    "gn:population":0,
    "gn:timezone":"Europe/Dublin",
    "iso:country":"IE",
    "name:ceb_x_preferred":[
        "Ardagh"
    ],
    "name:deu_x_preferred":[
        "Ardagh"
    ],
    "name:slv_x_preferred":[
        "Ardagh"
    ],
    "name:swe_x_preferred":[
        "Ardagh"
    ],
    "wof:name":"Ardagh",
    "wof:placetype":"locality"
},
  "geometry": {"coordinates":[-7.53472,54.93694],"type":"Point"}
}