{
  "type": "Feature",
  "properties": {
    "gn:admin1_code":"L",
    "gn:admin2_code":"21",
    "gn:asciiname":"Castlejordan",
    "gn:country_code":"IE",
    "gn:dem":75,
    "gn:feature_class":"P",
    "gn:feature_code":"PPL",
    "gn:name":"Castlejordan",
    "gn:population":0,
    "gn:timezone":"Europe/Dublin",
    "iso:country":"IE",
    "wof:name":"Castlejordan",
    "wof:placetype":"locality"
},
  "geometry": {"coordinates":[-7.12611,53.40028],"type":"Point"}
}