{
  "type": "Feature",
  "properties": {
    "gn:country":"IE",
    "gn:fcode":"PPL",
    "gn:population":0,
    "iso:country":"IE",
    "name:eng_x_preferred":[
        "Ogonnelloe"
    ],
    "name:gle_x_preferred":[
        "Tuath U\u00ed gConaile"
    ],
    "name:nld_x_preferred":[
        "Ogonnelloe"
    ],
    "qs_pg:aaroncc":"IE",
    "qs_pg:gn_country":"IE",
    "qs_pg:gn_fcode":"PPL",
    "qs_pg:gn_pop":0,
    "qs_pg:name":"Ogonnelloe",
    "qs_pg:name_adm0":"Ireland",
    "qs_pg:name_adm1":"Clare",
    "qs_pg:photos_9r":0,
    "qs_pg:photos_sr":0,
    "qs_pg:pop_sr":0,
    "qs_pg:qs_pg_placetype":"locality",
    "qs_pg:qs_pg_placetype_gp":"Town",
    "qs_pg:woe_adm0":23424803,
    "woe:adm0_id":23424803,
    "woe:name_adm0":"Ireland",
    "woe:name_adm1":"Clare",
    "woe:placetype":"Town",
    "wof:name":"Ogonnelloe",
    "wof:placetype":"locality"
},
  "geometry": {"coordinates":[-8.4575,52.88806],"type":"Point"}
}