{
  "type": "Feature",
  "properties": {
    "gn:admin1_code":"L",
    "gn:admin2_code":"30",
    "gn:asciiname":"Ballygillistown",
    "gn:country_code":"IE",
    "gn:dem":28,
    "gn:feature_class":"P",
    "gn:feature_code":"PPL",
    "gn:name":"Ballygillistown",
    "gn:population":0,
    "gn:timezone":"Europe/Dublin",
    "iso:country":"IE",
    "wof:name":"Ballygillistown",
    "wof:placetype":"locality"
},
  "geometry": {"coordinates":[-6.61806,52.47639],"type":"Point"}
}