{
  "type": "Feature",
  "properties": {
    "gn:admin1_code":"M",
    "gn:admin2_code":"04",
    "gn:asciiname":"Oldcastletown",
    "gn:country_code":"IE",
    "gn:dem":90,
    "gn:feature_class":"P",
    "gn:feature_code":"PPL",
    "gn:name":"Oldcastletown",
    "gn:population":0,
    "gn:timezone":"Europe/Dublin",
    "iso:country":"IE",
    "wof:name":"Oldcastletown",
    "wof:placetype":"locality"
},
  "geometry": {"coordinates":[-8.42861,52.25917000000001],"type":"Point"}
}