{
  "type": "Feature",
  "properties": {
    "gn:admin1_code":"M",
    "gn:admin2_code":"11",
    "gn:asciiname":"Bealtalaw Bridge",
    "gn:country_code":"IE",
    "gn:dem":46,
    "gn:feature_class":"P",
    "gn:feature_code":"PPL",
    "gn:name":"Bealtalaw Bridge",
    "gn:population":0,
    "gn:timezone":"Europe/Dublin",
    "iso:country":"IE",
    "wof:name":"Bealtalaw Bridge",
    "wof:placetype":"locality"
},
  "geometry": {"coordinates":[-9.87139,51.98833],"type":"Point"}
}