{
  "type": "Feature",
  "properties": {
    "gn:gn_country":"IE",
    "gn:gn_fcode":"PPL",
    "gn:gn_pop":0,
    "iso:country":"IE",
    "name:baq_x_preferred":[
        "Abbeyside"
    ],
    "name:dut_x_preferred":[
        "Abbeyside"
    ],
    "name:eng_x_preferred":[
        "Abbeyside"
    ],
    "name:gle_x_preferred":[
        "D\u00fan na Mainistreach"
    ],
    "name:rus_x_preferred":[
        "\u0410\u0431\u0431\u0438\u0441\u0430\u0439\u0434"
    ],
    "name:ukr_x_preferred":[
        "\u0410\u0431\u0431\u0456\u0441\u0430\u0439\u0434"
    ],
    "qs_pg:aaroncc":"IE",
    "qs_pg:gn_country":"IE",
    "qs_pg:gn_fcode":"PPL",
    "qs_pg:gn_pop":0,
    "qs_pg:name":"Abbeyside",
    "qs_pg:name_adm0":"Ireland",
    "qs_pg:name_adm1":"Waterford",
    "qs_pg:photos":297,
    "qs_pg:photos_1k":60,
    "qs_pg:photos_9k":1,
    "qs_pg:photos_9r":4,
    "qs_pg:photos_all":297,
    "qs_pg:photos_sr":5,
    "qs_pg:pop_sr":0,
    "qs_pg:qs_pg_placetype":"locality",
    "qs_pg:qs_pg_placetype_gp":"Town",
    "qs_pg:woe_adm0":23424803,
    "woe:adm0_id":23424803,
    "woe:name_adm0":"Ireland",
    "woe:name_adm1":"Waterford",
    "woe:placetype":"Town",
    "wof:name":"Abbeyside",
    "wof:placetype":"locality"
},
  "geometry": {"coordinates":[-7.61139,52.09389],"type":"Point"}
}