{
  "type": "Feature",
  "properties": {
    "gn:admin1_code":"L",
    "gn:admin2_code":"31.0",
    "gn:asciiname":"Nun's Cross",
    "gn:country_code":"IE",
    "gn:dem":43,
    "gn:feature_class":"P",
    "gn:feature_code":"PPL",
    "gn:name":"Nun\u2019s Cross",
    "gn:population":0,
    "gn:timezone":"Europe/Dublin",
    "iso:country":"IE",
    "wof:name":"Nun's Cross",
    "wof:placetype":"locality"
},
  "geometry": {"coordinates":[-6.12195,53.01598000000001],"type":"Point"}
}