{
  "type": "Feature",
  "properties": {
    "gn:admin1_code":"L",
    "gn:admin2_code":"23.0",
    "gn:asciiname":"Red Gate",
    "gn:country_code":"IE",
    "gn:dem":65,
    "gn:feature_class":"P",
    "gn:feature_code":"PPL",
    "gn:name":"Red Gate",
    "gn:population":0,
    "gn:timezone":"Europe/Dublin",
    "iso:country":"IE",
    "name:dan_x_preferred":[
        "Den R\u00f8de Port"
    ],
    "name:fry_x_preferred":[
        "Reade Poarte"
    ],
    "name:pol_x_preferred":[
        "Czerwona Brama"
    ],
    "name:rus_x_preferred":[
        "\u041a\u0440\u0430\u0441\u043d\u044b\u0435 \u0432\u043e\u0440\u043e\u0442\u0430"
    ],
    "name:zho_x_preferred":[
        "\u7d05\u9580"
    ],
    "wof:name":"Red Gate",
    "wof:placetype":"locality"
},
  "geometry": {"coordinates":[-7.50528,53.2625],"type":"Point"}
}