{
  "type": "Feature",
  "properties": {
    "gn:admin1_code":"L",
    "gn:admin2_code":"31.0",
    "gn:asciiname":"Kelshabeg",
    "gn:country_code":"IE",
    "gn:dem":197,
    "gn:feature_class":"P",
    "gn:feature_code":"PPL",
    "gn:name":"Kelshabeg",
    "gn:population":0,
    "gn:timezone":"Europe/Dublin",
    "iso:country":"IE",
    "wof:name":"Kelshabeg",
    "wof:placetype":"locality"
},
  "geometry": {"coordinates":[-6.61167,52.93306],"type":"Point"}
}