{
  "type": "Feature",
  "properties": {
    "gn:admin1_code":"C",
    "gn:admin2_code":"20",
    "gn:asciiname":"Gweesalia",
    "gn:country_code":"IE",
    "gn:dem":11,
    "gn:feature_class":"P",
    "gn:feature_code":"PPL",
    "gn:name":"Gweesalia",
    "gn:population":0,
    "gn:timezone":"Europe/Dublin",
    "iso:country":"IE",
    "name:cat_x_preferred":[
        "Gweesalia"
    ],
    "name:eus_x_preferred":[
        "Gweesalia"
    ],
    "name:gle_x_preferred":[
        "Gaoth S\u00e1ile"
    ],
    "name:rus_x_preferred":[
        "\u0413\u0443\u0438\u0441\u0430\u043b\u0438\u044f"
    ],
    "wof:name":"Gweesalia",
    "wof:placetype":"locality"
},
  "geometry": {"coordinates":[-9.89856,54.11139],"type":"Point"}
}