{
  "type": "Feature",
  "properties": {
    "gn:admin1_code":"C",
    "gn:admin2_code":"10.0",
    "gn:asciiname":"Derreen",
    "gn:country_code":"IE",
    "gn:dem":17,
    "gn:feature_class":"P",
    "gn:feature_code":"PPLL",
    "gn:name":"Derreen",
    "gn:population":0,
    "gn:timezone":"Europe/Dublin",
    "iso:country":"IE",
    "name:eng_x_preferred":[
        "Derreen"
    ],
    "name:gle_x_preferred":[
        "An Doir\u00edn"
    ],
    "wof:name":"Derreen",
    "wof:placetype":"locality"
},
  "geometry": {"coordinates":[-10.06389,53.50361],"type":"Point"}
}