{
  "type": "Feature",
  "properties": {
    "gn:admin1_code":"C",
    "gn:admin2_code":"24",
    "gn:asciiname":"Kingsland",
    "gn:country_code":"IE",
    "gn:dem":91,
    "gn:feature_class":"P",
    "gn:feature_code":"PPL",
    "gn:name":"Kingsland",
    "gn:population":0,
    "gn:timezone":"Europe/Dublin",
    "iso:country":"IE",
    "name:und_x_variant":[
        "Rinn a Rod\u00e1in",
        "Kingsland"
    ],
    "wof:name":"Kingsland",
    "wof:placetype":"locality"
},
  "geometry": {"coordinates":[-8.36667,53.91667],"type":"Point"}
}