{
  "type": "Feature",
  "properties": {
    "gn:admin1_code":"C",
    "gn:admin2_code":"24",
    "gn:asciiname":"Kingsland",
    "gn:country_code":"IE",
    "gn:dem":91,
    "gn:feature_class":"P",
    "gn:feature_code":"PPL",
    "gn:name":"Kingsland",
    "gn:population":0,
    "gn:timezone":"Europe/Dublin",
    "iso:country":"IE",
    "name:cat_x_preferred":[
        "Kingsland"
    ],
    "name:ceb_x_preferred":[
        "Kingsland"
    ],
    "name:deu_x_preferred":[
        "Kingsland"
    ],
    "name:fra_x_preferred":[
        "Kingsland"
    ],
    "name:ita_x_preferred":[
        "Kingsland"
    ],
    "name:nld_x_preferred":[
        "Kingsland"
    ],
    "name:pol_x_preferred":[
        "Kingsland"
    ],
    "name:por_x_preferred":[
        "Kingsland"
    ],
    "name:srp_x_preferred":[
        "\u041a\u0438\u043d\u0433\u0441\u043b\u0430\u043d\u0434"
    ],
    "name:swe_x_preferred":[
        "Kingsland"
    ],
    "name:ukr_x_preferred":[
        "\u041a\u0456\u043d\u0433\u0441\u043b\u0435\u043d\u0434"
    ],
    "name:und_x_variant":[
        "Rinn a Rod\u00e1in"
    ],
    "name:urd_x_preferred":[
        "\u06a9\u0646\u06af\u0632\u0644\u06cc\u0646\u0688"
    ],
    "name:vol_x_preferred":[
        "Kingsland"
    ],
    "wof:name":"Kingsland",
    "wof:placetype":"locality"
},
  "geometry": {"coordinates":[-8.36667,53.91667],"type":"Point"}
}