{
  "type": "Feature",
  "properties": {
    "gn:admin1_code":"U",
    "gn:admin2_code":"06",
    "gn:asciiname":"Liscooly Bridge",
    "gn:country_code":"IE",
    "gn:dem":5,
    "gn:feature_class":"P",
    "gn:feature_code":"PPLL",
    "gn:name":"Liscooly Bridge",
    "gn:population":0,
    "gn:timezone":"Europe/Dublin",
    "iso:country":"IE",
    "wof:name":"Liscooly Bridge",
    "wof:placetype":"locality"
},
  "geometry": {"coordinates":[-7.64222,54.79667],"type":"Point"}
}