{
  "type": "Feature",
  "properties": {
    "gn:admin1_code":"M",
    "gn:admin2_code":"11",
    "gn:asciiname":"Drehideighteragh Bridge",
    "gn:country_code":"IE",
    "gn:dem":309,
    "gn:feature_class":"P",
    "gn:feature_code":"PPLL",
    "gn:name":"Drehideighteragh Bridge",
    "gn:population":0,
    "gn:timezone":"Europe/Dublin",
    "iso:country":"IE",
    "wof:name":"Drehideighteragh Bridge",
    "wof:placetype":"locality"
},
  "geometry": {"coordinates":[-9.49722,51.8325],"type":"Point"}
}