{
  "type": "Feature",
  "properties": {
    "gn:admin1_code":"C",
    "gn:admin2_code":"14.0",
    "gn:asciiname":"Kilclare",
    "gn:country_code":"IE",
    "gn:dem":53,
    "gn:feature_class":"P",
    "gn:feature_code":"PPLL",
    "gn:name":"Kilclare",
    "gn:population":0,
    "gn:timezone":"Europe/Dublin",
    "iso:country":"IE",
    "wof:name":"Kilclare",
    "wof:placetype":"locality"
},
  "geometry": {"coordinates":[-8.01556,54.00778],"type":"Point"}
}