{
  "type": "Feature",
  "properties": {
    "gn:admin1_code":"U",
    "gn:admin2_code":"22.0",
    "gn:asciiname":"Carsons Bridge",
    "gn:country_code":"IE",
    "gn:dem":72,
    "gn:feature_class":"P",
    "gn:feature_code":"PPLL",
    "gn:name":"Carsons Bridge",
    "gn:population":0,
    "gn:timezone":"Europe/Dublin",
    "iso:country":"IE",
    "wof:name":"Carsons Bridge",
    "wof:placetype":"locality"
},
  "geometry": {"coordinates":[-7.02806,54.23778000000001],"type":"Point"}
}