{
  "type": "Feature",
  "properties": {
    "gn:admin1_code":"L",
    "gn:admin2_code":"21.0",
    "gn:asciiname":"Athgaine Little",
    "gn:country_code":"IE",
    "gn:dem":63,
    "gn:feature_class":"P",
    "gn:feature_code":"PPL",
    "gn:name":"Athgaine Little",
    "gn:population":0,
    "gn:timezone":"Europe/Dublin",
    "iso:country":"IE",
    "wof:name":"Athgaine Little",
    "wof:placetype":"locality"
},
  "geometry": {"coordinates":[-6.83034,53.68869],"type":"Point"}
}