{
  "type": "Feature",
  "properties": {
    "gn:admin1_code":"M",
    "gn:admin2_code":"11",
    "gn:asciiname":"Tooreen",
    "gn:country_code":"IE",
    "gn:dem":130,
    "gn:feature_class":"P",
    "gn:feature_code":"PPL",
    "gn:name":"Tooreen",
    "gn:population":0,
    "gn:timezone":"Europe/Dublin",
    "iso:country":"IE",
    "name:eng_x_preferred":[
        "Tooreen"
    ],
    "name:gle_x_preferred":[
        "An Tuair\u00edn"
    ],
    "wof:name":"Tooreen",
    "wof:placetype":"locality"
},
  "geometry": {"coordinates":[-9.42444,52.38028],"type":"Point"}
}