{
  "type": "Feature",
  "properties": {
    "gn:country":"IE",
    "gn:fcode":"PPL",
    "gn:population":0,
    "iso:country":"IE",
    "name:deu_x_preferred":[
        "Minard"
    ],
    "name:eng_x_preferred":[
        "Minard"
    ],
    "name:fra_x_preferred":[
        "Minard"
    ],
    "name:gle_x_preferred":[
        "An Mhin Aird"
    ],
    "qs_pg:aaroncc":"IE",
    "qs_pg:gn_country":"IE",
    "qs_pg:gn_fcode":"PPL",
    "qs_pg:gn_pop":0,
    "qs_pg:name":"Minard",
    "qs_pg:name_adm0":"Ireland",
    "qs_pg:name_adm1":"Kerry",
    "qs_pg:photos":193,
    "qs_pg:photos_1k":39,
    "qs_pg:photos_9k":2,
    "qs_pg:photos_9r":5,
    "qs_pg:photos_all":349,
    "qs_pg:photos_sr":4,
    "qs_pg:pop_sr":0,
    "qs_pg:qs_pg_placetype":"localadmin",
    "qs_pg:qs_pg_placetype_gp":"LocalAdmin",
    "qs_pg:woe_adm0":23424803,
    "woe:adm0_id":23424803,
    "woe:name_adm0":"Ireland",
    "woe:name_adm1":"Kerry",
    "woe:placetype":"LocalAdmin",
    "wof:name":"Minard",
    "wof:placetype":"localadmin"
},
  "geometry": {"coordinates":[-10.14028,52.12278],"type":"Point"}
}