{
  "type": "Feature",
  "properties": {
    "gn:admin1_code":"U",
    "gn:admin2_code":"06",
    "gn:asciiname":"Portnalong",
    "gn:country_code":"IE",
    "gn:dem":47,
    "gn:feature_class":"P",
    "gn:feature_code":"PPL",
    "gn:name":"Portnalong",
    "gn:population":0,
    "gn:timezone":"Europe/Dublin",
    "iso:country":"IE",
    "wof:name":"Portnalong",
    "wof:placetype":"locality"
},
  "geometry": {"coordinates":[-7.18333,55.31667],"type":"Point"}
}