{
  "type": "Feature",
  "properties": {
    "gn:admin1_code":"C",
    "gn:admin2_code":"10.0",
    "gn:asciiname":"Cahernashilleeny",
    "gn:country_code":"IE",
    "gn:dem":25,
    "gn:feature_class":"P",
    "gn:feature_code":"PPLL",
    "gn:name":"Cahernashilleeny",
    "gn:population":0,
    "gn:timezone":"Europe/Dublin",
    "iso:country":"IE",
    "wof:name":"Cahernashilleeny",
    "wof:placetype":"locality"
},
  "geometry": {"coordinates":[-8.88778,53.34972],"type":"Point"}
}