{
  "type": "Feature",
  "properties": {
    "gn:admin1_code":"L",
    "gn:admin2_code":"29.0",
    "gn:asciiname":"Paristown",
    "gn:country_code":"IE",
    "gn:dem":96,
    "gn:feature_class":"P",
    "gn:feature_code":"PPL",
    "gn:name":"Paristown",
    "gn:population":0,
    "gn:timezone":"Europe/Dublin",
    "iso:country":"IE",
    "wof:name":"Paristown",
    "wof:placetype":"locality"
},
  "geometry": {"coordinates":[-7.00309,53.63812],"type":"Point"}
}