{
  "type": "Feature",
  "properties": {
    "gn:admin1_code":"U",
    "gn:admin2_code":"06",
    "gn:asciiname":"Garvagh",
    "gn:country_code":"IE",
    "gn:dem":83,
    "gn:feature_class":"P",
    "gn:feature_code":"PPLL",
    "gn:name":"Garvagh",
    "gn:population":0,
    "gn:timezone":"Europe/Dublin",
    "iso:country":"IE",
    "name:ceb_x_preferred":[
        "Garvagh"
    ],
    "name:eus_x_preferred":[
        "Garvagh"
    ],
    "name:fas_x_preferred":[
        "\u06af\u0627\u0631\u0648\u0627\u06af"
    ],
    "name:gla_x_preferred":[
        "Garbhachadh"
    ],
    "name:gle_x_preferred":[
        "Garbhachadh"
    ],
    "name:ita_x_preferred":[
        "Garvagh"
    ],
    "name:msa_x_preferred":[
        "Garvagh"
    ],
    "name:nld_x_preferred":[
        "Garvagh"
    ],
    "name:pli_x_preferred":[
        "\u0917\u0930\u094d\u0935\u0918"
    ],
    "name:spa_x_preferred":[
        "Garvagh"
    ],
    "name:swe_x_preferred":[
        "Garvagh"
    ],
    "wof:name":"Garvagh",
    "wof:placetype":"locality"
},
  "geometry": {"coordinates":[-8.02667,54.7075],"type":"Point"}
}