{
  "type": "Feature",
  "properties": {
    "gn:admin1_code":"U",
    "gn:admin2_code":"06",
    "gn:asciiname":"Garvagh",
    "gn:country_code":"IE",
    "gn:dem":83,
    "gn:feature_class":"P",
    "gn:feature_code":"PPLL",
    "gn:name":"Garvagh",
    "gn:population":0,
    "gn:timezone":"Europe/Dublin",
    "iso:country":"IE",
    "wof:name":"Garvagh",
    "wof:placetype":"locality"
},
  "geometry": {"coordinates":[-8.02667,54.7075],"type":"Point"}
}