{
  "type": "Feature",
  "properties": {
    "gn:admin1_code":"L",
    "gn:admin2_code":"21",
    "gn:asciiname":"Donacarney",
    "gn:country_code":"IE",
    "gn:dem":23,
    "gn:feature_class":"P",
    "gn:feature_code":"PPL",
    "gn:name":"Donacarney",
    "gn:population":0,
    "gn:timezone":"Europe/Dublin",
    "iso:country":"IE",
    "name:eus_x_preferred":[
        "Donacarney"
    ],
    "name:gle_x_preferred":[
        "Domhnach Cearnaigh"
    ],
    "name:glv_x_preferred":[
        "Domhnach Cairnigh"
    ],
    "name:rus_x_preferred":[
        "\u0414\u043e\u043d\u0430\u043a\u0430\u0440\u043d\u0438"
    ],
    "wof:name":"Donacarney",
    "wof:placetype":"locality"
},
  "geometry": {"coordinates":[-6.27917,53.71333],"type":"Point"}
}