{
  "type": "Feature",
  "properties": {
    "gn:admin1_code":"L",
    "gn:admin2_code":"21",
    "gn:asciiname":"Donacarney",
    "gn:country_code":"IE",
    "gn:dem":23,
    "gn:feature_class":"P",
    "gn:feature_code":"PPL",
    "gn:name":"Donacarney",
    "gn:population":0,
    "gn:timezone":"Europe/Dublin",
    "iso:country":"IE",
    "wof:name":"Donacarney",
    "wof:placetype":"locality"
},
  "geometry": {"coordinates":[-6.27917,53.71333000000001],"type":"Point"}
}