{
  "type": "Feature",
  "properties": {
    "gn:admin1_code":"C",
    "gn:admin2_code":"10.0",
    "gn:asciiname":"Cloonnasee",
    "gn:country_code":"IE",
    "gn:dem":16,
    "gn:feature_class":"P",
    "gn:feature_code":"PPLL",
    "gn:name":"Cloonnasee",
    "gn:population":0,
    "gn:timezone":"Europe/Dublin",
    "iso:country":"IE",
    "wof:name":"Cloonnasee",
    "wof:placetype":"locality"
},
  "geometry": {"coordinates":[-8.94667,53.12778],"type":"Point"}
}