{
  "type": "Feature",
  "properties": {
    "gn:admin1_code":"C",
    "gn:admin2_code":"24.0",
    "gn:asciiname":"Creggan",
    "gn:country_code":"IE",
    "gn:dem":40,
    "gn:feature_class":"P",
    "gn:feature_code":"PPL",
    "gn:name":"Creggan",
    "gn:population":0,
    "gn:timezone":"Europe/Dublin",
    "iso:country":"IE",
    "name:spa_x_preferred":[
        "Creggan-Cranfield"
    ],
    "wof:name":"Creggan",
    "wof:placetype":"locality"
},
  "geometry": {"coordinates":[-8.09917,53.27944],"type":"Point"}
}