{
  "type": "Feature",
  "properties": {
    "gn:admin1_code":"L",
    "gn:admin2_code":"39.0",
    "gn:asciiname":"Riversdale",
    "gn:country_code":"IE",
    "gn:dem":66,
    "gn:feature_class":"P",
    "gn:feature_code":"PPL",
    "gn:name":"Riversdale",
    "gn:population":0,
    "gn:timezone":"Europe/Dublin",
    "iso:country":"IE",
    "wof:name":"Riversdale",
    "wof:placetype":"locality"
},
  "geometry": {"coordinates":[-6.5075,53.31721999999999],"type":"Point"}
}