{
  "type": "Feature",
  "properties": {
    "gn:admin1_code":"L",
    "gn:admin2_code":"23.0",
    "gn:asciiname":"Reask",
    "gn:country_code":"IE",
    "gn:dem":32,
    "gn:feature_class":"P",
    "gn:feature_code":"PPL",
    "gn:name":"Reask",
    "gn:population":0,
    "gn:timezone":"Europe/Dublin",
    "iso:country":"IE",
    "name:deu_x_preferred":[
        "Reask"
    ],
    "name:rus_x_preferred":[
        "\u0420\u0438\u0441\u043a"
    ],
    "wof:name":"Reask",
    "wof:placetype":"locality"
},
  "geometry": {"coordinates":[-7.98,53.22583],"type":"Point"}
}