{
  "type": "Feature",
  "properties": {
    "gn:admin1_code":"C",
    "gn:admin2_code":"20.0",
    "gn:asciiname":"Cushalogurt",
    "gn:country_code":"IE",
    "gn:dem":14,
    "gn:feature_class":"P",
    "gn:feature_code":"PPL",
    "gn:name":"Cushalogurt",
    "gn:population":0,
    "gn:timezone":"Europe/Dublin",
    "iso:country":"IE",
    "wof:name":"Cushalogurt",
    "wof:placetype":"locality"
},
  "geometry": {"coordinates":[-9.56099,53.84757],"type":"Point"}
}