{
  "type": "Feature",
  "properties": {
    "gn:admin1_code":"M",
    "gn:admin2_code":"04",
    "gn:asciiname":"Kilmona",
    "gn:country_code":"IE",
    "gn:dem":144,
    "gn:feature_class":"P",
    "gn:feature_code":"PPL",
    "gn:name":"Kilmona",
    "gn:population":0,
    "gn:timezone":"Europe/Dublin",
    "iso:country":"IE",
    "wof:name":"Kilmona",
    "wof:placetype":"locality"
},
  "geometry": {"coordinates":[-8.57083,51.99278],"type":"Point"}
}