{
  "type": "Feature",
  "properties": {
    "gn:admin1_code":"M",
    "gn:admin2_code":"04",
    "gn:asciiname":"Esk",
    "gn:country_code":"IE",
    "gn:dem":245,
    "gn:feature_class":"P",
    "gn:feature_code":"PPL",
    "gn:name":"Esk",
    "gn:population":0,
    "gn:timezone":"Europe/Dublin",
    "iso:country":"IE",
    "name:deu_x_preferred":[
        "Esk"
    ],
    "name:fin_x_preferred":[
        "Esk"
    ],
    "name:fra_x_preferred":[
        "Esk"
    ],
    "name:nds_x_preferred":[
        "Esk"
    ],
    "name:pol_x_preferred":[
        "Esk"
    ],
    "wof:name":"Esk",
    "wof:placetype":"locality"
},
  "geometry": {"coordinates":[-8.81028,52.0625],"type":"Point"}
}