{
  "type": "Feature",
  "properties": {
    "gn:admin1_code":"M",
    "gn:admin2_code":"04",
    "gn:asciiname":"Gortroe Cross Roads",
    "gn:country_code":"IE",
    "gn:dem":84,
    "gn:feature_class":"P",
    "gn:feature_code":"PPLL",
    "gn:name":"Gortroe Cross Roads",
    "gn:population":0,
    "gn:timezone":"Europe/Dublin",
    "iso:country":"IE",
    "wof:name":"Gortroe Cross Roads",
    "wof:placetype":"locality"
},
  "geometry": {"coordinates":[-9.10333,51.60806],"type":"Point"}
}