{
  "type": "Feature",
  "properties": {
    "iso:country":"IE",
    "name:ceb_x_preferred":[
        "Quigley's Point"
    ],
    "name:eng_x_preferred":[
        "Quigley's Point"
    ],
    "name:eus_x_preferred":[
        "Quigley's Point"
    ],
    "name:nld_x_preferred":[
        "Quigley's Point"
    ],
    "name:rus_x_preferred":[
        "\u041a\u0443\u0438\u0433\u043b\u0438\u0441-\u041f\u043e\u0439\u043d\u0442"
    ],
    "name:spa_x_preferred":[
        "Quigleys Point"
    ],
    "name:swe_x_preferred":[
        "Quigley's Point"
    ],
    "qs_pg:aaroncc":"IE",
    "qs_pg:name":"Quigleys Point",
    "qs_pg:name_adm0":"Ireland",
    "qs_pg:name_adm1":"Donegal",
    "qs_pg:photos":132,
    "qs_pg:photos_1k":27,
    "qs_pg:photos_9k":1,
    "qs_pg:photos_9r":3,
    "qs_pg:photos_all":132,
    "qs_pg:photos_sr":3,
    "qs_pg:pop_sr":0,
    "qs_pg:qs_pg_placetype":"locality",
    "qs_pg:qs_pg_placetype_gp":"Town",
    "qs_pg:woe_adm0":23424803,
    "woe:adm0_id":23424803,
    "woe:name_adm0":"Ireland",
    "woe:name_adm1":"Donegal",
    "woe:placetype":"Town",
    "wof:name":"Quigleys Point",
    "wof:placetype":"locality"
},
  "geometry": {"coordinates":[-7.127165,55.157738],"type":"Point"}
}