{
  "type": "Feature",
  "properties": {
    "gn:admin1_code":"M",
    "gn:admin2_code":"04",
    "gn:asciiname":"Walshtown",
    "gn:country_code":"IE",
    "gn:dem":147,
    "gn:feature_class":"P",
    "gn:feature_code":"PPL",
    "gn:name":"Walshtown",
    "gn:population":0,
    "gn:timezone":"Europe/Dublin",
    "iso:country":"IE",
    "wof:name":"Walshtown",
    "wof:placetype":"locality"
},
  "geometry": {"coordinates":[-8.18722,51.98306],"type":"Point"}
}