{
  "type": "Feature",
  "properties": {
    "gn:admin1_code":"L",
    "gn:admin2_code":"15.0",
    "gn:asciiname":"Clonagooden",
    "gn:country_code":"IE",
    "gn:dem":125,
    "gn:feature_class":"P",
    "gn:feature_code":"PPL",
    "gn:name":"Clonagooden",
    "gn:population":0,
    "gn:timezone":"Europe/Dublin",
    "iso:country":"IE",
    "wof:name":"Clonagooden",
    "wof:placetype":"locality"
},
  "geometry": {"coordinates":[-7.64972,52.91694],"type":"Point"}
}