{
  "type": "Feature",
  "properties": {
    "gn:admin1_code":"L",
    "gn:admin2_code":"15",
    "gn:asciiname":"Ballybrophy",
    "gn:cc2":"IE",
    "gn:country_code":"IE",
    "gn:dem":122,
    "gn:feature_class":"P",
    "gn:feature_code":"PPL",
    "gn:name":"Ballybrophy",
    "gn:population":0,
    "gn:timezone":"Europe/Dublin",
    "iso:country":"IE",
    "name:und_x_variant":[
        "Ballybrophy Junction",
        "Ballybrophy"
    ],
    "wof:name":"Ballybrophy",
    "wof:placetype":"locality"
},
  "geometry": {"coordinates":[-7.6025,52.89944000000001],"type":"Point"}
}