{
  "type": "Feature",
  "properties": {
    "gn:admin1_code":"L",
    "gn:admin2_code":"33.0",
    "gn:asciiname":"Harold's Cross",
    "gn:country_code":"IE",
    "gn:dem":25,
    "gn:feature_class":"P",
    "gn:feature_code":"PPL",
    "gn:name":"Harold's Cross",
    "gn:population":0,
    "gn:timezone":"Europe/Dublin",
    "iso:country":"IE",
    "wof:name":"Harold's Cross",
    "wof:placetype":"locality"
},
  "geometry": {"coordinates":[-6.27538,53.32634],"type":"Point"}
}