{
  "type": "Feature",
  "properties": {
    "gn:admin1_code":"L",
    "gn:admin2_code":"33.0",
    "gn:asciiname":"Harold's Cross",
    "gn:country_code":"IE",
    "gn:dem":25,
    "gn:feature_class":"P",
    "gn:feature_code":"PPL",
    "gn:name":"Harold's Cross",
    "gn:population":0,
    "gn:timezone":"Europe/Dublin",
    "iso:country":"IE",
    "name:eus_x_preferred":[
        "Harold's Cross"
    ],
    "name:gla_x_preferred":[
        "Cros Araild"
    ],
    "name:gle_x_preferred":[
        "Cros Araild"
    ],
    "name:rus_x_preferred":[
        "\u0413\u0430\u0440\u043e\u043b\u044c\u0434-\u041a\u0440\u043e\u0441\u0441"
    ],
    "name:swe_x_preferred":[
        "Harolds Cross"
    ],
    "wof:name":"Harold's Cross",
    "wof:placetype":"locality"
},
  "geometry": {"coordinates":[-6.27538,53.32634],"type":"Point"}
}