{
  "type": "Feature",
  "properties": {
    "gn:admin1_code":"L",
    "gn:admin2_code":"31.0",
    "gn:asciiname":"Newtownmountkennedy",
    "gn:country_code":"IE",
    "gn:dem":81,
    "gn:feature_class":"P",
    "gn:feature_code":"PPL",
    "gn:name":"Newtownmountkennedy",
    "gn:population":2410,
    "gn:timezone":"Europe/Dublin",
    "iso:country":"IE",
    "name:cat_x_preferred":[
        "Newtownmountkennedy"
    ],
    "name:ceb_x_preferred":[
        "Newtownmountkennedy"
    ],
    "name:eus_x_preferred":[
        "Newtownmountkennedy"
    ],
    "name:fra_x_preferred":[
        "Newtownmountkennedy"
    ],
    "name:ita_x_preferred":[
        "Newtownmountkennedy"
    ],
    "name:nld_x_preferred":[
        "Newtownmountkennedy"
    ],
    "name:rus_x_preferred":[
        "\u041d\u044c\u044e\u0442\u0430\u0443\u043d-\u041c\u0430\u0443\u043d\u0442-\u041a\u0435\u043d\u043d\u0435\u0434\u0438"
    ],
    "name:spa_x_preferred":[
        "Newtownmountkennedy"
    ],
    "name:swe_x_preferred":[
        "Newtownmountkennedy"
    ],
    "wof:name":"Newtownmountkennedy",
    "wof:placetype":"locality",
    "wof:population":2410
},
  "geometry": {"coordinates":[-6.11149,53.09052],"type":"Point"}
}