{
  "type": "Feature",
  "properties": {
    "gn:admin1_code":"L",
    "gn:admin2_code":"31.0",
    "gn:asciiname":"Newtownmountkennedy",
    "gn:country_code":"IE",
    "gn:dem":81,
    "gn:feature_class":"P",
    "gn:feature_code":"PPL",
    "gn:name":"Newtownmountkennedy",
    "gn:population":2410,
    "gn:timezone":"Europe/Dublin",
    "iso:country":"IE",
    "wof:name":"Newtownmountkennedy",
    "wof:placetype":"locality",
    "wof:population":2410
},
  "geometry": {"coordinates":[-6.11149,53.09052],"type":"Point"}
}