{
  "type": "Feature",
  "properties": {
    "gn:admin1_code":"M",
    "gn:admin2_code":"03",
    "gn:asciiname":"Trough",
    "gn:country_code":"IE",
    "gn:dem":95,
    "gn:feature_class":"P",
    "gn:feature_code":"PPL",
    "gn:name":"Trough",
    "gn:population":0,
    "gn:timezone":"Europe/Dublin",
    "iso:country":"IE",
    "name:jpn_x_preferred":[
        "\u30c8\u30e9\u30d5"
    ],
    "name:rus_x_preferred":[
        "\u0422\u0440\u043e\u0433"
    ],
    "name:spa_x_preferred":[
        "Vaguada"
    ],
    "name:ukr_x_preferred":[
        "\u0422\u0440\u043e\u0433"
    ],
    "wof:name":"Trough",
    "wof:placetype":"locality"
},
  "geometry": {"coordinates":[-8.61667,52.73333],"type":"Point"}
}