{
  "type": "Feature",
  "properties": {
    "gn:admin1_code":"C",
    "gn:admin2_code":"20.0",
    "gn:asciiname":"Bunnafinglas",
    "gn:country_code":"IE",
    "gn:dem":15,
    "gn:feature_class":"P",
    "gn:feature_code":"PPL",
    "gn:name":"Bunnafinglas",
    "gn:population":0,
    "gn:timezone":"Europe/Dublin",
    "iso:country":"IE",
    "wof:name":"Bunnafinglas",
    "wof:placetype":"locality"
},
  "geometry": {"coordinates":[-9.12764,54.02923000000001],"type":"Point"}
}