{
  "type": "Feature",
  "properties": {
    "gn:admin1_code":"M",
    "gn:admin2_code":"26",
    "gn:asciiname":"Cullen",
    "gn:country_code":"IE",
    "gn:dem":120,
    "gn:feature_class":"P",
    "gn:feature_code":"PPL",
    "gn:name":"Cullen",
    "gn:population":0,
    "gn:timezone":"Europe/Dublin",
    "iso:country":"IE",
    "name:ceb_x_preferred":[
        "Cullen"
    ],
    "name:deu_x_preferred":[
        "Cullen"
    ],
    "name:fra_x_preferred":[
        "Cullen"
    ],
    "name:heb_x_preferred":[
        "\u05e7\u05d0\u05dc\u05df"
    ],
    "name:ita_x_preferred":[
        "Cullen"
    ],
    "name:nld_x_preferred":[
        "Cullen"
    ],
    "name:pol_x_preferred":[
        "Cullen"
    ],
    "name:rus_x_preferred":[
        "\u041a\u0430\u043b\u043b\u0435\u043d"
    ],
    "name:spa_x_preferred":[
        "Cullen"
    ],
    "name:swe_x_preferred":[
        "Cullen"
    ],
    "name:ukr_x_preferred":[
        "\u041a\u0430\u043b\u043b\u0435\u043d"
    ],
    "wof:name":"Cullen",
    "wof:placetype":"locality"
},
  "geometry": {"coordinates":[-8.27028,52.51194],"type":"Point"}
}