{
  "type": "Feature",
  "properties": {
    "gn:admin1_code":"M",
    "gn:admin2_code":"04",
    "gn:asciiname":"Father Murphy's Bridge",
    "gn:country_code":"IE",
    "gn:dem":96,
    "gn:feature_class":"P",
    "gn:feature_code":"PPLL",
    "gn:name":"Father Murphy\u2019s Bridge",
    "gn:population":0,
    "gn:timezone":"Europe/Dublin",
    "iso:country":"IE",
    "wof:name":"Father Murphy's Bridge",
    "wof:placetype":"locality"
},
  "geometry": {"coordinates":[-8.88889,52.11167],"type":"Point"}
}