{
  "type": "Feature",
  "properties": {
    "gn:admin1_code":"M",
    "gn:admin2_code":"11",
    "gn:asciiname":"Listry Bridge",
    "gn:cc2":"IE",
    "gn:country_code":"IE",
    "gn:dem":36,
    "gn:feature_class":"P",
    "gn:feature_code":"PPL",
    "gn:name":"Listry Bridge",
    "gn:population":0,
    "gn:timezone":"Europe/Dublin",
    "iso:country":"IE",
    "name:und_x_variant":[
        "Listry",
        "Listry Bridge"
    ],
    "wof:name":"Listry Bridge",
    "wof:placetype":"locality"
},
  "geometry": {"coordinates":[-9.66667,52.11667],"type":"Point"}
}