{
  "type": "Feature",
  "properties": {
    "gn:admin1_code":"L",
    "gn:admin2_code":"15.0",
    "gn:asciiname":"Ballycoolan",
    "gn:country_code":"IE",
    "gn:dem":112,
    "gn:feature_class":"P",
    "gn:feature_code":"PPLL",
    "gn:name":"Ballycoolan",
    "gn:population":0,
    "gn:timezone":"Europe/Dublin",
    "iso:country":"IE",
    "wof:name":"Ballycoolan",
    "wof:placetype":"locality"
},
  "geometry": {"coordinates":[-7.15861,52.97556],"type":"Point"}
}