{
  "type": "Feature",
  "properties": {
    "gn:admin1_code":"U",
    "gn:admin2_code":"06",
    "gn:asciiname":"Carrickmore Lower",
    "gn:cc2":"IE",
    "gn:country_code":"IE",
    "gn:dem":0,
    "gn:feature_class":"P",
    "gn:feature_code":"PPL",
    "gn:name":"Carrickmore Lower",
    "gn:population":0,
    "gn:timezone":"Europe/Dublin",
    "iso:country":"IE",
    "name:und_x_variant":[
        "Carrickmore",
        "Carrickmore Lower"
    ],
    "wof:name":"Carrickmore Lower",
    "wof:placetype":"locality"
},
  "geometry": {"coordinates":[-7.45,54.88333000000001],"type":"Point"}
}