{
  "type": "Feature",
  "properties": {
    "gn:admin1_code":"M",
    "gn:admin2_code":"44",
    "gn:asciiname":"Monalour",
    "gn:country_code":"IE",
    "gn:dem":143,
    "gn:feature_class":"P",
    "gn:feature_code":"PPL",
    "gn:name":"Monalour",
    "gn:population":0,
    "gn:timezone":"Europe/Dublin",
    "iso:country":"IE",
    "wof:name":"Monalour",
    "wof:placetype":"locality"
},
  "geometry": {"coordinates":[-7.90528,52.17917],"type":"Point"}
}