{
  "type": "Feature",
  "properties": {
    "gn:admin1_code":"L",
    "gn:admin2_code":"23.0",
    "gn:asciiname":"Derrygarran Bridge",
    "gn:country_code":"IE",
    "gn:dem":65,
    "gn:feature_class":"P",
    "gn:feature_code":"PPLL",
    "gn:name":"Derrygarran Bridge",
    "gn:population":0,
    "gn:timezone":"Europe/Dublin",
    "iso:country":"IE",
    "wof:name":"Derrygarran Bridge",
    "wof:placetype":"locality"
},
  "geometry": {"coordinates":[-7.07333,53.23611],"type":"Point"}
}