{
  "type": "Feature",
  "properties": {
    "gn:country":"IE",
    "gn:fcode":"PPL",
    "gn:population":0,
    "iso:country":"IE",
    "name:eus_x_preferred":[
        "Glynn"
    ],
    "name:gla_x_preferred":[
        "An Gleann"
    ],
    "name:gle_x_preferred":[
        "An Gleann"
    ],
    "name:msa_x_preferred":[
        "Glynn"
    ],
    "name:nld_x_preferred":[
        "Glynn"
    ],
    "name:pli_x_preferred":[
        "\u0917\u094d\u0932\u094d\u092f\u0928\u094d\u0928"
    ],
    "name:spa_x_preferred":[
        "Glynn"
    ],
    "qs_pg:aaroncc":"IE",
    "qs_pg:gn_country":"IE",
    "qs_pg:gn_fcode":"PPL",
    "qs_pg:gn_pop":0,
    "qs_pg:name":"Glynn",
    "qs_pg:name_adm0":"Ireland",
    "qs_pg:name_adm1":"Carlow",
    "qs_pg:photos":1,
    "qs_pg:photos_1k":1,
    "qs_pg:photos_9k":1,
    "qs_pg:photos_9r":1,
    "qs_pg:photos_all":1,
    "qs_pg:photos_sr":1,
    "qs_pg:pop_sr":0,
    "qs_pg:qs_pg_placetype":"localadmin",
    "qs_pg:qs_pg_placetype_gp":"LocalAdmin",
    "qs_pg:woe_adm0":23424803,
    "woe:adm0_id":23424803,
    "woe:name_adm0":"Ireland",
    "woe:name_adm1":"Carlow",
    "woe:placetype":"LocalAdmin",
    "wof:name":"Glynn",
    "wof:placetype":"localadmin"
},
  "geometry": {"coordinates":[-6.90417,52.50333],"type":"Point"}
}