{
  "type": "Feature",
  "properties": {
    "gn:admin1_code":"M",
    "gn:admin2_code":"04",
    "gn:asciiname":"Carrahaly",
    "gn:country_code":"IE",
    "gn:dem":166,
    "gn:feature_class":"P",
    "gn:feature_code":"PPL",
    "gn:name":"Carrahaly",
    "gn:population":0,
    "gn:timezone":"Europe/Dublin",
    "iso:country":"IE",
    "wof:name":"Carrahaly",
    "wof:placetype":"locality"
},
  "geometry": {"coordinates":[-8.78722,51.86583],"type":"Point"}
}