{
  "type": "Feature",
  "properties": {
    "iso:country":"IE",
    "qs_pg:aaroncc":"IE",
    "qs_pg:name":"Grange A",
    "qs_pg:name_adm0":"Ireland",
    "qs_pg:name_adm1":"Dublin",
    "qs_pg:photos":393,
    "qs_pg:photos_1k":80,
    "qs_pg:photos_9k":2,
    "qs_pg:photos_9r":5,
    "qs_pg:photos_all":445,
    "qs_pg:photos_sr":6,
    "qs_pg:pop_sr":0,
    "qs_pg:qs_pg_placetype":"localadmin",
    "qs_pg:qs_pg_placetype_gp":"LocalAdmin",
    "qs_pg:woe_adm0":23424803,
    "woe:adm0_id":23424803,
    "woe:name_adm0":"Ireland",
    "woe:name_adm1":"Dublin",
    "woe:placetype":"LocalAdmin",
    "wof:name":"Grange A",
    "wof:placetype":"localadmin"
},
  "geometry": {"coordinates":[-6.178808,53.410145],"type":"Point"}
}