{
  "type": "Feature",
  "properties": {
    "gn:admin1_code":"M",
    "gn:admin2_code":"11",
    "gn:asciiname":"Scrahanaveal",
    "gn:country_code":"IE",
    "gn:dem":158,
    "gn:feature_class":"P",
    "gn:feature_code":"PPL",
    "gn:name":"Scrahanaveal",
    "gn:population":0,
    "gn:timezone":"Europe/Dublin",
    "iso:country":"IE",
    "wof:name":"Scrahanaveal",
    "wof:placetype":"locality"
},
  "geometry": {"coordinates":[-9.32889,52.10889],"type":"Point"}
}