{
  "type": "Feature",
  "properties": {
    "gn:admin1_code":"U",
    "gn:admin2_code":"06",
    "gn:asciiname":"Shanaghan",
    "gn:country_code":"IE",
    "gn:dem":7,
    "gn:feature_class":"P",
    "gn:feature_code":"PPLL",
    "gn:name":"Shanaghan",
    "gn:population":0,
    "gn:timezone":"Europe/Dublin",
    "iso:country":"IE",
    "wof:name":"Shanaghan",
    "wof:placetype":"locality"
},
  "geometry": {"coordinates":[-8.45,54.76806],"type":"Point"}
}