{
  "type": "Feature",
  "properties": {
    "gn:admin1_code":"C",
    "gn:admin2_code":"20.0",
    "gn:asciiname":"Streamstown",
    "gn:country_code":"IE",
    "gn:dem":29,
    "gn:feature_class":"P",
    "gn:feature_code":"PPL",
    "gn:name":"Streamstown",
    "gn:population":0,
    "gn:timezone":"Europe/Dublin",
    "iso:country":"IE",
    "name:eus_x_preferred":[
        "Streamstown"
    ],
    "name:rus_x_preferred":[
        "\u0421\u0442\u0440\u0438\u043c\u0441\u0442\u0430\u0443\u043d"
    ],
    "wof:name":"Streamstown",
    "wof:placetype":"locality"
},
  "geometry": {"coordinates":[-9.5632,53.78435],"type":"Point"}
}