{
  "type": "Feature",
  "properties": {
    "gn:admin1_code":"M",
    "gn:admin2_code":"11.0",
    "gn:asciiname":"Muckross Abbey",
    "gn:country_code":"IE",
    "gn:dem":34,
    "gn:feature_class":"P",
    "gn:feature_code":"PPL",
    "gn:name":"Muckross Abbey",
    "gn:population":0,
    "gn:timezone":"Europe/Dublin",
    "iso:country":"IE",
    "name:cat_x_preferred":[
        "Muckross Abbey"
    ],
    "name:deu_x_preferred":[
        "Muckross Abbey"
    ],
    "name:eus_x_preferred":[
        "Muckross abade-etxea"
    ],
    "name:gle_x_preferred":[
        "Mainistir Mhucrois"
    ],
    "name:pol_x_preferred":[
        "Muckross Abbey"
    ],
    "name:rus_x_preferred":[
        "\u0410\u0431\u0431\u0430\u0442\u0441\u0442\u0432\u043e \u041c\u0430\u043a\u0440\u043e\u0441\u0441"
    ],
    "name:slv_x_preferred":[
        "Samostan Muckros"
    ],
    "wof:name":"Muckross Abbey",
    "wof:placetype":"locality"
},
  "geometry": {"coordinates":[-9.49159,52.02525],"type":"Point"}
}