{
  "type": "Feature",
  "properties": {
    "gn:admin1_code":"C",
    "gn:admin2_code":"20",
    "gn:asciiname":"Raheens",
    "gn:country_code":"IE",
    "gn:dem":39,
    "gn:feature_class":"P",
    "gn:feature_code":"PPL",
    "gn:name":"Raheens",
    "gn:population":0,
    "gn:timezone":"Europe/Dublin",
    "iso:country":"IE",
    "wof:name":"Raheens",
    "wof:placetype":"locality"
},
  "geometry": {"coordinates":[-9.3652,53.8444],"type":"Point"}
}