{
  "type": "Feature",
  "properties": {
    "gn:admin1_code":"L",
    "gn:admin2_code":"30",
    "gn:asciiname":"Buck's Bridge",
    "gn:country_code":"IE",
    "gn:dem":75,
    "gn:feature_class":"P",
    "gn:feature_code":"PPL",
    "gn:name":"Buck\u2019s Bridge",
    "gn:population":0,
    "gn:timezone":"Europe/Dublin",
    "iso:country":"IE",
    "wof:name":"Buck's Bridge",
    "wof:placetype":"locality"
},
  "geometry": {"coordinates":[-6.71389,52.54167],"type":"Point"}
}