{
  "type": "Feature",
  "properties": {
    "gn:admin1_code":"C",
    "gn:admin2_code":"20",
    "gn:asciiname":"Bohola",
    "gn:country_code":"IE",
    "gn:dem":44,
    "gn:feature_class":"P",
    "gn:feature_code":"PPL",
    "gn:name":"Bohola",
    "gn:population":170,
    "gn:timezone":"Europe/Dublin",
    "iso:country":"IE",
    "name:ceb_x_preferred":[
        "Bohola"
    ],
    "name:eng_x_preferred":[
        "Bohola"
    ],
    "name:eus_x_preferred":[
        "Bohola"
    ],
    "name:gle_x_preferred":[
        "Both Chomhla"
    ],
    "name:kat_x_preferred":[
        "\u10d1\u10dd\u10f0\u10dd\u10da\u10d0"
    ],
    "name:rus_x_preferred":[
        "\u0411\u043e\u0445\u043e\u043b\u0430"
    ],
    "name:spa_x_preferred":[
        "Bohola"
    ],
    "name:swe_x_preferred":[
        "Bohola"
    ],
    "wof:name":"Bohola",
    "wof:placetype":"locality",
    "wof:population":170
},
  "geometry": {"coordinates":[-9.05471,53.90162],"type":"Point"}
}