{
  "type": "Feature",
  "properties": {
    "gn:admin1_code":"L",
    "gn:admin2_code":"33.0",
    "gn:asciiname":"Essex",
    "gn:country_code":"IE",
    "gn:dem":15,
    "gn:feature_class":"P",
    "gn:feature_code":"PPL",
    "gn:name":"Essex",
    "gn:population":0,
    "gn:timezone":"Europe/Dublin",
    "iso:country":"IE",
    "wof:name":"Essex",
    "wof:placetype":"locality"
},
  "geometry": {"coordinates":[-6.26754,53.34498000000001],"type":"Point"}
}