{
  "type": "Feature",
  "properties": {
    "gn:admin1_code":"M",
    "gn:admin2_code":"26.0",
    "gn:asciiname":"Saint Kieran's",
    "gn:country_code":"IE",
    "gn:dem":46,
    "gn:feature_class":"P",
    "gn:feature_code":"PPL",
    "gn:name":"Saint Kieran\u2019s",
    "gn:population":0,
    "gn:timezone":"Europe/Dublin",
    "iso:country":"IE",
    "wof:name":"Saint Kieran's",
    "wof:placetype":"locality"
},
  "geometry": {"coordinates":[-8.06444,53.11083000000001],"type":"Point"}
}