{
  "type": "Feature",
  "properties": {
    "gn:admin1_code":"L",
    "gn:admin2_code":"29.0",
    "gn:asciiname":"Balrath South",
    "gn:country_code":"IE",
    "gn:dem":83,
    "gn:feature_class":"P",
    "gn:feature_code":"PPL",
    "gn:name":"Balrath South",
    "gn:population":0,
    "gn:timezone":"Europe/Dublin",
    "iso:country":"IE",
    "wof:name":"Balrath South",
    "wof:placetype":"locality"
},
  "geometry": {"coordinates":[-7.07266,53.59905],"type":"Point"}
}