{
  "type": "Feature",
  "properties": {
    "gn:admin1_code":"L",
    "gn:admin2_code":"13",
    "gn:asciiname":"Kildrinagh Cross Roads",
    "gn:country_code":"IE",
    "gn:dem":148,
    "gn:feature_class":"P",
    "gn:feature_code":"PPL",
    "gn:name":"Kildrinagh Cross Roads",
    "gn:population":0,
    "gn:timezone":"Europe/Dublin",
    "iso:country":"IE",
    "wof:name":"Kildrinagh Cross Roads",
    "wof:placetype":"locality"
},
  "geometry": {"coordinates":[-7.50306,52.68972],"type":"Point"}
}