{
  "type": "Feature",
  "properties": {
    "gn:admin1_code":"C",
    "gn:admin2_code":"20.0",
    "gn:asciiname":"Pollranny Sweeny",
    "gn:country_code":"IE",
    "gn:dem":47,
    "gn:feature_class":"P",
    "gn:feature_code":"PPLL",
    "gn:name":"Pollranny Sweeny",
    "gn:population":0,
    "gn:timezone":"Europe/Dublin",
    "iso:country":"IE",
    "name:eng_x_preferred":[
        "Pollranny Sweeny"
    ],
    "name:gle_x_preferred":[
        "Poll Raithn\u00ed Sweeney"
    ],
    "wof:name":"Pollranny Sweeny",
    "wof:placetype":"locality"
},
  "geometry": {"coordinates":[-9.88583,53.93417],"type":"Point"}
}