{
  "type": "Feature",
  "properties": {
    "iso:country":"IE",
    "name:eng_x_preferred":[
        "The Docks"
    ],
    "wof:name":"The Docks",
    "wof:placetype":"neighbourhood"
},
  "geometry": {"coordinates":[-9.04904,53.269194],"type":"Point"}
}