{
  "type": "Feature",
  "properties": {
    "gn:admin1_code":"C",
    "gn:admin2_code":"10.0",
    "gn:asciiname":"Belleek",
    "gn:country_code":"IE",
    "gn:dem":64,
    "gn:feature_class":"P",
    "gn:feature_code":"PPLL",
    "gn:name":"Belleek",
    "gn:population":0,
    "gn:timezone":"Europe/Dublin",
    "iso:country":"IE",
    "name:ceb_x_preferred":[
        "Belleek"
    ],
    "name:swe_x_preferred":[
        "Belleek"
    ],
    "wof:name":"Belleek",
    "wof:placetype":"locality"
},
  "geometry": {"coordinates":[-10.0925,53.49833],"type":"Point"}
}