{
  "type": "Feature",
  "properties": {
    "gn:admin1_code":"L",
    "gn:admin2_code":"30",
    "gn:asciiname":"Milltown",
    "gn:country_code":"IE",
    "gn:dem":37,
    "gn:feature_class":"P",
    "gn:feature_code":"PPL",
    "gn:name":"Milltown",
    "gn:population":0,
    "gn:timezone":"Europe/Dublin",
    "iso:country":"IE",
    "name:ceb_x_preferred":[
        "Milltown"
    ],
    "name:deu_x_preferred":[
        "Milltown"
    ],
    "name:fra_x_preferred":[
        "Milltown"
    ],
    "name:ita_x_preferred":[
        "Milltown"
    ],
    "name:nld_x_preferred":[
        "Milltown"
    ],
    "name:pol_x_preferred":[
        "Milltown"
    ],
    "name:por_x_preferred":[
        "Milltown"
    ],
    "name:rus_x_preferred":[
        "\u041c\u0438\u043b\u0442\u0430\u0443\u043d"
    ],
    "name:srp_x_preferred":[
        "\u041c\u0438\u043b\u0442\u0430\u0443\u043d"
    ],
    "name:swe_x_preferred":[
        "Milltown"
    ],
    "name:ukr_x_preferred":[
        "\u041c\u0456\u043b\u043b\u0442\u0430\u0443\u043d"
    ],
    "name:vol_x_preferred":[
        "Milltown"
    ],
    "wof:name":"Milltown",
    "wof:placetype":"locality"
},
  "geometry": {"coordinates":[-6.47389,52.58667],"type":"Point"}
}