{
  "type": "Feature",
  "properties": {
    "gn:admin1_code":"L",
    "gn:admin2_code":"15.0",
    "gn:asciiname":"Drummond",
    "gn:country_code":"IE",
    "gn:dem":80,
    "gn:feature_class":"P",
    "gn:feature_code":"PPL",
    "gn:name":"Drummond",
    "gn:population":0,
    "gn:timezone":"Europe/Dublin",
    "iso:country":"IE",
    "name:ara_x_preferred":[
        "\u062f\u0631\u0648\u0645\u0648\u0646\u062f"
    ],
    "name:ceb_x_preferred":[
        "Drummond"
    ],
    "name:ces_x_preferred":[
        "Drummond"
    ],
    "name:deu_x_preferred":[
        "Drummond"
    ],
    "name:fra_x_preferred":[
        "Drummond"
    ],
    "name:ita_x_preferred":[
        "Drummond"
    ],
    "name:jpn_x_preferred":[
        "\u30c9\u30e9\u30e2\u30f3\u30c9"
    ],
    "name:nld_x_preferred":[
        "Drummond"
    ],
    "name:pol_x_preferred":[
        "Drummond"
    ],
    "name:por_x_preferred":[
        "Drummond"
    ],
    "name:rus_x_preferred":[
        "\u0414\u0440\u0430\u043c\u043c\u043e\u043d\u0434"
    ],
    "name:spa_x_preferred":[
        "Drummond"
    ],
    "name:srp_x_preferred":[
        "\u0414\u0440\u0430\u043c\u0430\u043d\u0434"
    ],
    "name:swe_x_preferred":[
        "Drummond"
    ],
    "name:ukr_x_preferred":[
        "\u0414\u0440\u0430\u043c\u043c\u043e\u043d\u0434"
    ],
    "name:vol_x_preferred":[
        "Drummond"
    ],
    "wof:name":"Drummond",
    "wof:placetype":"locality"
},
  "geometry": {"coordinates":[-7.42556,53.16917],"type":"Point"}
}