{
  "type": "Feature",
  "properties": {
    "gn:admin1_code":"L",
    "gn:admin2_code":"01",
    "gn:asciiname":"Ballyrvan",
    "gn:country_code":"IE",
    "gn:dem":134,
    "gn:feature_class":"P",
    "gn:feature_code":"PPL",
    "gn:name":"Ballyrvan",
    "gn:population":0,
    "gn:timezone":"Europe/Dublin",
    "iso:country":"IE",
    "wof:name":"Ballyrvan",
    "wof:placetype":"locality"
},
  "geometry": {"coordinates":[-6.90694,52.76056],"type":"Point"}
}