{
  "type": "Feature",
  "properties": {
    "gn:gn_country":"IE",
    "gn:gn_fcode":"PPL",
    "gn:gn_pop":0,
    "iso:country":"IE",
    "name:cat_x_preferred":[
        "Bloomfield"
    ],
    "name:ceb_x_preferred":[
        "Bloomfield"
    ],
    "name:ces_x_preferred":[
        "Bloomfield"
    ],
    "name:deu_x_preferred":[
        "Bloomfield"
    ],
    "name:epo_x_preferred":[
        "Bloomfield"
    ],
    "name:fas_x_preferred":[
        "\u0628\u0644\u0648\u0645\u0641\u06cc\u0644\u062f"
    ],
    "name:fra_x_preferred":[
        "Bloomfield"
    ],
    "name:heb_x_preferred":[
        "\u05d1\u05dc\u05d5\u05de\u05e4\u05d9\u05dc\u05d3"
    ],
    "name:hun_x_preferred":[
        "Bloomfield"
    ],
    "name:ido_x_preferred":[
        "Bloomfield"
    ],
    "name:ita_x_preferred":[
        "Bloomfield"
    ],
    "name:jpn_x_preferred":[
        "\u30d6\u30eb\u30fc\u30e0\u30d5\u30a3\u30fc\u30eb\u30c9"
    ],
    "name:kor_x_preferred":[
        "\ube14\ub8f8\ud544\ub4dc"
    ],
    "name:nds_x_preferred":[
        "Bloomfield"
    ],
    "name:nld_x_preferred":[
        "Bloomfield"
    ],
    "name:pol_x_preferred":[
        "Bloomfield"
    ],
    "name:por_x_preferred":[
        "Bloomfield"
    ],
    "name:rus_x_preferred":[
        "\u0411\u043b\u0443\u043c\u0444\u0438\u043b\u0434"
    ],
    "name:spa_x_preferred":[
        "Bloomfield"
    ],
    "name:srp_x_preferred":[
        "\u0411\u043b\u0443\u043c\u0444\u0438\u043b\u0434"
    ],
    "name:swe_x_preferred":[
        "Bloomfield"
    ],
    "name:ukr_x_preferred":[
        "\u0411\u043b\u0443\u043c\u0444\u0456\u043b\u0434"
    ],
    "name:urd_x_preferred":[
        "\u0628\u0644\u0648\u0645 \u0641\u06cc\u0644\u0688"
    ],
    "name:vol_x_preferred":[
        "Bloomfield"
    ],
    "qs_pg:aaroncc":"IE",
    "qs_pg:gn_country":"IE",
    "qs_pg:gn_fcode":"PPL",
    "qs_pg:gn_pop":0,
    "qs_pg:name":"Bloomfield",
    "qs_pg:name_adm0":"United Kingdom",
    "qs_pg:name_adm1":"Northern Ireland",
    "qs_pg:photos":264,
    "qs_pg:photos_1k":53,
    "qs_pg:photos_9k":1,
    "qs_pg:photos_9r":4,
    "qs_pg:photos_all":264,
    "qs_pg:photos_sr":5,
    "qs_pg:pop_sr":0,
    "qs_pg:qs_pg_placetype":"neighbourhood",
    "qs_pg:qs_pg_placetype_gp":"Suburb",
    "qs_pg:woe_adm0":23424975,
    "woe:adm0_id":23424975,
    "woe:name_adm0":"United Kingdom",
    "woe:name_adm1":"Northern Ireland",
    "woe:placetype":"Suburb",
    "wof:name":"Bloomfield",
    "wof:placetype":"neighbourhood"
},
  "geometry": {"coordinates":[-6.70028,54.06667],"type":"Point"}
}