{
  "type": "Feature",
  "properties": {
    "gn:admin1_code":"U",
    "gn:admin2_code":"02",
    "gn:asciiname":"Derryvony",
    "gn:country_code":"IE",
    "gn:dem":50,
    "gn:feature_class":"P",
    "gn:feature_code":"PPLL",
    "gn:name":"Derryvony",
    "gn:population":0,
    "gn:timezone":"Europe/Dublin",
    "iso:country":"IE",
    "wof:name":"Derryvony",
    "wof:placetype":"locality"
},
  "geometry": {"coordinates":[-7.42028,54.15028],"type":"Point"}
}