{
  "type": "Feature",
  "properties": {
    "gn:admin1_code":"C",
    "gn:admin2_code":"10",
    "gn:asciiname":"Lisheen",
    "gn:country_code":"IE",
    "gn:dem":68,
    "gn:feature_class":"P",
    "gn:feature_code":"PPL",
    "gn:name":"Lisheen",
    "gn:population":0,
    "gn:timezone":"Europe/Dublin",
    "iso:country":"IE",
    "wof:name":"Lisheen",
    "wof:placetype":"locality"
},
  "geometry": {"coordinates":[-8.48333,53.41667],"type":"Point"}
}