{
  "type": "Feature",
  "properties": {
    "gn:admin1_code":"L",
    "gn:admin2_code":"13",
    "gn:asciiname":"Booly Bridge",
    "gn:country_code":"IE",
    "gn:dem":197,
    "gn:feature_class":"P",
    "gn:feature_code":"PPL",
    "gn:name":"Booly Bridge",
    "gn:population":0,
    "gn:timezone":"Europe/Dublin",
    "iso:country":"IE",
    "wof:name":"Booly Bridge",
    "wof:placetype":"locality"
},
  "geometry": {"coordinates":[-7.27833,52.43222],"type":"Point"}
}