{
  "type": "Feature",
  "properties": {
    "iso:country":"IE",
    "name:eng_x_preferred":[
        "Old Bawn Cross"
    ],
    "wof:name":"Old Bawn Cross",
    "wof:placetype":"neighbourhood"
},
  "geometry": {"coordinates":[-6.353067,53.275193],"type":"Point"}
}