{
  "type": "Feature",
  "properties": {
    "gn:admin1_code":"L",
    "gn:admin2_code":"21.0",
    "gn:asciiname":"Hurdlestown",
    "gn:country_code":"IE",
    "gn:dem":50,
    "gn:feature_class":"P",
    "gn:feature_code":"PPL",
    "gn:name":"Hurdlestown",
    "gn:population":0,
    "gn:timezone":"Europe/Dublin",
    "iso:country":"IE",
    "wof:name":"Hurdlestown",
    "wof:placetype":"locality"
},
  "geometry": {"coordinates":[-6.80815,53.70293],"type":"Point"}
}