{
  "type": "Feature",
  "properties": {
    "gn:admin1_code":"M",
    "gn:admin2_code":"04",
    "gn:asciiname":"Tanyara Bridge",
    "gn:country_code":"IE",
    "gn:dem":146,
    "gn:feature_class":"P",
    "gn:feature_code":"PPLL",
    "gn:name":"Tanyara Bridge",
    "gn:population":0,
    "gn:timezone":"Europe/Dublin",
    "iso:country":"IE",
    "wof:name":"Tanyara Bridge",
    "wof:placetype":"locality"
},
  "geometry": {"coordinates":[-8.83778,51.7925],"type":"Point"}
}