{
  "type": "Feature",
  "properties": {
    "gn:admin1_code":"M",
    "gn:admin2_code":"44.0",
    "gn:asciiname":"Cappoquinn",
    "gn:country_code":"IE",
    "gn:dem":13,
    "gn:feature_class":"P",
    "gn:feature_code":"PPL",
    "gn:name":"Cappoquinn",
    "gn:population":0,
    "gn:timezone":"Europe/Dublin",
    "iso:country":"IE",
    "wof:name":"Cappoquinn",
    "wof:placetype":"locality"
},
  "geometry": {"coordinates":[-7.85179,52.1475],"type":"Point"}
}