{
  "type": "Feature",
  "properties": {
    "gn:admin1_code":"L",
    "gn:admin2_code":"15.0",
    "gn:asciiname":"Derrylemoge",
    "gn:country_code":"IE",
    "gn:dem":106,
    "gn:feature_class":"P",
    "gn:feature_code":"PPL",
    "gn:name":"Derrylemoge",
    "gn:population":0,
    "gn:timezone":"Europe/Dublin",
    "iso:country":"IE",
    "wof:name":"Derrylemoge",
    "wof:placetype":"locality"
},
  "geometry": {"coordinates":[-7.39806,53.11333000000001],"type":"Point"}
}