{
  "type": "Feature",
  "properties": {
    "gn:admin1_code":"L",
    "gn:admin2_code":"21.0",
    "gn:asciiname":"Springville",
    "gn:country_code":"IE",
    "gn:dem":84,
    "gn:feature_class":"P",
    "gn:feature_code":"PPL",
    "gn:name":"Springville",
    "gn:population":0,
    "gn:timezone":"Europe/Dublin",
    "iso:country":"IE",
    "name:bre_x_preferred":[
        "Springville"
    ],
    "name:cat_x_preferred":[
        "Springville"
    ],
    "name:ceb_x_preferred":[
        "Springville"
    ],
    "name:ces_x_preferred":[
        "Springville"
    ],
    "name:deu_x_preferred":[
        "Springville"
    ],
    "name:fra_x_preferred":[
        "Springville"
    ],
    "name:ita_x_preferred":[
        "Springville"
    ],
    "name:nld_x_preferred":[
        "Springville"
    ],
    "name:pol_x_preferred":[
        "Springville"
    ],
    "name:por_x_preferred":[
        "Springville"
    ],
    "name:rus_x_preferred":[
        "\u0421\u043f\u0440\u0438\u043d\u0433\u0432\u0438\u043b\u043b"
    ],
    "name:srp_x_preferred":[
        "\u0421\u043f\u0440\u0438\u043d\u0433\u0432\u0438\u043b"
    ],
    "name:swe_x_preferred":[
        "Springville"
    ],
    "name:ukr_x_preferred":[
        "\u0421\u043f\u0440\u0438\u043d\u0433\u0432\u0456\u043b\u043b"
    ],
    "name:und_x_variant":[
        "Dandlestown"
    ],
    "name:vol_x_preferred":[
        "Springville"
    ],
    "wof:name":"Springville",
    "wof:placetype":"locality"
},
  "geometry": {"coordinates":[-6.9647,53.70862],"type":"Point"}
}