{
  "type": "Feature",
  "properties": {
    "gn:admin1_code":"L",
    "gn:admin2_code":"21.0",
    "gn:asciiname":"Killallon",
    "gn:country_code":"IE",
    "gn:dem":102,
    "gn:feature_class":"P",
    "gn:feature_code":"PPL",
    "gn:name":"Killallon",
    "gn:population":0,
    "gn:timezone":"Europe/Dublin",
    "iso:country":"IE",
    "wof:name":"Killallon",
    "wof:placetype":"locality"
},
  "geometry": {"coordinates":[-7.06193,53.67843000000001],"type":"Point"}
}