{
  "type": "Feature",
  "properties": {
    "gn:admin1_code":"C",
    "gn:admin2_code":"20.0",
    "gn:asciiname":"Derrynagran",
    "gn:country_code":"IE",
    "gn:dem":29,
    "gn:feature_class":"P",
    "gn:feature_code":"PPL",
    "gn:name":"Derrynagran",
    "gn:population":0,
    "gn:timezone":"Europe/Dublin",
    "iso:country":"IE",
    "wof:name":"Derrynagran",
    "wof:placetype":"locality"
},
  "geometry": {"coordinates":[-9.14037,53.98974000000001],"type":"Point"}
}