{
  "type": "Feature",
  "properties": {
    "gn:gn_country":"IE",
    "gn:gn_fcode":"PPL",
    "gn:gn_pop":0,
    "gn:population":286,
    "iso:country":"IE",
    "name:eng_x_preferred":[
        "Mungret"
    ],
    "name:gle_x_preferred":[
        "Mungairit"
    ],
    "qs_pg:aaroncc":"IE",
    "qs_pg:gn_country":"IE",
    "qs_pg:gn_fcode":"PPL",
    "qs_pg:gn_pop":0,
    "qs_pg:name":"Mungret",
    "qs_pg:name_adm0":"Ireland",
    "qs_pg:name_adm1":"Limerick",
    "qs_pg:photos":85,
    "qs_pg:photos_1k":17,
    "qs_pg:photos_9k":1,
    "qs_pg:photos_9r":3,
    "qs_pg:photos_all":85,
    "qs_pg:photos_sr":3,
    "qs_pg:pop_sr":0,
    "qs_pg:qs_pg_placetype":"locality",
    "qs_pg:qs_pg_placetype_gp":"Town",
    "qs_pg:woe_adm0":23424803,
    "woe:adm0_id":23424803,
    "woe:name_adm0":"Ireland",
    "woe:name_adm1":"Limerick",
    "woe:placetype":"Town",
    "wof:name":"Mungret",
    "wof:placetype":"locality",
    "wof:population":286
},
  "geometry": {"coordinates":[-8.69667,52.63583],"type":"Point"}
}