{
  "type": "Feature",
  "properties": {
    "gn:admin1_code":"M",
    "gn:admin2_code":"11",
    "gn:asciiname":"Lisheen",
    "gn:country_code":"IE",
    "gn:dem":199,
    "gn:feature_class":"P",
    "gn:feature_code":"PPL",
    "gn:name":"Lisheen",
    "gn:population":0,
    "gn:timezone":"Europe/Dublin",
    "iso:country":"IE",
    "wof:name":"Lisheen",
    "wof:placetype":"locality"
},
  "geometry": {"coordinates":[-9.25,52.13333],"type":"Point"}
}