{
  "type": "Feature",
  "properties": {
    "gn:admin1_code":"M",
    "gn:admin2_code":"26",
    "gn:asciiname":"Thomastown",
    "gn:cc2":"IE",
    "gn:country_code":"IE",
    "gn:dem":78,
    "gn:feature_class":"P",
    "gn:feature_code":"PPL",
    "gn:name":"Thomastown",
    "gn:population":0,
    "gn:timezone":"Europe/Dublin",
    "iso:country":"IE",
    "name:bul_x_preferred":[
        "\u0422\u043e\u043c\u0430\u0441\u0442\u0430\u0443\u043d"
    ],
    "name:ceb_x_preferred":[
        "Thomastown"
    ],
    "name:deu_x_preferred":[
        "Thomastown"
    ],
    "name:eus_x_preferred":[
        "Thomastown"
    ],
    "name:fra_x_preferred":[
        "Thomastown"
    ],
    "name:ita_x_preferred":[
        "Thomastown"
    ],
    "name:mlg_x_preferred":[
        "Thomastown"
    ],
    "name:nld_x_preferred":[
        "Thomastown"
    ],
    "name:pol_x_preferred":[
        "Thomastown"
    ],
    "name:rus_x_preferred":[
        "\u0422\u043e\u043c\u0430\u0441\u0442\u0430\u0443\u043d"
    ],
    "name:spa_x_preferred":[
        "Thomastown"
    ],
    "name:swe_x_preferred":[
        "Thomastown"
    ],
    "name:und_x_variant":[
        "Thomastown Castle"
    ],
    "wof:name":"Thomastown",
    "wof:placetype":"locality"
},
  "geometry": {"coordinates":[-8.02444,52.49417],"type":"Point"}
}