{
  "type": "Feature",
  "properties": {
    "gn:admin1_code":"L",
    "gn:admin2_code":"31",
    "gn:asciiname":"Crab Lane Cross Roads",
    "gn:country_code":"IE",
    "gn:dem":171,
    "gn:feature_class":"P",
    "gn:feature_code":"PPL",
    "gn:name":"Crab Lane Cross Roads",
    "gn:population":0,
    "gn:timezone":"Europe/Dublin",
    "iso:country":"IE",
    "wof:name":"Crab Lane Cross Roads",
    "wof:placetype":"locality"
},
  "geometry": {"coordinates":[-6.61306,52.7725],"type":"Point"}
}