{
  "type": "Feature",
  "properties": {
    "gn:admin1_code":"L",
    "gn:admin2_code":"30",
    "gn:asciiname":"Hilltown",
    "gn:country_code":"IE",
    "gn:dem":49,
    "gn:feature_class":"P",
    "gn:feature_code":"PPL",
    "gn:name":"Hilltown",
    "gn:population":0,
    "gn:timezone":"Europe/Dublin",
    "iso:country":"IE",
    "name:deu_x_preferred":[
        "Hilltown"
    ],
    "name:ita_x_preferred":[
        "Hilltown"
    ],
    "wof:name":"Hilltown",
    "wof:placetype":"locality"
},
  "geometry": {"coordinates":[-6.70639,52.27472],"type":"Point"}
}