{
  "type": "Feature",
  "properties": {
    "gn:admin1_code":"C",
    "gn:admin2_code":"20.0",
    "gn:asciiname":"Killeen",
    "gn:country_code":"IE",
    "gn:dem":25,
    "gn:feature_class":"P",
    "gn:feature_code":"PPLL",
    "gn:name":"Killeen",
    "gn:population":0,
    "gn:timezone":"Europe/Dublin",
    "iso:country":"IE",
    "name:deu_x_preferred":[
        "Killeen"
    ],
    "name:hun_x_preferred":[
        "Killeen"
    ],
    "name:nld_x_preferred":[
        "Killeen"
    ],
    "name:por_x_preferred":[
        "Killeen"
    ],
    "wof:name":"Killeen",
    "wof:placetype":"locality"
},
  "geometry": {"coordinates":[-9.33333,54.31361],"type":"Point"}
}