{
  "type": "Feature",
  "properties": {
    "gn:admin1_code":"C",
    "gn:admin2_code":"10.0",
    "gn:asciiname":"Glashnacally",
    "gn:country_code":"IE",
    "gn:dem":7,
    "gn:feature_class":"P",
    "gn:feature_code":"PPL",
    "gn:name":"Glashnacally",
    "gn:population":0,
    "gn:timezone":"Europe/Dublin",
    "iso:country":"IE",
    "wof:name":"Glashnacally",
    "wof:placetype":"locality"
},
  "geometry": {"coordinates":[-9.59694,53.27861],"type":"Point"}
}