{
  "type": "Feature",
  "properties": {
    "gn:admin1_code":"L",
    "gn:admin2_code":"21.0",
    "gn:asciiname":"Galmoystown",
    "gn:country_code":"IE",
    "gn:dem":159,
    "gn:feature_class":"P",
    "gn:feature_code":"PPL",
    "gn:name":"Galmoystown",
    "gn:population":0,
    "gn:timezone":"Europe/Dublin",
    "iso:country":"IE",
    "wof:name":"Galmoystown",
    "wof:placetype":"locality"
},
  "geometry": {"coordinates":[-7.12031,53.70045],"type":"Point"}
}