{
  "type": "Feature",
  "properties": {
    "gn:admin1_code":"M",
    "gn:admin2_code":"26",
    "gn:asciiname":"Graystown",
    "gn:country_code":"IE",
    "gn:dem":168,
    "gn:feature_class":"P",
    "gn:feature_code":"PPLL",
    "gn:name":"Graystown",
    "gn:population":0,
    "gn:timezone":"Europe/Dublin",
    "iso:country":"IE",
    "wof:name":"Graystown",
    "wof:placetype":"locality"
},
  "geometry": {"coordinates":[-7.70694,52.56111],"type":"Point"}
}