{
  "type": "Feature",
  "properties": {
    "gn:admin1_code":"M",
    "gn:admin2_code":"04",
    "gn:asciiname":"Coole West",
    "gn:country_code":"IE",
    "gn:dem":127,
    "gn:feature_class":"P",
    "gn:feature_code":"PPL",
    "gn:name":"Coole West",
    "gn:population":0,
    "gn:timezone":"Europe/Dublin",
    "iso:country":"IE",
    "wof:name":"Coole West",
    "wof:placetype":"locality"
},
  "geometry": {"coordinates":[-8.47083,51.96639],"type":"Point"}
}