{
  "type": "Feature",
  "properties": {
    "gn:admin1_code":"M",
    "gn:admin2_code":"42",
    "gn:asciiname":"Annagh",
    "gn:country_code":"IE",
    "gn:dem":42,
    "gn:feature_class":"P",
    "gn:feature_code":"PPL",
    "gn:name":"Annagh",
    "gn:population":0,
    "gn:timezone":"Europe/Dublin",
    "iso:country":"IE",
    "wof:name":"Annagh",
    "wof:placetype":"locality"
},
  "geometry": {"coordinates":[-8.45167,52.67722],"type":"Point"}
}