{
  "type": "Feature",
  "properties": {
    "gn:admin1_code":"M",
    "gn:admin2_code":"11",
    "gn:asciiname":"Murreagh",
    "gn:country_code":"IE",
    "gn:dem":9,
    "gn:feature_class":"P",
    "gn:feature_code":"PPL",
    "gn:name":"Murreagh",
    "gn:population":0,
    "gn:timezone":"Europe/Dublin",
    "iso:country":"IE",
    "name:eng_x_preferred":[
        "Murreagh"
    ],
    "name:gle_x_preferred":[
        "An Mhuirioch"
    ],
    "wof:name":"Murreagh",
    "wof:placetype":"locality"
},
  "geometry": {"coordinates":[-10.36389,52.18694],"type":"Point"}
}