{
  "type": "Feature",
  "properties": {
    "gn:admin1_code":"M",
    "gn:admin2_code":"04",
    "gn:asciiname":"Templenoe",
    "gn:country_code":"IE",
    "gn:dem":31,
    "gn:feature_class":"P",
    "gn:feature_code":"PPL",
    "gn:name":"Templenoe",
    "gn:population":0,
    "gn:timezone":"Europe/Dublin",
    "iso:country":"IE",
    "name:eus_x_preferred":[
        "Templenoe"
    ],
    "name:rus_x_preferred":[
        "\u0422\u0435\u043c\u043f\u043b\u043d\u043e"
    ],
    "wof:name":"Templenoe",
    "wof:placetype":"locality"
},
  "geometry": {"coordinates":[-9.68333,51.86667],"type":"Point"}
}