{
  "type": "Feature",
  "properties": {
    "gn:admin1_code":"M",
    "gn:admin2_code":"04",
    "gn:asciiname":"Kilcummer Bridge",
    "gn:country_code":"IE",
    "gn:dem":36,
    "gn:feature_class":"P",
    "gn:feature_code":"PPL",
    "gn:name":"Kilcummer Bridge",
    "gn:population":0,
    "gn:timezone":"Europe/Dublin",
    "iso:country":"IE",
    "wof:name":"Kilcummer Bridge",
    "wof:placetype":"locality"
},
  "geometry": {"coordinates":[-8.45167,52.15556],"type":"Point"}
}