{
  "type": "Feature",
  "properties": {
    "gn:admin1_code":"M",
    "gn:admin2_code":"44",
    "gn:asciiname":"Bohernamuck Cross Roads",
    "gn:country_code":"IE",
    "gn:dem":54,
    "gn:feature_class":"P",
    "gn:feature_code":"PPL",
    "gn:name":"Bohernamuck Cross Roads",
    "gn:population":0,
    "gn:timezone":"Europe/Dublin",
    "iso:country":"IE",
    "wof:name":"Bohernamuck Cross Roads",
    "wof:placetype":"locality"
},
  "geometry": {"coordinates":[-7.34278,52.14722],"type":"Point"}
}