{
  "type": "Feature",
  "properties": {
    "gn:admin1_code":"C",
    "gn:admin2_code":"14.0",
    "gn:asciiname":"Newtowngore",
    "gn:country_code":"IE",
    "gn:dem":57,
    "gn:feature_class":"P",
    "gn:feature_code":"PPL",
    "gn:name":"Newtowngore",
    "gn:population":0,
    "gn:timezone":"Europe/Dublin",
    "iso:country":"IE",
    "name:eus_x_preferred":[
        "Newtowngore"
    ],
    "name:gle_x_preferred":[
        "An D\u00facharraig"
    ],
    "name:kat_x_preferred":[
        "\u10dc\u10d8\u10e3\u10e2\u10d0\u10e3\u10dc\u10d2\u10dd\u10e0\u10d8"
    ],
    "name:rus_x_preferred":[
        "\u041d\u044c\u044e\u0442\u0430\u0443\u043d\u0433\u043e\u0440"
    ],
    "name:urd_x_preferred":[
        "\u0646\u06cc\u0648 \u0679\u0627\u0624\u0646"
    ],
    "wof:name":"Newtowngore",
    "wof:placetype":"locality"
},
  "geometry": {"coordinates":[-7.67584,54.04326],"type":"Point"}
}