{
  "type": "Feature",
  "properties": {
    "gn:admin1_code":"L",
    "gn:admin2_code":"23.0",
    "gn:asciiname":"Clondelara",
    "gn:country_code":"IE",
    "gn:dem":44,
    "gn:feature_class":"P",
    "gn:feature_code":"PPL",
    "gn:name":"Clondelara",
    "gn:population":0,
    "gn:timezone":"Europe/Dublin",
    "iso:country":"IE",
    "wof:name":"Clondelara",
    "wof:placetype":"locality"
},
  "geometry": {"coordinates":[-7.99417,53.27],"type":"Point"}
}