{
  "type": "Feature",
  "properties": {
    "gn:admin1_code":"C",
    "gn:admin2_code":"20.0",
    "gn:asciiname":"Knockroe",
    "gn:country_code":"IE",
    "gn:dem":26,
    "gn:feature_class":"P",
    "gn:feature_code":"PPLL",
    "gn:name":"Knockroe",
    "gn:population":0,
    "gn:timezone":"Europe/Dublin",
    "iso:country":"IE",
    "wof:name":"Knockroe",
    "wof:placetype":"locality"
},
  "geometry": {"coordinates":[-9.12694,54.15444],"type":"Point"}
}