{
  "type": "Feature",
  "properties": {
    "gn:admin1_code":"L",
    "gn:admin2_code":"19",
    "gn:asciiname":"Lurgangreen",
    "gn:country_code":"IE",
    "gn:dem":4,
    "gn:feature_class":"P",
    "gn:feature_code":"PPL",
    "gn:name":"Lurgangreen",
    "gn:population":0,
    "gn:timezone":"Europe/Dublin",
    "iso:country":"IE",
    "wof:name":"Lurgangreen",
    "wof:placetype":"locality"
},
  "geometry": {"coordinates":[-6.38389,53.94333],"type":"Point"}
}