{
  "type": "Feature",
  "properties": {
    "gn:admin1_code":"L",
    "gn:admin2_code":"12.0",
    "gn:asciiname":"Tullylost Cross Roads",
    "gn:country_code":"IE",
    "gn:dem":79,
    "gn:feature_class":"P",
    "gn:feature_code":"PPL",
    "gn:name":"Tullylost Cross Roads",
    "gn:population":0,
    "gn:timezone":"Europe/Dublin",
    "iso:country":"IE",
    "wof:name":"Tullylost Cross Roads",
    "wof:placetype":"locality"
},
  "geometry": {"coordinates":[-7.00083,53.20639],"type":"Point"}
}