{
  "type": "Feature",
  "properties": {
    "gn:admin1_code":"C",
    "gn:admin2_code":"20",
    "gn:asciiname":"The Triangle",
    "gn:country_code":"IE",
    "gn:dem":56,
    "gn:feature_class":"P",
    "gn:feature_code":"PPLL",
    "gn:name":"The Triangle",
    "gn:population":0,
    "gn:timezone":"Europe/Dublin",
    "iso:country":"IE",
    "wof:name":"The Triangle",
    "wof:placetype":"locality"
},
  "geometry": {"coordinates":[-9.39612,53.77566],"type":"Point"}
}