{
  "type": "Feature",
  "properties": {
    "iso:country":"IE",
    "qs_pg:aaroncc":"IE",
    "qs_pg:name":"Stradbally",
    "qs_pg:name_adm0":"Ireland",
    "qs_pg:name_adm1":"Laois",
    "qs_pg:photos":2242,
    "qs_pg:photos_1k":454,
    "qs_pg:photos_9k":26,
    "qs_pg:photos_9r":14,
    "qs_pg:photos_all":5925,
    "qs_pg:photos_sr":16,
    "qs_pg:pop_sr":0,
    "qs_pg:qs_pg_placetype":"localadmin",
    "qs_pg:qs_pg_placetype_gp":"LocalAdmin",
    "qs_pg:woe_adm0":23424803,
    "woe:adm0_id":23424803,
    "woe:name_adm0":"Ireland",
    "woe:name_adm1":"Laois",
    "woe:placetype":"LocalAdmin",
    "wof:name":"Stradbally",
    "wof:placetype":"localadmin"
},
  "geometry": {"coordinates":[-7.151429,53.01229],"type":"Point"}
}