{
  "type": "Feature",
  "properties": {
    "iso:country":"IE",
    "name:cat_x_preferred":[
        "Stradbally"
    ],
    "name:ceb_x_preferred":[
        "Stradbally"
    ],
    "name:eus_x_preferred":[
        "Stradbally"
    ],
    "name:gle_x_preferred":[
        "An Sr\u00e1idbhaile"
    ],
    "name:lit_x_preferred":[
        "Stradbalis"
    ],
    "name:nld_x_preferred":[
        "Stradbally"
    ],
    "name:rus_x_preferred":[
        "\u0421\u0442\u0440\u0430\u0434\u0431\u0430\u043b\u043b\u0438"
    ],
    "name:swe_x_preferred":[
        "Stradbally"
    ],
    "qs_pg:aaroncc":"IE",
    "qs_pg:name":"Stradbally",
    "qs_pg:name_adm0":"Ireland",
    "qs_pg:name_adm1":"Laois",
    "qs_pg:photos":2242,
    "qs_pg:photos_1k":454,
    "qs_pg:photos_9k":26,
    "qs_pg:photos_9r":14,
    "qs_pg:photos_all":5925,
    "qs_pg:photos_sr":16,
    "qs_pg:pop_sr":0,
    "qs_pg:qs_pg_placetype":"localadmin",
    "qs_pg:qs_pg_placetype_gp":"LocalAdmin",
    "qs_pg:woe_adm0":23424803,
    "woe:adm0_id":23424803,
    "woe:name_adm0":"Ireland",
    "woe:name_adm1":"Laois",
    "woe:placetype":"LocalAdmin",
    "wof:name":"Stradbally",
    "wof:placetype":"localadmin"
},
  "geometry": {"coordinates":[-7.151429,53.01229],"type":"Point"}
}