{
  "type": "Feature",
  "properties": {
    "gn:admin1_code":"M",
    "gn:admin2_code":"11",
    "gn:asciiname":"Kilflynn",
    "gn:country_code":"IE",
    "gn:dem":59,
    "gn:feature_class":"P",
    "gn:feature_code":"PPL",
    "gn:name":"Kilflynn",
    "gn:population":126,
    "gn:timezone":"Europe/Dublin",
    "iso:country":"IE",
    "name:ceb_x_preferred":[
        "Kilflynn"
    ],
    "name:eus_x_preferred":[
        "Kilflynn"
    ],
    "name:gle_x_preferred":[
        "Cill Flainn"
    ],
    "name:rus_x_preferred":[
        "\u041a\u0438\u043b\u0444\u043b\u0438\u043d\u043d"
    ],
    "name:spa_x_preferred":[
        "Kilflynn"
    ],
    "name:swe_x_preferred":[
        "Kilflynn"
    ],
    "name:und_x_variant":[
        "Kilflyn",
        "Kilflynn"
    ],
    "wof:name":"Kilflynn",
    "wof:placetype":"locality",
    "wof:population":126
},
  "geometry": {"coordinates":[-9.62523,52.35077],"type":"Point"}
}