{
  "type": "Feature",
  "properties": {
    "gn:admin1_code":"L",
    "gn:admin2_code":"35.0",
    "gn:asciiname":"Dermotstown",
    "gn:country_code":"IE",
    "gn:dem":60,
    "gn:feature_class":"P",
    "gn:feature_code":"PPL",
    "gn:name":"Dermotstown",
    "gn:population":0,
    "gn:timezone":"Europe/Dublin",
    "iso:country":"IE",
    "wof:name":"Dermotstown",
    "wof:placetype":"locality"
},
  "geometry": {"coordinates":[-6.22417,53.59],"type":"Point"}
}