{
  "type": "Feature",
  "properties": {
    "gn:admin1_code":"L",
    "gn:admin2_code":"13.0",
    "gn:asciiname":"Moneenroe",
    "gn:country_code":"IE",
    "gn:dem":156,
    "gn:feature_class":"P",
    "gn:feature_code":"PPL",
    "gn:name":"Moneenroe",
    "gn:population":761,
    "gn:timezone":"Europe/Dublin",
    "iso:country":"IE",
    "name:ceb_x_preferred":[
        "Moneenroe"
    ],
    "name:rus_x_preferred":[
        "\u041c\u043e\u043d\u0438\u043d\u0440\u043e"
    ],
    "name:spa_x_preferred":[
        "Moneenroe"
    ],
    "name:swe_x_preferred":[
        "Moneenroe"
    ],
    "wof:name":"Moneenroe",
    "wof:placetype":"locality",
    "wof:population":761
},
  "geometry": {"coordinates":[-7.15549,52.84],"type":"Point"}
}