{
  "type": "Feature",
  "properties": {
    "gn:admin1_code":"C",
    "gn:admin2_code":"10.0",
    "gn:asciiname":"Moneymore",
    "gn:country_code":"IE",
    "gn:dem":12,
    "gn:feature_class":"P",
    "gn:feature_code":"PPL",
    "gn:name":"Moneymore",
    "gn:population":0,
    "gn:timezone":"Europe/Dublin",
    "iso:country":"IE",
    "name:ceb_x_preferred":[
        "Moneymore"
    ],
    "name:eus_x_preferred":[
        "Moneymore"
    ],
    "name:fas_x_preferred":[
        "\u0645\u0627\u0646\u06cc\u0645\u0648\u0631"
    ],
    "name:ita_x_preferred":[
        "Moneymore"
    ],
    "name:mri_x_preferred":[
        "Moneymore"
    ],
    "name:msa_x_preferred":[
        "Moneymore"
    ],
    "name:nld_x_preferred":[
        "Moneymore"
    ],
    "name:nor_x_preferred":[
        "Moneymore"
    ],
    "name:pli_x_preferred":[
        "\u092e\u094b\u0928\u0947\u092f\u094d\u092e\u094b\u0930\u0947"
    ],
    "name:spa_x_preferred":[
        "Moneymore"
    ],
    "name:swe_x_preferred":[
        "Moneymore"
    ],
    "wof:name":"Moneymore",
    "wof:placetype":"locality"
},
  "geometry": {"coordinates":[-8.8825,53.26],"type":"Point"}
}