{
  "type": "Feature",
  "properties": {
    "gn:admin1_code":"L",
    "gn:admin2_code":"21.0",
    "gn:asciiname":"Crossakiel",
    "gn:country_code":"IE",
    "gn:dem":153,
    "gn:feature_class":"P",
    "gn:feature_code":"PPL",
    "gn:name":"Crossakiel",
    "gn:population":0,
    "gn:timezone":"Europe/Dublin",
    "iso:country":"IE",
    "wof:name":"Crossakiel",
    "wof:placetype":"locality"
},
  "geometry": {"coordinates":[-7.02095,53.71398],"type":"Point"}
}