{
  "type": "Feature",
  "properties": {
    "gn:admin1_code":"M",
    "gn:admin2_code":"04",
    "gn:asciiname":"Spital",
    "gn:country_code":"IE",
    "gn:dem":99,
    "gn:feature_class":"P",
    "gn:feature_code":"PPL",
    "gn:name":"Spital",
    "gn:population":0,
    "gn:timezone":"Europe/Dublin",
    "iso:country":"IE",
    "wof:name":"Spital",
    "wof:placetype":"locality"
},
  "geometry": {"coordinates":[-8.65472,52.25083],"type":"Point"}
}