{
  "type": "Feature",
  "properties": {
    "gn:admin1_code":"M",
    "gn:admin2_code":"04",
    "gn:asciiname":"Spital",
    "gn:country_code":"IE",
    "gn:dem":99,
    "gn:feature_class":"P",
    "gn:feature_code":"PPL",
    "gn:name":"Spital",
    "gn:population":0,
    "gn:timezone":"Europe/Dublin",
    "iso:country":"IE",
    "name:bre_x_preferred":[
        "Spital"
    ],
    "name:ceb_x_preferred":[
        "Spital"
    ],
    "name:deu_x_preferred":[
        "Spital"
    ],
    "name:fin_x_preferred":[
        "Spital"
    ],
    "name:ita_x_preferred":[
        "Spital"
    ],
    "name:pol_x_preferred":[
        "Spital"
    ],
    "name:swe_x_preferred":[
        "Spital"
    ],
    "wof:name":"Spital",
    "wof:placetype":"locality"
},
  "geometry": {"coordinates":[-8.65472,52.25083],"type":"Point"}
}