{
  "type": "Feature",
  "properties": {
    "gn:admin1_code":"C",
    "gn:admin2_code":"14.0",
    "gn:asciiname":"Lavaur",
    "gn:country_code":"IE",
    "gn:dem":112,
    "gn:feature_class":"P",
    "gn:feature_code":"PPLL",
    "gn:name":"Lavaur",
    "gn:population":0,
    "gn:timezone":"Europe/Dublin",
    "iso:country":"IE",
    "name:ceb_x_preferred":[
        "Lavaur"
    ],
    "name:dan_x_preferred":[
        "Lavaur"
    ],
    "name:deu_x_preferred":[
        "Lavaur"
    ],
    "name:epo_x_preferred":[
        "Lavaur"
    ],
    "name:fra_x_preferred":[
        "Lavaur"
    ],
    "name:ita_x_preferred":[
        "Lavaur"
    ],
    "name:nds_x_preferred":[
        "Lavaur"
    ],
    "name:nld_x_preferred":[
        "Lavaur"
    ],
    "name:oci_x_preferred":[
        "La Vaur"
    ],
    "name:pol_x_preferred":[
        "Lavaur"
    ],
    "name:por_x_preferred":[
        "Lavaur"
    ],
    "name:rus_x_preferred":[
        "\u041b\u0430\u0432\u043e\u0440"
    ],
    "name:scn_x_preferred":[
        "Lavaur"
    ],
    "name:slk_x_preferred":[
        "Lavaur"
    ],
    "name:spa_x_preferred":[
        "Lavaur"
    ],
    "name:swe_x_preferred":[
        "Lavaur"
    ],
    "name:ukr_x_preferred":[
        "\u041b\u0430\u0432\u043e\u0440"
    ],
    "wof:name":"Lavaur",
    "wof:placetype":"locality"
},
  "geometry": {"coordinates":[-8.02528,54.0775],"type":"Point"}
}