{
  "type": "Feature",
  "properties": {
    "gn:admin1_code":"C",
    "gn:admin2_code":"14.0",
    "gn:asciiname":"Lavaur",
    "gn:country_code":"IE",
    "gn:dem":112,
    "gn:feature_class":"P",
    "gn:feature_code":"PPLL",
    "gn:name":"Lavaur",
    "gn:population":0,
    "gn:timezone":"Europe/Dublin",
    "iso:country":"IE",
    "wof:name":"Lavaur",
    "wof:placetype":"locality"
},
  "geometry": {"coordinates":[-8.02528,54.0775],"type":"Point"}
}