{
  "type": "Feature",
  "properties": {
    "gn:gn_country":"IE",
    "gn:gn_fcode":"PPL",
    "gn:gn_pop":0,
    "iso:country":"IE",
    "qs_pg:aaroncc":"IE",
    "qs_pg:gn_country":"IE",
    "qs_pg:gn_fcode":"PPL",
    "qs_pg:gn_pop":0,
    "qs_pg:name":"Kilmurry",
    "qs_pg:name_adm0":"Ireland",
    "qs_pg:name_adm1":"Clare",
    "qs_pg:photos":370,
    "qs_pg:photos_1k":75,
    "qs_pg:photos_9k":2,
    "qs_pg:photos_9r":5,
    "qs_pg:photos_all":512,
    "qs_pg:photos_sr":6,
    "qs_pg:pop_sr":0,
    "qs_pg:qs_pg_placetype":"localadmin",
    "qs_pg:qs_pg_placetype_gp":"LocalAdmin",
    "qs_pg:woe_adm0":23424803,
    "woe:adm0_id":23424803,
    "woe:name_adm0":"Ireland",
    "woe:name_adm1":"Clare",
    "woe:placetype":"LocalAdmin",
    "wof:name":"Kilmurry",
    "wof:placetype":"localadmin"
},
  "geometry": {"coordinates":[-9.45417,52.80111],"type":"Point"}
}