{
  "type": "Feature",
  "properties": {
    "gn:admin1_code":"U",
    "gn:admin2_code":"02",
    "gn:asciiname":"Claragh",
    "gn:country_code":"IE",
    "gn:dem":113,
    "gn:feature_class":"P",
    "gn:feature_code":"PPLL",
    "gn:name":"Claragh",
    "gn:population":0,
    "gn:timezone":"Europe/Dublin",
    "iso:country":"IE",
    "wof:name":"Claragh",
    "wof:placetype":"locality"
},
  "geometry": {"coordinates":[-7.27806,54.085],"type":"Point"}
}