{
  "type": "Feature",
  "properties": {
    "gn:admin1_code":"M",
    "gn:admin2_code":"4.0",
    "gn:asciiname":"Fisherman's Row",
    "gn:country_code":"IE",
    "gn:dem":8,
    "gn:feature_class":"P",
    "gn:feature_code":"PPL",
    "gn:name":"Fisherman's Row",
    "gn:population":0,
    "gn:timezone":"Europe/Dublin",
    "iso:country":"IE",
    "wof:name":"Fisherman's Row",
    "wof:placetype":"locality"
},
  "geometry": {"coordinates":[-9.3731,51.48408],"type":"Point"}
}