{
  "type": "Feature",
  "properties": {
    "gn:admin1_code":"M",
    "gn:admin2_code":"4.0",
    "gn:asciiname":"Coosheen",
    "gn:country_code":"IE",
    "gn:dem":29,
    "gn:feature_class":"P",
    "gn:feature_code":"PPL",
    "gn:name":"Coosheen",
    "gn:population":0,
    "gn:timezone":"Europe/Dublin",
    "iso:country":"IE",
    "wof:name":"Coosheen",
    "wof:placetype":"locality"
},
  "geometry": {"coordinates":[-9.52523,51.51924],"type":"Point"}
}