{
  "type": "Feature",
  "properties": {
    "gn:admin1_code":"L",
    "gn:admin2_code":"31.0",
    "gn:asciiname":"Newrath Bridge",
    "gn:country_code":"IE",
    "gn:dem":17,
    "gn:feature_class":"P",
    "gn:feature_code":"PPLL",
    "gn:name":"Newrath Bridge",
    "gn:population":0,
    "gn:timezone":"Europe/Dublin",
    "iso:country":"IE",
    "wof:name":"Newrath Bridge",
    "wof:placetype":"locality"
},
  "geometry": {"coordinates":[-6.085,53.00111],"type":"Point"}
}