{
  "type": "Feature",
  "properties": {
    "gn:admin1_code":"C",
    "gn:admin2_code":"25.0",
    "gn:asciiname":"Carrowreagh",
    "gn:country_code":"IE",
    "gn:dem":101,
    "gn:feature_class":"P",
    "gn:feature_code":"PPLL",
    "gn:name":"Carrowreagh",
    "gn:population":0,
    "gn:timezone":"Europe/Dublin",
    "iso:country":"IE",
    "wof:name":"Carrowreagh",
    "wof:placetype":"locality"
},
  "geometry": {"coordinates":[-8.7225,54.04],"type":"Point"}
}