{
  "type": "Feature",
  "properties": {
    "gn:admin1_code":"U",
    "gn:admin2_code":"22.0",
    "gn:asciiname":"Bryanhiller",
    "gn:country_code":"IE",
    "gn:dem":74,
    "gn:feature_class":"P",
    "gn:feature_code":"PPLL",
    "gn:name":"Bryanhiller",
    "gn:population":0,
    "gn:timezone":"Europe/Dublin",
    "iso:country":"IE",
    "wof:name":"Bryanhiller",
    "wof:placetype":"locality"
},
  "geometry": {"coordinates":[-6.83806,54.21889],"type":"Point"}
}