{
  "type": "Feature",
  "properties": {
    "gn:admin1_code":"C",
    "gn:admin2_code":"20.0",
    "gn:asciiname":"Knocknahorna",
    "gn:country_code":"IE",
    "gn:dem":63,
    "gn:feature_class":"P",
    "gn:feature_code":"PPLL",
    "gn:name":"Knocknahorna",
    "gn:population":0,
    "gn:timezone":"Europe/Dublin",
    "iso:country":"IE",
    "wof:name":"Knocknahorna",
    "wof:placetype":"locality"
},
  "geometry": {"coordinates":[-9.47694,54.08722],"type":"Point"}
}