{
  "type": "Feature",
  "properties": {
    "gn:admin1_code":"L",
    "gn:admin2_code":"12",
    "gn:asciiname":"Athgarvan",
    "gn:country_code":"IE",
    "gn:dem":98,
    "gn:feature_class":"P",
    "gn:feature_code":"PPL",
    "gn:name":"Athgarvan",
    "gn:population":1016,
    "gn:timezone":"Europe/Dublin",
    "iso:country":"IE",
    "wof:name":"Athgarvan",
    "wof:placetype":"locality",
    "wof:population":1016
},
  "geometry": {"coordinates":[-6.78173,53.15229],"type":"Point"}
}