{
  "type": "Feature",
  "properties": {
    "gn:admin1_code":"L",
    "gn:admin2_code":"12",
    "gn:asciiname":"Athgarvan",
    "gn:country_code":"IE",
    "gn:dem":98,
    "gn:feature_class":"P",
    "gn:feature_code":"PPL",
    "gn:name":"Athgarvan",
    "gn:population":1016,
    "gn:timezone":"Europe/Dublin",
    "iso:country":"IE",
    "name:ceb_x_preferred":[
        "Athgarvan"
    ],
    "name:gle_x_preferred":[
        "\u00c1th Garbh\u00e1in"
    ],
    "name:rus_x_preferred":[
        "\u0410\u0442\u0433\u0430\u0440\u0432\u0430\u043d"
    ],
    "name:spa_x_preferred":[
        "Athgarvan"
    ],
    "name:swe_x_preferred":[
        "Athgarvan"
    ],
    "wof:name":"Athgarvan",
    "wof:placetype":"locality",
    "wof:population":1016
},
  "geometry": {"coordinates":[-6.78173,53.15229],"type":"Point"}
}