{
  "type": "Feature",
  "properties": {
    "gn:admin1_code":"U",
    "gn:admin2_code":"22",
    "gn:asciiname":"Drumacreeve",
    "gn:country_code":"IE",
    "gn:dem":109,
    "gn:feature_class":"P",
    "gn:feature_code":"PPLL",
    "gn:name":"Drumacreeve",
    "gn:population":0,
    "gn:timezone":"Europe/Dublin",
    "iso:country":"IE",
    "wof:name":"Drumacreeve",
    "wof:placetype":"locality"
},
  "geometry": {"coordinates":[-7.14694,54.12722],"type":"Point"}
}