{
  "type": "Feature",
  "properties": {
    "gn:admin1_code":"U",
    "gn:admin2_code":"22.0",
    "gn:asciiname":"Mullan",
    "gn:country_code":"IE",
    "gn:dem":46,
    "gn:feature_class":"P",
    "gn:feature_code":"PPL",
    "gn:name":"Mullan",
    "gn:population":0,
    "gn:timezone":"Europe/Dublin",
    "iso:country":"IE",
    "wof:name":"Mullan",
    "wof:placetype":"locality"
},
  "geometry": {"coordinates":[-6.92028,54.36306],"type":"Point"}
}