{
  "type": "Feature",
  "properties": {
    "gn:admin1_code":"M",
    "gn:admin2_code":"11",
    "gn:asciiname":"Lisnakealwee",
    "gn:country_code":"IE",
    "gn:dem":115,
    "gn:feature_class":"P",
    "gn:feature_code":"PPL",
    "gn:name":"Lisnakealwee",
    "gn:population":0,
    "gn:timezone":"Europe/Dublin",
    "iso:country":"IE",
    "name:eng_x_preferred":[
        "Lisnakealwee"
    ],
    "name:gle_x_preferred":[
        "Lios na Caolbhu\u00ed"
    ],
    "wof:name":"Lisnakealwee",
    "wof:placetype":"locality"
},
  "geometry": {"coordinates":[-10.1725,52.27167],"type":"Point"}
}