{
  "type": "Feature",
  "properties": {
    "gn:admin1_code":"M",
    "gn:admin2_code":"04",
    "gn:asciiname":"Driminidy",
    "gn:country_code":"IE",
    "gn:dem":75,
    "gn:feature_class":"P",
    "gn:feature_code":"PPL",
    "gn:name":"Driminidy",
    "gn:population":0,
    "gn:timezone":"Europe/Dublin",
    "iso:country":"IE",
    "wof:name":"Driminidy",
    "wof:placetype":"locality"
},
  "geometry": {"coordinates":[-9.22417,51.63417000000001],"type":"Point"}
}