{
  "type": "Feature",
  "properties": {
    "gn:admin1_code":"L",
    "gn:admin2_code":"18",
    "gn:asciiname":"Moydow",
    "gn:country_code":"IE",
    "gn:dem":77,
    "gn:feature_class":"P",
    "gn:feature_code":"PPL",
    "gn:name":"Moydow",
    "gn:population":0,
    "gn:timezone":"Europe/Dublin",
    "iso:country":"IE",
    "name:eus_x_preferred":[
        "Moydow"
    ],
    "name:gle_x_preferred":[
        "Maigh Dumha"
    ],
    "name:rus_x_preferred":[
        "\u041c\u043e\u0439\u0434\u043e\u0443"
    ],
    "wof:name":"Moydow",
    "wof:placetype":"locality"
},
  "geometry": {"coordinates":[-7.76667,53.66667],"type":"Point"}
}