{
  "type": "Feature",
  "properties": {
    "gn:admin1_code":"M",
    "gn:admin2_code":"04",
    "gn:asciiname":"Sally Port",
    "gn:country_code":"IE",
    "gn:dem":37,
    "gn:feature_class":"P",
    "gn:feature_code":"PPLL",
    "gn:name":"Sally Port",
    "gn:population":0,
    "gn:timezone":"Europe/Dublin",
    "iso:country":"IE",
    "wof:name":"Sally Port",
    "wof:placetype":"locality"
},
  "geometry": {"coordinates":[-8.49972,51.69222],"type":"Point"}
}