{
  "type": "Feature",
  "properties": {
    "gn:admin1_code":"L",
    "gn:admin2_code":"21.0",
    "gn:asciiname":"Saraghstown",
    "gn:country_code":"IE",
    "gn:dem":92,
    "gn:feature_class":"P",
    "gn:feature_code":"PPL",
    "gn:name":"Saraghstown",
    "gn:population":0,
    "gn:timezone":"Europe/Dublin",
    "iso:country":"IE",
    "wof:name":"Saraghstown",
    "wof:placetype":"locality"
},
  "geometry": {"coordinates":[-7.02701,53.69076],"type":"Point"}
}