{
  "type": "Feature",
  "properties": {
    "gn:admin1_code":"L",
    "gn:admin2_code":"15.0",
    "gn:asciiname":"Shanahoe",
    "gn:country_code":"IE",
    "gn:dem":99,
    "gn:feature_class":"P",
    "gn:feature_code":"PPL",
    "gn:name":"Shanahoe",
    "gn:population":0,
    "gn:timezone":"Europe/Dublin",
    "iso:country":"IE",
    "name:eus_x_preferred":[
        "Shanahoe"
    ],
    "name:rus_x_preferred":[
        "\u0428\u0430\u043d\u0430\u0445\u043e"
    ],
    "wof:name":"Shanahoe",
    "wof:placetype":"locality"
},
  "geometry": {"coordinates":[-7.42472,52.92528000000001],"type":"Point"}
}