{
  "type": "Feature",
  "properties": {
    "gn:admin1_code":"L",
    "gn:admin2_code":"21.0",
    "gn:asciiname":"Mullagh",
    "gn:country_code":"IE",
    "gn:dem":128,
    "gn:feature_class":"P",
    "gn:feature_code":"PPL",
    "gn:name":"Mullagh",
    "gn:population":0,
    "gn:timezone":"Europe/Dublin",
    "iso:country":"IE",
    "name:nld_x_preferred":[
        "Mullagh"
    ],
    "name:rus_x_preferred":[
        "\u041c\u0430\u043b\u043b\u0430\u0445"
    ],
    "wof:name":"Mullagh",
    "wof:placetype":"locality"
},
  "geometry": {"coordinates":[-7.1528,53.73987],"type":"Point"}
}