{
  "type": "Feature",
  "properties": {
    "gn:country":"IE",
    "gn:fcode":"PPL",
    "gn:population":0,
    "iso:country":"IE",
    "name:bul_x_preferred":[
        "\u0411\u0435\u043d\u0435\u0442\u0446\u0431\u0440\u0438\u0434\u0433\u0435"
    ],
    "name:ceb_x_preferred":[
        "Bennettsbridge"
    ],
    "name:eng_x_preferred":[
        "Bennettsbridge"
    ],
    "name:eus_x_preferred":[
        "Bennettsbridge"
    ],
    "name:gle_x_preferred":[
        "Droichead Bin\u00e9id"
    ],
    "name:nld_x_preferred":[
        "Bennettsbridge"
    ],
    "name:rus_x_preferred":[
        "\u0411\u0435\u043d\u043d\u0435\u0442\u0441\u0431\u0440\u0438\u0434\u0436"
    ],
    "name:spa_x_preferred":[
        "Bennettsbridge"
    ],
    "name:swe_x_preferred":[
        "Bennettsbridge"
    ],
    "qs_pg:aaroncc":"IE",
    "qs_pg:gn_country":"IE",
    "qs_pg:gn_fcode":"PPL",
    "qs_pg:gn_pop":0,
    "qs_pg:name":"Bennettsbridge",
    "qs_pg:name_adm0":"Ireland",
    "qs_pg:name_adm1":"Kilkenny",
    "qs_pg:photos":31,
    "qs_pg:photos_1k":6,
    "qs_pg:photos_9k":1,
    "qs_pg:photos_9r":2,
    "qs_pg:photos_all":31,
    "qs_pg:photos_sr":2,
    "qs_pg:pop_sr":0,
    "qs_pg:qs_pg_placetype":"locality",
    "qs_pg:qs_pg_placetype_gp":"Town",
    "qs_pg:woe_adm0":23424803,
    "woe:adm0_id":23424803,
    "woe:name_adm0":"Ireland",
    "woe:name_adm1":"Kilkenny",
    "woe:placetype":"Town",
    "wof:name":"Bennettsbridge",
    "wof:placetype":"locality",
    "wof:population":729
},
  "geometry": {"coordinates":[-7.18,52.59194],"type":"Point"}
}