{
  "type": "Feature",
  "properties": {
    "gn:admin1_code":"L",
    "gn:admin2_code":"31.0",
    "gn:asciiname":"Tullytusk",
    "gn:country_code":"IE",
    "gn:dem":135,
    "gn:feature_class":"P",
    "gn:feature_code":"PPL",
    "gn:name":"Tullytusk",
    "gn:population":0,
    "gn:timezone":"Europe/Dublin",
    "iso:country":"IE",
    "wof:name":"Tullytusk",
    "wof:placetype":"locality"
},
  "geometry": {"coordinates":[-6.18333,52.92056],"type":"Point"}
}