{
  "type": "Feature",
  "properties": {
    "gn:admin1_code":"M",
    "gn:admin2_code":"26",
    "gn:asciiname":"Galbertstown",
    "gn:country_code":"IE",
    "gn:dem":98,
    "gn:feature_class":"P",
    "gn:feature_code":"PPL",
    "gn:name":"Galbertstown",
    "gn:population":0,
    "gn:timezone":"Europe/Dublin",
    "iso:country":"IE",
    "wof:name":"Galbertstown",
    "wof:placetype":"locality"
},
  "geometry": {"coordinates":[-7.85194,52.62583000000001],"type":"Point"}
}