{
  "type": "Feature",
  "properties": {
    "gn:admin1_code":"L",
    "gn:admin2_code":"12.0",
    "gn:asciiname":"Cloncumber",
    "gn:country_code":"IE",
    "gn:dem":75,
    "gn:feature_class":"P",
    "gn:feature_code":"PPL",
    "gn:name":"Cloncumber",
    "gn:population":0,
    "gn:timezone":"Europe/Dublin",
    "iso:country":"IE",
    "wof:name":"Cloncumber",
    "wof:placetype":"locality"
},
  "geometry": {"coordinates":[-6.90056,53.25417],"type":"Point"}
}