{
  "type": "Feature",
  "properties": {
    "gn:admin1_code":"C",
    "gn:admin2_code":"25.0",
    "gn:asciiname":"Magheraboy",
    "gn:country_code":"IE",
    "gn:dem":16,
    "gn:feature_class":"P",
    "gn:feature_code":"PPL",
    "gn:name":"Magheraboy",
    "gn:population":0,
    "gn:timezone":"Europe/Dublin",
    "iso:country":"IE",
    "name:gle_x_preferred":[
        "Machaire Bui"
    ],
    "wof:name":"Magheraboy",
    "wof:placetype":"locality"
},
  "geometry": {"coordinates":[-8.49444,54.26889],"type":"Point"}
}