{
  "type": "Feature",
  "properties": {
    "gn:country":"IE",
    "iso:country":"IE",
    "qs_pg:aaroncc":"IE",
    "qs_pg:gn_country":"IE",
    "qs_pg:name":"Lissadill North",
    "qs_pg:name_adm0":"Ireland",
    "qs_pg:name_adm1":"Sligo",
    "qs_pg:photos":76,
    "qs_pg:photos_1k":15,
    "qs_pg:photos_9k":3,
    "qs_pg:photos_9r":5,
    "qs_pg:photos_all":583,
    "qs_pg:photos_sr":3,
    "qs_pg:pop_sr":0,
    "qs_pg:qs_pg_placetype":"localadmin",
    "qs_pg:qs_pg_placetype_gp":"LocalAdmin",
    "qs_pg:woe_adm0":23424803,
    "woe:adm0_id":23424803,
    "woe:name_adm0":"Ireland",
    "woe:name_adm1":"Sligo",
    "woe:placetype":"LocalAdmin",
    "wof:name":"Lissadill North",
    "wof:placetype":"localadmin"
},
  "geometry": {"coordinates":[-8.55144,54.405443],"type":"Point"}
}