{
  "type": "Feature",
  "properties": {
    "gn:admin1_code":"C",
    "gn:admin2_code":"10.0",
    "gn:asciiname":"Kilgill",
    "gn:country_code":"IE",
    "gn:dem":27,
    "gn:feature_class":"P",
    "gn:feature_code":"PPLL",
    "gn:name":"Kilgill",
    "gn:population":0,
    "gn:timezone":"Europe/Dublin",
    "iso:country":"IE",
    "wof:name":"Kilgill",
    "wof:placetype":"locality"
},
  "geometry": {"coordinates":[-8.9225,53.40444],"type":"Point"}
}