{
  "type": "Feature",
  "properties": {
    "gn:admin1_code":"L",
    "gn:admin2_code":"21.0",
    "gn:asciiname":"Oldtown",
    "gn:country_code":"IE",
    "gn:dem":68,
    "gn:feature_class":"P",
    "gn:feature_code":"PPL",
    "gn:name":"Oldtown",
    "gn:population":0,
    "gn:timezone":"Europe/Dublin",
    "iso:country":"IE",
    "name:ceb_x_preferred":[
        "Oldtown"
    ],
    "name:deu_x_preferred":[
        "Oldtown"
    ],
    "name:pol_x_preferred":[
        "Oldtown"
    ],
    "name:rus_x_preferred":[
        "\u041e\u043b\u0434\u0442\u0430\u0443\u043d"
    ],
    "name:srp_x_preferred":[
        "\u041e\u043b\u0434\u0442\u0430\u0443\u043d"
    ],
    "name:swe_x_preferred":[
        "Oldtown"
    ],
    "wof:name":"Oldtown",
    "wof:placetype":"locality"
},
  "geometry": {"coordinates":[-6.80043,53.67448],"type":"Point"}
}