{
  "type": "Feature",
  "properties": {
    "gn:admin1_code":"C",
    "gn:admin2_code":"10.0",
    "gn:asciiname":"Doon",
    "gn:country_code":"IE",
    "gn:dem":65,
    "gn:feature_class":"P",
    "gn:feature_code":"PPL",
    "gn:name":"Doon",
    "gn:population":0,
    "gn:timezone":"Europe/Dublin",
    "iso:country":"IE",
    "name:ceb_x_preferred":[
        "Doon"
    ],
    "name:deu_x_preferred":[
        "Doon"
    ],
    "name:fra_x_preferred":[
        "Doon"
    ],
    "name:ita_x_preferred":[
        "Doon"
    ],
    "name:pol_x_preferred":[
        "Doon"
    ],
    "name:swe_x_preferred":[
        "Doon"
    ],
    "wof:name":"Doon",
    "wof:placetype":"locality"
},
  "geometry": {"coordinates":[-8.37833,53.37833000000001],"type":"Point"}
}