{
  "type": "Feature",
  "properties": {
    "gn:admin1_code":"U",
    "gn:admin2_code":"06",
    "gn:asciiname":"Plaster",
    "gn:country_code":"IE",
    "gn:dem":33,
    "gn:feature_class":"P",
    "gn:feature_code":"PPLL",
    "gn:name":"Plaster",
    "gn:population":0,
    "gn:timezone":"Europe/Dublin",
    "iso:country":"IE",
    "name:ara_x_preferred":[
        "\u0642\u0635\u0627\u0631\u0629"
    ],
    "name:arg_x_preferred":[
        "Cheso"
    ],
    "name:bel_x_preferred":[
        "\u0422\u044b\u043d\u043a\u043e\u045e\u043a\u0430"
    ],
    "name:cat_x_preferred":[
        "Guix"
    ],
    "name:ces_x_preferred":[
        "Om\u00edtka"
    ],
    "name:deu_x_preferred":[
        "Putz"
    ],
    "name:ell_x_preferred":[
        "\u0393\u03cd\u03c8\u03bf\u03c2"
    ],
    "name:epo_x_preferred":[
        "Gipso"
    ],
    "name:est_x_preferred":[
        "Krohv"
    ],
    "name:eus_x_preferred":[
        "Igeltsu"
    ],
    "name:fin_x_preferred":[
        "Rappaus"
    ],
    "name:fra_x_preferred":[
        "Pl\u00e2tre"
    ],
    "name:heb_x_preferred":[
        "\u05d8\u05d9\u05d7"
    ],
    "name:hin_x_preferred":[
        "\u092a\u094d\u0932\u093e\u0938\u094d\u091f\u0930"
    ],
    "name:hrv_x_preferred":[
        "\u017dbuka"
    ],
    "name:hun_x_preferred":[
        "Vakolat"
    ],
    "name:ita_x_preferred":[
        "Intonaco"
    ],
    "name:kor_x_preferred":[
        "\ud50c\ub77c\uc2a4\ud130"
    ],
    "name:kur_x_preferred":[
        "\u015e\u00eal"
    ],
    "name:lmo_x_preferred":[
        "Stabilidura"
    ],
    "name:msa_x_preferred":[
        "Plaster"
    ],
    "name:nah_x_preferred":[
        "Tezoquitl"
    ],
    "name:nap_x_preferred":[
        "Ntuonaco"
    ],
    "name:nld_x_preferred":[
        "Pleister"
    ],
    "name:pol_x_preferred":[
        "G\u0142ad\u017a szpachlowa"
    ],
    "name:por_x_preferred":[
        "Gesso"
    ],
    "name:ron_x_preferred":[
        "Ipsos"
    ],
    "name:rus_x_preferred":[
        "\u0428\u0442\u0443\u043a\u0430\u0442\u0443\u0440\u043a\u0430"
    ],
    "name:scn_x_preferred":[
        "Jissu"
    ],
    "name:sco_x_preferred":[
        "Plaister"
    ],
    "name:slk_x_preferred":[
        "Omietka"
    ],
    "name:spa_x_preferred":[
        "Yeso"
    ],
    "name:swe_x_preferred":[
        "Puts"
    ],
    "name:tam_x_preferred":[
        "\u0baa\u0bc2\u0b9a\u0bcd\u0b9a\u0bc1"
    ],
    "name:tel_x_preferred":[
        "\u0c2a\u0c4d\u0c32\u0c3e\u0c38\u0c4d\u0c1f\u0c30\u0c4d"
    ],
    "name:tha_x_preferred":[
        "\u0e1b\u0e39\u0e19\u0e1b\u0e25\u0e32\u0e2a\u0e40\u0e15\u0e2d\u0e23\u0e4c"
    ],
    "name:tur_x_preferred":[
        "Al\u00e7\u0131"
    ],
    "wof:name":"Plaster",
    "wof:placetype":"locality"
},
  "geometry": {"coordinates":[-7.52722,54.98389],"type":"Point"}
}