{
  "type": "Feature",
  "properties": {
    "gn:admin1_code":"L",
    "gn:admin2_code":"30",
    "gn:asciiname":"Wood Village",
    "gn:country_code":"IE",
    "gn:dem":-9999,
    "gn:feature_class":"P",
    "gn:feature_code":"PPL",
    "gn:name":"Wood Village",
    "gn:population":0,
    "gn:timezone":"Europe/Dublin",
    "iso:country":"IE",
    "wof:name":"Wood Village",
    "wof:placetype":"locality"
},
  "geometry": {"coordinates":[-6.82083,52.19972],"type":"Point"}
}