{
  "type": "Feature",
  "properties": {
    "gn:admin1_code":"L",
    "gn:admin2_code":"13",
    "gn:asciiname":"Colliery",
    "gn:country_code":"IE",
    "gn:dem":196,
    "gn:feature_class":"P",
    "gn:feature_code":"PPL",
    "gn:name":"Colliery",
    "gn:population":0,
    "gn:timezone":"Europe/Dublin",
    "iso:country":"IE",
    "wof:name":"Colliery",
    "wof:placetype":"locality"
},
  "geometry": {"coordinates":[-7.22889,52.82722],"type":"Point"}
}