{
  "type": "Feature",
  "properties": {
    "iso:country":"IE",
    "name:ceb_x_preferred":[
        "Carlingford"
    ],
    "name:ces_x_preferred":[
        "Carlingford"
    ],
    "name:slk_x_preferred":[
        "Carlingford"
    ],
    "name:swe_x_preferred":[
        "Carlingford"
    ],
    "qs_pg:aaroncc":"IE",
    "qs_pg:name":"Carlingford",
    "qs_pg:name_adm0":"Ireland",
    "qs_pg:name_adm1":"Louth",
    "qs_pg:photos":1,
    "qs_pg:photos_1k":1,
    "qs_pg:photos_9k":9,
    "qs_pg:photos_9r":9,
    "qs_pg:photos_all":1934,
    "qs_pg:photos_sr":1,
    "qs_pg:pop_sr":0,
    "qs_pg:qs_pg_placetype":"localadmin",
    "qs_pg:qs_pg_placetype_gp":"LocalAdmin",
    "qs_pg:woe_adm0":23424803,
    "woe:adm0_id":23424803,
    "woe:name_adm0":"Ireland",
    "woe:name_adm1":"Louth",
    "woe:placetype":"LocalAdmin",
    "wof:name":"Carlingford",
    "wof:placetype":"localadmin"
},
  "geometry": {"coordinates":[-6.185753,54.040202],"type":"Point"}
}