{
  "type": "Feature",
  "properties": {
    "gn:admin1_code":"M",
    "gn:admin2_code":"11",
    "gn:asciiname":"Broughane Cross Roads",
    "gn:country_code":"IE",
    "gn:dem":231,
    "gn:feature_class":"P",
    "gn:feature_code":"PPLL",
    "gn:name":"Broughane Cross Roads",
    "gn:population":0,
    "gn:timezone":"Europe/Dublin",
    "iso:country":"IE",
    "wof:name":"Broughane Cross Roads",
    "wof:placetype":"locality"
},
  "geometry": {"coordinates":[-9.505,52.27917],"type":"Point"}
}