{
  "type": "Feature",
  "properties": {
    "iso:country":"IE",
    "qs_pg:aaroncc":"IE",
    "qs_pg:name":"Trumra",
    "qs_pg:name_adm0":"Ireland",
    "qs_pg:name_adm1":"Laois",
    "qs_pg:photos":27,
    "qs_pg:photos_1k":5,
    "qs_pg:photos_9k":1,
    "qs_pg:photos_9r":2,
    "qs_pg:photos_all":27,
    "qs_pg:photos_sr":2,
    "qs_pg:pop_sr":0,
    "qs_pg:qs_pg_placetype":"localadmin",
    "qs_pg:qs_pg_placetype_gp":"LocalAdmin",
    "qs_pg:woe_adm0":23424803,
    "woe:adm0_id":23424803,
    "woe:name_adm0":"Ireland",
    "woe:name_adm1":"Laois",
    "woe:placetype":"LocalAdmin",
    "wof:name":"Trumra",
    "wof:placetype":"localadmin"
},
  "geometry": {"coordinates":[-7.41944,52.98472],"type":"Point"}
}