{
  "type": "Feature",
  "properties": {
    "gn:country":"IE",
    "gn:fcode":"PPL",
    "gn:population":0,
    "iso:country":"IE",
    "qs_pg:aaroncc":"IE",
    "qs_pg:gn_country":"IE",
    "qs_pg:gn_fcode":"PPL",
    "qs_pg:gn_pop":0,
    "qs_pg:name":"Rathcor",
    "qs_pg:name_adm0":"Ireland",
    "qs_pg:name_adm1":"Louth",
    "qs_pg:photos":262,
    "qs_pg:photos_1k":53,
    "qs_pg:photos_9k":1,
    "qs_pg:photos_9r":4,
    "qs_pg:photos_all":262,
    "qs_pg:photos_sr":5,
    "qs_pg:pop_sr":0,
    "qs_pg:qs_pg_placetype":"locality",
    "qs_pg:qs_pg_placetype_gp":"Town",
    "qs_pg:woe_adm0":23424803,
    "woe:adm0_id":23424803,
    "woe:name_adm0":"Ireland",
    "woe:name_adm1":"Louth",
    "woe:placetype":"Town",
    "wof:name":"Rathcor",
    "wof:placetype":"locality"
},
  "geometry": {"coordinates":[-6.19389,53.98528],"type":"Point"}
}