{
  "type": "Feature",
  "properties": {
    "gn:admin1_code":"M",
    "gn:admin2_code":"04",
    "gn:asciiname":"Glengarriff",
    "gn:country_code":"IE",
    "gn:dem":14,
    "gn:feature_class":"P",
    "gn:feature_code":"PPL",
    "gn:name":"Glengarriff",
    "gn:population":250,
    "gn:timezone":"Europe/Dublin",
    "iso:country":"IE",
    "name:cat_x_preferred":[
        "Glengarriff"
    ],
    "name:ceb_x_preferred":[
        "Glengarriff"
    ],
    "name:deu_x_preferred":[
        "Glengarriff"
    ],
    "name:eng_x_preferred":[
        "Glengarriff"
    ],
    "name:eus_x_preferred":[
        "Glengarriff"
    ],
    "name:fas_x_preferred":[
        "\u06af\u0644\u0646\u06af\u0627\u0631\u06cc\u0641"
    ],
    "name:gle_x_preferred":[
        "An Gleann Garbh"
    ],
    "name:ita_x_preferred":[
        "Glengarriff"
    ],
    "name:nld_x_preferred":[
        "Glengarriff"
    ],
    "name:pol_x_preferred":[
        "Glengarriff"
    ],
    "name:rus_x_preferred":[
        "\u0413\u043b\u0435\u043d\u0433\u0430\u0440\u0438\u0444\u0444"
    ],
    "name:rus_x_variant":[
        "\u0413\u043b\u0435\u043d\u0433\u0430\u0440\u0440\u0438\u0444\u0444"
    ],
    "name:spa_x_preferred":[
        "Glengarriff"
    ],
    "name:swe_x_preferred":[
        "Glengarriff"
    ],
    "name:und_x_variant":[
        "Glengariff"
    ],
    "wof:name":"Glengarriff",
    "wof:placetype":"locality",
    "wof:population":250
},
  "geometry": {"coordinates":[-9.55,51.75],"type":"Point"}
}