{
  "type": "Feature",
  "properties": {
    "gn:admin1_code":"M",
    "gn:admin2_code":"11",
    "gn:asciiname":"New Chapel Cross",
    "gn:country_code":"IE",
    "gn:dem":27,
    "gn:feature_class":"P",
    "gn:feature_code":"PPL",
    "gn:name":"New Chapel Cross",
    "gn:population":0,
    "gn:timezone":"Europe/Dublin",
    "iso:country":"IE",
    "wof:name":"New Chapel Cross",
    "wof:placetype":"locality"
},
  "geometry": {"coordinates":[-10.16667,51.85139],"type":"Point"}
}