{
  "type": "Feature",
  "properties": {
    "gn:admin1_code":"L",
    "gn:admin2_code":"19",
    "gn:asciiname":"Ballymakenny",
    "gn:country_code":"IE",
    "gn:dem":85,
    "gn:feature_class":"P",
    "gn:feature_code":"PPL",
    "gn:name":"Ballymakenny",
    "gn:population":0,
    "gn:timezone":"Europe/Dublin",
    "iso:country":"IE",
    "wof:name":"Ballymakenny",
    "wof:placetype":"locality"
},
  "geometry": {"coordinates":[-6.34444,53.76889],"type":"Point"}
}