{
  "type": "Feature",
  "properties": {
    "gn:admin1_code":"C",
    "gn:admin2_code":"20.0",
    "gn:asciiname":"Claggarnagh West",
    "gn:country_code":"IE",
    "gn:dem":51,
    "gn:feature_class":"P",
    "gn:feature_code":"PPL",
    "gn:name":"Claggarnagh West",
    "gn:population":0,
    "gn:timezone":"Europe/Dublin",
    "iso:country":"IE",
    "wof:name":"Claggarnagh West",
    "wof:placetype":"locality"
},
  "geometry": {"coordinates":[-9.4788,53.92943],"type":"Point"}
}