{
  "type": "Feature",
  "properties": {
    "gn:admin1_code":"C",
    "gn:admin2_code":"20.0",
    "gn:asciiname":"Ballintleva",
    "gn:country_code":"IE",
    "gn:dem":39,
    "gn:feature_class":"P",
    "gn:feature_code":"PPL",
    "gn:name":"Ballintleva",
    "gn:population":0,
    "gn:timezone":"Europe/Dublin",
    "iso:country":"IE",
    "wof:name":"Ballintleva",
    "wof:placetype":"locality"
},
  "geometry": {"coordinates":[-9.46079,53.84192],"type":"Point"}
}