{
  "type": "Feature",
  "properties": {
    "gn:country":"IE",
    "gn:fcode":"PPL",
    "gn:population":0,
    "iso:country":"IE",
    "name:und_x_variant":[
        "Monasterboice"
    ],
    "qs_pg:aaroncc":"IE",
    "qs_pg:gn_country":"IE",
    "qs_pg:gn_fcode":"PPL",
    "qs_pg:gn_pop":0,
    "qs_pg:name":"Newtown Monasterboice",
    "qs_pg:name_adm0":"Ireland",
    "qs_pg:name_adm1":"Louth",
    "qs_pg:photos":596,
    "qs_pg:photos_1k":121,
    "qs_pg:photos_9k":3,
    "qs_pg:photos_9r":5,
    "qs_pg:photos_all":596,
    "qs_pg:photos_sr":8,
    "qs_pg:pop_sr":0,
    "qs_pg:qs_pg_placetype":"locality",
    "qs_pg:qs_pg_placetype_gp":"Town",
    "qs_pg:woe_adm0":23424803,
    "woe:adm0_id":23424803,
    "woe:name_adm0":"Ireland",
    "woe:name_adm1":"Louth",
    "woe:placetype":"Town",
    "wof:name":"Newtown Monasterboice",
    "wof:placetype":"locality"
},
  "geometry": {"coordinates":[-6.40529,53.76627],"type":"Point"}
}