{
  "type": "Feature",
  "properties": {
    "gn:admin1_code":"L",
    "gn:admin2_code":"21",
    "gn:asciiname":"Dunderry",
    "gn:country_code":"IE",
    "gn:dem":61,
    "gn:feature_class":"P",
    "gn:feature_code":"PPL",
    "gn:name":"Dunderry",
    "gn:population":186,
    "gn:timezone":"Europe/Dublin",
    "iso:country":"IE",
    "wof:name":"Dunderry",
    "wof:placetype":"locality",
    "wof:population":186
},
  "geometry": {"coordinates":[-6.77296,53.60746999999999],"type":"Point"}
}