{
  "type": "Feature",
  "properties": {
    "gn:country":"IE",
    "gn:fcode":"PPL",
    "gn:population":0,
    "iso:country":"IE",
    "name:ceb_x_preferred":[
        "Tyrrellspass"
    ],
    "name:eng_x_preferred":[
        "Tyrrellspass"
    ],
    "name:eus_x_preferred":[
        "Tyrrellspass"
    ],
    "name:fas_x_preferred":[
        "\u062a\u06cc\u0631\u0644\u0633\u067e\u0627\u0633"
    ],
    "name:gle_x_preferred":[
        "Bealach an Tirialaigh"
    ],
    "name:nld_x_preferred":[
        "Tyrrellspass"
    ],
    "name:rus_x_preferred":[
        "\u0422\u0438\u0440\u0440\u0435\u043b\u0441\u043f\u0430\u0441\u0441"
    ],
    "name:spa_x_preferred":[
        "Tyrrellspass"
    ],
    "name:swe_x_preferred":[
        "Tyrrellspass"
    ],
    "name:und_x_variant":[
        "Tyrrelspass"
    ],
    "qs_pg:aaroncc":"IE",
    "qs_pg:gn_country":"IE",
    "qs_pg:gn_fcode":"PPL",
    "qs_pg:gn_pop":0,
    "qs_pg:name":"Tyrrellspass",
    "qs_pg:name_adm0":"Ireland",
    "qs_pg:name_adm1":"Westmeath",
    "qs_pg:photos":200,
    "qs_pg:photos_1k":41,
    "qs_pg:photos_9k":1,
    "qs_pg:photos_9r":4,
    "qs_pg:photos_all":200,
    "qs_pg:photos_sr":4,
    "qs_pg:pop_sr":0,
    "qs_pg:qs_pg_placetype":"locality",
    "qs_pg:qs_pg_placetype_gp":"Town",
    "qs_pg:woe_adm0":23424803,
    "woe:adm0_id":23424803,
    "woe:name_adm0":"Ireland",
    "woe:name_adm1":"Westmeath",
    "woe:placetype":"Town",
    "wof:name":"Tyrrellspass",
    "wof:placetype":"locality",
    "wof:population":506
},
  "geometry": {"coordinates":[-7.37361,53.38889],"type":"Point"}
}