{
  "type": "Feature",
  "properties": {
    "gn:admin1_code":"C",
    "gn:admin2_code":"20.0",
    "gn:asciiname":"Mullaghnacross",
    "gn:country_code":"IE",
    "gn:dem":29,
    "gn:feature_class":"P",
    "gn:feature_code":"PPLL",
    "gn:name":"Mullaghnacross",
    "gn:population":0,
    "gn:timezone":"Europe/Dublin",
    "iso:country":"IE",
    "wof:name":"Mullaghnacross",
    "wof:placetype":"locality"
},
  "geometry": {"coordinates":[-9.25361,54.2425],"type":"Point"}
}