{
  "type": "Feature",
  "properties": {
    "gn:admin1_code":"L",
    "gn:admin2_code":"13",
    "gn:asciiname":"Bruckana",
    "gn:country_code":"IE",
    "gn:dem":135,
    "gn:feature_class":"P",
    "gn:feature_code":"PPL",
    "gn:name":"Bruckana",
    "gn:population":0,
    "gn:timezone":"Europe/Dublin",
    "iso:country":"IE",
    "wof:name":"Bruckana",
    "wof:placetype":"locality"
},
  "geometry": {"coordinates":[-7.64222,52.77361],"type":"Point"}
}