{
  "type": "Feature",
  "properties": {
    "gn:admin1_code":"M",
    "gn:admin2_code":"11",
    "gn:asciiname":"Banane Bridge",
    "gn:country_code":"IE",
    "gn:dem":169,
    "gn:feature_class":"P",
    "gn:feature_code":"PPLL",
    "gn:name":"Banane Bridge",
    "gn:population":0,
    "gn:timezone":"Europe/Dublin",
    "iso:country":"IE",
    "wof:name":"Banane Bridge",
    "wof:placetype":"locality"
},
  "geometry": {"coordinates":[-9.5375,51.82361],"type":"Point"}
}