{
  "type": "Feature",
  "properties": {
    "gn:admin1_code":"C",
    "gn:admin2_code":"20.0",
    "gn:asciiname":"Ballyknock",
    "gn:country_code":"IE",
    "gn:dem":63,
    "gn:feature_class":"P",
    "gn:feature_code":"PPL",
    "gn:name":"Ballyknock",
    "gn:population":0,
    "gn:timezone":"Europe/Dublin",
    "iso:country":"IE",
    "wof:name":"Ballyknock",
    "wof:placetype":"locality"
},
  "geometry": {"coordinates":[-9.31424,53.96621999999999],"type":"Point"}
}