{
  "type": "Feature",
  "properties": {
    "iso:country":"IE",
    "qs_pg:aaroncc":"IE",
    "qs_pg:name":"Tullamore Urban",
    "qs_pg:name_adm0":"Ireland",
    "qs_pg:name_adm1":"Offaly",
    "qs_pg:photos":1,
    "qs_pg:photos_1k":1,
    "qs_pg:photos_9k":3,
    "qs_pg:photos_9r":6,
    "qs_pg:photos_all":760,
    "qs_pg:photos_sr":1,
    "qs_pg:pop_sr":0,
    "qs_pg:qs_pg_placetype":"localadmin",
    "qs_pg:qs_pg_placetype_gp":"LocalAdmin",
    "qs_pg:woe_adm0":23424803,
    "woe:adm0_id":23424803,
    "woe:name_adm0":"Ireland",
    "woe:name_adm1":"Offaly",
    "woe:placetype":"LocalAdmin",
    "wof:name":"Tullamore Urban",
    "wof:placetype":"localadmin"
},
  "geometry": {"coordinates":[-7.492203,53.276608],"type":"Point"}
}