{
  "type": "Feature",
  "properties": {
    "gn:admin1_code":"L",
    "gn:admin2_code":"13",
    "gn:asciiname":"Brittas Cross Roads",
    "gn:country_code":"IE",
    "gn:dem":174,
    "gn:feature_class":"P",
    "gn:feature_code":"PPL",
    "gn:name":"Brittas Cross Roads",
    "gn:population":0,
    "gn:timezone":"Europe/Dublin",
    "iso:country":"IE",
    "wof:name":"Brittas Cross Roads",
    "wof:placetype":"locality"
},
  "geometry": {"coordinates":[-7.43833,52.67722],"type":"Point"}
}