{
  "type": "Feature",
  "properties": {
    "gn:admin1_code":"M",
    "gn:admin2_code":"04",
    "gn:asciiname":"Ballybrack",
    "gn:country_code":"IE",
    "gn:dem":8,
    "gn:feature_class":"P",
    "gn:feature_code":"PPL",
    "gn:name":"Ballybrack",
    "gn:population":0,
    "gn:timezone":"Europe/Dublin",
    "iso:country":"IE",
    "wof:name":"Ballybrack",
    "wof:placetype":"locality"
},
  "geometry": {"coordinates":[-9.61306,51.49917],"type":"Point"}
}