{
  "type": "Feature",
  "properties": {
    "gn:admin1_code":"M",
    "gn:admin2_code":"04",
    "gn:asciiname":"Ballybrack",
    "gn:country_code":"IE",
    "gn:dem":8,
    "gn:feature_class":"P",
    "gn:feature_code":"PPL",
    "gn:name":"Ballybrack",
    "gn:population":0,
    "gn:timezone":"Europe/Dublin",
    "iso:country":"IE",
    "name:eus_x_preferred":[
        "Ballybrack"
    ],
    "name:pol_x_preferred":[
        "Ballybrack"
    ],
    "name:rus_x_preferred":[
        "\u0411\u0430\u043b\u043b\u0438\u0431\u0440\u0430\u043a"
    ],
    "wof:name":"Ballybrack",
    "wof:placetype":"locality"
},
  "geometry": {"coordinates":[-9.61306,51.49917],"type":"Point"}
}