{
  "type": "Feature",
  "properties": {
    "gn:admin1_code":"M",
    "gn:admin2_code":"04",
    "gn:asciiname":"Monanveel",
    "gn:country_code":"IE",
    "gn:dem":185,
    "gn:feature_class":"P",
    "gn:feature_code":"PPL",
    "gn:name":"Monanveel",
    "gn:population":0,
    "gn:timezone":"Europe/Dublin",
    "iso:country":"IE",
    "wof:name":"Monanveel",
    "wof:placetype":"locality"
},
  "geometry": {"coordinates":[-8.83333,52.06667],"type":"Point"}
}