{
  "type": "Feature",
  "properties": {
    "gn:admin1_code":"L",
    "gn:admin2_code":"23",
    "gn:asciiname":"Fivealley",
    "gn:country_code":"IE",
    "gn:dem":63,
    "gn:feature_class":"P",
    "gn:feature_code":"PPL",
    "gn:name":"Fivealley",
    "gn:population":0,
    "gn:timezone":"Europe/Dublin",
    "iso:country":"IE",
    "wof:name":"Fivealley",
    "wof:placetype":"locality"
},
  "geometry": {"coordinates":[-7.83583,53.15],"type":"Point"}
}