{
  "type": "Feature",
  "properties": {
    "gn:admin1_code":"M",
    "gn:admin2_code":"11",
    "gn:asciiname":"Ross Behy",
    "gn:country_code":"IE",
    "gn:dem":1,
    "gn:feature_class":"P",
    "gn:feature_code":"PPL",
    "gn:name":"Ross Behy",
    "gn:population":0,
    "gn:timezone":"Europe/Dublin",
    "iso:country":"IE",
    "wof:name":"Ross Behy",
    "wof:placetype":"locality"
},
  "geometry": {"coordinates":[-9.9775,52.05417],"type":"Point"}
}