{
  "type": "Feature",
  "properties": {
    "gn:admin1_code":"M",
    "gn:admin2_code":"04",
    "gn:asciiname":"Ballykenly Bridge",
    "gn:country_code":"IE",
    "gn:dem":44,
    "gn:feature_class":"P",
    "gn:feature_code":"PPL",
    "gn:name":"Ballykenly Bridge",
    "gn:population":0,
    "gn:timezone":"Europe/Dublin",
    "iso:country":"IE",
    "wof:name":"Ballykenly Bridge",
    "wof:placetype":"locality"
},
  "geometry": {"coordinates":[-8.35194,52.21194000000001],"type":"Point"}
}