{
  "type": "Feature",
  "properties": {
    "gn:admin1_code":"M",
    "gn:admin2_code":"04",
    "gn:asciiname":"Tooreenavuscaun",
    "gn:country_code":"IE",
    "gn:dem":209,
    "gn:feature_class":"P",
    "gn:feature_code":"PPL",
    "gn:name":"Tooreenavuscaun",
    "gn:population":0,
    "gn:timezone":"Europe/Dublin",
    "iso:country":"IE",
    "wof:name":"Tooreenavuscaun",
    "wof:placetype":"locality"
},
  "geometry": {"coordinates":[-9.11722,52.17083],"type":"Point"}
}