{
  "type": "Feature",
  "properties": {
    "gn:admin1_code":"M",
    "gn:admin2_code":"04",
    "gn:asciiname":"Churchtown",
    "gn:country_code":"IE",
    "gn:dem":16,
    "gn:feature_class":"P",
    "gn:feature_code":"PPL",
    "gn:name":"Churchtown",
    "gn:population":0,
    "gn:timezone":"Europe/Dublin",
    "iso:country":"IE",
    "name:ceb_x_preferred":[
        "Churchtown"
    ],
    "name:deu_x_preferred":[
        "Churchtown"
    ],
    "name:nld_x_preferred":[
        "Churchtown"
    ],
    "name:pol_x_preferred":[
        "Churchtown"
    ],
    "name:swe_x_preferred":[
        "Churchtown"
    ],
    "wof:name":"Churchtown",
    "wof:placetype":"locality"
},
  "geometry": {"coordinates":[-8.12806,51.91361],"type":"Point"}
}