{
  "type": "Feature",
  "properties": {
    "gn:admin1_code":"L",
    "gn:admin2_code":"18",
    "gn:asciiname":"Bawn Cross Roads",
    "gn:country_code":"IE",
    "gn:dem":77,
    "gn:feature_class":"P",
    "gn:feature_code":"PPL",
    "gn:name":"Bawn Cross Roads",
    "gn:population":0,
    "gn:timezone":"Europe/Dublin",
    "iso:country":"IE",
    "wof:name":"Bawn Cross Roads",
    "wof:placetype":"locality"
},
  "geometry": {"coordinates":[-7.76667,53.66667],"type":"Point"}
}