{
  "type": "Feature",
  "properties": {
    "gn:admin1_code":"M",
    "gn:admin2_code":"11",
    "gn:asciiname":"Flesk Bridge",
    "gn:country_code":"IE",
    "gn:dem":78,
    "gn:feature_class":"P",
    "gn:feature_code":"PPLL",
    "gn:name":"Flesk Bridge",
    "gn:population":0,
    "gn:timezone":"Europe/Dublin",
    "iso:country":"IE",
    "wof:name":"Flesk Bridge",
    "wof:placetype":"locality"
},
  "geometry": {"coordinates":[-9.40528,52.03056],"type":"Point"}
}