{
  "type": "Feature",
  "properties": {
    "gn:admin1_code":"U",
    "gn:admin2_code":"06",
    "gn:asciiname":"Leslie Hill",
    "gn:country_code":"IE",
    "gn:dem":9,
    "gn:feature_class":"P",
    "gn:feature_code":"PPLL",
    "gn:name":"Leslie Hill",
    "gn:population":0,
    "gn:timezone":"Europe/Dublin",
    "iso:country":"IE",
    "name:ara_x_preferred":[
        "\u0644\u064a\u0632\u0644\u064a \u0647\u064a\u0644"
    ],
    "wof:name":"Leslie Hill",
    "wof:placetype":"locality"
},
  "geometry": {"coordinates":[-7.62639,54.93583],"type":"Point"}
}