{
  "type": "Feature",
  "properties": {
    "gn:admin1_code":"C",
    "gn:admin2_code":"20.0",
    "gn:asciiname":"Kilhale",
    "gn:country_code":"IE",
    "gn:dem":142,
    "gn:feature_class":"P",
    "gn:feature_code":"PPLL",
    "gn:name":"Kilhale",
    "gn:population":0,
    "gn:timezone":"Europe/Dublin",
    "iso:country":"IE",
    "wof:name":"Kilhale",
    "wof:placetype":"locality"
},
  "geometry": {"coordinates":[-9.38239,53.90746],"type":"Point"}
}