{
  "type": "Feature",
  "properties": {
    "gn:admin1_code":"M",
    "gn:admin2_code":"11",
    "gn:asciiname":"Cromane",
    "gn:country_code":"IE",
    "gn:dem":7,
    "gn:feature_class":"P",
    "gn:feature_code":"PPL",
    "gn:name":"Cromane",
    "gn:population":115,
    "gn:timezone":"Europe/Dublin",
    "iso:country":"IE",
    "name:ceb_x_preferred":[
        "Cromane"
    ],
    "name:eng_x_preferred":[
        "Cromane"
    ],
    "name:gle_x_preferred":[
        "An Crom\u00e1n"
    ],
    "name:sco_x_preferred":[
        "Cromane"
    ],
    "name:swe_x_preferred":[
        "Cromane"
    ],
    "wof:name":"Cromane",
    "wof:placetype":"locality",
    "wof:population":115
},
  "geometry": {"coordinates":[-9.89714,52.10635],"type":"Point"}
}