{
  "type": "Feature",
  "properties": {
    "gn:admin1_code":"L",
    "gn:admin2_code":"30",
    "gn:asciiname":"Coolvally",
    "gn:country_code":"IE",
    "gn:dem":106,
    "gn:feature_class":"P",
    "gn:feature_code":"PPL",
    "gn:name":"Coolvally",
    "gn:population":0,
    "gn:timezone":"Europe/Dublin",
    "iso:country":"IE",
    "wof:name":"Coolvally",
    "wof:placetype":"locality"
},
  "geometry": {"coordinates":[-6.75,52.55],"type":"Point"}
}