{
  "type": "Feature",
  "properties": {
    "gn:country":"IE",
    "gn:fcode":"PPL",
    "gn:population":0,
    "iso:country":"IE",
    "name:ceb_x_preferred":[
        "Ardrahan"
    ],
    "name:eng_x_preferred":[
        "Ardrahan"
    ],
    "name:eus_x_preferred":[
        "Ardrahan"
    ],
    "name:gle_x_preferred":[
        "Ard Raithin"
    ],
    "name:ita_x_preferred":[
        "Ardrahan"
    ],
    "name:kat_x_preferred":[
        "\u10d0\u10e0\u10d3\u10e0\u10d0\u10f0\u10d0\u10dc\u10d8"
    ],
    "name:nld_x_preferred":[
        "Ardrahan"
    ],
    "name:pol_x_preferred":[
        "Ardrahan"
    ],
    "name:rus_x_preferred":[
        "\u0410\u0440\u0434\u0440\u0430\u0445\u0430\u043d"
    ],
    "name:swe_x_preferred":[
        "Ardrahan"
    ],
    "qs_pg:aaroncc":"IE",
    "qs_pg:gn_country":"IE",
    "qs_pg:gn_fcode":"PPL",
    "qs_pg:gn_pop":0,
    "qs_pg:name":"Ardrahan",
    "qs_pg:name_adm0":"Ireland",
    "qs_pg:name_adm1":"Galway",
    "qs_pg:photos_9r":0,
    "qs_pg:photos_sr":0,
    "qs_pg:pop_sr":0,
    "qs_pg:qs_pg_placetype":"localadmin",
    "qs_pg:qs_pg_placetype_gp":"LocalAdmin",
    "qs_pg:woe_adm0":23424803,
    "woe:adm0_id":23424803,
    "woe:name_adm0":"Ireland",
    "woe:name_adm1":"Galway",
    "woe:placetype":"LocalAdmin",
    "wof:name":"Ardrahan",
    "wof:placetype":"localadmin"
},
  "geometry": {"coordinates":[-8.80583,53.1575],"type":"Point"}
}