{
  "type": "Feature",
  "properties": {
    "gn:admin1_code":"M",
    "gn:admin2_code":"11",
    "gn:asciiname":"Clogher",
    "gn:country_code":"IE",
    "gn:dem":47,
    "gn:feature_class":"P",
    "gn:feature_code":"PPL",
    "gn:name":"Clogher",
    "gn:population":0,
    "gn:timezone":"Europe/Dublin",
    "iso:country":"IE",
    "name:eng_x_preferred":[
        "Clogher"
    ],
    "name:gle_x_preferred":[
        "Cloichear"
    ],
    "wof:name":"Clogher",
    "wof:placetype":"locality"
},
  "geometry": {"coordinates":[-9.57722,52.25889],"type":"Point"}
}