{
  "type": "Feature",
  "properties": {
    "gn:admin1_code":"M",
    "gn:admin2_code":"11",
    "gn:asciiname":"Clogher",
    "gn:country_code":"IE",
    "gn:dem":47,
    "gn:feature_class":"P",
    "gn:feature_code":"PPL",
    "gn:name":"Clogher",
    "gn:population":0,
    "gn:timezone":"Europe/Dublin",
    "iso:country":"IE",
    "name:cat_x_preferred":[
        "Clogher"
    ],
    "name:ceb_x_preferred":[
        "Clogher"
    ],
    "name:eng_x_preferred":[
        "Clogher"
    ],
    "name:eus_x_preferred":[
        "Clogher"
    ],
    "name:fas_x_preferred":[
        "\u06a9\u0644\u0648\u06af\u0631"
    ],
    "name:fra_x_preferred":[
        "Clogher"
    ],
    "name:gle_x_preferred":[
        "Cloichear"
    ],
    "name:gle_x_variant":[
        "Clochar"
    ],
    "name:ita_x_preferred":[
        "Clogher"
    ],
    "name:msa_x_preferred":[
        "Clogher"
    ],
    "name:pli_x_preferred":[
        "\u0915\u094d\u0932\u094b\u0918\u0947\u0930"
    ],
    "name:spa_x_preferred":[
        "Clogher"
    ],
    "name:urd_x_preferred":[
        "\u06a9\u0644\u0627\u06af\u0631"
    ],
    "wof:name":"Clogher",
    "wof:placetype":"locality"
},
  "geometry": {"coordinates":[-9.57722,52.25889],"type":"Point"}
}