{
  "type": "Feature",
  "properties": {
    "gn:admin1_code":"M",
    "gn:admin2_code":"03",
    "gn:asciiname":"Ballynew Bridge",
    "gn:country_code":"IE",
    "gn:dem":134,
    "gn:feature_class":"P",
    "gn:feature_code":"PPL",
    "gn:name":"Ballynew Bridge",
    "gn:population":0,
    "gn:timezone":"Europe/Dublin",
    "iso:country":"IE",
    "wof:name":"Ballynew Bridge",
    "wof:placetype":"locality"
},
  "geometry": {"coordinates":[-9.35361,52.86167],"type":"Point"}
}