{
  "type": "Feature",
  "properties": {
    "gn:admin1_code":"M",
    "gn:admin2_code":"26",
    "gn:asciiname":"Turnpike",
    "gn:country_code":"IE",
    "gn:dem":121,
    "gn:feature_class":"P",
    "gn:feature_code":"PPL",
    "gn:name":"Turnpike",
    "gn:population":0,
    "gn:timezone":"Europe/Dublin",
    "iso:country":"IE",
    "name:deu_x_preferred":[
        "Turnpike"
    ],
    "name:fin_x_preferred":[
        "Turnpike"
    ],
    "wof:name":"Turnpike",
    "wof:placetype":"locality"
},
  "geometry": {"coordinates":[-7.68361,52.66972],"type":"Point"}
}