{
  "type": "Feature",
  "properties": {
    "iso:country":"IE",
    "qs_pg:aaroncc":"IE",
    "qs_pg:name":"Coolakay",
    "qs_pg:name_adm0":"Ireland",
    "qs_pg:name_adm1":"Wicklow",
    "qs_pg:photos":1385,
    "qs_pg:photos_1k":281,
    "qs_pg:photos_9k":6,
    "qs_pg:photos_9r":7,
    "qs_pg:photos_all":1385,
    "qs_pg:photos_sr":12,
    "qs_pg:pop_sr":0,
    "qs_pg:qs_pg_placetype":"locality",
    "qs_pg:qs_pg_placetype_gp":"Town",
    "qs_pg:woe_adm0":23424803,
    "woe:adm0_id":23424803,
    "woe:name_adm0":"Ireland",
    "woe:name_adm1":"Wicklow",
    "woe:placetype":"Town",
    "wof:name":"Coolakay",
    "wof:placetype":"locality"
},
  "geometry": {"coordinates":[-6.206417,53.163137],"type":"Point"}
}