{
  "type": "Feature",
  "properties": {
    "gn:admin1_code":"L",
    "gn:admin2_code":"23",
    "gn:asciiname":"Killane",
    "gn:cc2":"IE",
    "gn:country_code":"IE",
    "gn:dem":85,
    "gn:feature_class":"P",
    "gn:feature_code":"PPL",
    "gn:name":"Killane",
    "gn:population":0,
    "gn:timezone":"Europe/Dublin",
    "iso:country":"IE",
    "name:und_x_variant":[
        "Killan",
        "Killane"
    ],
    "wof:name":"Killane",
    "wof:placetype":"locality"
},
  "geometry": {"coordinates":[-7.07194,53.33556],"type":"Point"}
}