{
  "type": "Feature",
  "properties": {
    "gn:admin1_code":"M",
    "gn:admin2_code":"04",
    "gn:asciiname":"Mount Keeffe",
    "gn:country_code":"IE",
    "gn:dem":210,
    "gn:feature_class":"P",
    "gn:feature_code":"PPL",
    "gn:name":"Mount Keeffe",
    "gn:population":0,
    "gn:timezone":"Europe/Dublin",
    "iso:country":"IE",
    "name:und_x_variant":[
        "Mount Keefe",
        "Mount Keeffe"
    ],
    "wof:name":"Mount Keeffe",
    "wof:placetype":"locality"
},
  "geometry": {"coordinates":[-8.98333,52.23333],"type":"Point"}
}