{
  "type": "Feature",
  "properties": {
    "gn:admin1_code":"M",
    "gn:admin2_code":"3.0",
    "gn:asciiname":"Clonlara",
    "gn:country_code":"IE",
    "gn:dem":26,
    "gn:feature_class":"P",
    "gn:feature_code":"PPL",
    "gn:name":"Clonlara",
    "gn:population":627,
    "gn:timezone":"Europe/Dublin",
    "iso:country":"IE",
    "name:ceb_x_preferred":[
        "Clonlara"
    ],
    "name:eus_x_preferred":[
        "Clonlara"
    ],
    "name:gle_x_preferred":[
        "Cluain L\u00e1ra"
    ],
    "name:spa_x_preferred":[
        "Clonlara"
    ],
    "name:swe_x_preferred":[
        "Clonlara"
    ],
    "wof:name":"Clonlara",
    "wof:placetype":"locality",
    "wof:population":627
},
  "geometry": {"coordinates":[-8.55251,52.72439],"type":"Point"}
}