{
  "type": "Feature",
  "properties": {
    "gn:admin1_code":"L",
    "gn:admin2_code":"31.0",
    "gn:asciiname":"Derrynamuck",
    "gn:country_code":"IE",
    "gn:dem":287,
    "gn:feature_class":"P",
    "gn:feature_code":"PPL",
    "gn:name":"Derrynamuck",
    "gn:population":0,
    "gn:timezone":"Europe/Dublin",
    "iso:country":"IE",
    "wof:name":"Derrynamuck",
    "wof:placetype":"locality"
},
  "geometry": {"coordinates":[-6.56361,52.96083],"type":"Point"}
}