{
  "type": "Feature",
  "properties": {
    "gn:gn_country":"IE",
    "gn:gn_fcode":"PPL",
    "gn:gn_pop":1504,
    "gn:population":1504,
    "iso:country":"IE",
    "name:cat_x_preferred":[
        "Moate"
    ],
    "name:deu_x_preferred":[
        "Moate"
    ],
    "name:eus_x_preferred":[
        "Moate"
    ],
    "name:fra_x_preferred":[
        "Moate"
    ],
    "name:gle_x_preferred":[
        "An M\u00f3ta"
    ],
    "name:glg_x_preferred":[
        "Moate"
    ],
    "name:ita_x_preferred":[
        "Moate"
    ],
    "name:nld_x_preferred":[
        "Moate"
    ],
    "name:rus_x_preferred":[
        "\u041c\u043e\u0443\u0442"
    ],
    "name:spa_x_preferred":[
        "Moate"
    ],
    "name:swe_x_preferred":[
        "Moate"
    ],
    "qs_pg:aaroncc":"IE",
    "qs_pg:gn_country":"IE",
    "qs_pg:gn_fcode":"PPL",
    "qs_pg:gn_pop":1504,
    "qs_pg:name":"Moate",
    "qs_pg:name_adm0":"Ireland",
    "qs_pg:name_adm1":"Westmeath",
    "qs_pg:photos":389,
    "qs_pg:photos_1k":79,
    "qs_pg:photos_9k":2,
    "qs_pg:photos_9r":5,
    "qs_pg:photos_all":455,
    "qs_pg:photos_sr":6,
    "qs_pg:pop_sr":3,
    "qs_pg:qs_pg_placetype":"localadmin",
    "qs_pg:qs_pg_placetype_gp":"LocalAdmin",
    "qs_pg:woe_adm0":23424803,
    "woe:adm0_id":23424803,
    "woe:name_adm0":"Ireland",
    "woe:name_adm1":"Westmeath",
    "woe:placetype":"LocalAdmin",
    "wof:name":"Moate",
    "wof:placetype":"localadmin",
    "wof:population":1504
},
  "geometry": {"coordinates":[-7.71667,53.55],"type":"Point"}
}