{
  "type": "Feature",
  "properties": {
    "gn:admin1_code":"L",
    "gn:admin2_code":"30",
    "gn:asciiname":"Oulart",
    "gn:country_code":"IE",
    "gn:dem":96,
    "gn:feature_class":"P",
    "gn:feature_code":"PPL",
    "gn:name":"Oulart",
    "gn:population":257,
    "gn:timezone":"Europe/Dublin",
    "iso:country":"IE",
    "name:cat_x_preferred":[
        "Oulart"
    ],
    "name:ceb_x_preferred":[
        "Oulart"
    ],
    "name:eng_x_preferred":[
        "Oulart"
    ],
    "name:eus_x_preferred":[
        "Oulart"
    ],
    "name:gle_x_preferred":[
        "An tAbhallort"
    ],
    "name:rus_x_preferred":[
        "\u0423\u043b\u0430\u0440\u0442"
    ],
    "name:spa_x_preferred":[
        "Oulart"
    ],
    "name:swe_x_preferred":[
        "Oulart"
    ],
    "wof:name":"Oulart",
    "wof:placetype":"locality",
    "wof:population":257
},
  "geometry": {"coordinates":[-6.38995,52.50473],"type":"Point"}
}