{
  "type": "Feature",
  "properties": {
    "gn:admin1_code":"M",
    "gn:admin2_code":"11",
    "gn:asciiname":"Mall",
    "gn:country_code":"IE",
    "gn:dem":93,
    "gn:feature_class":"P",
    "gn:feature_code":"PPL",
    "gn:name":"Mall",
    "gn:population":0,
    "gn:timezone":"Europe/Dublin",
    "iso:country":"IE",
    "name:ceb_x_preferred":[
        "Mall"
    ],
    "name:ces_x_preferred":[
        "Mall"
    ],
    "name:deu_x_preferred":[
        "Mall"
    ],
    "name:est_x_preferred":[
        "Mall"
    ],
    "name:ita_x_preferred":[
        "Mall"
    ],
    "name:nld_x_preferred":[
        "The Mall"
    ],
    "name:ron_x_preferred":[
        "Mall"
    ],
    "name:swe_x_preferred":[
        "Mall"
    ],
    "wof:name":"Mall",
    "wof:placetype":"locality"
},
  "geometry": {"coordinates":[-10.03028,52.16056],"type":"Point"}
}