{
  "type": "Feature",
  "properties": {
    "gn:admin1_code":"M",
    "gn:admin2_code":"26",
    "gn:asciiname":"Cappagh White",
    "gn:country_code":"IE",
    "gn:dem":133,
    "gn:feature_class":"P",
    "gn:feature_code":"PPL",
    "gn:name":"Cappagh White",
    "gn:population":0,
    "gn:timezone":"Europe/Dublin",
    "iso:country":"IE",
    "name:eng_x_preferred":[
        "Cappagh White"
    ],
    "name:gle_x_preferred":[
        "An Cheapach"
    ],
    "wof:name":"Cappagh White",
    "wof:placetype":"locality"
},
  "geometry": {"coordinates":[-8.16361,52.58194],"type":"Point"}
}