{
  "type": "Feature",
  "properties": {
    "gn:admin1_code":"U",
    "gn:admin2_code":"06",
    "gn:asciiname":"Drumnaha",
    "gn:country_code":"IE",
    "gn:dem":91,
    "gn:feature_class":"P",
    "gn:feature_code":"PPLL",
    "gn:name":"Drumnaha",
    "gn:population":0,
    "gn:timezone":"Europe/Dublin",
    "iso:country":"IE",
    "wof:name":"Drumnaha",
    "wof:placetype":"locality"
},
  "geometry": {"coordinates":[-8.14667,54.89056],"type":"Point"}
}