{
  "type": "Feature",
  "properties": {
    "gn:admin1_code":"L",
    "gn:admin2_code":"31.0",
    "gn:asciiname":"Newpark",
    "gn:country_code":"IE",
    "gn:dem":240,
    "gn:feature_class":"P",
    "gn:feature_code":"PPL",
    "gn:name":"Newpark",
    "gn:population":0,
    "gn:timezone":"Europe/Dublin",
    "iso:country":"IE",
    "wof:name":"Newpark",
    "wof:placetype":"locality"
},
  "geometry": {"coordinates":[-6.57889,53.01444],"type":"Point"}
}