{
  "type": "Feature",
  "properties": {
    "gn:admin1_code":"M",
    "gn:admin2_code":"44",
    "gn:asciiname":"Five Cross Roads",
    "gn:country_code":"IE",
    "gn:dem":133,
    "gn:feature_class":"P",
    "gn:feature_code":"PPL",
    "gn:name":"Five Cross Roads",
    "gn:population":0,
    "gn:timezone":"Europe/Dublin",
    "iso:country":"IE",
    "wof:name":"Five Cross Roads",
    "wof:placetype":"locality"
},
  "geometry": {"coordinates":[-7.92722,52.07083],"type":"Point"}
}