{
  "type": "Feature",
  "properties": {
    "gn:admin1_code":"L",
    "gn:admin2_code":"29.0",
    "gn:asciiname":"Bolandstown",
    "gn:country_code":"IE",
    "gn:dem":87,
    "gn:feature_class":"P",
    "gn:feature_code":"PPL",
    "gn:name":"Bolandstown",
    "gn:population":0,
    "gn:timezone":"Europe/Dublin",
    "iso:country":"IE",
    "wof:name":"Bolandstown",
    "wof:placetype":"locality"
},
  "geometry": {"coordinates":[-7.08089,53.58997],"type":"Point"}
}