{
  "type": "Feature",
  "properties": {
    "gn:admin1_code":"L",
    "gn:admin2_code":"19.0",
    "gn:asciiname":"The White Cross",
    "gn:country_code":"IE",
    "gn:dem":28,
    "gn:feature_class":"P",
    "gn:feature_code":"PPLL",
    "gn:name":"The White Cross",
    "gn:population":0,
    "gn:timezone":"Europe/Dublin",
    "iso:country":"IE",
    "wof:name":"The White Cross",
    "wof:placetype":"locality"
},
  "geometry": {"coordinates":[-6.52444,53.95278],"type":"Point"}
}