{
  "type": "Feature",
  "properties": {
    "gn:admin1_code":"M",
    "gn:admin2_code":"11",
    "gn:asciiname":"Ballinrannig",
    "gn:country_code":"IE",
    "gn:dem":8,
    "gn:feature_class":"P",
    "gn:feature_code":"PPL",
    "gn:name":"Ballinrannig",
    "gn:population":0,
    "gn:timezone":"Europe/Dublin",
    "iso:country":"IE",
    "wof:name":"Ballinrannig",
    "wof:placetype":"locality"
},
  "geometry": {"coordinates":[-10.40917,52.175],"type":"Point"}
}