{
  "type": "Feature",
  "properties": {
    "gn:admin1_code":"C",
    "gn:admin2_code":"20.0",
    "gn:asciiname":"Massbrook South",
    "gn:country_code":"IE",
    "gn:dem":63,
    "gn:feature_class":"P",
    "gn:feature_code":"PPL",
    "gn:name":"Massbrook South",
    "gn:population":0,
    "gn:timezone":"Europe/Dublin",
    "iso:country":"IE",
    "wof:name":"Massbrook South",
    "wof:placetype":"locality"
},
  "geometry": {"coordinates":[-9.27535,53.97987],"type":"Point"}
}