{
  "type": "Feature",
  "properties": {
    "gn:admin1_code":"M",
    "gn:admin2_code":"04",
    "gn:asciiname":"Lispatrick",
    "gn:country_code":"IE",
    "gn:dem":-9999,
    "gn:feature_class":"P",
    "gn:feature_code":"PPL",
    "gn:name":"Lispatrick",
    "gn:population":0,
    "gn:timezone":"Europe/Dublin",
    "iso:country":"IE",
    "wof:name":"Lispatrick",
    "wof:placetype":"locality"
},
  "geometry": {"coordinates":[-8.56389,51.63472],"type":"Point"}
}