{
  "type": "Feature",
  "properties": {
    "gn:admin1_code":"L",
    "gn:admin2_code":"21",
    "gn:asciiname":"Ash Field",
    "gn:country_code":"IE",
    "gn:dem":144,
    "gn:feature_class":"P",
    "gn:feature_code":"PPL",
    "gn:name":"Ash Field",
    "gn:population":0,
    "gn:timezone":"Europe/Dublin",
    "iso:country":"IE",
    "wof:name":"Ash Field",
    "wof:placetype":"locality"
},
  "geometry": {"coordinates":[-6.87306,53.85917],"type":"Point"}
}