{
  "type": "Feature",
  "properties": {
    "gn:admin1_code":"C",
    "gn:admin2_code":"25.0",
    "gn:asciiname":"Drumcormick",
    "gn:country_code":"IE",
    "gn:dem":116,
    "gn:feature_class":"P",
    "gn:feature_code":"PPL",
    "gn:name":"Drumcormick",
    "gn:population":0,
    "gn:timezone":"Europe/Dublin",
    "iso:country":"IE",
    "wof:name":"Drumcormick",
    "wof:placetype":"locality"
},
  "geometry": {"coordinates":[-8.41389,54.07889],"type":"Point"}
}