{
  "type": "Feature",
  "properties": {
    "gn:admin1_code":"L",
    "gn:admin2_code":"21.0",
    "gn:asciiname":"Fletcherstown",
    "gn:country_code":"IE",
    "gn:dem":70,
    "gn:feature_class":"P",
    "gn:feature_code":"PPL",
    "gn:name":"Fletcherstown",
    "gn:population":0,
    "gn:timezone":"Europe/Dublin",
    "iso:country":"IE",
    "wof:name":"Fletcherstown",
    "wof:placetype":"locality"
},
  "geometry": {"coordinates":[-6.74079,53.74298],"type":"Point"}
}