{
  "type": "Feature",
  "properties": {
    "gn:admin1_code":"C",
    "gn:admin2_code":"20.0",
    "gn:asciiname":"Carrick",
    "gn:country_code":"IE",
    "gn:dem":26,
    "gn:feature_class":"P",
    "gn:feature_code":"PPL",
    "gn:name":"Carrick",
    "gn:population":0,
    "gn:timezone":"Europe/Dublin",
    "iso:country":"IE",
    "wof:name":"Carrick",
    "wof:placetype":"locality"
},
  "geometry": {"coordinates":[-10.01794,54.23813000000001],"type":"Point"}
}