{
  "type": "Feature",
  "properties": {
    "gn:admin1_code":"C",
    "gn:admin2_code":"20.0",
    "gn:asciiname":"Carrick",
    "gn:country_code":"IE",
    "gn:dem":26,
    "gn:feature_class":"P",
    "gn:feature_code":"PPL",
    "gn:name":"Carrick",
    "gn:population":0,
    "gn:timezone":"Europe/Dublin",
    "iso:country":"IE",
    "name:ceb_x_preferred":[
        "Carrick"
    ],
    "name:deu_x_preferred":[
        "Carrick"
    ],
    "name:fra_x_preferred":[
        "Carrick"
    ],
    "name:fry_x_preferred":[
        "Carrick"
    ],
    "name:ita_x_preferred":[
        "Carrick"
    ],
    "name:nld_x_preferred":[
        "Carrick"
    ],
    "name:nor_x_preferred":[
        "Carrick"
    ],
    "name:rus_x_preferred":[
        "\u041a\u0430\u0440\u0440\u0438\u043a"
    ],
    "name:slk_x_preferred":[
        "Carrick"
    ],
    "name:swe_x_preferred":[
        "Carrick"
    ],
    "wof:name":"Carrick",
    "wof:placetype":"locality"
},
  "geometry": {"coordinates":[-10.01794,54.23813000000001],"type":"Point"}
}