{
  "type": "Feature",
  "properties": {
    "gn:admin1_code":"U",
    "gn:admin2_code":"6.0",
    "gn:asciiname":"Curraghlea",
    "gn:country_code":"IE",
    "gn:dem":163,
    "gn:feature_class":"P",
    "gn:feature_code":"PPL",
    "gn:name":"Curraghlea",
    "gn:population":0,
    "gn:timezone":"Europe/Dublin",
    "iso:country":"IE",
    "wof:name":"Curraghlea",
    "wof:placetype":"locality"
},
  "geometry": {"coordinates":[-7.73163,54.97745],"type":"Point"}
}