{
  "type": "Feature",
  "properties": {
    "gn:admin1_code":"L",
    "gn:admin2_code":"19.0",
    "gn:asciiname":"Lurgan",
    "gn:country_code":"IE",
    "gn:dem":3,
    "gn:feature_class":"P",
    "gn:feature_code":"PPLL",
    "gn:name":"Lurgan",
    "gn:population":0,
    "gn:timezone":"Europe/Dublin",
    "iso:country":"IE",
    "name:bre_x_preferred":[
        "An Lorgain"
    ],
    "name:bul_x_preferred":[
        "\u041b\u044a\u0440\u0433\u0430\u043d"
    ],
    "name:cat_x_preferred":[
        "Lurgan"
    ],
    "name:ceb_x_preferred":[
        "Lurgan"
    ],
    "name:deu_x_preferred":[
        "Lurgan"
    ],
    "name:eus_x_preferred":[
        "Lurgan"
    ],
    "name:fra_x_preferred":[
        "Lurgan"
    ],
    "name:gla_x_preferred":[
        "An Lorgain"
    ],
    "name:gle_x_preferred":[
        "An Lorgain"
    ],
    "name:ita_x_preferred":[
        "Lurgan"
    ],
    "name:lit_x_preferred":[
        "Lerganas"
    ],
    "name:msa_x_preferred":[
        "Lurgan"
    ],
    "name:nld_x_preferred":[
        "Lurgan"
    ],
    "name:pol_x_preferred":[
        "Lurgan"
    ],
    "name:por_x_preferred":[
        "Lurgan"
    ],
    "name:ron_x_preferred":[
        "Lurgan"
    ],
    "name:rus_x_preferred":[
        "\u041b\u0443\u0440\u0433\u0430\u043d"
    ],
    "name:spa_x_preferred":[
        "Lurgan"
    ],
    "name:swe_x_preferred":[
        "Lurgan"
    ],
    "wof:name":"Lurgan",
    "wof:placetype":"locality"
},
  "geometry": {"coordinates":[-6.37778,53.925],"type":"Point"}
}