{
  "type": "Feature",
  "properties": {
    "gn:admin1_code":"L",
    "gn:admin2_code":"30",
    "gn:asciiname":"Marley Bridge",
    "gn:country_code":"IE",
    "gn:dem":48,
    "gn:feature_class":"P",
    "gn:feature_code":"PPL",
    "gn:name":"Marley Bridge",
    "gn:population":0,
    "gn:timezone":"Europe/Dublin",
    "iso:country":"IE",
    "wof:name":"Marley Bridge",
    "wof:placetype":"locality"
},
  "geometry": {"coordinates":[-6.62333,52.53333000000001],"type":"Point"}
}