{
  "type": "Feature",
  "properties": {
    "gn:admin1_code":"M",
    "gn:admin2_code":"04",
    "gn:asciiname":"Gortafludig",
    "gn:country_code":"IE",
    "gn:dem":217,
    "gn:feature_class":"P",
    "gn:feature_code":"PPL",
    "gn:name":"Gortafludig",
    "gn:population":0,
    "gn:timezone":"Europe/Dublin",
    "iso:country":"IE",
    "wof:name":"Gortafludig",
    "wof:placetype":"locality"
},
  "geometry": {"coordinates":[-9.28389,51.85556],"type":"Point"}
}