{
  "type": "Feature",
  "properties": {
    "gn:admin1_code":"U",
    "gn:admin2_code":"02",
    "gn:asciiname":"Lagan",
    "gn:country_code":"IE",
    "gn:dem":48,
    "gn:feature_class":"P",
    "gn:feature_code":"PPL",
    "gn:name":"Lagan",
    "gn:population":0,
    "gn:timezone":"Europe/Dublin",
    "iso:country":"IE",
    "name:bul_x_preferred":[
        "\u041b\u0430\u0433\u0430\u043d"
    ],
    "name:ceb_x_preferred":[
        "Lagan"
    ],
    "name:deu_x_preferred":[
        "Lagan"
    ],
    "name:fin_x_preferred":[
        "Lagan"
    ],
    "name:fra_x_preferred":[
        "Lagan"
    ],
    "name:ita_x_preferred":[
        "Lagan"
    ],
    "name:nld_x_preferred":[
        "Lagan"
    ],
    "name:nno_x_preferred":[
        "Lagan"
    ],
    "name:nor_x_preferred":[
        "Lagan"
    ],
    "name:pol_x_preferred":[
        "Lagan"
    ],
    "name:slv_x_preferred":[
        "Lagan"
    ],
    "name:swe_x_preferred":[
        "Lagan"
    ],
    "name:ukr_x_preferred":[
        "\u041b\u0430\u0433\u0430\u043d"
    ],
    "name:und_x_variant":[
        "Aghalane"
    ],
    "wof:name":"Lagan",
    "wof:placetype":"locality"
},
  "geometry": {"coordinates":[-7.48157,54.12103000000001],"type":"Point"}
}