{
  "type": "Feature",
  "properties": {
    "gn:admin1_code":"C",
    "gn:admin2_code":"20.0",
    "gn:asciiname":"Bunawillin",
    "gn:country_code":"IE",
    "gn:dem":4,
    "gn:feature_class":"P",
    "gn:feature_code":"PPL",
    "gn:name":"Bunawillin",
    "gn:population":0,
    "gn:timezone":"Europe/Dublin",
    "iso:country":"IE",
    "name:eng_x_preferred":[
        "Bunawillin"
    ],
    "name:gle_x_preferred":[
        "Bun an Mhulinn"
    ],
    "wof:name":"Bunawillin",
    "wof:placetype":"locality"
},
  "geometry": {"coordinates":[-9.92877,54.16105],"type":"Point"}
}