{
  "type": "Feature",
  "properties": {
    "gn:admin1_code":"C",
    "gn:admin2_code":"25.0",
    "gn:asciiname":"Drinaghan",
    "gn:country_code":"IE",
    "gn:dem":50,
    "gn:feature_class":"P",
    "gn:feature_code":"PPL",
    "gn:name":"Drinaghan",
    "gn:population":0,
    "gn:timezone":"Europe/Dublin",
    "iso:country":"IE",
    "wof:name":"Drinaghan",
    "wof:placetype":"locality"
},
  "geometry": {"coordinates":[-9.03444,54.22722],"type":"Point"}
}