{
  "type": "Feature",
  "properties": {
    "gn:admin1_code":"C",
    "gn:admin2_code":"20",
    "gn:asciiname":"Creevagh",
    "gn:country_code":"IE",
    "gn:dem":59,
    "gn:feature_class":"P",
    "gn:feature_code":"PPL",
    "gn:name":"Creevagh",
    "gn:population":0,
    "gn:timezone":"Europe/Dublin",
    "iso:country":"IE",
    "wof:name":"Creevagh",
    "wof:placetype":"locality"
},
  "geometry": {"coordinates":[-9.26722,54.30306],"type":"Point"}
}