{
  "type": "Feature",
  "properties": {
    "gn:admin1_code":"L",
    "gn:admin2_code":"30",
    "gn:asciiname":"Ballymurn",
    "gn:country_code":"IE",
    "gn:dem":69,
    "gn:feature_class":"P",
    "gn:feature_code":"PPL",
    "gn:name":"Ballymurn",
    "gn:population":464,
    "gn:timezone":"Europe/Dublin",
    "iso:country":"IE",
    "wof:name":"Ballymurn",
    "wof:placetype":"locality",
    "wof:population":464
},
  "geometry": {"coordinates":[-6.47472,52.44111],"type":"Point"}
}