{
  "type": "Feature",
  "properties": {
    "gn:admin1_code":"C",
    "gn:admin2_code":"20.0",
    "gn:asciiname":"Cloonconra",
    "gn:country_code":"IE",
    "gn:dem":21,
    "gn:feature_class":"P",
    "gn:feature_code":"PPL",
    "gn:name":"Cloonconra",
    "gn:population":0,
    "gn:timezone":"Europe/Dublin",
    "iso:country":"IE",
    "wof:name":"Cloonconra",
    "wof:placetype":"locality"
},
  "geometry": {"coordinates":[-9.10604,53.92739],"type":"Point"}
}