{
  "type": "Feature",
  "properties": {
    "gn:admin1_code":"M",
    "gn:admin2_code":"42",
    "gn:asciiname":"Pallasgreen",
    "gn:cc2":"IE",
    "gn:country_code":"IE",
    "gn:dem":61,
    "gn:feature_class":"P",
    "gn:feature_code":"PPL",
    "gn:name":"Pallasgreen",
    "gn:population":589,
    "gn:timezone":"Europe/Dublin",
    "iso:country":"IE",
    "name:ceb_x_preferred":[
        "Pallasgreen"
    ],
    "name:eus_x_preferred":[
        "Pallasgreen"
    ],
    "name:gle_x_preferred":[
        "Pail\u00eds Ghr\u00e9ine"
    ],
    "name:rus_x_preferred":[
        "\u041f\u0430\u043b\u043b\u0430\u0441-\u0413\u0440\u0438\u043d"
    ],
    "name:spa_x_preferred":[
        "Pallas Grean"
    ],
    "name:swe_x_preferred":[
        "Pallasgreen"
    ],
    "name:und_x_variant":[
        "New Pallas Grean",
        "Pallas Grean"
    ],
    "wof:name":"Pallasgreen",
    "wof:placetype":"locality",
    "wof:population":589
},
  "geometry": {"coordinates":[-8.33794,52.5679],"type":"Point"}
}