{
  "type": "Feature",
  "properties": {
    "gn:admin1_code":"M",
    "gn:admin2_code":"04",
    "gn:asciiname":"Glenville",
    "gn:country_code":"IE",
    "gn:dem":150,
    "gn:feature_class":"P",
    "gn:feature_code":"PPL",
    "gn:name":"Glenville",
    "gn:population":489,
    "gn:timezone":"Europe/Dublin",
    "iso:country":"IE",
    "name:bar_x_preferred":[
        "Glenville"
    ],
    "name:cat_x_preferred":[
        "Glenville"
    ],
    "name:ceb_x_preferred":[
        "Glenville"
    ],
    "name:deu_x_preferred":[
        "Glenville"
    ],
    "name:eng_x_preferred":[
        "Glenville"
    ],
    "name:gle_x_preferred":[
        "Gleann an Phr\u00e9ach\u00e1in"
    ],
    "name:hun_x_preferred":[
        "Glenville"
    ],
    "name:ita_x_preferred":[
        "Glenville"
    ],
    "name:nld_x_preferred":[
        "Glenville"
    ],
    "name:pol_x_preferred":[
        "Glenville"
    ],
    "name:por_x_preferred":[
        "Glenville"
    ],
    "name:rus_x_preferred":[
        "\u0413\u043b\u0435\u043d\u0432\u0438\u043b\u043b"
    ],
    "name:srp_x_preferred":[
        "\u0413\u043b\u0435\u043d\u0432\u0438\u043b"
    ],
    "name:swe_x_preferred":[
        "Glenville"
    ],
    "name:vol_x_preferred":[
        "Glenville"
    ],
    "wof:name":"Glenville",
    "wof:placetype":"locality",
    "wof:population":489
},
  "geometry": {"coordinates":[-8.42472,52.04389000000001],"type":"Point"}
}