{
  "type": "Feature",
  "properties": {
    "gn:admin1_code":"M",
    "gn:admin2_code":"11",
    "gn:asciiname":"Ballynahow",
    "gn:country_code":"IE",
    "gn:dem":207,
    "gn:feature_class":"P",
    "gn:feature_code":"PPL",
    "gn:name":"Ballynahow",
    "gn:population":0,
    "gn:timezone":"Europe/Dublin",
    "iso:country":"IE",
    "name:eng_x_preferred":[
        "Ballynahow"
    ],
    "name:gle_x_preferred":[
        "Baile na hAbha"
    ],
    "wof:name":"Ballynahow",
    "wof:placetype":"locality"
},
  "geometry": {"coordinates":[-10.36222,51.85472],"type":"Point"}
}