{
  "type": "Feature",
  "properties": {
    "gn:admin1_code":"M",
    "gn:admin2_code":"04",
    "gn:asciiname":"Cross Barry",
    "gn:country_code":"IE",
    "gn:dem":45,
    "gn:feature_class":"P",
    "gn:feature_code":"PPL",
    "gn:name":"Cross Barry",
    "gn:population":354,
    "gn:timezone":"Europe/Dublin",
    "iso:country":"IE",
    "name:gle_x_preferred":[
        "Crois an Bharraigh"
    ],
    "name:und_x_variant":[
        "Crossbarry"
    ],
    "wof:name":"Cross Barry",
    "wof:placetype":"locality",
    "wof:population":354
},
  "geometry": {"coordinates":[-8.64504,51.80211],"type":"Point"}
}