{
  "type": "Feature",
  "properties": {
    "gn:admin1_code":"L",
    "gn:admin2_code":"21.0",
    "gn:asciiname":"Springhall",
    "gn:country_code":"IE",
    "gn:dem":113,
    "gn:feature_class":"P",
    "gn:feature_code":"PPL",
    "gn:name":"Springhall",
    "gn:population":0,
    "gn:timezone":"Europe/Dublin",
    "iso:country":"IE",
    "wof:name":"Springhall",
    "wof:placetype":"locality"
},
  "geometry": {"coordinates":[-7.18396,53.73075],"type":"Point"}
}