{
  "type": "Feature",
  "properties": {
    "gn:admin1_code":"C",
    "gn:admin2_code":"25.0",
    "gn:asciiname":"Finned Bridge",
    "gn:country_code":"IE",
    "gn:dem":5,
    "gn:feature_class":"P",
    "gn:feature_code":"PPLL",
    "gn:name":"Finned Bridge",
    "gn:population":0,
    "gn:timezone":"Europe/Dublin",
    "iso:country":"IE",
    "wof:name":"Finned Bridge",
    "wof:placetype":"locality"
},
  "geometry": {"coordinates":[-8.99833,54.28917],"type":"Point"}
}