{
  "type": "Feature",
  "properties": {
    "gn:admin1_code":"L",
    "gn:admin2_code":"21",
    "gn:asciiname":"Ballynare Cross Roads",
    "gn:cc2":"IE",
    "gn:country_code":"IE",
    "gn:dem":77,
    "gn:feature_class":"P",
    "gn:feature_code":"PPL",
    "gn:name":"Ballynare Cross Roads",
    "gn:population":0,
    "gn:timezone":"Europe/Dublin",
    "iso:country":"IE",
    "name:und_x_variant":[
        "Ballynare",
        "Ballynare Cross Roads"
    ],
    "wof:name":"Ballynare Cross Roads",
    "wof:placetype":"locality"
},
  "geometry": {"coordinates":[-6.57472,53.42306],"type":"Point"}
}