{
  "type": "Feature",
  "properties": {
    "gn:admin1_code":"C",
    "gn:admin2_code":"20.0",
    "gn:asciiname":"Creggaun",
    "gn:country_code":"IE",
    "gn:dem":124,
    "gn:feature_class":"P",
    "gn:feature_code":"PPLL",
    "gn:name":"Creggaun",
    "gn:population":0,
    "gn:timezone":"Europe/Dublin",
    "iso:country":"IE",
    "wof:name":"Creggaun",
    "wof:placetype":"locality"
},
  "geometry": {"coordinates":[-8.96139,54.01167],"type":"Point"}
}