{
  "type": "Feature",
  "properties": {
    "iso:country":"IE",
    "name:eng_x_preferred":[
        "Jobstown"
    ],
    "wof:name":"Jobstown",
    "wof:placetype":"neighbourhood"
},
  "geometry": {"coordinates":[-6.40409,53.279413],"type":"Point"}
}