{
  "type": "Feature",
  "properties": {
    "iso:country":"IE",
    "name:eng_x_preferred":[
        "Togher"
    ],
    "wof:name":"Togher",
    "wof:placetype":"neighbourhood"
},
  "geometry": {"coordinates":[-8.492847,51.87824],"type":"Point"}
}