{
  "type": "Feature",
  "properties": {
    "gn:admin1_code":"C",
    "gn:admin2_code":"24.0",
    "gn:asciiname":"Culliagharny",
    "gn:country_code":"IE",
    "gn:dem":49,
    "gn:feature_class":"P",
    "gn:feature_code":"PPL",
    "gn:name":"Culliagharny",
    "gn:population":0,
    "gn:timezone":"Europe/Dublin",
    "iso:country":"IE",
    "wof:name":"Culliagharny",
    "wof:placetype":"locality"
},
  "geometry": {"coordinates":[-8.19528,53.35944],"type":"Point"}
}