{
  "type": "Feature",
  "properties": {
    "gn:admin1_code":"L",
    "gn:admin2_code":"12.0",
    "gn:asciiname":"Goatstown",
    "gn:country_code":"IE",
    "gn:dem":94,
    "gn:feature_class":"P",
    "gn:feature_code":"PPL",
    "gn:name":"Goatstown",
    "gn:population":0,
    "gn:timezone":"Europe/Dublin",
    "iso:country":"IE",
    "name:eus_x_preferred":[
        "Goatstown"
    ],
    "name:rus_x_preferred":[
        "\u0413\u043e\u0442\u0441\u0442\u0430\u0443\u043d"
    ],
    "wof:name":"Goatstown",
    "wof:placetype":"locality"
},
  "geometry": {"coordinates":[-6.76139,53.27389],"type":"Point"}
}