{
  "type": "Feature",
  "properties": {
    "gn:admin1_code":"L",
    "gn:admin2_code":"23.0",
    "gn:asciiname":"Coolaghansglaster",
    "gn:country_code":"IE",
    "gn:dem":37,
    "gn:feature_class":"P",
    "gn:feature_code":"PPL",
    "gn:name":"Coolaghansglaster",
    "gn:population":0,
    "gn:timezone":"Europe/Dublin",
    "iso:country":"IE",
    "wof:name":"Coolaghansglaster",
    "wof:placetype":"locality"
},
  "geometry": {"coordinates":[-7.97056,53.13694],"type":"Point"}
}