{
  "type": "Feature",
  "properties": {
    "gn:admin1_code":"C",
    "gn:admin2_code":"25.0",
    "gn:asciiname":"Raghly",
    "gn:country_code":"IE",
    "gn:dem":4,
    "gn:feature_class":"P",
    "gn:feature_code":"PPL",
    "gn:name":"Raghly",
    "gn:population":0,
    "gn:timezone":"Europe/Dublin",
    "iso:country":"IE",
    "wof:name":"Raghly",
    "wof:placetype":"locality"
},
  "geometry": {"coordinates":[-8.64667,54.33221999999999],"type":"Point"}
}