{
  "type": "Feature",
  "properties": {
    "gn:admin1_code":"U",
    "gn:admin2_code":"02",
    "gn:asciiname":"Crossmakeelan",
    "gn:country_code":"IE",
    "gn:dem":196,
    "gn:feature_class":"P",
    "gn:feature_code":"PPLL",
    "gn:name":"Crossmakeelan",
    "gn:population":0,
    "gn:timezone":"Europe/Dublin",
    "iso:country":"IE",
    "wof:name":"Crossmakeelan",
    "wof:placetype":"locality"
},
  "geometry": {"coordinates":[-6.90778,53.93944000000001],"type":"Point"}
}