{
  "type": "Feature",
  "properties": {
    "gn:admin1_code":"L",
    "gn:admin2_code":"31.0",
    "gn:asciiname":"Knockadreet",
    "gn:country_code":"IE",
    "gn:dem":204,
    "gn:feature_class":"P",
    "gn:feature_code":"PPLL",
    "gn:name":"Knockadreet",
    "gn:population":0,
    "gn:timezone":"Europe/Dublin",
    "iso:country":"IE",
    "wof:name":"Knockadreet",
    "wof:placetype":"locality"
},
  "geometry": {"coordinates":[-6.18389,53.03667],"type":"Point"}
}