{
  "type": "Feature",
  "properties": {
    "gn:admin1_code":"L",
    "gn:admin2_code":"21.0",
    "gn:asciiname":"Turkstown",
    "gn:country_code":"IE",
    "gn:dem":67,
    "gn:feature_class":"P",
    "gn:feature_code":"PPL",
    "gn:name":"Turkstown",
    "gn:population":0,
    "gn:timezone":"Europe/Dublin",
    "iso:country":"IE",
    "wof:name":"Turkstown",
    "wof:placetype":"locality"
},
  "geometry": {"coordinates":[-6.87036,53.76177],"type":"Point"}
}