{
  "type": "Feature",
  "properties": {
    "gn:admin1_code":"U",
    "gn:admin2_code":"06",
    "gn:asciiname":"Fawnaboy Lower",
    "gn:country_code":"IE",
    "gn:dem":55,
    "gn:feature_class":"P",
    "gn:feature_code":"PPL",
    "gn:name":"Fawnaboy Lower",
    "gn:population":0,
    "gn:timezone":"Europe/Dublin",
    "iso:country":"IE",
    "wof:name":"Fawnaboy Lower",
    "wof:placetype":"locality"
},
  "geometry": {"coordinates":[-8.13333,55.08333],"type":"Point"}
}