{
  "type": "Feature",
  "properties": {
    "iso:country":"IE",
    "name:eng_x_preferred":[
        "Doora"
    ],
    "name:gle_x_preferred":[
        "D\u00faire"
    ],
    "name:jpn_x_preferred":[
        "\u30c9\u30a5\u30fc\u30e9"
    ],
    "name:nld_x_preferred":[
        "Doora"
    ],
    "name:vie_x_preferred":[
        "Doora"
    ],
    "qs_pg:aaroncc":"IE",
    "qs_pg:name":"Doora",
    "qs_pg:name_adm0":"Ireland",
    "qs_pg:name_adm1":"Clare",
    "qs_pg:photos":5000,
    "qs_pg:photos_1k":1000,
    "qs_pg:photos_9k":22,
    "qs_pg:photos_9r":14,
    "qs_pg:photos_all":5000,
    "qs_pg:photos_sr":24,
    "qs_pg:pop_sr":0,
    "qs_pg:qs_pg_placetype":"locality",
    "qs_pg:qs_pg_placetype_gp":"Town",
    "qs_pg:woe_adm0":23424803,
    "woe:adm0_id":23424803,
    "woe:name_adm0":"Ireland",
    "woe:name_adm1":"Clare",
    "woe:placetype":"Town",
    "wof:name":"Doora",
    "wof:placetype":"locality"
},
  "geometry": {"coordinates":[-8.971514,52.83967],"type":"Point"}
}