{
  "type": "Feature",
  "properties": {
    "gn:admin1_code":"L",
    "gn:admin2_code":"21.0",
    "gn:asciiname":"Johnstown",
    "gn:country_code":"IE",
    "gn:dem":84,
    "gn:feature_class":"P",
    "gn:feature_code":"PPL",
    "gn:name":"Johnstown",
    "gn:population":0,
    "gn:timezone":"Europe/Dublin",
    "iso:country":"IE",
    "wof:name":"Johnstown",
    "wof:placetype":"locality"
},
  "geometry": {"coordinates":[-6.9761,53.67649],"type":"Point"}
}