{
  "type": "Feature",
  "properties": {
    "gn:admin1_code":"M",
    "gn:admin2_code":"44",
    "gn:asciiname":"Villierstown",
    "gn:country_code":"IE",
    "gn:dem":24,
    "gn:feature_class":"P",
    "gn:feature_code":"PPL",
    "gn:name":"Villierstown",
    "gn:population":279,
    "gn:timezone":"Europe/Dublin",
    "iso:country":"IE",
    "name:ceb_x_preferred":[
        "Villierstown"
    ],
    "name:eng_x_preferred":[
        "Villierstown"
    ],
    "name:eus_x_preferred":[
        "Villierstown"
    ],
    "name:gle_x_preferred":[
        "An Baile Nua"
    ],
    "name:rus_x_preferred":[
        "\u0412\u0438\u043b\u043b\u0438\u0435\u0440\u0441\u0442\u0430\u0443\u043d"
    ],
    "name:spa_x_preferred":[
        "Villierstown"
    ],
    "name:swe_x_preferred":[
        "Villierstown"
    ],
    "wof:name":"Villierstown",
    "wof:placetype":"locality",
    "wof:population":279
},
  "geometry": {"coordinates":[-7.85306,52.08889],"type":"Point"}
}