{
  "type": "Feature",
  "properties": {
    "gn:gn_country":"IE",
    "gn:gn_fcode":"PPL",
    "gn:gn_pop":0,
    "gn:population":1378,
    "iso:country":"IE",
    "name:eng_x_preferred":[
        "Longwood"
    ],
    "name:eus_x_preferred":[
        "Longwood"
    ],
    "name:gle_x_preferred":[
        "Maigh Dearmha\u00ed"
    ],
    "name:glv_x_preferred":[
        "Maigh Dearmha\u00ed"
    ],
    "name:ita_x_preferred":[
        "Longwood"
    ],
    "name:lit_x_preferred":[
        "Longvudas"
    ],
    "name:nld_x_preferred":[
        "Longwood"
    ],
    "name:rus_x_preferred":[
        "\u041b\u043e\u043d\u0433\u0432\u0443\u0434"
    ],
    "name:swe_x_preferred":[
        "Longwood"
    ],
    "qs_pg:aaroncc":"IE",
    "qs_pg:gn_country":"IE",
    "qs_pg:gn_fcode":"PPL",
    "qs_pg:gn_pop":0,
    "qs_pg:name":"Longwood",
    "qs_pg:name_adm0":"Ireland",
    "qs_pg:name_adm1":"Meath",
    "qs_pg:photos_9k":15,
    "qs_pg:photos_9r":11,
    "qs_pg:photos_all":3460,
    "qs_pg:photos_sr":0,
    "qs_pg:pop_sr":0,
    "qs_pg:qs_pg_placetype":"locality",
    "qs_pg:qs_pg_placetype_gp":"Town",
    "qs_pg:woe_adm0":23424803,
    "woe:adm0_id":23424803,
    "woe:name_adm0":"Ireland",
    "woe:name_adm1":"Meath",
    "woe:placetype":"Town",
    "wof:name":"Longwood",
    "wof:placetype":"locality",
    "wof:population":1378
},
  "geometry": {"coordinates":[-6.92194,53.45389],"type":"Point"}
}