{
  "type": "Feature",
  "properties": {
    "gn:admin1_code":"M",
    "gn:admin2_code":"42",
    "gn:asciiname":"Mountcollins",
    "gn:country_code":"IE",
    "gn:dem":121,
    "gn:feature_class":"P",
    "gn:feature_code":"PPL",
    "gn:name":"Mountcollins",
    "gn:population":0,
    "gn:timezone":"Europe/Dublin",
    "iso:country":"IE",
    "name:eus_x_preferred":[
        "Mountcollins"
    ],
    "name:rus_x_preferred":[
        "\u041c\u0430\u0443\u043d\u0442\u043a\u043e\u043b\u043b\u0438\u043d\u0441"
    ],
    "name:spa_x_preferred":[
        "Mountcollins"
    ],
    "wof:name":"Mountcollins",
    "wof:placetype":"locality"
},
  "geometry": {"coordinates":[-9.23333,52.31667],"type":"Point"}
}