{
  "type": "Feature",
  "properties": {
    "gn:admin1_code":"M",
    "gn:admin2_code":"04",
    "gn:asciiname":"Corran Cross Roads",
    "gn:country_code":"IE",
    "gn:dem":156,
    "gn:feature_class":"P",
    "gn:feature_code":"PPLL",
    "gn:name":"Corran Cross Roads",
    "gn:population":0,
    "gn:timezone":"Europe/Dublin",
    "iso:country":"IE",
    "wof:name":"Corran Cross Roads",
    "wof:placetype":"locality"
},
  "geometry": {"coordinates":[-8.60806,51.82028],"type":"Point"}
}