{
  "type": "Feature",
  "properties": {
    "gn:admin1_code":"C",
    "gn:admin2_code":"20.0",
    "gn:asciiname":"Westland",
    "gn:country_code":"IE",
    "gn:dem":44,
    "gn:feature_class":"P",
    "gn:feature_code":"PPL",
    "gn:name":"Westland",
    "gn:population":0,
    "gn:timezone":"Europe/Dublin",
    "iso:country":"IE",
    "name:ceb_x_preferred":[
        "Westland"
    ],
    "name:deu_x_preferred":[
        "Westland"
    ],
    "name:fin_x_preferred":[
        "Westland"
    ],
    "name:fra_x_preferred":[
        "Westland"
    ],
    "name:ita_x_preferred":[
        "Westland"
    ],
    "name:lim_x_preferred":[
        "Westland"
    ],
    "name:nld_x_preferred":[
        "Westland"
    ],
    "name:pol_x_preferred":[
        "Westland"
    ],
    "name:por_x_preferred":[
        "Westland"
    ],
    "name:spa_x_preferred":[
        "Westland"
    ],
    "name:srp_x_preferred":[
        "\u0412\u0435\u0441\u0442\u043b\u0430\u043d\u0434"
    ],
    "name:vol_x_preferred":[
        "Westland"
    ],
    "wof:name":"Westland",
    "wof:placetype":"locality"
},
  "geometry": {"coordinates":[-9.33349,53.8054],"type":"Point"}
}