{
  "type": "Feature",
  "properties": {
    "gn:admin1_code":"U",
    "gn:admin2_code":"06",
    "gn:asciiname":"Cashel",
    "gn:country_code":"IE",
    "gn:dem":95,
    "gn:feature_class":"P",
    "gn:feature_code":"PPL",
    "gn:name":"Cashel",
    "gn:population":0,
    "gn:timezone":"Europe/Dublin",
    "iso:country":"IE",
    "name:eng_x_preferred":[
        "Cashel"
    ],
    "name:gle_x_preferred":[
        "An Caiseal"
    ],
    "wof:name":"Cashel",
    "wof:placetype":"locality"
},
  "geometry": {"coordinates":[-8.20194,54.53694],"type":"Point"}
}