{
  "type": "Feature",
  "properties": {
    "gn:admin1_code":"U",
    "gn:admin2_code":"06",
    "gn:asciiname":"Cashel",
    "gn:country_code":"IE",
    "gn:dem":95,
    "gn:feature_class":"P",
    "gn:feature_code":"PPL",
    "gn:name":"Cashel",
    "gn:population":0,
    "gn:timezone":"Europe/Dublin",
    "iso:country":"IE",
    "name:bar_x_preferred":[
        "Cashel"
    ],
    "name:ceb_x_preferred":[
        "Cashel"
    ],
    "name:deu_x_preferred":[
        "Cashel"
    ],
    "name:eng_x_preferred":[
        "Cashel"
    ],
    "name:epo_x_preferred":[
        "Cashel"
    ],
    "name:fra_x_preferred":[
        "Cashel"
    ],
    "name:gle_x_preferred":[
        "An Caiseal"
    ],
    "name:jpn_x_preferred":[
        "\u30ab\u30b7\u30a7\u30eb"
    ],
    "name:kat_x_preferred":[
        "\u10d9\u10d0\u10e8\u10d4\u10da\u10d8"
    ],
    "name:por_x_preferred":[
        "Cashel"
    ],
    "name:rus_x_preferred":[
        "\u041a\u0430\u0448\u0435\u043b"
    ],
    "name:swe_x_preferred":[
        "Cashel"
    ],
    "wof:name":"Cashel",
    "wof:placetype":"locality"
},
  "geometry": {"coordinates":[-8.20194,54.53694],"type":"Point"}
}