{
  "type": "Feature",
  "properties": {
    "gn:admin1_code":"L",
    "gn:admin2_code":"23.0",
    "gn:asciiname":"Doon Cross Road",
    "gn:country_code":"IE",
    "gn:dem":50,
    "gn:feature_class":"P",
    "gn:feature_code":"PPL",
    "gn:name":"Doon Cross Road",
    "gn:population":0,
    "gn:timezone":"Europe/Dublin",
    "iso:country":"IE",
    "wof:name":"Doon Cross Road",
    "wof:placetype":"locality"
},
  "geometry": {"coordinates":[-7.81889,53.33028],"type":"Point"}
}