{
  "type": "Feature",
  "properties": {
    "gn:admin1_code":"M",
    "gn:admin2_code":"3.0",
    "gn:asciiname":"Tullygarvan",
    "gn:country_code":"IE",
    "gn:dem":42,
    "gn:feature_class":"P",
    "gn:feature_code":"PPL",
    "gn:name":"Tullygarvan",
    "gn:population":0,
    "gn:timezone":"Europe/Dublin",
    "iso:country":"IE",
    "wof:name":"Tullygarvan",
    "wof:placetype":"locality"
},
  "geometry": {"coordinates":[-9.32278,52.91528],"type":"Point"}
}