{
  "type": "Feature",
  "properties": {
    "gn:admin1_code":"C",
    "gn:admin2_code":"14.0",
    "gn:asciiname":"Foxfield",
    "gn:country_code":"IE",
    "gn:dem":66,
    "gn:feature_class":"P",
    "gn:feature_code":"PPLL",
    "gn:name":"Foxfield",
    "gn:population":0,
    "gn:timezone":"Europe/Dublin",
    "iso:country":"IE",
    "wof:name":"Foxfield",
    "wof:placetype":"locality"
},
  "geometry": {"coordinates":[-7.86028,54.02417],"type":"Point"}
}