{
  "type": "Feature",
  "properties": {
    "gn:gn_country":"IE",
    "gn:gn_fcode":"PPL",
    "gn:gn_pop":0,
    "iso:country":"IE",
    "name:baq_x_preferred":[
        "Castlecove"
    ],
    "name:bre_x_preferred":[
        "An Siopa Dubh"
    ],
    "name:dut_x_preferred":[
        "Castlecove"
    ],
    "name:eng_x_preferred":[
        "Castlecove"
    ],
    "name:ger_x_preferred":[
        "Castlecove"
    ],
    "name:gle_x_preferred":[
        "Cuan an Chaisle\u00e1in"
    ],
    "name:rus_x_preferred":[
        "\u041a\u0430\u0441\u043b\u043a\u043e\u0432"
    ],
    "name:unk_x_variant":[
        "An Siopa Dubh"
    ],
    "qs_pg:aaroncc":"IE",
    "qs_pg:gn_country":"IE",
    "qs_pg:gn_fcode":"PPL",
    "qs_pg:gn_pop":0,
    "qs_pg:name":"Castlecove",
    "qs_pg:name_adm0":"Ireland",
    "qs_pg:name_adm1":"Kerry",
    "qs_pg:photos":301,
    "qs_pg:photos_1k":61,
    "qs_pg:photos_9k":1,
    "qs_pg:photos_9r":5,
    "qs_pg:photos_all":301,
    "qs_pg:photos_sr":5,
    "qs_pg:pop_sr":0,
    "qs_pg:qs_pg_placetype":"locality",
    "qs_pg:qs_pg_placetype_gp":"Town",
    "qs_pg:woe_adm0":23424803,
    "woe:adm0_id":23424803,
    "woe:name_adm0":"Ireland",
    "woe:name_adm1":"Kerry",
    "woe:placetype":"Town",
    "wof:name":"Castlecove",
    "wof:placetype":"locality"
},
  "geometry": {"coordinates":[-10.03326,51.77846],"type":"Point"}
}