{
  "type": "Feature",
  "properties": {
    "gn:admin1_code":"C",
    "gn:admin2_code":"10",
    "gn:asciiname":"Attymon",
    "gn:country_code":"IE",
    "gn:dem":76,
    "gn:feature_class":"P",
    "gn:feature_code":"PPL",
    "gn:name":"Attymon",
    "gn:population":0,
    "gn:timezone":"Europe/Dublin",
    "iso:country":"IE",
    "name:eng_x_preferred":[
        "Attymon"
    ],
    "name:gle_x_preferred":[
        "\u00c1th T\u00edom\u00e1in"
    ],
    "wof:name":"Attymon",
    "wof:placetype":"locality"
},
  "geometry": {"coordinates":[-8.60639,53.31861],"type":"Point"}
}