{
  "type": "Feature",
  "properties": {
    "gn:admin1_code":"M",
    "gn:admin2_code":"11",
    "gn:asciiname":"Bauraneag",
    "gn:country_code":"IE",
    "gn:dem":165,
    "gn:feature_class":"P",
    "gn:feature_code":"PPL",
    "gn:name":"Bauraneag",
    "gn:population":0,
    "gn:timezone":"Europe/Dublin",
    "iso:country":"IE",
    "wof:name":"Bauraneag",
    "wof:placetype":"locality"
},
  "geometry": {"coordinates":[-9.16889,52.51583],"type":"Point"}
}