{
  "type": "Feature",
  "properties": {
    "gn:admin1_code":"M",
    "gn:admin2_code":"04",
    "gn:asciiname":"Ballindangan",
    "gn:country_code":"IE",
    "gn:dem":73,
    "gn:feature_class":"P",
    "gn:feature_code":"PPL",
    "gn:name":"Ballindangan",
    "gn:population":0,
    "gn:timezone":"Europe/Dublin",
    "iso:country":"IE",
    "wof:name":"Ballindangan",
    "wof:placetype":"locality"
},
  "geometry": {"coordinates":[-8.33167,52.23444],"type":"Point"}
}