{
  "type": "Feature",
  "properties": {
    "gn:admin1_code":"C",
    "gn:admin2_code":"20",
    "gn:asciiname":"Carnhill",
    "gn:country_code":"IE",
    "gn:dem":26,
    "gn:feature_class":"P",
    "gn:feature_code":"PPL",
    "gn:name":"Carnhill",
    "gn:population":0,
    "gn:timezone":"Europe/Dublin",
    "iso:country":"IE",
    "name:eng_x_preferred":[
        "Carnhill"
    ],
    "name:gle_x_preferred":[
        "Gort an Chairn"
    ],
    "wof:name":"Carnhill",
    "wof:placetype":"locality"
},
  "geometry": {"coordinates":[-9.80229,54.26571],"type":"Point"}
}