{
  "type": "Feature",
  "properties": {
    "gn:admin1_code":"L",
    "gn:admin2_code":"21.0",
    "gn:asciiname":"Demailestown",
    "gn:country_code":"IE",
    "gn:dem":86,
    "gn:feature_class":"P",
    "gn:feature_code":"PPL",
    "gn:name":"Demailestown",
    "gn:population":0,
    "gn:timezone":"Europe/Dublin",
    "iso:country":"IE",
    "wof:name":"Demailestown",
    "wof:placetype":"locality"
},
  "geometry": {"coordinates":[-6.68469,53.7213],"type":"Point"}
}