{
  "type": "Feature",
  "properties": {
    "gn:admin1_code":"C",
    "gn:admin2_code":"20.0",
    "gn:asciiname":"Carrowteige",
    "gn:country_code":"IE",
    "gn:dem":94,
    "gn:feature_class":"P",
    "gn:feature_code":"PPLL",
    "gn:name":"Carrowteige",
    "gn:population":0,
    "gn:timezone":"Europe/Dublin",
    "iso:country":"IE",
    "name:gle_x_preferred":[
        "Ceathr\u00fa Thaidhg"
    ],
    "wof:name":"Carrowteige",
    "wof:placetype":"locality"
},
  "geometry": {"coordinates":[-9.81403,54.31355],"type":"Point"}
}