{
  "type": "Feature",
  "properties": {
    "gn:admin1_code":"C",
    "gn:admin2_code":"10.0",
    "gn:asciiname":"Derrygoolin",
    "gn:country_code":"IE",
    "gn:dem":180,
    "gn:feature_class":"P",
    "gn:feature_code":"PPL",
    "gn:name":"Derrygoolin",
    "gn:population":0,
    "gn:timezone":"Europe/Dublin",
    "iso:country":"IE",
    "wof:name":"Derrygoolin",
    "wof:placetype":"locality"
},
  "geometry": {"coordinates":[-8.43611,52.98167],"type":"Point"}
}