{
  "type": "Feature",
  "properties": {
    "iso:country":"IE",
    "name:cat_x_preferred":[
        "Kilcummin"
    ],
    "name:eus_x_preferred":[
        "Kilcummin"
    ],
    "name:gle_x_preferred":[
        "Cill Chuim\u00edn"
    ],
    "name:spa_x_preferred":[
        "Kilcummin"
    ],
    "qs_pg:aaroncc":"IE",
    "qs_pg:name":"Kilcummin",
    "qs_pg:name_adm0":"Ireland",
    "qs_pg:name_adm1":"Galway",
    "qs_pg:photos":4,
    "qs_pg:photos_1k":1,
    "qs_pg:photos_9k":1,
    "qs_pg:photos_9r":5,
    "qs_pg:photos_all":331,
    "qs_pg:photos_sr":1,
    "qs_pg:pop_sr":0,
    "qs_pg:qs_pg_placetype":"localadmin",
    "qs_pg:qs_pg_placetype_gp":"LocalAdmin",
    "qs_pg:woe_adm0":23424803,
    "woe:adm0_id":23424803,
    "woe:name_adm0":"Ireland",
    "woe:name_adm1":"Galway",
    "woe:placetype":"LocalAdmin",
    "wof:name":"Kilcummin",
    "wof:placetype":"localadmin"
},
  "geometry": {"coordinates":[-9.5338685,53.244468],"type":"Point"}
}