{
  "type": "Feature",
  "properties": {
    "gn:admin1_code":"L",
    "gn:admin2_code":"15",
    "gn:asciiname":"Sleatygraigue",
    "gn:country_code":"IE",
    "gn:dem":56,
    "gn:feature_class":"P",
    "gn:feature_code":"PPL",
    "gn:name":"Sleatygraigue",
    "gn:population":0,
    "gn:timezone":"Europe/Dublin",
    "iso:country":"IE",
    "wof:name":"Sleatygraigue",
    "wof:placetype":"locality"
},
  "geometry": {"coordinates":[-6.97167,52.84472],"type":"Point"}
}