{
  "type": "Feature",
  "properties": {
    "gn:admin1_code":"C",
    "gn:admin2_code":"14",
    "gn:asciiname":"Rivers Town",
    "gn:country_code":"IE",
    "gn:dem":46,
    "gn:feature_class":"P",
    "gn:feature_code":"PPL",
    "gn:name":"Rivers Town",
    "gn:population":0,
    "gn:timezone":"Europe/Dublin",
    "iso:country":"IE",
    "wof:name":"Rivers Town",
    "wof:placetype":"locality"
},
  "geometry": {"coordinates":[-7.81667,53.91667],"type":"Point"}
}