{
  "type": "Feature",
  "properties": {
    "gn:admin1_code":"L",
    "gn:admin2_code":"18",
    "gn:asciiname":"Killasona",
    "gn:country_code":"IE",
    "gn:dem":87,
    "gn:feature_class":"P",
    "gn:feature_code":"PPL",
    "gn:name":"Killasona",
    "gn:population":0,
    "gn:timezone":"Europe/Dublin",
    "iso:country":"IE",
    "wof:name":"Killasona",
    "wof:placetype":"locality"
},
  "geometry": {"coordinates":[-7.48333,53.73333],"type":"Point"}
}