{
  "type": "Feature",
  "properties": {
    "gn:admin1_code":"M",
    "gn:admin2_code":"11",
    "gn:asciiname":"Maulyneill",
    "gn:country_code":"IE",
    "gn:dem":210,
    "gn:feature_class":"P",
    "gn:feature_code":"PPL",
    "gn:name":"Maulyneill",
    "gn:population":0,
    "gn:timezone":"Europe/Dublin",
    "iso:country":"IE",
    "wof:name":"Maulyneill",
    "wof:placetype":"locality"
},
  "geometry": {"coordinates":[-9.71667,51.91667],"type":"Point"}
}