{
  "type": "Feature",
  "properties": {
    "gn:admin1_code":"C",
    "gn:admin2_code":"10.0",
    "gn:asciiname":"Crockaunroe",
    "gn:country_code":"IE",
    "gn:dem":26,
    "gn:feature_class":"P",
    "gn:feature_code":"PPL",
    "gn:name":"Crockaunroe",
    "gn:population":0,
    "gn:timezone":"Europe/Dublin",
    "iso:country":"IE",
    "wof:name":"Crockaunroe",
    "wof:placetype":"locality"
},
  "geometry": {"coordinates":[-10.02722,53.55444],"type":"Point"}
}