{
  "type": "Feature",
  "properties": {
    "gn:admin1_code":"C",
    "gn:admin2_code":"20.0",
    "gn:asciiname":"Cloghan",
    "gn:country_code":"IE",
    "gn:dem":30,
    "gn:feature_class":"P",
    "gn:feature_code":"PPL",
    "gn:name":"Cloghan",
    "gn:population":0,
    "gn:timezone":"Europe/Dublin",
    "iso:country":"IE",
    "name:rus_x_preferred":[
        "\u041a\u043b\u043e\u0445\u0430\u043d"
    ],
    "wof:name":"Cloghan",
    "wof:placetype":"locality"
},
  "geometry": {"coordinates":[-9.54942,53.78936],"type":"Point"}
}