{
  "type": "Feature",
  "properties": {
    "iso:country":"IE",
    "name:ceb_x_preferred":[
        "Portobello"
    ],
    "name:deu_x_preferred":[
        "Portobello"
    ],
    "name:eus_x_preferred":[
        "Portobello"
    ],
    "name:fra_x_preferred":[
        "Portobello"
    ],
    "name:heb_x_preferred":[
        "\u05e4\u05d5\u05e8\u05d8\u05d5\u05d1\u05dc\u05d5"
    ],
    "name:ita_x_preferred":[
        "Portobello"
    ],
    "name:nld_x_preferred":[
        "Portobello"
    ],
    "name:por_x_preferred":[
        "Portobello"
    ],
    "name:spa_x_preferred":[
        "Portobello"
    ],
    "name:swe_x_preferred":[
        "Portobello"
    ],
    "wd:wordcount":116,
    "wof:name":"Portobello",
    "wof:placetype":"neighbourhood"
},
  "geometry": {"coordinates":[-6.26910544809858,53.33087105043612],"type":"Point"}
}