{
  "type": "Feature",
  "properties": {
    "gn:admin1_code":"M",
    "gn:admin2_code":"04",
    "gn:asciiname":"Fort Prospect",
    "gn:country_code":"IE",
    "gn:dem":97,
    "gn:feature_class":"P",
    "gn:feature_code":"PPL",
    "gn:name":"Fort Prospect",
    "gn:population":0,
    "gn:timezone":"Europe/Dublin",
    "iso:country":"IE",
    "wof:name":"Fort Prospect",
    "wof:placetype":"locality"
},
  "geometry": {"coordinates":[-8.83972,51.63889],"type":"Point"}
}