{
  "type": "Feature",
  "properties": {
    "gn:admin1_code":"M",
    "gn:admin2_code":"03",
    "gn:asciiname":"Killadysert",
    "gn:country_code":"IE",
    "gn:dem":28,
    "gn:feature_class":"P",
    "gn:feature_code":"PPL",
    "gn:name":"Killadysert",
    "gn:population":378,
    "gn:timezone":"Europe/Dublin",
    "iso:country":"IE",
    "name:eng_x_preferred":[
        "Killadysert"
    ],
    "name:gle_x_preferred":[
        "Cill an D\u00edsirt"
    ],
    "name:und_x_variant":[
        "Kildysart"
    ],
    "wof:name":"Killadysert",
    "wof:placetype":"locality",
    "wof:population":378
},
  "geometry": {"coordinates":[-9.10639,52.67167],"type":"Point"}
}