{
  "type": "Feature",
  "properties": {
    "gn:gn_country":"IE",
    "gn:gn_fcode":"PPL",
    "gn:gn_pop":0,
    "iso:country":"IE",
    "name:bul_x_preferred":[
        "\u0420\u0435\u0430\u0440\u0434\u043d\u043e\u0433\u0439"
    ],
    "name:eng_x_preferred":[
        "Rearcross"
    ],
    "name:eus_x_preferred":[
        "Rearcross"
    ],
    "name:gle_x_preferred":[
        "Crois na Rae"
    ],
    "name:nld_x_preferred":[
        "Rearcross"
    ],
    "name:rus_x_preferred":[
        "\u0420\u0438\u0440\u043a\u0440\u043e\u0441\u0441"
    ],
    "name:swe_x_preferred":[
        "Reardnogy"
    ],
    "qs_pg:aaroncc":"IE",
    "qs_pg:gn_country":"IE",
    "qs_pg:gn_fcode":"PPL",
    "qs_pg:gn_pop":0,
    "qs_pg:name":"Rearcross",
    "qs_pg:name_adm0":"Ireland",
    "qs_pg:name_adm1":"Tipperary",
    "qs_pg:photos":10,
    "qs_pg:photos_1k":2,
    "qs_pg:photos_9k":1,
    "qs_pg:photos_9r":1,
    "qs_pg:photos_all":10,
    "qs_pg:photos_sr":1,
    "qs_pg:pop_sr":0,
    "qs_pg:qs_pg_placetype":"locality",
    "qs_pg:qs_pg_placetype_gp":"Town",
    "qs_pg:woe_adm0":23424803,
    "woe:adm0_id":23424803,
    "woe:name_adm0":"Ireland",
    "woe:name_adm1":"Tipperary",
    "woe:placetype":"Town",
    "wof:name":"Rearcross",
    "wof:placetype":"locality"
},
  "geometry": {"coordinates":[-8.23583,52.68639],"type":"Point"}
}