{
  "type": "Feature",
  "properties": {
    "iso:country":"IE",
    "name:ita_x_preferred":[
        "Shankill"
    ],
    "name:slk_x_preferred":[
        "Shankill"
    ],
    "qs_pg:aaroncc":"IE",
    "qs_pg:name":"Shankill",
    "qs_pg:name_adm0":"Ireland",
    "qs_pg:name_adm1":"Kilkenny",
    "qs_pg:photos":1,
    "qs_pg:photos_1k":1,
    "qs_pg:photos_9k":1,
    "qs_pg:photos_9r":1,
    "qs_pg:photos_all":19,
    "qs_pg:photos_sr":1,
    "qs_pg:pop_sr":0,
    "qs_pg:qs_pg_placetype":"localadmin",
    "qs_pg:qs_pg_placetype_gp":"LocalAdmin",
    "qs_pg:woe_adm0":23424803,
    "woe:adm0_id":23424803,
    "woe:name_adm0":"Ireland",
    "woe:name_adm1":"Kilkenny",
    "woe:placetype":"LocalAdmin",
    "wof:name":"Shankill",
    "wof:placetype":"localadmin"
},
  "geometry": {"coordinates":[-7.006959,52.689039],"type":"Point"}
}