{
  "type": "Feature",
  "properties": {
    "gn:admin1_code":"L",
    "gn:admin2_code":"15",
    "gn:asciiname":"The Togher",
    "gn:country_code":"IE",
    "gn:dem":92,
    "gn:feature_class":"P",
    "gn:feature_code":"PPL",
    "gn:name":"The Togher",
    "gn:population":0,
    "gn:timezone":"Europe/Dublin",
    "iso:country":"IE",
    "wof:name":"The Togher",
    "wof:placetype":"locality"
},
  "geometry": {"coordinates":[-7.19972,53.07972],"type":"Point"}
}