{
  "type": "Feature",
  "properties": {
    "gn:admin1_code":"M",
    "gn:admin2_code":"26",
    "gn:asciiname":"Ashhill",
    "gn:country_code":"IE",
    "gn:dem":115,
    "gn:feature_class":"P",
    "gn:feature_code":"PPL",
    "gn:name":"Ashhill",
    "gn:population":0,
    "gn:timezone":"Europe/Dublin",
    "iso:country":"IE",
    "wof:name":"Ashhill",
    "wof:placetype":"locality"
},
  "geometry": {"coordinates":[-7.79722,52.59778000000001],"type":"Point"}
}