{
  "type": "Feature",
  "properties": {
    "iso:country":"IE",
    "qs_pg:aaroncc":"IE",
    "qs_pg:name":"Kill",
    "qs_pg:name_adm0":"Ireland",
    "qs_pg:name_adm1":"Kildare",
    "qs_pg:photos":286,
    "qs_pg:photos_1k":58,
    "qs_pg:photos_9k":2,
    "qs_pg:photos_9r":5,
    "qs_pg:photos_all":415,
    "qs_pg:photos_sr":5,
    "qs_pg:pop_sr":0,
    "qs_pg:qs_pg_placetype":"localadmin",
    "qs_pg:qs_pg_placetype_gp":"LocalAdmin",
    "qs_pg:woe_adm0":23424803,
    "woe:adm0_id":23424803,
    "woe:name_adm0":"Ireland",
    "woe:name_adm1":"Kildare",
    "woe:placetype":"LocalAdmin",
    "wof:name":"Kill",
    "wof:placetype":"localadmin"
},
  "geometry": {"coordinates":[-6.609649,53.245405],"type":"Point"}
}