{
  "type": "Feature",
  "properties": {
    "gn:admin1_code":"L",
    "gn:admin2_code":"13",
    "gn:asciiname":"Ballyfoyle",
    "gn:country_code":"IE",
    "gn:dem":127,
    "gn:feature_class":"P",
    "gn:feature_code":"PPL",
    "gn:name":"Ballyfoyle",
    "gn:population":0,
    "gn:timezone":"Europe/Dublin",
    "iso:country":"IE",
    "wof:name":"Ballyfoyle",
    "wof:placetype":"locality"
},
  "geometry": {"coordinates":[-7.23028,52.72361],"type":"Point"}
}