{
  "type": "Feature",
  "properties": {
    "gn:admin1_code":"M",
    "gn:admin2_code":"3.0",
    "gn:asciiname":"Caherconnell",
    "gn:country_code":"IE",
    "gn:dem":120,
    "gn:feature_class":"P",
    "gn:feature_code":"PPLL",
    "gn:name":"Caherconnell",
    "gn:population":0,
    "gn:timezone":"Europe/Dublin",
    "iso:country":"IE",
    "name:deu_x_preferred":[
        "Caherconnell"
    ],
    "name:epo_x_preferred":[
        "Cathair Chonaill"
    ],
    "name:gle_x_preferred":[
        "Cathair Chonaill"
    ],
    "name:nld_x_preferred":[
        "Caherconnell"
    ],
    "name:spa_x_preferred":[
        "Caherconnell"
    ],
    "wof:name":"Caherconnell",
    "wof:placetype":"locality"
},
  "geometry": {"coordinates":[-9.1475,53.04111],"type":"Point"}
}