{
  "type": "Feature",
  "properties": {
    "gn:admin1_code":"M",
    "gn:admin2_code":"04",
    "gn:asciiname":"Ballynamought",
    "gn:country_code":"IE",
    "gn:dem":128,
    "gn:feature_class":"P",
    "gn:feature_code":"PPL",
    "gn:name":"Ballynamought",
    "gn:population":0,
    "gn:timezone":"Europe/Dublin",
    "iso:country":"IE",
    "wof:name":"Ballynamought",
    "wof:placetype":"locality"
},
  "geometry": {"coordinates":[-9.31028,51.77639],"type":"Point"}
}