{
  "type": "Feature",
  "properties": {
    "gn:admin1_code":"M",
    "gn:admin2_code":"42",
    "gn:asciiname":"Kilfinny",
    "gn:cc2":"IE",
    "gn:country_code":"IE",
    "gn:dem":45,
    "gn:feature_class":"P",
    "gn:feature_code":"PPL",
    "gn:name":"Kilfinny",
    "gn:population":0,
    "gn:timezone":"Europe/Dublin",
    "iso:country":"IE",
    "name:und_x_variant":[
        "Kilfinney",
        "Kilfinny"
    ],
    "wof:name":"Kilfinny",
    "wof:placetype":"locality"
},
  "geometry": {"coordinates":[-8.80667,52.51167],"type":"Point"}
}