{
  "type": "Feature",
  "properties": {
    "gn:admin1_code":"C",
    "gn:admin2_code":"20.0",
    "gn:asciiname":"Dereenmanus",
    "gn:country_code":"IE",
    "gn:dem":100,
    "gn:feature_class":"P",
    "gn:feature_code":"PPL",
    "gn:name":"Dereenmanus",
    "gn:population":0,
    "gn:timezone":"Europe/Dublin",
    "iso:country":"IE",
    "wof:name":"Dereenmanus",
    "wof:placetype":"locality"
},
  "geometry": {"coordinates":[-9.31158,53.88161],"type":"Point"}
}