{
  "type": "Feature",
  "properties": {
    "gn:admin1_code":"L",
    "gn:admin2_code":"30",
    "gn:asciiname":"Kyle Cross Roads",
    "gn:country_code":"IE",
    "gn:dem":53,
    "gn:feature_class":"P",
    "gn:feature_code":"PPL",
    "gn:name":"Kyle Cross Roads",
    "gn:population":0,
    "gn:timezone":"Europe/Dublin",
    "iso:country":"IE",
    "wof:name":"Kyle Cross Roads",
    "wof:placetype":"locality"
},
  "geometry": {"coordinates":[-6.52056,52.38444000000001],"type":"Point"}
}