{
  "type": "Feature",
  "properties": {
    "gn:admin1_code":"M",
    "gn:admin2_code":"04",
    "gn:asciiname":"Glounthaune",
    "gn:country_code":"IE",
    "gn:dem":71,
    "gn:feature_class":"P",
    "gn:feature_code":"PPL",
    "gn:name":"Glounthaune",
    "gn:population":0,
    "gn:timezone":"Europe/Dublin",
    "iso:country":"IE",
    "wof:name":"Glounthaune",
    "wof:placetype":"locality"
},
  "geometry": {"coordinates":[-8.36111,51.91111],"type":"Point"}
}