{
  "type": "Feature",
  "properties": {
    "gn:admin1_code":"M",
    "gn:admin2_code":"04",
    "gn:asciiname":"Glounthaune",
    "gn:country_code":"IE",
    "gn:dem":71,
    "gn:feature_class":"P",
    "gn:feature_code":"PPL",
    "gn:name":"Glounthaune",
    "gn:population":0,
    "gn:timezone":"Europe/Dublin",
    "iso:country":"IE",
    "name:cat_x_preferred":[
        "Glounthaune"
    ],
    "name:eus_x_preferred":[
        "Glounthaune"
    ],
    "name:gle_x_preferred":[
        "An Gleannt\u00e1n"
    ],
    "name:rus_x_preferred":[
        "\u0413\u043b\u043e\u0443\u043d\u0442\u043e\u043d"
    ],
    "name:swe_x_preferred":[
        "Glounthaune"
    ],
    "wof:name":"Glounthaune",
    "wof:placetype":"locality"
},
  "geometry": {"coordinates":[-8.36111,51.91111],"type":"Point"}
}