{
  "type": "Feature",
  "properties": {
    "gn:admin1_code":"C",
    "gn:admin2_code":"10.0",
    "gn:asciiname":"Kill",
    "gn:country_code":"IE",
    "gn:dem":15,
    "gn:feature_class":"P",
    "gn:feature_code":"PPL",
    "gn:name":"Kill",
    "gn:population":0,
    "gn:timezone":"Europe/Dublin",
    "iso:country":"IE",
    "name:ceb_x_preferred":[
        "Kill"
    ],
    "name:ces_x_preferred":[
        "Kill"
    ],
    "name:deu_x_preferred":[
        "Kill"
    ],
    "name:fra_x_preferred":[
        "Kill"
    ],
    "name:ita_x_preferred":[
        "Kill"
    ],
    "name:jpn_x_preferred":[
        "Kill"
    ],
    "name:nld_x_preferred":[
        "Kill"
    ],
    "name:por_x_preferred":[
        "Kill"
    ],
    "name:rus_x_preferred":[
        "\u041a\u0438\u043b\u043b"
    ],
    "name:swe_x_preferred":[
        "Kill"
    ],
    "wof:name":"Kill",
    "wof:placetype":"locality"
},
  "geometry": {"coordinates":[-10.09472,53.51],"type":"Point"}
}