{
  "type": "Feature",
  "properties": {
    "gn:admin1_code":"C",
    "gn:admin2_code":"20.0",
    "gn:asciiname":"Gortnaheltia",
    "gn:country_code":"IE",
    "gn:dem":111,
    "gn:feature_class":"P",
    "gn:feature_code":"PPL",
    "gn:name":"Gortnaheltia",
    "gn:population":0,
    "gn:timezone":"Europe/Dublin",
    "iso:country":"IE",
    "wof:name":"Gortnaheltia",
    "wof:placetype":"locality"
},
  "geometry": {"coordinates":[-9.47183,53.9469],"type":"Point"}
}