{
  "type": "Feature",
  "properties": {
    "gn:admin1_code":"M",
    "gn:admin2_code":"42",
    "gn:asciiname":"Loughgur Cross",
    "gn:country_code":"IE",
    "gn:dem":91,
    "gn:feature_class":"P",
    "gn:feature_code":"PPL",
    "gn:name":"Loughgur Cross",
    "gn:population":0,
    "gn:timezone":"Europe/Dublin",
    "iso:country":"IE",
    "wof:name":"Loughgur Cross",
    "wof:placetype":"locality"
},
  "geometry": {"coordinates":[-8.50806,52.51389],"type":"Point"}
}