{
  "type": "Feature",
  "properties": {
    "gn:admin1_code":"L",
    "gn:admin2_code":"18",
    "gn:asciiname":"Abbeyshrule",
    "gn:country_code":"IE",
    "gn:dem":56,
    "gn:feature_class":"P",
    "gn:feature_code":"PPL",
    "gn:name":"Abbeyshrule",
    "gn:population":0,
    "gn:timezone":"Europe/Dublin",
    "iso:country":"IE",
    "name:deu_x_preferred":[
        "Abbeyshrule"
    ],
    "name:eus_x_preferred":[
        "Abbeyshrule"
    ],
    "name:fas_x_preferred":[
        "\u0627\u0628\u06cc\u0634\u0631\u0648\u0644"
    ],
    "name:fra_x_preferred":[
        "Abbeyshrule"
    ],
    "name:gle_x_preferred":[
        "Mainistir Shruthla"
    ],
    "name:ita_x_preferred":[
        "Abbeyshrule"
    ],
    "name:pol_x_preferred":[
        "Abbeyshrule"
    ],
    "name:rus_x_preferred":[
        "\u0410\u0431\u0431\u0438\u0448\u0440\u0443\u043b"
    ],
    "name:spa_x_preferred":[
        "Abbeyshrule"
    ],
    "name:ukr_x_preferred":[
        "\u0410\u0431\u0431\u0456\u0448\u0440\u0443\u043b"
    ],
    "wof:name":"Abbeyshrule",
    "wof:placetype":"locality"
},
  "geometry": {"coordinates":[-7.65,53.58333],"type":"Point"}
}