{
  "type": "Feature",
  "properties": {
    "gn:admin1_code":"C",
    "gn:admin2_code":"14.0",
    "gn:asciiname":"Meenymore",
    "gn:country_code":"IE",
    "gn:dem":165,
    "gn:feature_class":"P",
    "gn:feature_code":"PPLL",
    "gn:name":"Meenymore",
    "gn:population":0,
    "gn:timezone":"Europe/Dublin",
    "iso:country":"IE",
    "wof:name":"Meenymore",
    "wof:placetype":"locality"
},
  "geometry": {"coordinates":[-8.14222,54.26221999999999],"type":"Point"}
}