{
  "type": "Feature",
  "properties": {
    "gn:admin1_code":"U",
    "gn:admin2_code":"02",
    "gn:asciiname":"Tonyduff",
    "gn:country_code":"IE",
    "gn:dem":165,
    "gn:feature_class":"P",
    "gn:feature_code":"PPL",
    "gn:name":"Tonyduff",
    "gn:population":0,
    "gn:timezone":"Europe/Dublin",
    "iso:country":"IE",
    "wof:name":"Tonyduff",
    "wof:placetype":"locality"
},
  "geometry": {"coordinates":[-7.05889,53.95721999999999],"type":"Point"}
}