{
  "type": "Feature",
  "properties": {
    "gn:gn_country":"IE",
    "gn:gn_fcode":"UNIV",
    "gn:gn_pop":16000,
    "gn:population":16000,
    "iso:country":"IE",
    "name:eng_x_preferred":[
        "National University of Ireland, Galway"
    ],
    "name:eng_x_variant":[
        "NUI Galway",
        "UCG",
        "University College Galway"
    ],
    "name:gle_x_preferred":[
        "Ollscoil na h\u00c9ireann, Gaillimh"
    ],
    "qs_pg:aaroncc":"IE",
    "qs_pg:gn_country":"IE",
    "qs_pg:gn_fcode":"UNIV",
    "qs_pg:gn_pop":16000,
    "qs_pg:name":"NUIG",
    "qs_pg:photos_9r":0,
    "qs_pg:photos_sr":0,
    "qs_pg:pop_sr":6,
    "qs_pg:qs_pg_placetype":"locality",
    "wof:name":"NUIG",
    "wof:placetype":"locality",
    "wof:population":16000
},
  "geometry": {"coordinates":[-9.06186,53.27779],"type":"Point"}
}