{
  "type": "Feature",
  "properties": {
    "gn:admin1_code":"M",
    "gn:admin2_code":"04",
    "gn:asciiname":"Boolard",
    "gn:country_code":"IE",
    "gn:dem":155,
    "gn:feature_class":"P",
    "gn:feature_code":"PPL",
    "gn:name":"Boolard",
    "gn:population":0,
    "gn:timezone":"Europe/Dublin",
    "iso:country":"IE",
    "wof:name":"Boolard",
    "wof:placetype":"locality"
},
  "geometry": {"coordinates":[-8.76528,52.32472],"type":"Point"}
}