{
  "type": "Feature",
  "properties": {
    "gn:admin1_code":"L",
    "gn:admin2_code":"23",
    "gn:asciiname":"Rhode",
    "gn:cc2":"IE",
    "gn:country_code":"IE",
    "gn:dem":94,
    "gn:feature_class":"P",
    "gn:feature_code":"PPL",
    "gn:name":"Rhode",
    "gn:population":778,
    "gn:timezone":"Europe/Dublin",
    "iso:country":"IE",
    "name:ceb_x_preferred":[
        "Rhode"
    ],
    "name:eng_x_preferred":[
        "Rhode"
    ],
    "name:eus_x_preferred":[
        "Rhode"
    ],
    "name:gle_x_preferred":[
        "R\u00f3d"
    ],
    "name:rus_x_preferred":[
        "\u0420\u043e\u0434"
    ],
    "name:spa_x_preferred":[
        "Rhode"
    ],
    "name:und_x_variant":[
        "Road"
    ],
    "wof:name":"Rhode",
    "wof:placetype":"locality",
    "wof:population":778
},
  "geometry": {"coordinates":[-7.20167,53.35222],"type":"Point"}
}