{
  "type": "Feature",
  "properties": {
    "gn:admin1_code":"C",
    "gn:admin2_code":"20.0",
    "gn:asciiname":"Snugborough",
    "gn:country_code":"IE",
    "gn:dem":42,
    "gn:feature_class":"P",
    "gn:feature_code":"PPL",
    "gn:name":"Snugborough",
    "gn:population":0,
    "gn:timezone":"Europe/Dublin",
    "iso:country":"IE",
    "name:gle_x_preferred":[
        "Coill \u00d3g"
    ],
    "wof:name":"Snugborough",
    "wof:placetype":"locality"
},
  "geometry": {"coordinates":[-9.32547,53.86044],"type":"Point"}
}