{
  "type": "Feature",
  "properties": {
    "gn:admin1_code":"M",
    "gn:admin2_code":"03",
    "gn:asciiname":"Mahonburgh Bridge",
    "gn:country_code":"IE",
    "gn:dem":27,
    "gn:feature_class":"P",
    "gn:feature_code":"PPL",
    "gn:name":"Mahonburgh Bridge",
    "gn:population":0,
    "gn:timezone":"Europe/Dublin",
    "iso:country":"IE",
    "wof:name":"Mahonburgh Bridge",
    "wof:placetype":"locality"
},
  "geometry": {"coordinates":[-9.05,52.81639000000001],"type":"Point"}
}