{
  "type": "Feature",
  "properties": {
    "gn:admin1_code":"M",
    "gn:admin2_code":"04",
    "gn:asciiname":"Gouladoo",
    "gn:country_code":"IE",
    "gn:dem":90,
    "gn:feature_class":"P",
    "gn:feature_code":"PPL",
    "gn:name":"Gouladoo",
    "gn:population":0,
    "gn:timezone":"Europe/Dublin",
    "iso:country":"IE",
    "wof:name":"Gouladoo",
    "wof:placetype":"locality"
},
  "geometry": {"coordinates":[-9.68083,51.62056],"type":"Point"}
}