{
  "type": "Feature",
  "properties": {
    "gn:admin1_code":"M",
    "gn:admin2_code":"3.0",
    "gn:asciiname":"Coolcoosaun",
    "gn:country_code":"IE",
    "gn:dem":54,
    "gn:feature_class":"P",
    "gn:feature_code":"PPL",
    "gn:name":"Coolcoosaun",
    "gn:population":0,
    "gn:timezone":"Europe/Dublin",
    "iso:country":"IE",
    "wof:name":"Coolcoosaun",
    "wof:placetype":"locality"
},
  "geometry": {"coordinates":[-8.53444,52.92444],"type":"Point"}
}