{
  "type": "Feature",
  "properties": {
    "gn:admin1_code":"C",
    "gn:admin2_code":"10.0",
    "gn:asciiname":"Clooniff",
    "gn:country_code":"IE",
    "gn:dem":9,
    "gn:feature_class":"P",
    "gn:feature_code":"PPL",
    "gn:name":"Clooniff",
    "gn:population":0,
    "gn:timezone":"Europe/Dublin",
    "iso:country":"IE",
    "name:eng_x_preferred":[
        "Clooniffe"
    ],
    "name:gle_x_preferred":[
        "Cluain Aoibh"
    ],
    "name:gle_x_variant":[
        "Cluain Duibh"
    ],
    "wof:name":"Clooniff",
    "wof:placetype":"locality"
},
  "geometry": {"coordinates":[-9.13944,53.32694],"type":"Point"}
}