{
  "type": "Feature",
  "properties": {
    "gn:admin1_code":"L",
    "gn:admin2_code":"23.0",
    "gn:asciiname":"Rathvilla",
    "gn:country_code":"IE",
    "gn:dem":73,
    "gn:feature_class":"P",
    "gn:feature_code":"PPL",
    "gn:name":"Rathvilla",
    "gn:population":0,
    "gn:timezone":"Europe/Dublin",
    "iso:country":"IE",
    "wof:name":"Rathvilla",
    "wof:placetype":"locality"
},
  "geometry": {"coordinates":[-7.14611,53.29667],"type":"Point"}
}