{
  "type": "Feature",
  "properties": {
    "gn:admin1_code":"U",
    "gn:admin2_code":"06",
    "gn:asciiname":"Currs",
    "gn:country_code":"IE",
    "gn:dem":73,
    "gn:feature_class":"P",
    "gn:feature_code":"PPLL",
    "gn:name":"Currs",
    "gn:population":0,
    "gn:timezone":"Europe/Dublin",
    "iso:country":"IE",
    "wof:name":"Currs",
    "wof:placetype":"locality"
},
  "geometry": {"coordinates":[-8.62361,54.63417],"type":"Point"}
}