{
  "type": "Feature",
  "properties": {
    "gn:admin1_code":"U",
    "gn:admin2_code":"06",
    "gn:asciiname":"Raymoghy",
    "gn:country_code":"IE",
    "gn:dem":11,
    "gn:feature_class":"P",
    "gn:feature_code":"PPLL",
    "gn:name":"Raymoghy",
    "gn:population":0,
    "gn:timezone":"Europe/Dublin",
    "iso:country":"IE",
    "wof:name":"Raymoghy",
    "wof:placetype":"locality"
},
  "geometry": {"coordinates":[-7.62028,54.94611],"type":"Point"}
}