{
  "type": "Feature",
  "properties": {
    "gn:admin1_code":"U",
    "gn:admin2_code":"2.0",
    "gn:asciiname":"Binkeeragh",
    "gn:country_code":"IE",
    "gn:dem":212,
    "gn:feature_class":"P",
    "gn:feature_code":"PPLL",
    "gn:name":"Binkeeragh",
    "gn:population":0,
    "gn:timezone":"Europe/Dublin",
    "iso:country":"IE",
    "wof:name":"Binkeeragh",
    "wof:placetype":"locality"
},
  "geometry": {"coordinates":[-7.74889,54.18306],"type":"Point"}
}