{
  "type": "Feature",
  "properties": {
    "gn:admin1_code":"C",
    "gn:admin2_code":"10",
    "gn:asciiname":"Killeany",
    "gn:country_code":"IE",
    "gn:dem":11,
    "gn:feature_class":"P",
    "gn:feature_code":"PPL",
    "gn:name":"Killeany",
    "gn:population":0,
    "gn:timezone":"Europe/Dublin",
    "iso:country":"IE",
    "name:eng_x_preferred":[
        "Killeany"
    ],
    "name:gle_x_preferred":[
        "Cill Einne"
    ],
    "wof:name":"Killeany",
    "wof:placetype":"locality"
},
  "geometry": {"coordinates":[-9.66741,53.10791],"type":"Point"}
}