{
  "type": "Feature",
  "properties": {
    "gn:admin1_code":"U",
    "gn:admin2_code":"06",
    "gn:asciiname":"Brockagh",
    "gn:country_code":"IE",
    "gn:dem":125,
    "gn:feature_class":"P",
    "gn:feature_code":"PPLL",
    "gn:name":"Brockagh",
    "gn:population":0,
    "gn:timezone":"Europe/Dublin",
    "iso:country":"IE",
    "name:eus_x_preferred":[
        "Brockagh"
    ],
    "name:gle_x_preferred":[
        "Brocach"
    ],
    "name:msa_x_preferred":[
        "Brockagh"
    ],
    "name:pli_x_preferred":[
        "\u092c\u094d\u0930\u094b\u091a\u094d\u0915\u0918"
    ],
    "wof:name":"Brockagh",
    "wof:placetype":"locality"
},
  "geometry": {"coordinates":[-8.24333,54.94556],"type":"Point"}
}