{
  "type": "Feature",
  "properties": {
    "gn:admin1_code":"M",
    "gn:admin2_code":"3.0",
    "gn:asciiname":"Bishopsquarter",
    "gn:country_code":"IE",
    "gn:dem":41,
    "gn:feature_class":"P",
    "gn:feature_code":"PPLL",
    "gn:name":"Bishopsquarter",
    "gn:population":0,
    "gn:timezone":"Europe/Dublin",
    "iso:country":"IE",
    "wof:name":"Bishopsquarter",
    "wof:placetype":"locality"
},
  "geometry": {"coordinates":[-9.11944,53.12583000000001],"type":"Point"}
}