{
  "type": "Feature",
  "properties": {
    "gn:admin1_code":"M",
    "gn:admin2_code":"04",
    "gn:asciiname":"Gortnakilly",
    "gn:country_code":"IE",
    "gn:dem":149,
    "gn:feature_class":"P",
    "gn:feature_code":"PPL",
    "gn:name":"Gortnakilly",
    "gn:population":0,
    "gn:timezone":"Europe/Dublin",
    "iso:country":"IE",
    "wof:name":"Gortnakilly",
    "wof:placetype":"locality"
},
  "geometry": {"coordinates":[-9.69472,51.61417],"type":"Point"}
}