{
  "type": "Feature",
  "properties": {
    "gn:admin1_code":"L",
    "gn:admin2_code":"30",
    "gn:asciiname":"Ford",
    "gn:country_code":"IE",
    "gn:dem":48,
    "gn:feature_class":"P",
    "gn:feature_code":"PPL",
    "gn:name":"Ford",
    "gn:population":654,
    "gn:timezone":"Europe/Dublin",
    "iso:country":"IE",
    "wof:name":"Ford",
    "wof:placetype":"locality",
    "wof:population":654
},
  "geometry": {"coordinates":[-6.28028,52.51194],"type":"Point"}
}