{
  "type": "Feature",
  "properties": {
    "gn:admin1_code":"L",
    "gn:admin2_code":"15.0",
    "gn:asciiname":"Yellowpit Cross Roads",
    "gn:country_code":"IE",
    "gn:dem":92,
    "gn:feature_class":"P",
    "gn:feature_code":"PPL",
    "gn:name":"Yellowpit Cross Roads",
    "gn:population":0,
    "gn:timezone":"Europe/Dublin",
    "iso:country":"IE",
    "wof:name":"Yellowpit Cross Roads",
    "wof:placetype":"locality"
},
  "geometry": {"coordinates":[-7.15611,53.04667],"type":"Point"}
}