{
  "type": "Feature",
  "properties": {
    "gn:admin1_code":"C",
    "gn:admin2_code":"10.0",
    "gn:asciiname":"Lissaniska",
    "gn:country_code":"IE",
    "gn:dem":96,
    "gn:feature_class":"P",
    "gn:feature_code":"PPLL",
    "gn:name":"Lissaniska",
    "gn:population":0,
    "gn:timezone":"Europe/Dublin",
    "iso:country":"IE",
    "wof:name":"Lissaniska",
    "wof:placetype":"locality"
},
  "geometry": {"coordinates":[-8.74556,53.40221999999999],"type":"Point"}
}