{
  "type": "Feature",
  "properties": {
    "gn:admin1_code":"U",
    "gn:admin2_code":"06",
    "gn:asciiname":"Drumfree",
    "gn:cc2":"IE",
    "gn:country_code":"IE",
    "gn:dem":91,
    "gn:feature_class":"P",
    "gn:feature_code":"PPL",
    "gn:name":"Drumfree",
    "gn:population":0,
    "gn:timezone":"Europe/Dublin",
    "iso:country":"IE",
    "name:eng_x_preferred":[
        "Drumfree"
    ],
    "name:gle_x_preferred":[
        "Droim Fraoigh"
    ],
    "wof:name":"Drumfree",
    "wof:placetype":"locality"
},
  "geometry": {"coordinates":[-7.39694,55.19639],"type":"Point"}
}