{
  "type": "Feature",
  "properties": {
    "gn:admin1_code":"L",
    "gn:admin2_code":"30",
    "gn:asciiname":"Clonard Little",
    "gn:country_code":"IE",
    "gn:dem":66,
    "gn:feature_class":"P",
    "gn:feature_code":"PPL",
    "gn:name":"Clonard Little",
    "gn:population":0,
    "gn:timezone":"Europe/Dublin",
    "iso:country":"IE",
    "wof:name":"Clonard Little",
    "wof:placetype":"locality"
},
  "geometry": {"coordinates":[-6.49417,52.32583],"type":"Point"}
}