{
  "type": "Feature",
  "properties": {
    "gn:admin1_code":"L",
    "gn:admin2_code":"12",
    "gn:asciiname":"Thomastown",
    "gn:country_code":"IE",
    "gn:dem":77,
    "gn:feature_class":"P",
    "gn:feature_code":"PPL",
    "gn:name":"Thomastown",
    "gn:population":0,
    "gn:timezone":"Europe/Dublin",
    "iso:country":"IE",
    "wof:name":"Thomastown",
    "wof:placetype":"locality"
},
  "geometry": {"coordinates":[-6.88417,53.39639],"type":"Point"}
}