{
  "type": "Feature",
  "properties": {
    "gn:admin1_code":"M",
    "gn:admin2_code":"44.0",
    "gn:asciiname":"Rathgormack",
    "gn:country_code":"IE",
    "gn:dem":137,
    "gn:feature_class":"P",
    "gn:feature_code":"PPL",
    "gn:name":"Rathgormack",
    "gn:population":0,
    "gn:timezone":"Europe/Dublin",
    "iso:country":"IE",
    "name:eus_x_preferred":[
        "Rathgormack"
    ],
    "name:fra_x_preferred":[
        "Rathgormack"
    ],
    "name:rus_x_preferred":[
        "\u0420\u0430\u0442\u0433\u043e\u0440\u043c\u0430\u043a"
    ],
    "wof:name":"Rathgormack",
    "wof:placetype":"locality"
},
  "geometry": {"coordinates":[-7.49783,52.3037],"type":"Point"}
}