{
  "type": "Feature",
  "properties": {
    "gn:admin1_code":"M",
    "gn:admin2_code":"44",
    "gn:asciiname":"Redgate Cross Roads",
    "gn:country_code":"IE",
    "gn:dem":145,
    "gn:feature_class":"P",
    "gn:feature_code":"PPL",
    "gn:name":"Redgate Cross Roads",
    "gn:population":0,
    "gn:timezone":"Europe/Dublin",
    "iso:country":"IE",
    "wof:name":"Redgate Cross Roads",
    "wof:placetype":"locality"
},
  "geometry": {"coordinates":[-7.77611,52.16278],"type":"Point"}
}