{
  "type": "Feature",
  "properties": {
    "gn:admin1_code":"C",
    "gn:admin2_code":"10.0",
    "gn:asciiname":"Tullywee Bridge",
    "gn:country_code":"IE",
    "gn:dem":31,
    "gn:feature_class":"P",
    "gn:feature_code":"PPLL",
    "gn:name":"Tullywee Bridge",
    "gn:population":0,
    "gn:timezone":"Europe/Dublin",
    "iso:country":"IE",
    "wof:name":"Tullywee Bridge",
    "wof:placetype":"locality"
},
  "geometry": {"coordinates":[-9.91722,53.56139],"type":"Point"}
}