{
  "type": "Feature",
  "properties": {
    "gn:admin1_code":"L",
    "gn:admin2_code":"13",
    "gn:asciiname":"Rochestown",
    "gn:country_code":"IE",
    "gn:dem":9,
    "gn:feature_class":"P",
    "gn:feature_code":"PPL",
    "gn:name":"Rochestown",
    "gn:population":0,
    "gn:timezone":"Europe/Dublin",
    "iso:country":"IE",
    "name:eus_x_preferred":[
        "Rochestown"
    ],
    "wof:name":"Rochestown",
    "wof:placetype":"locality"
},
  "geometry": {"coordinates":[-7.00333,52.31833],"type":"Point"}
}