{
  "type": "Feature",
  "properties": {
    "gn:admin1_code":"U",
    "gn:admin2_code":"06",
    "gn:asciiname":"Strahack",
    "gn:country_code":"IE",
    "gn:dem":18,
    "gn:feature_class":"P",
    "gn:feature_code":"PPLL",
    "gn:name":"Strahack",
    "gn:population":0,
    "gn:timezone":"Europe/Dublin",
    "iso:country":"IE",
    "wof:name":"Strahack",
    "wof:placetype":"locality"
},
  "geometry": {"coordinates":[-7.48861,55.07694],"type":"Point"}
}