{
  "type": "Feature",
  "properties": {
    "gn:admin1_code":"U",
    "gn:admin2_code":"06",
    "gn:asciiname":"Rathglass",
    "gn:country_code":"IE",
    "gn:dem":22,
    "gn:feature_class":"P",
    "gn:feature_code":"PPLL",
    "gn:name":"Rathglass",
    "gn:population":0,
    "gn:timezone":"Europe/Dublin",
    "iso:country":"IE",
    "wof:name":"Rathglass",
    "wof:placetype":"locality"
},
  "geometry": {"coordinates":[-8.23417,54.47333],"type":"Point"}
}