{
  "type": "Feature",
  "properties": {
    "gn:admin1_code":"M",
    "gn:admin2_code":"04",
    "gn:asciiname":"Sheskinny Cross",
    "gn:country_code":"IE",
    "gn:dem":177,
    "gn:feature_class":"P",
    "gn:feature_code":"PPLL",
    "gn:name":"Sheskinny Cross",
    "gn:population":0,
    "gn:timezone":"Europe/Dublin",
    "iso:country":"IE",
    "wof:name":"Sheskinny Cross",
    "wof:placetype":"locality"
},
  "geometry": {"coordinates":[-8.83583,51.97778],"type":"Point"}
}