{
  "type": "Feature",
  "properties": {
    "gn:admin1_code":"C",
    "gn:admin2_code":"20.0",
    "gn:asciiname":"Grallagh",
    "gn:country_code":"IE",
    "gn:dem":42,
    "gn:feature_class":"P",
    "gn:feature_code":"PPL",
    "gn:name":"Grallagh",
    "gn:population":0,
    "gn:timezone":"Europe/Dublin",
    "iso:country":"IE",
    "wof:name":"Grallagh",
    "wof:placetype":"locality"
},
  "geometry": {"coordinates":[-9.10289,53.90393],"type":"Point"}
}