{
  "type": "Feature",
  "properties": {
    "gn:admin1_code":"U",
    "gn:admin2_code":"06",
    "gn:asciiname":"Teelin",
    "gn:country_code":"IE",
    "gn:dem":24,
    "gn:feature_class":"P",
    "gn:feature_code":"PPL",
    "gn:name":"Teelin",
    "gn:population":0,
    "gn:timezone":"Europe/Dublin",
    "iso:country":"IE",
    "name:gle_x_preferred":[
        "Teileann"
    ],
    "wof:name":"Teelin",
    "wof:placetype":"locality"
},
  "geometry": {"coordinates":[-8.64167,54.63472],"type":"Point"}
}