{
  "type": "Feature",
  "properties": {
    "iso:country":"IE",
    "name:eng_x_preferred":[
        "Springfield"
    ],
    "wof:name":"Springfield",
    "wof:placetype":"neighbourhood"
},
  "geometry": {"coordinates":[-6.383048,53.287381],"type":"Point"}
}