{
  "type": "Feature",
  "properties": {
    "gn:admin1_code":"U",
    "gn:admin2_code":"06",
    "gn:asciiname":"Kincasslagh",
    "gn:country_code":"IE",
    "gn:dem":6,
    "gn:feature_class":"P",
    "gn:feature_code":"PPL",
    "gn:name":"Kincasslagh",
    "gn:population":0,
    "gn:timezone":"Europe/Dublin",
    "iso:country":"IE",
    "name:cat_x_preferred":[
        "Cionn Caslach"
    ],
    "name:eng_x_preferred":[
        "Kincaslough"
    ],
    "name:eus_x_preferred":[
        "Cionn Caslach"
    ],
    "name:gle_x_preferred":[
        "Cionn Caslach"
    ],
    "name:rus_x_preferred":[
        "\u041a\u0438\u043d\u043a\u0430\u0441\u043b\u043e\u0445"
    ],
    "name:und_x_variant":[
        "Kincashla",
        "Kincasslagh"
    ],
    "wof:name":"Kincasslagh",
    "wof:placetype":"locality"
},
  "geometry": {"coordinates":[-8.39098,55.02526999999999],"type":"Point"}
}