{
  "type": "Feature",
  "properties": {
    "gn:admin1_code":"C",
    "gn:admin2_code":"20.0",
    "gn:asciiname":"Pollatomish",
    "gn:country_code":"IE",
    "gn:dem":49,
    "gn:feature_class":"P",
    "gn:feature_code":"PPL",
    "gn:name":"Pollatomish",
    "gn:population":0,
    "gn:timezone":"Europe/Dublin",
    "iso:country":"IE",
    "name:eng_x_preferred":[
        "Pollatomish"
    ],
    "name:gle_x_preferred":[
        "Poll an tS\u00f3mais"
    ],
    "wof:name":"Pollatomish",
    "wof:placetype":"locality"
},
  "geometry": {"coordinates":[-9.79662,54.26203],"type":"Point"}
}