{
  "type": "Feature",
  "properties": {
    "gn:admin1_code":"M",
    "gn:admin2_code":"04",
    "gn:asciiname":"Clykeel Leary's Cross",
    "gn:country_code":"IE",
    "gn:dem":73,
    "gn:feature_class":"P",
    "gn:feature_code":"PPL",
    "gn:name":"Clykeel Leary\u2019s Cross",
    "gn:population":0,
    "gn:timezone":"Europe/Dublin",
    "iso:country":"IE",
    "wof:name":"Clykeel Leary's Cross",
    "wof:placetype":"locality"
},
  "geometry": {"coordinates":[-8.21806,52.07],"type":"Point"}
}