{
  "type": "Feature",
  "properties": {
    "gn:admin1_code":"L",
    "gn:admin2_code":"01",
    "gn:asciiname":"Kellys Quarter",
    "gn:country_code":"IE",
    "gn:dem":175,
    "gn:feature_class":"P",
    "gn:feature_code":"PPL",
    "gn:name":"Kellys Quarter",
    "gn:population":0,
    "gn:timezone":"Europe/Dublin",
    "iso:country":"IE",
    "wof:name":"Kellys Quarter",
    "wof:placetype":"locality"
},
  "geometry": {"coordinates":[-6.73611,52.64694],"type":"Point"}
}