{
  "type": "Feature",
  "properties": {
    "gn:admin1_code":"U",
    "gn:admin2_code":"06",
    "gn:asciiname":"Ballincrick",
    "gn:country_code":"IE",
    "gn:dem":28,
    "gn:feature_class":"P",
    "gn:feature_code":"PPLL",
    "gn:name":"Ballincrick",
    "gn:population":0,
    "gn:timezone":"Europe/Dublin",
    "iso:country":"IE",
    "name:eng_x_preferred":[
        "Ballincrick"
    ],
    "name:gle_x_preferred":[
        "Baile an Chnoic"
    ],
    "wof:name":"Ballincrick",
    "wof:placetype":"locality"
},
  "geometry": {"coordinates":[-8.36222,54.86556],"type":"Point"}
}