{
  "type": "Feature",
  "properties": {
    "gn:admin1_code":"M",
    "gn:admin2_code":"42.0",
    "gn:asciiname":"Bartholomews Bridge",
    "gn:country_code":"IE",
    "gn:dem":15,
    "gn:feature_class":"P",
    "gn:feature_code":"PPL",
    "gn:name":"Bartholomews Bridge",
    "gn:population":0,
    "gn:timezone":"Europe/Dublin",
    "iso:country":"IE",
    "wof:name":"Bartholomews Bridge",
    "wof:placetype":"locality"
},
  "geometry": {"coordinates":[-9.07944,52.57583],"type":"Point"}
}