{
  "type": "Feature",
  "properties": {
    "gn:admin1_code":"C",
    "gn:admin2_code":"20.0",
    "gn:asciiname":"Derrynameel",
    "gn:country_code":"IE",
    "gn:dem":25,
    "gn:feature_class":"P",
    "gn:feature_code":"PPL",
    "gn:name":"Derrynameel",
    "gn:population":0,
    "gn:timezone":"Europe/Dublin",
    "iso:country":"IE",
    "name:eng_x_preferred":[
        "Derrynameel"
    ],
    "name:gle_x_preferred":[
        "Doire na Maol"
    ],
    "wof:name":"Derrynameel",
    "wof:placetype":"locality"
},
  "geometry": {"coordinates":[-9.89531,54.20909],"type":"Point"}
}