{
  "type": "Feature",
  "properties": {
    "iso:country":"IE",
    "name:eng_x_preferred":[
        "Stoneybatter"
    ],
    "wof:name":"Stoneybatter",
    "wof:placetype":"neighbourhood"
},
  "geometry": {"coordinates":[-6.281268,53.351884],"type":"Point"}
}