{
  "type": "Feature",
  "properties": {
    "gn:admin1_code":"M",
    "gn:admin2_code":"04",
    "gn:asciiname":"Dromina",
    "gn:cc2":"IE",
    "gn:country_code":"IE",
    "gn:dem":145,
    "gn:feature_class":"P",
    "gn:feature_code":"PPL",
    "gn:name":"Dromina",
    "gn:population":269,
    "gn:timezone":"Europe/Dublin",
    "iso:country":"IE",
    "name:eng_x_preferred":[
        "Dromina"
    ],
    "name:gle_x_preferred":[
        "Drom Aidhne"
    ],
    "wof:name":"Dromina",
    "wof:placetype":"locality",
    "wof:population":269
},
  "geometry": {"coordinates":[-8.80115,52.3116],"type":"Point"}
}