{
  "type": "Feature",
  "properties": {
    "gn:country":"IE",
    "gn:fcode":"PPL",
    "gn:population":0,
    "iso:country":"IE",
    "name:eng_x_preferred":[
        "Glinsk"
    ],
    "name:gle_x_preferred":[
        "Glinsce"
    ],
    "name:hsb_x_preferred":[
        "Glinsk"
    ],
    "name:swe_x_preferred":[
        "Glinsk"
    ],
    "qs_pg:aaroncc":"IE",
    "qs_pg:gn_country":"IE",
    "qs_pg:gn_fcode":"PPL",
    "qs_pg:gn_pop":0,
    "qs_pg:name":"Glinsk",
    "qs_pg:name_adm0":"Ireland",
    "qs_pg:name_adm1":"Galway",
    "qs_pg:photos":16,
    "qs_pg:photos_1k":3,
    "qs_pg:photos_9k":1,
    "qs_pg:photos_9r":1,
    "qs_pg:photos_all":16,
    "qs_pg:photos_sr":1,
    "qs_pg:pop_sr":0,
    "qs_pg:qs_pg_placetype":"locality",
    "qs_pg:qs_pg_placetype_gp":"Town",
    "qs_pg:woe_adm0":23424803,
    "woe:adm0_id":23424803,
    "woe:name_adm0":"Ireland",
    "woe:name_adm1":"Galway",
    "woe:placetype":"Town",
    "wof:name":"Glinsk",
    "wof:placetype":"locality"
},
  "geometry": {"coordinates":[-8.41667,53.65],"type":"Point"}
}