{
  "type": "Feature",
  "properties": {
    "gn:admin1_code":"C",
    "gn:admin2_code":"20.0",
    "gn:asciiname":"Cornanool",
    "gn:country_code":"IE",
    "gn:dem":42,
    "gn:feature_class":"P",
    "gn:feature_code":"PPL",
    "gn:name":"Cornanool",
    "gn:population":0,
    "gn:timezone":"Europe/Dublin",
    "iso:country":"IE",
    "wof:name":"Cornanool",
    "wof:placetype":"locality"
},
  "geometry": {"coordinates":[-9.3538,53.85225],"type":"Point"}
}