{
  "type": "Feature",
  "properties": {
    "gn:admin1_code":"M",
    "gn:admin2_code":"42",
    "gn:asciiname":"Ballysteen",
    "gn:country_code":"IE",
    "gn:dem":13,
    "gn:feature_class":"P",
    "gn:feature_code":"PPL",
    "gn:name":"Ballysteen",
    "gn:population":0,
    "gn:timezone":"Europe/Dublin",
    "iso:country":"IE",
    "wof:name":"Ballysteen",
    "wof:placetype":"locality"
},
  "geometry": {"coordinates":[-8.955,52.64556],"type":"Point"}
}