{
  "type": "Feature",
  "properties": {
    "gn:admin1_code":"L",
    "gn:admin2_code":"15",
    "gn:asciiname":"Kilcotton",
    "gn:cc2":"IE",
    "gn:country_code":"IE",
    "gn:dem":121,
    "gn:feature_class":"P",
    "gn:feature_code":"PPL",
    "gn:name":"Kilcotton",
    "gn:population":0,
    "gn:timezone":"Europe/Dublin",
    "iso:country":"IE",
    "name:und_x_variant":[
        "Kilkotton",
        "Kilcotton"
    ],
    "wof:name":"Kilcotton",
    "wof:placetype":"locality"
},
  "geometry": {"coordinates":[-7.53972,52.92083],"type":"Point"}
}