{
  "type": "Feature",
  "properties": {
    "gn:admin1_code":"C",
    "gn:admin2_code":"24.0",
    "gn:asciiname":"Mounthussey",
    "gn:country_code":"IE",
    "gn:dem":61,
    "gn:feature_class":"P",
    "gn:feature_code":"PPL",
    "gn:name":"Mounthussey",
    "gn:population":0,
    "gn:timezone":"Europe/Dublin",
    "iso:country":"IE",
    "wof:name":"Mounthussey",
    "wof:placetype":"locality"
},
  "geometry": {"coordinates":[-8.02333,53.38778000000001],"type":"Point"}
}