{
  "type": "Feature",
  "properties": {
    "gn:admin1_code":"U",
    "gn:admin2_code":"06",
    "gn:asciiname":"Drumboarn Bridge",
    "gn:country_code":"IE",
    "gn:dem":72,
    "gn:feature_class":"P",
    "gn:feature_code":"PPLL",
    "gn:name":"Drumboarn Bridge",
    "gn:population":0,
    "gn:timezone":"Europe/Dublin",
    "iso:country":"IE",
    "wof:name":"Drumboarn Bridge",
    "wof:placetype":"locality"
},
  "geometry": {"coordinates":[-8.15528,54.69722],"type":"Point"}
}