{
  "type": "Feature",
  "properties": {
    "gn:gn_country":"IE",
    "gn:gn_fcode":"PPL",
    "gn:gn_pop":0,
    "gn:population":935,
    "iso:country":"IE",
    "name:deu_x_preferred":[
        "Quin"
    ],
    "name:eng_x_preferred":[
        "Quin"
    ],
    "name:fra_x_preferred":[
        "Quin"
    ],
    "name:gle_x_preferred":[
        "Cuinche"
    ],
    "name:ita_x_preferred":[
        "Quin"
    ],
    "name:ron_x_preferred":[
        "Quin"
    ],
    "name:unk_x_variant":[
        "Quinn"
    ],
    "qs_pg:aaroncc":"IE",
    "qs_pg:gn_country":"IE",
    "qs_pg:gn_fcode":"PPL",
    "qs_pg:gn_pop":0,
    "qs_pg:name":"Quin",
    "qs_pg:name_adm0":"Ireland",
    "qs_pg:name_adm1":"Clare",
    "qs_pg:photos":333,
    "qs_pg:photos_1k":67,
    "qs_pg:photos_9k":4,
    "qs_pg:photos_9r":6,
    "qs_pg:photos_all":808,
    "qs_pg:photos_sr":5,
    "qs_pg:pop_sr":0,
    "qs_pg:qs_pg_placetype":"localadmin",
    "qs_pg:qs_pg_placetype_gp":"LocalAdmin",
    "qs_pg:woe_adm0":23424803,
    "woe:adm0_id":23424803,
    "woe:name_adm0":"Ireland",
    "woe:name_adm1":"Clare",
    "woe:placetype":"LocalAdmin",
    "wof:name":"Quin",
    "wof:placetype":"localadmin",
    "wof:population":935
},
  "geometry": {"coordinates":[-8.86694,52.81861],"type":"Point"}
}