{
  "type": "Feature",
  "properties": {
    "gn:admin1_code":"L",
    "gn:admin2_code":"30.0",
    "gn:asciiname":"Our Lady's Island",
    "gn:country_code":"IE",
    "gn:dem":12,
    "gn:feature_class":"P",
    "gn:feature_code":"PPL",
    "gn:name":"Our Lady's Island",
    "gn:population":0,
    "gn:timezone":"Europe/Dublin",
    "iso:country":"IE",
    "wof:name":"Our Lady's Island",
    "wof:placetype":"locality"
},
  "geometry": {"coordinates":[-6.38186,52.21245],"type":"Point"}
}