{
  "type": "Feature",
  "properties": {
    "gn:admin1_code":"C",
    "gn:admin2_code":"20.0",
    "gn:asciiname":"Keeloges",
    "gn:country_code":"IE",
    "gn:dem":19,
    "gn:feature_class":"P",
    "gn:feature_code":"PPL",
    "gn:name":"Keeloges",
    "gn:population":0,
    "gn:timezone":"Europe/Dublin",
    "iso:country":"IE",
    "wof:name":"Keeloges",
    "wof:placetype":"locality"
},
  "geometry": {"coordinates":[-9.59819,53.89777],"type":"Point"}
}