{
  "type": "Feature",
  "properties": {
    "gn:gn_country":"IE",
    "gn:gn_fcode":"PPL",
    "gn:gn_pop":0,
    "gn:population":229,
    "iso:country":"IE",
    "name:baq_x_preferred":[
        "Blacklion"
    ],
    "name:dut_x_preferred":[
        "Blacklion"
    ],
    "name:eng_x_preferred":[
        "Blacklion"
    ],
    "name:ger_x_preferred":[
        "Blacklion"
    ],
    "name:gla_x_preferred":[
        "An Blaic"
    ],
    "name:gle_x_preferred":[
        "An Blaic"
    ],
    "name:rus_x_preferred":[
        "\u0411\u043b\u044d\u043a\u043b\u0430\u0439\u043e\u043d"
    ],
    "name:swe_x_preferred":[
        "Blacklion"
    ],
    "qs_pg:aaroncc":"IE",
    "qs_pg:gn_country":"IE",
    "qs_pg:gn_fcode":"PPL",
    "qs_pg:gn_pop":0,
    "qs_pg:name":"Blacklion",
    "qs_pg:name_adm0":"Ireland",
    "qs_pg:name_adm1":"Cavan",
    "qs_pg:photos":69,
    "qs_pg:photos_1k":14,
    "qs_pg:photos_9k":1,
    "qs_pg:photos_9r":2,
    "qs_pg:photos_all":69,
    "qs_pg:photos_sr":2,
    "qs_pg:pop_sr":0,
    "qs_pg:qs_pg_placetype":"locality",
    "qs_pg:qs_pg_placetype_gp":"Town",
    "qs_pg:woe_adm0":23424803,
    "woe:adm0_id":23424803,
    "woe:name_adm0":"Ireland",
    "woe:name_adm1":"Cavan",
    "woe:placetype":"Town",
    "wof:name":"Blacklion",
    "wof:placetype":"locality",
    "wof:population":229
},
  "geometry": {"coordinates":[-7.87528,54.29278],"type":"Point"}
}