{
  "type": "Feature",
  "properties": {
    "gn:admin1_code":"L",
    "gn:admin2_code":"19",
    "gn:asciiname":"Ardaghy",
    "gn:country_code":"IE",
    "gn:dem":155,
    "gn:feature_class":"P",
    "gn:feature_code":"PPLL",
    "gn:name":"Ardaghy",
    "gn:population":0,
    "gn:timezone":"Europe/Dublin",
    "iso:country":"IE",
    "wof:name":"Ardaghy",
    "wof:placetype":"locality"
},
  "geometry": {"coordinates":[-6.28389,54.08389],"type":"Point"}
}