{
  "type": "Feature",
  "properties": {
    "gn:admin1_code":"L",
    "gn:admin2_code":"21.0",
    "gn:asciiname":"Balgill",
    "gn:country_code":"IE",
    "gn:dem":53,
    "gn:feature_class":"P",
    "gn:feature_code":"PPL",
    "gn:name":"Balgill",
    "gn:population":0,
    "gn:timezone":"Europe/Dublin",
    "iso:country":"IE",
    "wof:name":"Balgill",
    "wof:placetype":"locality"
},
  "geometry": {"coordinates":[-6.69623,53.59887],"type":"Point"}
}