{
  "type": "Feature",
  "properties": {
    "gn:admin1_code":"M",
    "gn:admin2_code":"03",
    "gn:asciiname":"Kilmihil",
    "gn:country_code":"IE",
    "gn:dem":69,
    "gn:feature_class":"P",
    "gn:feature_code":"PPL",
    "gn:name":"Kilmihil",
    "gn:population":426,
    "gn:timezone":"Europe/Dublin",
    "iso:country":"IE",
    "name:ceb_x_preferred":[
        "Kilmihil"
    ],
    "name:eng_x_preferred":[
        "Kilmihil"
    ],
    "name:eus_x_preferred":[
        "Kilmihil"
    ],
    "name:gle_x_preferred":[
        "Cill Mhich\u00edl"
    ],
    "name:nld_x_preferred":[
        "Kilmihil"
    ],
    "name:rus_x_preferred":[
        "\u041a\u0438\u043b\u043c\u0438\u0445\u0438\u043b"
    ],
    "name:spa_x_preferred":[
        "Kilmihil"
    ],
    "name:swe_x_preferred":[
        "Kilmihil"
    ],
    "name:und_x_variant":[
        "Cill Mhic\u00edl",
        "Kilmihill"
    ],
    "wof:name":"Kilmihil",
    "wof:placetype":"locality",
    "wof:population":426
},
  "geometry": {"coordinates":[-9.31861,52.72139],"type":"Point"}
}