{
  "type": "Feature",
  "properties": {
    "gn:admin1_code":"L",
    "gn:admin2_code":"21.0",
    "gn:asciiname":"Phoenixtown",
    "gn:country_code":"IE",
    "gn:dem":59,
    "gn:feature_class":"P",
    "gn:feature_code":"PPL",
    "gn:name":"Phoenixtown",
    "gn:population":0,
    "gn:timezone":"Europe/Dublin",
    "iso:country":"IE",
    "wof:name":"Phoenixtown",
    "wof:placetype":"locality"
},
  "geometry": {"coordinates":[-6.7982,53.68614],"type":"Point"}
}