{
  "type": "Feature",
  "properties": {
    "gn:admin1_code":"M",
    "gn:admin2_code":"11",
    "gn:asciiname":"Maine Bridge",
    "gn:country_code":"IE",
    "gn:dem":13,
    "gn:feature_class":"P",
    "gn:feature_code":"PPLL",
    "gn:name":"Maine Bridge",
    "gn:population":0,
    "gn:timezone":"Europe/Dublin",
    "iso:country":"IE",
    "wof:name":"Maine Bridge",
    "wof:placetype":"locality"
},
  "geometry": {"coordinates":[-9.57167,52.19722],"type":"Point"}
}