{
  "type": "Feature",
  "properties": {
    "gn:admin1_code":"U",
    "gn:admin2_code":"06",
    "gn:asciiname":"Leatbeg",
    "gn:country_code":"IE",
    "gn:dem":1,
    "gn:feature_class":"P",
    "gn:feature_code":"PPL",
    "gn:name":"Leatbeg",
    "gn:population":0,
    "gn:timezone":"Europe/Dublin",
    "iso:country":"IE",
    "wof:name":"Leatbeg",
    "wof:placetype":"locality"
},
  "geometry": {"coordinates":[-7.75,55.18333000000001],"type":"Point"}
}