{
  "type": "Feature",
  "properties": {
    "gn:admin1_code":"M",
    "gn:admin2_code":"11",
    "gn:asciiname":"Kilvickadownig",
    "gn:country_code":"IE",
    "gn:dem":65,
    "gn:feature_class":"P",
    "gn:feature_code":"PPL",
    "gn:name":"Kilvickadownig",
    "gn:population":0,
    "gn:timezone":"Europe/Dublin",
    "iso:country":"IE",
    "name:eng_x_preferred":[
        "Kilvickadownig"
    ],
    "name:gle_x_preferred":[
        "Cill Mhic an Domhnaigh"
    ],
    "wof:name":"Kilvickadownig",
    "wof:placetype":"locality"
},
  "geometry": {"coordinates":[-10.39833,52.10944],"type":"Point"}
}