{
  "type": "Feature",
  "properties": {
    "gn:admin1_code":"C",
    "gn:admin2_code":"25.0",
    "gn:asciiname":"Rockfield",
    "gn:country_code":"IE",
    "gn:dem":78,
    "gn:feature_class":"P",
    "gn:feature_code":"PPL",
    "gn:name":"Rockfield",
    "gn:population":0,
    "gn:timezone":"Europe/Dublin",
    "iso:country":"IE",
    "name:bre_x_preferred":[
        "Rockfield"
    ],
    "name:ceb_x_preferred":[
        "Rockfield"
    ],
    "name:ces_x_preferred":[
        "Rockfield"
    ],
    "name:deu_x_preferred":[
        "Rockfield"
    ],
    "name:epo_x_preferred":[
        "Rockfield"
    ],
    "name:fra_x_preferred":[
        "Rockfield"
    ],
    "name:swe_x_preferred":[
        "Rockfield"
    ],
    "wof:name":"Rockfield",
    "wof:placetype":"locality"
},
  "geometry": {"coordinates":[-8.62083,54.16778000000001],"type":"Point"}
}