{
  "type": "Feature",
  "properties": {
    "gn:admin1_code":"C",
    "gn:admin2_code":"20.0",
    "gn:asciiname":"Formoyle",
    "gn:country_code":"IE",
    "gn:dem":103,
    "gn:feature_class":"P",
    "gn:feature_code":"PPLL",
    "gn:name":"Formoyle",
    "gn:population":0,
    "gn:timezone":"Europe/Dublin",
    "iso:country":"IE",
    "wof:name":"Formoyle",
    "wof:placetype":"locality"
},
  "geometry": {"coordinates":[-9.45639,54.13806],"type":"Point"}
}