{
  "type": "Feature",
  "properties": {
    "gn:admin1_code":"U",
    "gn:admin2_code":"06",
    "gn:asciiname":"Tullynaglack",
    "gn:country_code":"IE",
    "gn:dem":114,
    "gn:feature_class":"P",
    "gn:feature_code":"PPLL",
    "gn:name":"Tullynaglack",
    "gn:population":0,
    "gn:timezone":"Europe/Dublin",
    "iso:country":"IE",
    "wof:name":"Tullynaglack",
    "wof:placetype":"locality"
},
  "geometry": {"coordinates":[-8.2125,54.72],"type":"Point"}
}