{
  "type": "Feature",
  "properties": {
    "gn:admin1_code":"L",
    "gn:admin2_code":"01",
    "gn:asciiname":"Tiknock",
    "gn:country_code":"IE",
    "gn:dem":117,
    "gn:feature_class":"P",
    "gn:feature_code":"PPL",
    "gn:name":"Tiknock",
    "gn:population":0,
    "gn:timezone":"Europe/Dublin",
    "iso:country":"IE",
    "wof:name":"Tiknock",
    "wof:placetype":"locality"
},
  "geometry": {"coordinates":[-6.63556,52.89194000000001],"type":"Point"}
}