{
  "type": "Feature",
  "properties": {
    "gn:admin1_code":"L",
    "gn:admin2_code":"29.0",
    "gn:asciiname":"Brownstown",
    "gn:country_code":"IE",
    "gn:dem":105,
    "gn:feature_class":"P",
    "gn:feature_code":"PPL",
    "gn:name":"Brownstown",
    "gn:population":0,
    "gn:timezone":"Europe/Dublin",
    "iso:country":"IE",
    "name:cat_x_preferred":[
        "Brownstown"
    ],
    "name:ceb_x_preferred":[
        "Brownstown"
    ],
    "name:deu_x_preferred":[
        "Brownstown"
    ],
    "name:hun_x_preferred":[
        "Brownstown"
    ],
    "name:ita_x_preferred":[
        "Brownstown"
    ],
    "name:nld_x_preferred":[
        "Brownstown"
    ],
    "name:pol_x_preferred":[
        "Brownstown"
    ],
    "name:por_x_preferred":[
        "Brownstown"
    ],
    "name:rus_x_preferred":[
        "\u0411\u0440\u0430\u0443\u043d\u0441\u0442\u0430\u0443\u043d"
    ],
    "name:spa_x_preferred":[
        "Brownstown"
    ],
    "name:srp_x_preferred":[
        "\u0411\u0440\u0430\u0443\u043d\u0441\u0442\u0430\u0443\u043d"
    ],
    "name:swe_x_preferred":[
        "Brownstown"
    ],
    "name:urd_x_preferred":[
        "\u0628\u0631\u0627\u0624\u0646\u0632\u0679\u0627\u0624\u0646"
    ],
    "name:vol_x_preferred":[
        "Brownstown"
    ],
    "wof:name":"Brownstown",
    "wof:placetype":"locality"
},
  "geometry": {"coordinates":[-7.12896,53.65949000000001],"type":"Point"}
}