{
  "type": "Feature",
  "properties": {
    "gn:admin1_code":"L",
    "gn:admin2_code":"29.0",
    "gn:asciiname":"Brownstown",
    "gn:country_code":"IE",
    "gn:dem":105,
    "gn:feature_class":"P",
    "gn:feature_code":"PPL",
    "gn:name":"Brownstown",
    "gn:population":0,
    "gn:timezone":"Europe/Dublin",
    "iso:country":"IE",
    "wof:name":"Brownstown",
    "wof:placetype":"locality"
},
  "geometry": {"coordinates":[-7.12896,53.65949000000001],"type":"Point"}
}