{
  "type": "Feature",
  "properties": {
    "gn:gn_country":"IE",
    "gn:gn_fcode":"PPL",
    "gn:gn_pop":0,
    "gn:population":252,
    "iso:country":"IE",
    "name:ceb_x_preferred":[
        "Drumkeeran"
    ],
    "name:eng_x_preferred":[
        "Drumkeeran"
    ],
    "name:eus_x_preferred":[
        "Drumkeeran"
    ],
    "name:gle_x_preferred":[
        "Droim Caorthainn"
    ],
    "name:kat_x_preferred":[
        "\u10d3\u10e0\u10d0\u10db\u10d9\u10d8\u10e0\u10d0\u10dc\u10d8"
    ],
    "name:nld_x_preferred":[
        "Drumkeeran"
    ],
    "name:rus_x_preferred":[
        "\u0414\u0440\u0430\u043c\u043a\u0438\u0440\u0430\u043d"
    ],
    "name:spa_x_preferred":[
        "Drumkeeran"
    ],
    "name:swe_x_preferred":[
        "Drumkeeran"
    ],
    "name:unk_x_variant":[
        "Drumkeerin"
    ],
    "qs_pg:aaroncc":"IE",
    "qs_pg:gn_country":"IE",
    "qs_pg:gn_fcode":"PPL",
    "qs_pg:gn_pop":0,
    "qs_pg:name":"Drumkeeran",
    "qs_pg:name_adm0":"Ireland",
    "qs_pg:name_adm1":"Leitrim",
    "qs_pg:photos":15,
    "qs_pg:photos_1k":3,
    "qs_pg:photos_9k":1,
    "qs_pg:photos_9r":1,
    "qs_pg:photos_all":15,
    "qs_pg:photos_sr":1,
    "qs_pg:pop_sr":0,
    "qs_pg:qs_pg_placetype":"localadmin",
    "qs_pg:qs_pg_placetype_gp":"LocalAdmin",
    "qs_pg:woe_adm0":23424803,
    "woe:adm0_id":23424803,
    "woe:name_adm0":"Ireland",
    "woe:name_adm1":"Leitrim",
    "woe:placetype":"LocalAdmin",
    "wof:name":"Drumkeeran",
    "wof:placetype":"localadmin",
    "wof:population":252
},
  "geometry": {"coordinates":[-8.15,54.16667],"type":"Point"}
}