{
  "type": "Feature",
  "properties": {
    "gn:admin1_code":"L",
    "gn:admin2_code":"30",
    "gn:asciiname":"Mye Cross Roads",
    "gn:country_code":"IE",
    "gn:dem":95,
    "gn:feature_class":"P",
    "gn:feature_code":"PPL",
    "gn:name":"Mye Cross Roads",
    "gn:population":0,
    "gn:timezone":"Europe/Dublin",
    "iso:country":"IE",
    "wof:name":"Mye Cross Roads",
    "wof:placetype":"locality"
},
  "geometry": {"coordinates":[-6.5125,52.47167],"type":"Point"}
}