{
  "type": "Feature",
  "properties": {
    "gn:admin1_code":"M",
    "gn:admin2_code":"04",
    "gn:asciiname":"Barnard Cross Roads",
    "gn:country_code":"IE",
    "gn:dem":181,
    "gn:feature_class":"P",
    "gn:feature_code":"PPLL",
    "gn:name":"Barnard Cross Roads",
    "gn:population":0,
    "gn:timezone":"Europe/Dublin",
    "iso:country":"IE",
    "wof:name":"Barnard Cross Roads",
    "wof:placetype":"locality"
},
  "geometry": {"coordinates":[-8.73194,52.00111],"type":"Point"}
}