{
  "type": "Feature",
  "properties": {
    "gn:gn_country":"IE",
    "gn:gn_fcode":"PPL",
    "gn:gn_pop":0,
    "gn:population":142,
    "iso:country":"IE",
    "name:eng_x_preferred":[
        "Bellanagare"
    ],
    "name:gle_x_preferred":[
        "B\u00e9al \u00c1tha na gCarr"
    ],
    "qs_pg:aaroncc":"IE",
    "qs_pg:gn_country":"IE",
    "qs_pg:gn_fcode":"PPL",
    "qs_pg:gn_pop":0,
    "qs_pg:name":"Bellanagare",
    "qs_pg:name_adm0":"Ireland",
    "qs_pg:name_adm1":"Roscommon",
    "qs_pg:photos":1,
    "qs_pg:photos_1k":1,
    "qs_pg:photos_9k":1,
    "qs_pg:photos_9r":4,
    "qs_pg:photos_all":234,
    "qs_pg:photos_sr":1,
    "qs_pg:pop_sr":0,
    "qs_pg:qs_pg_placetype":"localadmin",
    "qs_pg:qs_pg_placetype_gp":"LocalAdmin",
    "qs_pg:woe_adm0":23424803,
    "woe:adm0_id":23424803,
    "woe:name_adm0":"Ireland",
    "woe:name_adm1":"Roscommon",
    "woe:placetype":"LocalAdmin",
    "wof:name":"Bellanagare",
    "wof:placetype":"localadmin",
    "wof:population":142
},
  "geometry": {"coordinates":[-8.38333,53.83333],"type":"Point"}
}