{
  "type": "Feature",
  "properties": {
    "gn:admin1_code":"L",
    "gn:admin2_code":"23.0",
    "gn:asciiname":"Derryvilla",
    "gn:country_code":"IE",
    "gn:dem":72,
    "gn:feature_class":"P",
    "gn:feature_code":"PPL",
    "gn:name":"Derryvilla",
    "gn:population":0,
    "gn:timezone":"Europe/Dublin",
    "iso:country":"IE",
    "wof:name":"Derryvilla",
    "wof:placetype":"locality"
},
  "geometry": {"coordinates":[-7.18028,53.17806],"type":"Point"}
}