{
  "type": "Feature",
  "properties": {
    "gn:admin1_code":"U",
    "gn:admin2_code":"06",
    "gn:asciiname":"Ballyboe",
    "gn:country_code":"IE",
    "gn:dem":125,
    "gn:feature_class":"P",
    "gn:feature_code":"PPL",
    "gn:name":"Ballyboe",
    "gn:population":0,
    "gn:timezone":"Europe/Dublin",
    "iso:country":"IE",
    "name:eng_x_preferred":[
        "Ballyboe"
    ],
    "name:gle_x_preferred":[
        "Baile na B\u00f3"
    ],
    "wof:name":"Ballyboe",
    "wof:placetype":"locality"
},
  "geometry": {"coordinates":[-7.66028,55.11],"type":"Point"}
}