{
  "type": "Feature",
  "properties": {
    "gn:admin1_code":"M",
    "gn:admin2_code":"11",
    "gn:asciiname":"Annagh",
    "gn:country_code":"IE",
    "gn:dem":219,
    "gn:feature_class":"P",
    "gn:feature_code":"PPLL",
    "gn:name":"Annagh",
    "gn:population":0,
    "gn:timezone":"Europe/Dublin",
    "iso:country":"IE",
    "name:nld_x_preferred":[
        "Annagh"
    ],
    "wof:name":"Annagh",
    "wof:placetype":"locality"
},
  "geometry": {"coordinates":[-9.32611,52.00889],"type":"Point"}
}