{
  "type": "Feature",
  "properties": {
    "gn:admin1_code":"L",
    "gn:admin2_code":"23.0",
    "gn:asciiname":"New Row",
    "gn:country_code":"IE",
    "gn:dem":78,
    "gn:feature_class":"P",
    "gn:feature_code":"PPL",
    "gn:name":"New Row",
    "gn:population":0,
    "gn:timezone":"Europe/Dublin",
    "iso:country":"IE",
    "name:bre_x_preferred":[
        "Rhes Newydd"
    ],
    "name:cym_x_preferred":[
        "Rhes Newydd"
    ],
    "wof:name":"New Row",
    "wof:placetype":"locality"
},
  "geometry": {"coordinates":[-7.21944,53.22139],"type":"Point"}
}