{
  "type": "Feature",
  "properties": {
    "gn:admin1_code":"M",
    "gn:admin2_code":"04",
    "gn:asciiname":"Tooreen",
    "gn:country_code":"IE",
    "gn:dem":319,
    "gn:feature_class":"P",
    "gn:feature_code":"PPL",
    "gn:name":"Tooreen",
    "gn:population":0,
    "gn:timezone":"Europe/Dublin",
    "iso:country":"IE",
    "wof:name":"Tooreen",
    "wof:placetype":"locality"
},
  "geometry": {"coordinates":[-8.55556,52.29167],"type":"Point"}
}