{
  "type": "Feature",
  "properties": {
    "gn:admin1_code":"L",
    "gn:admin2_code":"30",
    "gn:asciiname":"Craanford",
    "gn:cc2":"IE",
    "gn:country_code":"IE",
    "gn:dem":93,
    "gn:feature_class":"P",
    "gn:feature_code":"PPL",
    "gn:name":"Craanford",
    "gn:population":0,
    "gn:timezone":"Europe/Dublin",
    "iso:country":"IE",
    "name:eus_x_preferred":[
        "Craanford"
    ],
    "name:rus_x_preferred":[
        "\u041a\u0440\u0430\u043d\u0444\u043e\u0440\u0434"
    ],
    "name:und_x_variant":[
        "Crannford"
    ],
    "wof:name":"Craanford",
    "wof:placetype":"locality"
},
  "geometry": {"coordinates":[-6.39167,52.67916999999999],"type":"Point"}
}