{
  "type": "Feature",
  "properties": {
    "iso:country":"IE",
    "name:eng_x_preferred":[
        "Corduff"
    ],
    "name:gla_x_preferred":[
        "An Chorr Dhubh"
    ],
    "name:gle_x_preferred":[
        "An Chorr Dhubh"
    ],
    "name:nld_x_preferred":[
        "Corduff"
    ],
    "name:rus_x_preferred":[
        "\u041a\u043e\u0440\u0434\u0430\u0444\u0444"
    ],
    "qs_pg:aaroncc":"IE",
    "qs_pg:name":"Corduff",
    "qs_pg:name_adm0":"Ireland",
    "qs_pg:name_adm1":"Dublin",
    "qs_pg:photos":64,
    "qs_pg:photos_1k":13,
    "qs_pg:photos_9k":1,
    "qs_pg:photos_9r":2,
    "qs_pg:photos_all":64,
    "qs_pg:photos_sr":2,
    "qs_pg:pop_sr":0,
    "qs_pg:qs_pg_placetype":"locality",
    "qs_pg:qs_pg_placetype_gp":"Town",
    "qs_pg:woe_adm0":23424803,
    "woe:adm0_id":23424803,
    "woe:name_adm0":"Ireland",
    "woe:name_adm1":"Dublin",
    "woe:placetype":"Town",
    "wof:name":"Corduff",
    "wof:placetype":"locality"
},
  "geometry": {"coordinates":[-6.3851575,53.4032905],"type":"Point"}
}