{
  "type": "Feature",
  "properties": {
    "gn:admin1_code":"L",
    "gn:admin2_code":"12.0",
    "gn:asciiname":"Grange Beg",
    "gn:country_code":"IE",
    "gn:dem":99,
    "gn:feature_class":"P",
    "gn:feature_code":"PPL",
    "gn:name":"Grange Beg",
    "gn:population":0,
    "gn:timezone":"Europe/Dublin",
    "iso:country":"IE",
    "wof:name":"Grange Beg",
    "wof:placetype":"locality"
},
  "geometry": {"coordinates":[-6.98028,53.1375],"type":"Point"}
}