{
  "type": "Feature",
  "properties": {
    "gn:admin1_code":"M",
    "gn:admin2_code":"26",
    "gn:asciiname":"Anghvaneen",
    "gn:country_code":"IE",
    "gn:dem":161,
    "gn:feature_class":"P",
    "gn:feature_code":"PPL",
    "gn:name":"Anghvaneen",
    "gn:population":0,
    "gn:timezone":"Europe/Dublin",
    "iso:country":"IE",
    "wof:name":"Anghvaneen",
    "wof:placetype":"locality"
},
  "geometry": {"coordinates":[-7.46139,52.45194],"type":"Point"}
}