{
  "type": "Feature",
  "properties": {
    "gn:country":"IE",
    "gn:fcode":"PPL",
    "gn:population":0,
    "iso:country":"IE",
    "name:bul_x_preferred":[
        "\u041a\u0438\u043b\u0431\u0440\u0438\u0442\u0430\u0438\u043d"
    ],
    "name:ceb_x_preferred":[
        "Kilbrittain"
    ],
    "name:eng_x_preferred":[
        "Kilbrittain"
    ],
    "name:eus_x_preferred":[
        "Kilbrittain"
    ],
    "name:gle_x_preferred":[
        "Cill Briot\u00e1in"
    ],
    "name:nld_x_preferred":[
        "Kilbrittain"
    ],
    "name:rus_x_preferred":[
        "\u041a\u0438\u043b\u0431\u0440\u0438\u0442\u0442\u0435\u043d"
    ],
    "name:spa_x_preferred":[
        "Kilbrittain"
    ],
    "name:swe_x_preferred":[
        "Kilbrittain"
    ],
    "qs_pg:aaroncc":"IE",
    "qs_pg:gn_country":"IE",
    "qs_pg:gn_fcode":"PPL",
    "qs_pg:gn_pop":0,
    "qs_pg:name":"Kilbrittain",
    "qs_pg:name_adm0":"Ireland",
    "qs_pg:name_adm1":"Cork",
    "qs_pg:photos":64,
    "qs_pg:photos_1k":13,
    "qs_pg:photos_9k":1,
    "qs_pg:photos_9r":2,
    "qs_pg:photos_all":64,
    "qs_pg:photos_sr":2,
    "qs_pg:pop_sr":0,
    "qs_pg:qs_pg_placetype":"locality",
    "qs_pg:qs_pg_placetype_gp":"Town",
    "qs_pg:woe_adm0":23424803,
    "woe:adm0_id":23424803,
    "woe:name_adm0":"Ireland",
    "woe:name_adm1":"Cork",
    "woe:placetype":"Town",
    "wof:name":"Kilbrittain",
    "wof:placetype":"locality",
    "wof:population":196
},
  "geometry": {"coordinates":[-8.69333,51.67556],"type":"Point"}
}