{
  "type": "Feature",
  "properties": {
    "gn:admin1_code":"M",
    "gn:admin2_code":"03",
    "gn:asciiname":"Lehinch",
    "gn:country_code":"IE",
    "gn:dem":17,
    "gn:feature_class":"P",
    "gn:feature_code":"PPL",
    "gn:name":"Lehinch",
    "gn:population":642,
    "gn:timezone":"Europe/Dublin",
    "iso:country":"IE",
    "name:eng_x_preferred":[
        "Lahinch"
    ],
    "name:eng_x_variant":[
        "Lehinch"
    ],
    "name:gle_x_preferred":[
        "An Leacht"
    ],
    "wof:name":"Lehinch",
    "wof:placetype":"locality",
    "wof:population":642
},
  "geometry": {"coordinates":[-9.33666,52.93268000000001],"type":"Point"}
}