{
  "type": "Feature",
  "properties": {
    "gn:admin1_code":"M",
    "gn:admin2_code":"03",
    "gn:asciiname":"Lehinch",
    "gn:country_code":"IE",
    "gn:dem":17,
    "gn:feature_class":"P",
    "gn:feature_code":"PPL",
    "gn:name":"Lehinch",
    "gn:population":642,
    "gn:timezone":"Europe/Dublin",
    "iso:country":"IE",
    "name:ceb_x_preferred":[
        "Lehinch"
    ],
    "name:deu_x_preferred":[
        "Lahinch"
    ],
    "name:eng_x_preferred":[
        "Lahinch"
    ],
    "name:eng_x_variant":[
        "Lehinch"
    ],
    "name:eus_x_preferred":[
        "Lahinch"
    ],
    "name:gle_x_preferred":[
        "An Leacht"
    ],
    "name:glg_x_preferred":[
        "Lahinch"
    ],
    "name:nld_x_preferred":[
        "Lahinch"
    ],
    "name:nor_x_preferred":[
        "Lahinch"
    ],
    "name:pol_x_preferred":[
        "Lahinch"
    ],
    "name:rus_x_preferred":[
        "\u041b\u0435\u0445\u0438\u043d\u0447"
    ],
    "name:spa_x_preferred":[
        "Lahinch"
    ],
    "name:swe_x_preferred":[
        "Lahinch"
    ],
    "name:urd_x_preferred":[
        "\u0644\u0627\u06c1\u06cc\u0646\u0686"
    ],
    "wof:name":"Lehinch",
    "wof:placetype":"locality",
    "wof:population":642
},
  "geometry": {"coordinates":[-9.33666,52.93268000000001],"type":"Point"}
}