{
  "type": "Feature",
  "properties": {
    "gn:admin1_code":"L",
    "gn:admin2_code":"39.0",
    "gn:asciiname":"Milltown",
    "gn:country_code":"IE",
    "gn:dem":70,
    "gn:feature_class":"P",
    "gn:feature_code":"PPL",
    "gn:name":"Milltown",
    "gn:population":0,
    "gn:timezone":"Europe/Dublin",
    "iso:country":"IE",
    "wof:name":"Milltown",
    "wof:placetype":"locality"
},
  "geometry": {"coordinates":[-6.45944,53.32083000000001],"type":"Point"}
}