{
  "type": "Feature",
  "properties": {
    "gn:admin1_code":"L",
    "gn:admin2_code":"21.0",
    "gn:asciiname":"Oakstown",
    "gn:country_code":"IE",
    "gn:dem":72,
    "gn:feature_class":"P",
    "gn:feature_code":"PPL",
    "gn:name":"Oakstown",
    "gn:population":0,
    "gn:timezone":"Europe/Dublin",
    "iso:country":"IE",
    "wof:name":"Oakstown",
    "wof:placetype":"locality"
},
  "geometry": {"coordinates":[-6.83129,53.57054],"type":"Point"}
}