{
  "type": "Feature",
  "properties": {
    "gn:admin1_code":"L",
    "gn:admin2_code":"15.0",
    "gn:asciiname":"Lough",
    "gn:country_code":"IE",
    "gn:dem":78,
    "gn:feature_class":"P",
    "gn:feature_code":"PPLL",
    "gn:name":"Lough",
    "gn:population":0,
    "gn:timezone":"Europe/Dublin",
    "iso:country":"IE",
    "wof:name":"Lough",
    "wof:placetype":"locality"
},
  "geometry": {"coordinates":[-7.19583,53.12416999999999],"type":"Point"}
}