{
  "type": "Feature",
  "properties": {
    "gn:gn_country":"IE",
    "gn:gn_fcode":"PPL",
    "gn:gn_pop":0,
    "gn:population":1089,
    "iso:country":"IE",
    "name:ceb_x_preferred":[
        "Ballyragget"
    ],
    "name:eng_x_preferred":[
        "Ballyragget"
    ],
    "name:eus_x_preferred":[
        "Ballyragget"
    ],
    "name:gle_x_preferred":[
        "B\u00e9al \u00c1tha Ragad"
    ],
    "name:ita_x_preferred":[
        "Ballyragget"
    ],
    "name:nor_x_preferred":[
        "Ballyragget"
    ],
    "name:rus_x_preferred":[
        "\u0411\u0430\u043b\u043b\u0438\u0440\u0430\u0433\u0433\u0435\u0442"
    ],
    "name:spa_x_preferred":[
        "Ballyragget"
    ],
    "name:swe_x_preferred":[
        "Ballyragget"
    ],
    "qs_pg:aaroncc":"IE",
    "qs_pg:gn_country":"IE",
    "qs_pg:gn_fcode":"PPL",
    "qs_pg:gn_pop":0,
    "qs_pg:name":"Ballyragget",
    "qs_pg:name_adm0":"Ireland",
    "qs_pg:name_adm1":"Kilkenny",
    "qs_pg:photos_9k":1,
    "qs_pg:photos_9r":1,
    "qs_pg:photos_all":5,
    "qs_pg:photos_sr":0,
    "qs_pg:pop_sr":0,
    "qs_pg:qs_pg_placetype":"localadmin",
    "qs_pg:qs_pg_placetype_gp":"LocalAdmin",
    "qs_pg:woe_adm0":23424803,
    "woe:adm0_id":23424803,
    "woe:name_adm0":"Ireland",
    "woe:name_adm1":"Kilkenny",
    "woe:placetype":"LocalAdmin",
    "wof:name":"Ballyragget",
    "wof:placetype":"localadmin",
    "wof:population":1089
},
  "geometry": {"coordinates":[-7.33028,52.78889],"type":"Point"}
}