{
  "type": "Feature",
  "properties": {
    "gn:admin1_code":"M",
    "gn:admin2_code":"11",
    "gn:asciiname":"Drommartin",
    "gn:country_code":"IE",
    "gn:dem":48,
    "gn:feature_class":"P",
    "gn:feature_code":"PPL",
    "gn:name":"Drommartin",
    "gn:population":0,
    "gn:timezone":"Europe/Dublin",
    "iso:country":"IE",
    "wof:name":"Drommartin",
    "wof:placetype":"locality"
},
  "geometry": {"coordinates":[-9.69972,52.42806],"type":"Point"}
}