{
  "type": "Feature",
  "properties": {
    "gn:admin1_code":"U",
    "gn:admin2_code":"06",
    "gn:asciiname":"Meenataggart",
    "gn:country_code":"IE",
    "gn:dem":133,
    "gn:feature_class":"P",
    "gn:feature_code":"PPL",
    "gn:name":"Meenataggart",
    "gn:population":0,
    "gn:timezone":"Europe/Dublin",
    "iso:country":"IE",
    "wof:name":"Meenataggart",
    "wof:placetype":"locality"
},
  "geometry": {"coordinates":[-8.12417,54.72028],"type":"Point"}
}