{
  "type": "Feature",
  "properties": {
    "gn:admin1_code":"U",
    "gn:admin2_code":"06",
    "gn:asciiname":"Crocknagapple",
    "gn:country_code":"IE",
    "gn:dem":147,
    "gn:feature_class":"P",
    "gn:feature_code":"PPLL",
    "gn:name":"Crocknagapple",
    "gn:population":0,
    "gn:timezone":"Europe/Dublin",
    "iso:country":"IE",
    "name:eng_x_preferred":[
        "Crocknagapple"
    ],
    "name:gle_x_preferred":[
        "Cnoc na gCapall"
    ],
    "wof:name":"Crocknagapple",
    "wof:placetype":"locality"
},
  "geometry": {"coordinates":[-8.33528,54.73333],"type":"Point"}
}