{
  "type": "Feature",
  "properties": {
    "gn:admin1_code":"M",
    "gn:admin2_code":"04",
    "gn:asciiname":"Clashflugh Cross Roads",
    "gn:country_code":"IE",
    "gn:dem":65,
    "gn:feature_class":"P",
    "gn:feature_code":"PPLL",
    "gn:name":"Clashflugh Cross Roads",
    "gn:population":0,
    "gn:timezone":"Europe/Dublin",
    "iso:country":"IE",
    "wof:name":"Clashflugh Cross Roads",
    "wof:placetype":"locality"
},
  "geometry": {"coordinates":[-8.82667,51.63528],"type":"Point"}
}