{
  "type": "Feature",
  "properties": {
    "gn:admin1_code":"L",
    "gn:admin2_code":"19.0",
    "gn:asciiname":"Gibstown",
    "gn:country_code":"IE",
    "gn:dem":38,
    "gn:feature_class":"P",
    "gn:feature_code":"PPLL",
    "gn:name":"Gibstown",
    "gn:population":0,
    "gn:timezone":"Europe/Dublin",
    "iso:country":"IE",
    "wof:name":"Gibstown",
    "wof:placetype":"locality"
},
  "geometry": {"coordinates":[-6.42305,53.9782],"type":"Point"}
}