{
  "type": "Feature",
  "properties": {
    "gn:admin1_code":"M",
    "gn:admin2_code":"04",
    "gn:asciiname":"Glendine Bridge",
    "gn:country_code":"IE",
    "gn:dem":181,
    "gn:feature_class":"P",
    "gn:feature_code":"PPL",
    "gn:name":"Glendine Bridge",
    "gn:population":0,
    "gn:timezone":"Europe/Dublin",
    "iso:country":"IE",
    "wof:name":"Glendine Bridge",
    "wof:placetype":"locality"
},
  "geometry": {"coordinates":[-8.14972,52.00472],"type":"Point"}
}