{
  "type": "Feature",
  "properties": {
    "gn:admin1_code":"U",
    "gn:admin2_code":"2.0",
    "gn:asciiname":"Sruhanagh",
    "gn:country_code":"IE",
    "gn:dem":143,
    "gn:feature_class":"P",
    "gn:feature_code":"PPLL",
    "gn:name":"Sruhanagh",
    "gn:population":0,
    "gn:timezone":"Europe/Dublin",
    "iso:country":"IE",
    "wof:name":"Sruhanagh",
    "wof:placetype":"locality"
},
  "geometry": {"coordinates":[-7.98361,54.18889],"type":"Point"}
}