{
  "type": "Feature",
  "properties": {
    "gn:admin1_code":"C",
    "gn:admin2_code":"24.0",
    "gn:asciiname":"Feevaghmore",
    "gn:country_code":"IE",
    "gn:dem":53,
    "gn:feature_class":"P",
    "gn:feature_code":"PPL",
    "gn:name":"Feevaghmore",
    "gn:population":0,
    "gn:timezone":"Europe/Dublin",
    "iso:country":"IE",
    "wof:name":"Feevaghmore",
    "wof:placetype":"locality"
},
  "geometry": {"coordinates":[-8.22583,53.42194],"type":"Point"}
}