{
  "type": "Feature",
  "properties": {
    "gn:admin1_code":"L",
    "gn:admin2_code":"21.0",
    "gn:asciiname":"Ferganstown and Ballymacon",
    "gn:country_code":"IE",
    "gn:dem":49,
    "gn:feature_class":"P",
    "gn:feature_code":"PPL",
    "gn:name":"Ferganstown and Ballymacon",
    "gn:population":0,
    "gn:timezone":"Europe/Dublin",
    "iso:country":"IE",
    "wof:name":"Ferganstown and Ballymacon",
    "wof:placetype":"locality"
},
  "geometry": {"coordinates":[-6.64823,53.65922],"type":"Point"}
}