{
  "type": "Feature",
  "properties": {
    "gn:admin1_code":"C",
    "gn:admin2_code":"20.0",
    "gn:asciiname":"Barreitsplot East",
    "gn:country_code":"IE",
    "gn:dem":11,
    "gn:feature_class":"P",
    "gn:feature_code":"PPL",
    "gn:name":"Barreitsplot East",
    "gn:population":0,
    "gn:timezone":"Europe/Dublin",
    "iso:country":"IE",
    "name:eng_x_preferred":[
        "Barreitsplot East"
    ],
    "name:gle_x_preferred":[
        "Plota an Bhair\u00e9adaigh Thoir"
    ],
    "wof:name":"Barreitsplot East",
    "wof:placetype":"locality"
},
  "geometry": {"coordinates":[-10.05927,54.17726999999999],"type":"Point"}
}