{
  "type": "Feature",
  "properties": {
    "gn:admin1_code":"L",
    "gn:admin2_code":"12",
    "gn:asciiname":"Palatine",
    "gn:country_code":"IE",
    "gn:dem":70,
    "gn:feature_class":"P",
    "gn:feature_code":"PPL",
    "gn:name":"Palatine",
    "gn:population":351,
    "gn:timezone":"Europe/Dublin",
    "iso:country":"IE",
    "name:ceb_x_preferred":[
        "Palatine"
    ],
    "name:gle_x_preferred":[
        "Cnoc Arda"
    ],
    "wof:name":"Palatine",
    "wof:placetype":"locality",
    "wof:population":351
},
  "geometry": {"coordinates":[-6.86105,52.86483000000001],"type":"Point"}
}