{
  "type": "Feature",
  "properties": {
    "gn:admin1_code":"L",
    "gn:admin2_code":"29.0",
    "gn:asciiname":"Knockmant",
    "gn:country_code":"IE",
    "gn:dem":92,
    "gn:feature_class":"P",
    "gn:feature_code":"PPL",
    "gn:name":"Knockmant",
    "gn:population":0,
    "gn:timezone":"Europe/Dublin",
    "iso:country":"IE",
    "wof:name":"Knockmant",
    "wof:placetype":"locality"
},
  "geometry": {"coordinates":[-7.20249,53.50579000000001],"type":"Point"}
}