{
  "type": "Feature",
  "properties": {
    "gn:admin1_code":"M",
    "gn:admin2_code":"44",
    "gn:asciiname":"Islandtarsney",
    "gn:country_code":"IE",
    "gn:dem":74,
    "gn:feature_class":"P",
    "gn:feature_code":"PPL",
    "gn:name":"Islandtarsney",
    "gn:population":0,
    "gn:timezone":"Europe/Dublin",
    "iso:country":"IE",
    "wof:name":"Islandtarsney",
    "wof:placetype":"locality"
},
  "geometry": {"coordinates":[-7.20667,52.155],"type":"Point"}
}