{
  "type": "Feature",
  "properties": {
    "gn:admin1_code":"M",
    "gn:admin2_code":"11",
    "gn:asciiname":"Kilnanare",
    "gn:country_code":"IE",
    "gn:dem":19,
    "gn:feature_class":"P",
    "gn:feature_code":"PPL",
    "gn:name":"Kilnanare",
    "gn:population":0,
    "gn:timezone":"Europe/Dublin",
    "iso:country":"IE",
    "wof:name":"Kilnanare",
    "wof:placetype":"locality"
},
  "geometry": {"coordinates":[-9.62833,52.16417],"type":"Point"}
}