{
  "type": "Feature",
  "properties": {
    "gn:admin1_code":"U",
    "gn:admin2_code":"06",
    "gn:asciiname":"Meenlaragh",
    "gn:cc2":"IE",
    "gn:country_code":"IE",
    "gn:dem":31,
    "gn:feature_class":"P",
    "gn:feature_code":"PPL",
    "gn:name":"Meenlaragh",
    "gn:population":442,
    "gn:timezone":"Europe/Dublin",
    "iso:country":"IE",
    "name:eng_x_preferred":[
        "Meenlaragh"
    ],
    "name:gle_x_preferred":[
        "M\u00edn L\u00e1rach"
    ],
    "wof:name":"Meenlaragh",
    "wof:placetype":"locality",
    "wof:population":442
},
  "geometry": {"coordinates":[-8.18667,55.14471999999999],"type":"Point"}
}