{
  "type": "Feature",
  "properties": {
    "gn:admin1_code":"L",
    "gn:admin2_code":"23.0",
    "gn:asciiname":"Ballyduff",
    "gn:country_code":"IE",
    "gn:dem":89,
    "gn:feature_class":"P",
    "gn:feature_code":"PPL",
    "gn:name":"Ballyduff",
    "gn:population":0,
    "gn:timezone":"Europe/Dublin",
    "iso:country":"IE",
    "name:rus_x_preferred":[
        "\u0411\u0430\u043b\u043b\u0438\u0434\u0430\u0444\u0444"
    ],
    "wof:name":"Ballyduff",
    "wof:placetype":"locality"
},
  "geometry": {"coordinates":[-7.29278,53.24611],"type":"Point"}
}