{
  "type": "Feature",
  "properties": {
    "gn:admin1_code":"M",
    "gn:admin2_code":"04",
    "gn:asciiname":"Aghnamarroge Cross Roads",
    "gn:country_code":"IE",
    "gn:dem":148,
    "gn:feature_class":"P",
    "gn:feature_code":"PPLL",
    "gn:name":"Aghnamarroge Cross Roads",
    "gn:population":0,
    "gn:timezone":"Europe/Dublin",
    "iso:country":"IE",
    "wof:name":"Aghnamarroge Cross Roads",
    "wof:placetype":"locality"
},
  "geometry": {"coordinates":[-8.74833,51.83639],"type":"Point"}
}