{
  "type": "Feature",
  "properties": {
    "gn:country":"IE",
    "gn:fcode":"PPL",
    "gn:population":0,
    "iso:country":"IE",
    "name:afr_x_preferred":[
        "Glen"
    ],
    "name:eus_x_preferred":[
        "Glen"
    ],
    "name:fra_x_preferred":[
        "Glen"
    ],
    "name:ita_x_preferred":[
        "Glen"
    ],
    "name:mkd_x_preferred":[
        "\u0413\u043b\u0435\u043d"
    ],
    "name:nld_x_preferred":[
        "Glen"
    ],
    "name:rus_x_preferred":[
        "\u0420\u0430\u0441\u043f\u0430\u0434\u043e\u043a"
    ],
    "name:sco_x_preferred":[
        "Glen"
    ],
    "qs_pg:aaroncc":"IE",
    "qs_pg:gn_country":"IE",
    "qs_pg:gn_fcode":"PPL",
    "qs_pg:gn_pop":0,
    "qs_pg:name":"Glen",
    "qs_pg:name_adm0":"Ireland",
    "qs_pg:name_adm1":"Donegal",
    "qs_pg:photos":15,
    "qs_pg:photos_1k":3,
    "qs_pg:photos_9k":1,
    "qs_pg:photos_9r":1,
    "qs_pg:photos_all":15,
    "qs_pg:photos_sr":1,
    "qs_pg:pop_sr":0,
    "qs_pg:qs_pg_placetype":"locality",
    "qs_pg:qs_pg_placetype_gp":"Town",
    "qs_pg:woe_adm0":23424803,
    "woe:adm0_id":23424803,
    "woe:name_adm0":"Ireland",
    "woe:name_adm1":"Donegal",
    "woe:placetype":"Town",
    "wof:name":"Glen",
    "wof:placetype":"locality"
},
  "geometry": {"coordinates":[-7.81139,55.12556],"type":"Point"}
}