{
  "type": "Feature",
  "properties": {
    "gn:admin1_code":"M",
    "gn:admin2_code":"11",
    "gn:asciiname":"Lackabaun",
    "gn:country_code":"IE",
    "gn:dem":253,
    "gn:feature_class":"P",
    "gn:feature_code":"PPL",
    "gn:name":"Lackabaun",
    "gn:population":0,
    "gn:timezone":"Europe/Dublin",
    "iso:country":"IE",
    "wof:name":"Lackabaun",
    "wof:placetype":"locality"
},
  "geometry": {"coordinates":[-9.31833,51.88139],"type":"Point"}
}