{
  "type": "Feature",
  "properties": {
    "gn:admin1_code":"L",
    "gn:admin2_code":"30",
    "gn:asciiname":"Bounds Bridge",
    "gn:country_code":"IE",
    "gn:dem":45,
    "gn:feature_class":"P",
    "gn:feature_code":"PPL",
    "gn:name":"Bounds Bridge",
    "gn:population":0,
    "gn:timezone":"Europe/Dublin",
    "iso:country":"IE",
    "wof:name":"Bounds Bridge",
    "wof:placetype":"locality"
},
  "geometry": {"coordinates":[-6.18722,52.76611],"type":"Point"}
}