{
  "type": "Feature",
  "properties": {
    "gn:country":"IE",
    "gn:fcode":"PPL",
    "gn:population":0,
    "iso:country":"IE",
    "name:eus_x_preferred":[
        "Lisgoold"
    ],
    "name:rus_x_preferred":[
        "\u041b\u0438\u0441\u0433\u0443\u043b\u0434"
    ],
    "qs_pg:aaroncc":"IE",
    "qs_pg:gn_country":"IE",
    "qs_pg:gn_fcode":"PPL",
    "qs_pg:gn_pop":0,
    "qs_pg:name":"Lisgoold",
    "qs_pg:name_adm0":"Ireland",
    "qs_pg:name_adm1":"Cork",
    "qs_pg:photos":2,
    "qs_pg:photos_1k":1,
    "qs_pg:photos_9k":1,
    "qs_pg:photos_9r":1,
    "qs_pg:photos_all":2,
    "qs_pg:photos_sr":1,
    "qs_pg:pop_sr":0,
    "qs_pg:qs_pg_placetype":"localadmin",
    "qs_pg:qs_pg_placetype_gp":"LocalAdmin",
    "qs_pg:woe_adm0":23424803,
    "woe:adm0_id":23424803,
    "woe:name_adm0":"Ireland",
    "woe:name_adm1":"Cork",
    "woe:placetype":"LocalAdmin",
    "wof:name":"Lisgoold",
    "wof:placetype":"localadmin"
},
  "geometry": {"coordinates":[-8.21917,51.97333],"type":"Point"}
}