{
  "type": "Feature",
  "properties": {
    "gn:admin1_code":"C",
    "gn:admin2_code":"24.0",
    "gn:asciiname":"Altagowlan",
    "gn:country_code":"IE",
    "gn:dem":169,
    "gn:feature_class":"P",
    "gn:feature_code":"PPL",
    "gn:name":"Altagowlan",
    "gn:population":0,
    "gn:timezone":"Europe/Dublin",
    "iso:country":"IE",
    "wof:name":"Altagowlan",
    "wof:placetype":"locality"
},
  "geometry": {"coordinates":[-8.15278,54.10833],"type":"Point"}
}