{
  "type": "Feature",
  "properties": {
    "gn:admin1_code":"C",
    "gn:admin2_code":"14.0",
    "gn:asciiname":"Killenna",
    "gn:country_code":"IE",
    "gn:dem":128,
    "gn:feature_class":"P",
    "gn:feature_code":"PPLL",
    "gn:name":"Killenna",
    "gn:population":0,
    "gn:timezone":"Europe/Dublin",
    "iso:country":"IE",
    "wof:name":"Killenna",
    "wof:placetype":"locality"
},
  "geometry": {"coordinates":[-8.25222,54.29639],"type":"Point"}
}