{
  "type": "Feature",
  "properties": {
    "gn:admin1_code":"C",
    "gn:admin2_code":"14",
    "gn:asciiname":"Derrinvoney",
    "gn:country_code":"IE",
    "gn:dem":61,
    "gn:feature_class":"P",
    "gn:feature_code":"PPL",
    "gn:name":"Derrinvoney",
    "gn:population":0,
    "gn:timezone":"Europe/Dublin",
    "iso:country":"IE",
    "wof:name":"Derrinvoney",
    "wof:placetype":"locality"
},
  "geometry": {"coordinates":[-8.08333,54.16667],"type":"Point"}
}