{
  "type": "Feature",
  "properties": {
    "gn:admin1_code":"M",
    "gn:admin2_code":"11",
    "gn:asciiname":"Garrane",
    "gn:country_code":"IE",
    "gn:dem":4,
    "gn:feature_class":"P",
    "gn:feature_code":"PPL",
    "gn:name":"Garrane",
    "gn:population":0,
    "gn:timezone":"Europe/Dublin",
    "iso:country":"IE",
    "name:eng_x_preferred":[
        "Garrane"
    ],
    "name:gle_x_preferred":[
        "An Garr\u00e1n"
    ],
    "wof:name":"Garrane",
    "wof:placetype":"locality"
},
  "geometry": {"coordinates":[-9.82806,52.11611],"type":"Point"}
}