{
  "type": "Feature",
  "properties": {
    "gn:admin1_code":"C",
    "gn:admin2_code":"10.0",
    "gn:asciiname":"Annaghvaan",
    "gn:country_code":"IE",
    "gn:dem":1,
    "gn:feature_class":"P",
    "gn:feature_code":"PPLL",
    "gn:name":"Annaghvaan",
    "gn:population":0,
    "gn:timezone":"Europe/Dublin",
    "iso:country":"IE",
    "name:eng_x_preferred":[
        "Annaghvaan"
    ],
    "name:gle_x_preferred":[
        "Eanach Mhe\u00e1in"
    ],
    "wof:name":"Annaghvaan",
    "wof:placetype":"locality"
},
  "geometry": {"coordinates":[-9.6475,53.32],"type":"Point"}
}