{
  "type": "Feature",
  "properties": {
    "gn:admin1_code":"C",
    "gn:admin2_code":"20.0",
    "gn:asciiname":"Kiltyroe",
    "gn:country_code":"IE",
    "gn:dem":20,
    "gn:feature_class":"P",
    "gn:feature_code":"PPL",
    "gn:name":"Kiltyroe",
    "gn:population":0,
    "gn:timezone":"Europe/Dublin",
    "iso:country":"IE",
    "wof:name":"Kiltyroe",
    "wof:placetype":"locality"
},
  "geometry": {"coordinates":[-9.51481,53.8536],"type":"Point"}
}