{
  "type": "Feature",
  "properties": {
    "gn:admin1_code":"M",
    "gn:admin2_code":"11",
    "gn:asciiname":"Ballynahulla",
    "gn:country_code":"IE",
    "gn:dem":235,
    "gn:feature_class":"P",
    "gn:feature_code":"PPL",
    "gn:name":"Ballynahulla",
    "gn:population":0,
    "gn:timezone":"Europe/Dublin",
    "iso:country":"IE",
    "wof:name":"Ballynahulla",
    "wof:placetype":"locality"
},
  "geometry": {"coordinates":[-9.26278,52.17389],"type":"Point"}
}