{
  "type": "Feature",
  "properties": {
    "gn:country":"IE",
    "gn:fcode":"PPL",
    "gn:population":0,
    "iso:country":"IE",
    "name:ceb_x_preferred":[
        "Golden"
    ],
    "name:eng_x_preferred":[
        "Golden"
    ],
    "name:eus_x_preferred":[
        "Golden"
    ],
    "name:gle_x_preferred":[
        "An Gabhail\u00edn"
    ],
    "name:ita_x_preferred":[
        "Golden"
    ],
    "name:nld_x_preferred":[
        "Golden"
    ],
    "name:rus_x_preferred":[
        "\u0413\u043e\u043b\u0434\u0435\u043d"
    ],
    "name:spa_x_preferred":[
        "Golden"
    ],
    "name:swe_x_preferred":[
        "Golden"
    ],
    "name:urd_x_preferred":[
        "\u06af\u0648\u0644\u0688\u0646\u060c \u06a9\u0627\u0624\u0646\u0679\u06cc \u0679\u06cc\u067e\u06cc\u0631\u0627\u0631\u06cc"
    ],
    "name:urd_x_variant":[
        "\u06af\u0648\u0644\u0688\u0646"
    ],
    "qs_pg:aaroncc":"IE",
    "qs_pg:gn_country":"IE",
    "qs_pg:gn_fcode":"PPL",
    "qs_pg:gn_pop":0,
    "qs_pg:name":"Golden",
    "qs_pg:name_adm0":"Ireland",
    "qs_pg:name_adm1":"Tipperary",
    "qs_pg:photos":39,
    "qs_pg:photos_1k":8,
    "qs_pg:photos_9k":1,
    "qs_pg:photos_9r":2,
    "qs_pg:photos_all":39,
    "qs_pg:photos_sr":2,
    "qs_pg:pop_sr":0,
    "qs_pg:qs_pg_placetype":"locality",
    "qs_pg:qs_pg_placetype_gp":"Town",
    "qs_pg:woe_adm0":23424803,
    "woe:adm0_id":23424803,
    "woe:name_adm0":"Ireland",
    "woe:name_adm1":"Tipperary",
    "woe:placetype":"Town",
    "wof:name":"Golden",
    "wof:placetype":"locality",
    "wof:population":269
},
  "geometry": {"coordinates":[-7.98028,52.49778],"type":"Point"}
}