{
  "type": "Feature",
  "properties": {
    "iso:country":"IE",
    "name:eng_x_preferred":[
        "Fedamore"
    ],
    "name:gle_x_preferred":[
        "Feadamair"
    ],
    "name:nld_x_preferred":[
        "Fedamore"
    ],
    "qs:a0":"Ireland",
    "qs:a1":"*Limerick",
    "qs:a1r":"0",
    "qs:adm0":"Ireland",
    "qs:la_lc":"*",
    "qs:level":"locality",
    "qs:loc":"Fedamore",
    "qs:loc_alt":"Fedamore",
    "qs:pop":0,
    "qs:type":"buffered point",
    "wd:wordcount":500,
    "wof:lang":[
        "eng"
    ],
    "wof:name":"Fedamore",
    "wof:placetype":"locality"
},
  "geometry": {"coordinates":[-8.595789,52.54694],"type":"Point"}
}