{
  "type": "Feature",
  "properties": {
    "gn:admin1_code":"U",
    "gn:admin2_code":"02",
    "gn:asciiname":"Kilcrossduff",
    "gn:country_code":"IE",
    "gn:dem":175,
    "gn:feature_class":"P",
    "gn:feature_code":"PPLL",
    "gn:name":"Kilcrossduff",
    "gn:population":0,
    "gn:timezone":"Europe/Dublin",
    "iso:country":"IE",
    "wof:name":"Kilcrossduff",
    "wof:placetype":"locality"
},
  "geometry": {"coordinates":[-6.90389,53.965],"type":"Point"}
}