{
  "type": "Feature",
  "properties": {
    "gn:admin1_code":"C",
    "gn:admin2_code":"10.0",
    "gn:asciiname":"Tully",
    "gn:country_code":"IE",
    "gn:dem":64,
    "gn:feature_class":"P",
    "gn:feature_code":"PPLL",
    "gn:name":"Tully",
    "gn:population":0,
    "gn:timezone":"Europe/Dublin",
    "iso:country":"IE",
    "name:eng_x_preferred":[
        "Tully"
    ],
    "name:gle_x_preferred":[
        "An Tulaigh"
    ],
    "wof:name":"Tully",
    "wof:placetype":"locality"
},
  "geometry": {"coordinates":[-8.16472,53.19278000000001],"type":"Point"}
}