{
  "type": "Feature",
  "properties": {
    "gn:admin1_code":"C",
    "gn:admin2_code":"10.0",
    "gn:asciiname":"Tully",
    "gn:country_code":"IE",
    "gn:dem":64,
    "gn:feature_class":"P",
    "gn:feature_code":"PPLL",
    "gn:name":"Tully",
    "gn:population":0,
    "gn:timezone":"Europe/Dublin",
    "iso:country":"IE",
    "name:cat_x_preferred":[
        "Tully"
    ],
    "name:ceb_x_preferred":[
        "Tully"
    ],
    "name:deu_x_preferred":[
        "Tully"
    ],
    "name:eng_x_preferred":[
        "Tully"
    ],
    "name:fas_x_preferred":[
        "\u062a\u0627\u0644\u06cc"
    ],
    "name:fra_x_preferred":[
        "Tully"
    ],
    "name:gle_x_preferred":[
        "An Tulaigh"
    ],
    "name:ita_x_preferred":[
        "Tully"
    ],
    "name:jpn_x_preferred":[
        "\u30bf\u30ea\u30fc"
    ],
    "name:nds_x_preferred":[
        "Tully"
    ],
    "name:nld_x_preferred":[
        "Tully"
    ],
    "name:pol_x_preferred":[
        "Tully"
    ],
    "name:rus_x_preferred":[
        "\u0422\u0430\u043b\u043b\u0438"
    ],
    "name:swe_x_preferred":[
        "Tully"
    ],
    "wof:name":"Tully",
    "wof:placetype":"locality"
},
  "geometry": {"coordinates":[-8.16472,53.19278000000001],"type":"Point"}
}