{
  "type": "Feature",
  "properties": {
    "gn:admin1_code":"M",
    "gn:admin2_code":"11",
    "gn:asciiname":"Derreendarragh",
    "gn:country_code":"IE",
    "gn:dem":54,
    "gn:feature_class":"P",
    "gn:feature_code":"PPLL",
    "gn:name":"Derreendarragh",
    "gn:population":0,
    "gn:timezone":"Europe/Dublin",
    "iso:country":"IE",
    "wof:name":"Derreendarragh",
    "wof:placetype":"locality"
},
  "geometry": {"coordinates":[-9.75056,51.89333],"type":"Point"}
}