{
  "type": "Feature",
  "properties": {
    "gn:gn_country":"IE",
    "gn:gn_fcode":"PPL",
    "gn:gn_pop":0,
    "gn:population":777,
    "iso:country":"IE",
    "name:eng_x_preferred":[
        "Milltown Malbay"
    ],
    "name:gle_x_preferred":[
        "Sr\u00e1id na Cathrach"
    ],
    "name:unk_x_variant":[
        "Miltown Malbay"
    ],
    "qs_pg:aaroncc":"IE",
    "qs_pg:gn_country":"IE",
    "qs_pg:gn_fcode":"PPL",
    "qs_pg:gn_pop":0,
    "qs_pg:name":"Milltown Malbay",
    "qs_pg:name_adm0":"Ireland",
    "qs_pg:name_adm1":"Clare",
    "qs_pg:photos":3,
    "qs_pg:photos_1k":1,
    "qs_pg:photos_9k":4,
    "qs_pg:photos_9r":6,
    "qs_pg:photos_all":990,
    "qs_pg:photos_sr":1,
    "qs_pg:pop_sr":0,
    "qs_pg:qs_pg_placetype":"localadmin",
    "qs_pg:qs_pg_placetype_gp":"LocalAdmin",
    "qs_pg:woe_adm0":23424803,
    "woe:adm0_id":23424803,
    "woe:name_adm0":"Ireland",
    "woe:name_adm1":"Clare",
    "woe:placetype":"LocalAdmin",
    "wof:name":"Milltown Malbay",
    "wof:placetype":"localadmin",
    "wof:population":777
},
  "geometry": {"coordinates":[-9.39833,52.85528],"type":"Point"}
}