{
  "type": "Feature",
  "properties": {
    "gn:admin1_code":"C",
    "gn:admin2_code":"10.0",
    "gn:asciiname":"Rossaveal",
    "gn:country_code":"IE",
    "gn:dem":3,
    "gn:feature_class":"P",
    "gn:feature_code":"PPL",
    "gn:name":"Rossaveal",
    "gn:population":0,
    "gn:timezone":"Europe/Dublin",
    "iso:country":"IE",
    "wof:name":"Rossaveal",
    "wof:placetype":"locality"
},
  "geometry": {"coordinates":[-9.56066,53.2655],"type":"Point"}
}