{
  "type": "Feature",
  "properties": {
    "gn:admin1_code":"C",
    "gn:admin2_code":"10.0",
    "gn:asciiname":"Rossaveal",
    "gn:country_code":"IE",
    "gn:dem":3,
    "gn:feature_class":"P",
    "gn:feature_code":"PPL",
    "gn:name":"Rossaveal",
    "gn:population":0,
    "gn:timezone":"Europe/Dublin",
    "iso:country":"IE",
    "name:jpn_x_preferred":[
        "\u30ed\u30c3\u30b5\u30f4\u30a3\u30fc\u30eb"
    ],
    "name:kat_x_preferred":[
        "\u10e0\u10dd\u10e1\u10d0\u10d5\u10d8\u10da\u10d8"
    ],
    "name:rus_x_preferred":[
        "\u0420\u043e\u0441\u0441\u0430\u0432\u0438\u043b"
    ],
    "wof:name":"Rossaveal",
    "wof:placetype":"locality"
},
  "geometry": {"coordinates":[-9.56066,53.2655],"type":"Point"}
}