{
  "type": "Feature",
  "properties": {
    "gn:admin1_code":"L",
    "gn:admin2_code":"13",
    "gn:asciiname":"Priory",
    "gn:country_code":"IE",
    "gn:dem":68,
    "gn:feature_class":"P",
    "gn:feature_code":"PPL",
    "gn:name":"Priory",
    "gn:population":0,
    "gn:timezone":"Europe/Dublin",
    "iso:country":"IE",
    "name:bul_x_preferred":[
        "\u041f\u0440\u0438\u043e\u0440\u0430\u0442"
    ],
    "name:cat_x_preferred":[
        "Priorat"
    ],
    "name:cym_x_preferred":[
        "Priordy"
    ],
    "name:fra_x_preferred":[
        "Prieur\u00e9"
    ],
    "name:gle_x_preferred":[
        "Pri\u00f3ireacht"
    ],
    "name:hye_x_preferred":[
        "\u0544\u0565\u0576\u0561\u057d\u057f\u0561\u0576"
    ],
    "name:ind_x_preferred":[
        "Priorat"
    ],
    "name:kor_x_preferred":[
        "\ud504\ub9ac\uc624\ub77c\ud22c\uc2a4"
    ],
    "name:lat_x_preferred":[
        "Prioratus"
    ],
    "name:lim_x_preferred":[
        "Priorie"
    ],
    "name:nld_x_preferred":[
        "Priorij"
    ],
    "name:nrm_x_preferred":[
        "Prioura\u00e9"
    ],
    "name:oci_x_preferred":[
        "Priorat"
    ],
    "name:pol_x_preferred":[
        "Klasztor"
    ],
    "name:por_x_preferred":[
        "Priorado"
    ],
    "name:rus_x_preferred":[
        "\u041f\u0440\u0438\u043e\u0440\u0430\u0442"
    ],
    "name:spa_x_preferred":[
        "Priorato"
    ],
    "wof:name":"Priory",
    "wof:placetype":"locality"
},
  "geometry": {"coordinates":[-7.26139,52.53444],"type":"Point"}
}