{
  "type": "Feature",
  "properties": {
    "gn:admin1_code":"M",
    "gn:admin2_code":"11",
    "gn:asciiname":"Knocknaman",
    "gn:country_code":"IE",
    "gn:dem":40,
    "gn:feature_class":"P",
    "gn:feature_code":"PPL",
    "gn:name":"Knocknaman",
    "gn:population":0,
    "gn:timezone":"Europe/Dublin",
    "iso:country":"IE",
    "wof:name":"Knocknaman",
    "wof:placetype":"locality"
},
  "geometry": {"coordinates":[-9.66944,52.12306],"type":"Point"}
}