{
  "type": "Feature",
  "properties": {
    "gn:admin1_code":"L",
    "gn:admin2_code":"21.0",
    "gn:asciiname":"Ginnets Great",
    "gn:country_code":"IE",
    "gn:dem":77,
    "gn:feature_class":"P",
    "gn:feature_code":"PPL",
    "gn:name":"Ginnets Great",
    "gn:population":0,
    "gn:timezone":"Europe/Dublin",
    "iso:country":"IE",
    "wof:name":"Ginnets Great",
    "wof:placetype":"locality"
},
  "geometry": {"coordinates":[-6.73511,53.50613000000001],"type":"Point"}
}