{
  "type": "Feature",
  "properties": {
    "gn:admin1_code":"L",
    "gn:admin2_code":"21.0",
    "gn:asciiname":"Loughanbran",
    "gn:country_code":"IE",
    "gn:dem":115,
    "gn:feature_class":"P",
    "gn:feature_code":"PPL",
    "gn:name":"Loughanbran",
    "gn:population":0,
    "gn:timezone":"Europe/Dublin",
    "iso:country":"IE",
    "wof:name":"Loughanbran",
    "wof:placetype":"locality"
},
  "geometry": {"coordinates":[-7.08172,53.67605],"type":"Point"}
}