{
  "type": "Feature",
  "properties": {
    "gn:admin1_code":"M",
    "gn:admin2_code":"04",
    "gn:asciiname":"Pound Cross Roads",
    "gn:country_code":"IE",
    "gn:dem":121,
    "gn:feature_class":"P",
    "gn:feature_code":"PPL",
    "gn:name":"Pound Cross Roads",
    "gn:population":0,
    "gn:timezone":"Europe/Dublin",
    "iso:country":"IE",
    "wof:name":"Pound Cross Roads",
    "wof:placetype":"locality"
},
  "geometry": {"coordinates":[-8.11056,52.01417],"type":"Point"}
}