{
  "type": "Feature",
  "properties": {
    "gn:admin1_code":"U",
    "gn:admin2_code":"06",
    "gn:asciiname":"Barnesmore",
    "gn:country_code":"IE",
    "gn:dem":98,
    "gn:feature_class":"P",
    "gn:feature_code":"PPL",
    "gn:name":"Barnesmore",
    "gn:population":0,
    "gn:timezone":"Europe/Dublin",
    "iso:country":"IE",
    "wof:name":"Barnesmore",
    "wof:placetype":"locality"
},
  "geometry": {"coordinates":[-7.99472,54.69194],"type":"Point"}
}