{
  "type": "Feature",
  "properties": {
    "gn:admin1_code":"U",
    "gn:admin2_code":"06",
    "gn:asciiname":"Copan",
    "gn:country_code":"IE",
    "gn:dem":82,
    "gn:feature_class":"P",
    "gn:feature_code":"PPLL",
    "gn:name":"Copan",
    "gn:population":0,
    "gn:timezone":"Europe/Dublin",
    "iso:country":"IE",
    "wof:name":"Copan",
    "wof:placetype":"locality"
},
  "geometry": {"coordinates":[-8.03056,54.64583],"type":"Point"}
}