{
  "type": "Feature",
  "properties": {
    "gn:admin1_code":"L",
    "gn:admin2_code":"23.0",
    "gn:asciiname":"L'Estrange Bridge",
    "gn:country_code":"IE",
    "gn:dem":39,
    "gn:feature_class":"P",
    "gn:feature_code":"PPL",
    "gn:name":"L\u2019Estrange Bridge",
    "gn:population":0,
    "gn:timezone":"Europe/Dublin",
    "iso:country":"IE",
    "wof:name":"L'Estrange Bridge",
    "wof:placetype":"locality"
},
  "geometry": {"coordinates":[-7.91583,53.23111],"type":"Point"}
}