{
  "type": "Feature",
  "properties": {
    "gn:admin1_code":"L",
    "gn:admin2_code":"31.0",
    "gn:asciiname":"Keadeen",
    "gn:country_code":"IE",
    "gn:dem":282,
    "gn:feature_class":"P",
    "gn:feature_code":"PPL",
    "gn:name":"Keadeen",
    "gn:population":0,
    "gn:timezone":"Europe/Dublin",
    "iso:country":"IE",
    "wof:name":"Keadeen",
    "wof:placetype":"locality"
},
  "geometry": {"coordinates":[-6.60028,52.94306],"type":"Point"}
}