{
  "type": "Feature",
  "properties": {
    "gn:admin1_code":"C",
    "gn:admin2_code":"14.0",
    "gn:asciiname":"Balinlig",
    "gn:country_code":"IE",
    "gn:dem":131,
    "gn:feature_class":"P",
    "gn:feature_code":"PPLL",
    "gn:name":"Balinlig",
    "gn:population":0,
    "gn:timezone":"Europe/Dublin",
    "iso:country":"IE",
    "wof:name":"Balinlig",
    "wof:placetype":"locality"
},
  "geometry": {"coordinates":[-8.32778,54.37722],"type":"Point"}
}