{
  "type": "Feature",
  "properties": {
    "gn:admin1_code":"M",
    "gn:admin2_code":"11",
    "gn:asciiname":"Feohanagh",
    "gn:country_code":"IE",
    "gn:dem":54,
    "gn:feature_class":"P",
    "gn:feature_code":"PPL",
    "gn:name":"Feohanagh",
    "gn:population":0,
    "gn:timezone":"Europe/Dublin",
    "iso:country":"IE",
    "name:eng_x_preferred":[
        "Feohanagh"
    ],
    "name:gle_x_preferred":[
        "An Fheothanach"
    ],
    "wof:name":"Feohanagh",
    "wof:placetype":"locality"
},
  "geometry": {"coordinates":[-10.35556,52.21611],"type":"Point"}
}