{
  "type": "Feature",
  "properties": {
    "gn:admin1_code":"M",
    "gn:admin2_code":"42",
    "gn:asciiname":"Dromtrasna",
    "gn:country_code":"IE",
    "gn:dem":229,
    "gn:feature_class":"P",
    "gn:feature_code":"PPL",
    "gn:name":"Dromtrasna",
    "gn:population":0,
    "gn:timezone":"Europe/Dublin",
    "iso:country":"IE",
    "wof:name":"Dromtrasna",
    "wof:placetype":"locality"
},
  "geometry": {"coordinates":[-9.27861,52.36417],"type":"Point"}
}