{
  "type": "Feature",
  "properties": {
    "gn:admin1_code":"M",
    "gn:admin2_code":"04",
    "gn:asciiname":"Holy's Cross Roads",
    "gn:country_code":"IE",
    "gn:dem":95,
    "gn:feature_class":"P",
    "gn:feature_code":"PPLL",
    "gn:name":"Holy\u2019s Cross Roads",
    "gn:population":0,
    "gn:timezone":"Europe/Dublin",
    "iso:country":"IE",
    "wof:name":"Holy's Cross Roads",
    "wof:placetype":"locality"
},
  "geometry": {"coordinates":[-8.77278,52.17611],"type":"Point"}
}