{
  "type": "Feature",
  "properties": {
    "gn:admin1_code":"M",
    "gn:admin2_code":"03",
    "gn:asciiname":"Moveen",
    "gn:country_code":"IE",
    "gn:dem":43,
    "gn:feature_class":"P",
    "gn:feature_code":"PPL",
    "gn:name":"Moveen",
    "gn:population":0,
    "gn:timezone":"Europe/Dublin",
    "iso:country":"IE",
    "wof:name":"Moveen",
    "wof:placetype":"locality"
},
  "geometry": {"coordinates":[-9.70083,52.64861],"type":"Point"}
}