{
  "type": "Feature",
  "properties": {
    "gn:admin1_code":"M",
    "gn:admin2_code":"26",
    "gn:asciiname":"The Fourteen Roads",
    "gn:country_code":"IE",
    "gn:dem":166,
    "gn:feature_class":"P",
    "gn:feature_code":"PPL",
    "gn:name":"The Fourteen Roads",
    "gn:population":0,
    "gn:timezone":"Europe/Dublin",
    "iso:country":"IE",
    "wof:name":"The Fourteen Roads",
    "wof:placetype":"locality"
},
  "geometry": {"coordinates":[-7.87778,52.88583000000001],"type":"Point"}
}