{
  "type": "Feature",
  "properties": {
    "gn:admin1_code":"U",
    "gn:admin2_code":"06",
    "gn:asciiname":"Monargan Glebe",
    "gn:country_code":"IE",
    "gn:dem":45,
    "gn:feature_class":"P",
    "gn:feature_code":"PPLL",
    "gn:name":"Monargan Glebe",
    "gn:population":0,
    "gn:timezone":"Europe/Dublin",
    "iso:country":"IE",
    "wof:name":"Monargan Glebe",
    "wof:placetype":"locality"
},
  "geometry": {"coordinates":[-8.38972,54.75611],"type":"Point"}
}