{
  "type": "Feature",
  "properties": {
    "gn:admin1_code":"M",
    "gn:admin2_code":"11",
    "gn:asciiname":"Reacaslagh",
    "gn:country_code":"IE",
    "gn:dem":71,
    "gn:feature_class":"P",
    "gn:feature_code":"PPL",
    "gn:name":"Reacaslagh",
    "gn:population":0,
    "gn:timezone":"Europe/Dublin",
    "iso:country":"IE",
    "wof:name":"Reacaslagh",
    "wof:placetype":"locality"
},
  "geometry": {"coordinates":[-10.10333,52.01028],"type":"Point"}
}