{
  "type": "Feature",
  "properties": {
    "gn:admin1_code":"L",
    "gn:admin2_code":"29",
    "gn:asciiname":"Lynnbury",
    "gn:country_code":"IE",
    "gn:dem":107,
    "gn:feature_class":"P",
    "gn:feature_code":"PPL",
    "gn:name":"Lynnbury",
    "gn:population":0,
    "gn:timezone":"Europe/Dublin",
    "iso:country":"IE",
    "wof:name":"Lynnbury",
    "wof:placetype":"locality"
},
  "geometry": {"coordinates":[-7.35,53.48333],"type":"Point"}
}