{
  "type": "Feature",
  "properties": {
    "gn:admin1_code":"L",
    "gn:admin2_code":"21.0",
    "gn:asciiname":"Dreminstown",
    "gn:country_code":"IE",
    "gn:dem":93,
    "gn:feature_class":"P",
    "gn:feature_code":"PPL",
    "gn:name":"Dreminstown",
    "gn:population":0,
    "gn:timezone":"Europe/Dublin",
    "iso:country":"IE",
    "wof:name":"Dreminstown",
    "wof:placetype":"locality"
},
  "geometry": {"coordinates":[-6.63702,53.74845],"type":"Point"}
}