{
  "type": "Feature",
  "properties": {
    "gn:gn_country":"IE",
    "gn:gn_fcode":"PPL",
    "gn:gn_pop":0,
    "iso:country":"IE",
    "name:ara_x_preferred":[
        "\u0623\u0648\u0645\u0627\u0647"
    ],
    "name:bre_x_preferred":[
        "An \u00d3maigh"
    ],
    "name:bul_x_preferred":[
        "\u041e\u0443\u043c\u0430"
    ],
    "name:cat_x_preferred":[
        "Omagh"
    ],
    "name:ceb_x_preferred":[
        "Omagh"
    ],
    "name:cym_x_preferred":[
        "Omagh"
    ],
    "name:dan_x_preferred":[
        "Omagh"
    ],
    "name:deu_x_preferred":[
        "Omagh"
    ],
    "name:eng_x_preferred":[
        "Doagh"
    ],
    "name:epo_x_preferred":[
        "Omagh"
    ],
    "name:eus_x_preferred":[
        "Omagh"
    ],
    "name:fas_x_preferred":[
        "\u0627\u0648\u0645\u0627\u06af"
    ],
    "name:fra_x_preferred":[
        "Omagh"
    ],
    "name:gle_x_preferred":[
        "Dumhaigh"
    ],
    "name:gle_x_variant":[
        "An \u00d3maigh"
    ],
    "name:glg_x_preferred":[
        "Omagh"
    ],
    "name:hun_x_preferred":[
        "Omagh"
    ],
    "name:ita_x_preferred":[
        "Omagh"
    ],
    "name:jpn_x_preferred":[
        "\u30aa\u30de\u30fc"
    ],
    "name:lit_x_preferred":[
        "Oma"
    ],
    "name:msa_x_preferred":[
        "Omagh"
    ],
    "name:nld_x_preferred":[
        "Omagh"
    ],
    "name:nor_x_preferred":[
        "Omagh"
    ],
    "name:pol_x_preferred":[
        "Omagh"
    ],
    "name:por_x_preferred":[
        "Omagh"
    ],
    "name:rus_x_preferred":[
        "\u041e\u043c\u0430"
    ],
    "name:sco_x_preferred":[
        "Omey"
    ],
    "name:slk_x_preferred":[
        "Omagh"
    ],
    "name:spa_x_preferred":[
        "Omagh"
    ],
    "name:swe_x_preferred":[
        "Omagh"
    ],
    "name:urd_x_preferred":[
        "\u0627\u0648\u0645\u0627"
    ],
    "qs_pg:aaroncc":"IE",
    "qs_pg:gn_country":"IE",
    "qs_pg:gn_fcode":"PPL",
    "qs_pg:gn_pop":0,
    "qs_pg:name":"Omagh",
    "qs_pg:name_adm0":"United Kingdom",
    "qs_pg:name_adm1":"Northern Ireland",
    "qs_pg:photos":985,
    "qs_pg:photos_1k":200,
    "qs_pg:photos_9k":4,
    "qs_pg:photos_9r":6,
    "qs_pg:photos_all":985,
    "qs_pg:photos_sr":10,
    "qs_pg:pop_sr":0,
    "qs_pg:qs_pg_placetype":"locality",
    "qs_pg:qs_pg_placetype_gp":"Town",
    "qs_pg:woe_adm0":23424975,
    "woe:adm0_id":23424975,
    "woe:name_adm0":"United Kingdom",
    "woe:name_adm1":"Northern Ireland",
    "woe:placetype":"Town",
    "wof:name":"Omagh",
    "wof:placetype":"locality"
},
  "geometry": {"coordinates":[-7.85139,55.22583],"type":"Point"}
}