{
  "type": "Feature",
  "properties": {
    "gn:admin1_code":"M",
    "gn:admin2_code":"11",
    "gn:asciiname":"Tarmon",
    "gn:country_code":"IE",
    "gn:dem":64,
    "gn:feature_class":"P",
    "gn:feature_code":"PPL",
    "gn:name":"Tarmon",
    "gn:population":0,
    "gn:timezone":"Europe/Dublin",
    "iso:country":"IE",
    "name:eus_x_preferred":[
        "Tarmon"
    ],
    "name:gle_x_preferred":[
        "An Tearmann"
    ],
    "wof:name":"Tarmon",
    "wof:placetype":"locality"
},
  "geometry": {"coordinates":[-9.37889,52.53806],"type":"Point"}
}