{
  "type": "Feature",
  "properties": {
    "gn:admin1_code":"M",
    "gn:admin2_code":"04",
    "gn:asciiname":"Ballycroneen",
    "gn:country_code":"IE",
    "gn:dem":23,
    "gn:feature_class":"P",
    "gn:feature_code":"PPL",
    "gn:name":"Ballycroneen",
    "gn:population":0,
    "gn:timezone":"Europe/Dublin",
    "iso:country":"IE",
    "wof:name":"Ballycroneen",
    "wof:placetype":"locality"
},
  "geometry": {"coordinates":[-8.10833,51.80833],"type":"Point"}
}